package com.tencent.open.b;

final class l
  implements Runnable
{
  l(g paramg)
  {
  }

  // ERROR //
  public final void run()
  {
    // Byte code:
    //   0: aload_0
    //   1: getfield 12	com/tencent/open/b/l:a	Lcom/tencent/open/b/g;
    //   4: invokevirtual 37	com/tencent/open/b/g:d	()Landroid/os/Bundle;
    //   7: astore 29
    //   9: aload 29
    //   11: ifnonnull +4 -> 15
    //   14: return
    //   15: ldc 39
    //   17: new 41	java/lang/StringBuilder
    //   20: dup
    //   21: ldc 43
    //   23: invokespecial 46	java/lang/StringBuilder:<init>	(Ljava/lang/String;)V
    //   26: aload 29
    //   28: invokevirtual 52	android/os/Bundle:toString	()Ljava/lang/String;
    //   31: invokevirtual 56	java/lang/StringBuilder:append	(Ljava/lang/String;)Ljava/lang/StringBuilder;
    //   34: invokevirtual 57	java/lang/StringBuilder:toString	()Ljava/lang/String;
    //   37: invokestatic 62	com/tencent/open/a/h:a	(Ljava/lang/String;Ljava/lang/String;)V
    //   40: invokestatic 67	com/tencent/open/b/e:a	()I
    //   43: istore 8
    //   45: iconst_0
    //   46: istore 4
    //   48: iconst_0
    //   49: istore 10
    //   51: invokestatic 73	android/os/SystemClock:elapsedRealtime	()J
    //   54: lstore 21
    //   56: lconst_0
    //   57: lstore 27
    //   59: lconst_0
    //   60: lstore 23
    //   62: iconst_0
    //   63: istore_3
    //   64: iload 4
    //   66: iconst_1
    //   67: iadd
    //   68: istore_2
    //   69: iload 10
    //   71: istore 11
    //   73: iload_2
    //   74: istore 7
    //   76: iload 10
    //   78: istore 12
    //   80: iload_2
    //   81: istore 4
    //   83: iload 10
    //   85: istore 13
    //   87: iload 10
    //   89: istore 14
    //   91: iload_2
    //   92: istore 5
    //   94: iload 10
    //   96: istore 15
    //   98: iload_2
    //   99: istore 6
    //   101: iload 10
    //   103: istore 16
    //   105: invokestatic 78	com/tencent/open/utils/g:a	()Landroid/content/Context;
    //   108: ldc 80
    //   110: ldc 82
    //   112: aload 29
    //   114: invokestatic 87	com/tencent/open/utils/HttpUtils:a	(Landroid/content/Context;Ljava/lang/String;Ljava/lang/String;Landroid/os/Bundle;)Lcom/tencent/open/utils/t;
    //   117: astore 30
    //   119: iload 10
    //   121: istore 11
    //   123: iload_2
    //   124: istore 7
    //   126: iload 10
    //   128: istore 12
    //   130: iload_2
    //   131: istore 4
    //   133: iload 10
    //   135: istore 13
    //   137: iload 10
    //   139: istore 14
    //   141: iload_2
    //   142: istore 5
    //   144: iload 10
    //   146: istore 15
    //   148: iload_2
    //   149: istore 6
    //   151: iload 10
    //   153: istore 16
    //   155: aload 30
    //   157: getfield 92	com/tencent/open/utils/t:a	Ljava/lang/String;
    //   160: invokestatic 97	com/tencent/open/utils/s:d	(Ljava/lang/String;)Lorg/json/JSONObject;
    //   163: astore 31
    //   165: iload 10
    //   167: istore 11
    //   169: iload_2
    //   170: istore 7
    //   172: iload 10
    //   174: istore 12
    //   176: iload_2
    //   177: istore 4
    //   179: iload 10
    //   181: istore 13
    //   183: iload 10
    //   185: istore 14
    //   187: iload_2
    //   188: istore 5
    //   190: iload 10
    //   192: istore 16
    //   194: aload 31
    //   196: ldc 99
    //   198: invokevirtual 105	org/json/JSONObject:getInt	(Ljava/lang/String;)I
    //   201: istore_1
    //   202: iload_1
    //   203: ifeq +462 -> 665
    //   206: iload 10
    //   208: istore 9
    //   210: iload_2
    //   211: istore_1
    //   212: iload 10
    //   214: istore 11
    //   216: iload_2
    //   217: istore 7
    //   219: iload 10
    //   221: istore 12
    //   223: iload_2
    //   224: istore 4
    //   226: iload 10
    //   228: istore 13
    //   230: iload 10
    //   232: istore 14
    //   234: iload_2
    //   235: istore 5
    //   237: iload 10
    //   239: istore 15
    //   241: iload_2
    //   242: istore 6
    //   244: iload 10
    //   246: istore 16
    //   248: aload 30
    //   250: getfield 92	com/tencent/open/utils/t:a	Ljava/lang/String;
    //   253: invokestatic 111	android/text/TextUtils:isEmpty	(Ljava/lang/CharSequence;)Z
    //   256: ifne +6 -> 262
    //   259: goto +406 -> 665
    //   262: iload 9
    //   264: istore 11
    //   266: iload_1
    //   267: istore 7
    //   269: iload 9
    //   271: istore 12
    //   273: iload_1
    //   274: istore 4
    //   276: iload 9
    //   278: istore 13
    //   280: iload 9
    //   282: istore 14
    //   284: iload_1
    //   285: istore 5
    //   287: iload 9
    //   289: istore 15
    //   291: iload_1
    //   292: istore 6
    //   294: iload 9
    //   296: istore 16
    //   298: aload 30
    //   300: getfield 115	com/tencent/open/utils/t:b	J
    //   303: lstore 17
    //   305: iload 9
    //   307: istore 11
    //   309: iload_1
    //   310: istore 7
    //   312: iload 9
    //   314: istore 12
    //   316: iload_1
    //   317: istore 4
    //   319: iload 9
    //   321: istore 14
    //   323: iload_1
    //   324: istore 5
    //   326: iload 9
    //   328: istore 15
    //   330: iload_1
    //   331: istore 6
    //   333: iload 9
    //   335: istore 16
    //   337: aload 30
    //   339: getfield 118	com/tencent/open/utils/t:c	J
    //   342: lstore 27
    //   344: iload_1
    //   345: istore_2
    //   346: lload 21
    //   348: lstore 25
    //   350: lload 17
    //   352: lstore 19
    //   354: lload 27
    //   356: lstore 17
    //   358: iload_3
    //   359: istore_1
    //   360: iload_1
    //   361: istore_3
    //   362: iload 9
    //   364: istore 10
    //   366: lload 17
    //   368: lstore 23
    //   370: lload 19
    //   372: lstore 27
    //   374: lload 25
    //   376: lstore 21
    //   378: iload_2
    //   379: istore 4
    //   381: iload_2
    //   382: iload 8
    //   384: if_icmplt -320 -> 64
    //   387: lload 17
    //   389: lstore 21
    //   391: lload 25
    //   393: lstore 17
    //   395: aload_0
    //   396: getfield 12	com/tencent/open/b/l:a	Lcom/tencent/open/b/g;
    //   399: ldc 120
    //   401: lload 17
    //   403: lload 19
    //   405: lload 21
    //   407: iload_1
    //   408: aconst_null
    //   409: invokevirtual 123	com/tencent/open/b/g:a	(Ljava/lang/String;JJJILjava/lang/String;)V
    //   412: iload 9
    //   414: ifeq +224 -> 638
    //   417: invokestatic 128	com/tencent/open/b/f:a	()Lcom/tencent/open/b/f;
    //   420: ldc 130
    //   422: invokevirtual 132	com/tencent/open/b/f:b	(Ljava/lang/String;)V
    //   425: aload_0
    //   426: getfield 12	com/tencent/open/b/l:a	Lcom/tencent/open/b/g;
    //   429: getfield 135	com/tencent/open/b/g:d	Ljava/util/List;
    //   432: invokeinterface 140 1 0
    //   437: ldc 39
    //   439: new 41	java/lang/StringBuilder
    //   442: dup
    //   443: ldc 142
    //   445: invokespecial 46	java/lang/StringBuilder:<init>	(Ljava/lang/String;)V
    //   448: iload 9
    //   450: invokevirtual 145	java/lang/StringBuilder:append	(Z)Ljava/lang/StringBuilder;
    //   453: invokevirtual 57	java/lang/StringBuilder:toString	()Ljava/lang/String;
    //   456: invokestatic 147	com/tencent/open/a/h:b	(Ljava/lang/String;Ljava/lang/String;)V
    //   459: return
    //   460: astore 29
    //   462: ldc 39
    //   464: ldc 149
    //   466: aload 29
    //   468: invokestatic 152	com/tencent/open/a/h:b	(Ljava/lang/String;Ljava/lang/String;Ljava/lang/Throwable;)V
    //   471: return
    //   472: astore 31
    //   474: bipush 252
    //   476: istore_1
    //   477: goto -275 -> 202
    //   480: astore 30
    //   482: invokestatic 73	android/os/SystemClock:elapsedRealtime	()J
    //   485: lstore 25
    //   487: iload 7
    //   489: istore_2
    //   490: bipush 249
    //   492: istore_1
    //   493: lconst_0
    //   494: lstore 17
    //   496: lconst_0
    //   497: lstore 19
    //   499: iload 11
    //   501: istore 9
    //   503: goto -143 -> 360
    //   506: astore 30
    //   508: invokestatic 73	android/os/SystemClock:elapsedRealtime	()J
    //   511: lstore 25
    //   513: lconst_0
    //   514: lstore 19
    //   516: lconst_0
    //   517: lstore 17
    //   519: bipush 248
    //   521: istore_1
    //   522: iload 12
    //   524: istore 9
    //   526: iload 4
    //   528: istore_2
    //   529: goto -169 -> 360
    //   532: astore 29
    //   534: aload_0
    //   535: getfield 12	com/tencent/open/b/l:a	Lcom/tencent/open/b/g;
    //   538: getfield 135	com/tencent/open/b/g:d	Ljava/util/List;
    //   541: invokeinterface 140 1 0
    //   546: ldc 39
    //   548: ldc 154
    //   550: invokestatic 147	com/tencent/open/a/h:b	(Ljava/lang/String;Ljava/lang/String;)V
    //   553: return
    //   554: astore 29
    //   556: iload 13
    //   558: istore 9
    //   560: aload 29
    //   562: invokevirtual 157	com/tencent/open/utils/HttpUtils$HttpStatusException:getMessage	()Ljava/lang/String;
    //   565: ldc 159
    //   567: ldc 161
    //   569: invokevirtual 167	java/lang/String:replace	(Ljava/lang/CharSequence;Ljava/lang/CharSequence;)Ljava/lang/String;
    //   572: invokestatic 172	java/lang/Integer:parseInt	(Ljava/lang/String;)I
    //   575: istore_1
    //   576: lload 21
    //   578: lstore 17
    //   580: lload 27
    //   582: lstore 19
    //   584: lload 23
    //   586: lstore 21
    //   588: goto -193 -> 395
    //   591: astore 29
    //   593: iload_3
    //   594: istore_1
    //   595: lload 21
    //   597: lstore 17
    //   599: lload 27
    //   601: lstore 19
    //   603: lload 23
    //   605: lstore 21
    //   607: goto -212 -> 395
    //   610: astore 30
    //   612: lconst_0
    //   613: lstore 19
    //   615: lconst_0
    //   616: lstore 17
    //   618: aload 30
    //   620: invokestatic 175	com/tencent/open/utils/HttpUtils:a	(Ljava/io/IOException;)I
    //   623: istore_1
    //   624: iload 14
    //   626: istore 9
    //   628: lload 21
    //   630: lstore 25
    //   632: iload 5
    //   634: istore_2
    //   635: goto -275 -> 360
    //   638: invokestatic 128	com/tencent/open/b/f:a	()Lcom/tencent/open/b/f;
    //   641: ldc 130
    //   643: aload_0
    //   644: getfield 12	com/tencent/open/b/l:a	Lcom/tencent/open/b/g;
    //   647: getfield 135	com/tencent/open/b/g:d	Ljava/util/List;
    //   650: invokevirtual 178	com/tencent/open/b/f:a	(Ljava/lang/String;Ljava/util/List;)V
    //   653: goto -228 -> 425
    //   656: astore 29
    //   658: lload 17
    //   660: lstore 27
    //   662: goto -102 -> 560
    //   665: iconst_1
    //   666: istore 9
    //   668: iload 8
    //   670: istore_1
    //   671: goto -409 -> 262
    //   674: astore 30
    //   676: lconst_0
    //   677: lstore 19
    //   679: lconst_0
    //   680: lstore 17
    //   682: bipush 252
    //   684: istore_1
    //   685: iload 15
    //   687: istore 9
    //   689: lload 21
    //   691: lstore 25
    //   693: iload 6
    //   695: istore_2
    //   696: goto -336 -> 360
    //   699: astore 30
    //   701: lconst_0
    //   702: lstore 19
    //   704: lconst_0
    //   705: lstore 17
    //   707: bipush 250
    //   709: istore_1
    //   710: iload 8
    //   712: istore_2
    //   713: iload 16
    //   715: istore 9
    //   717: lload 21
    //   719: lstore 25
    //   721: goto -361 -> 360
    //
    // Exception table:
    //   from	to	target	type
    //   0	9	460	java/lang/Exception
    //   15	45	460	java/lang/Exception
    //   51	56	460	java/lang/Exception
    //   395	412	460	java/lang/Exception
    //   417	425	460	java/lang/Exception
    //   425	459	460	java/lang/Exception
    //   482	487	460	java/lang/Exception
    //   508	513	460	java/lang/Exception
    //   534	553	460	java/lang/Exception
    //   618	624	460	java/lang/Exception
    //   638	653	460	java/lang/Exception
    //   194	202	472	org/json/JSONException
    //   105	119	480	org/apache/http/conn/ConnectTimeoutException
    //   155	165	480	org/apache/http/conn/ConnectTimeoutException
    //   194	202	480	org/apache/http/conn/ConnectTimeoutException
    //   248	259	480	org/apache/http/conn/ConnectTimeoutException
    //   298	305	480	org/apache/http/conn/ConnectTimeoutException
    //   337	344	480	org/apache/http/conn/ConnectTimeoutException
    //   105	119	506	java/net/SocketTimeoutException
    //   155	165	506	java/net/SocketTimeoutException
    //   194	202	506	java/net/SocketTimeoutException
    //   248	259	506	java/net/SocketTimeoutException
    //   298	305	506	java/net/SocketTimeoutException
    //   337	344	506	java/net/SocketTimeoutException
    //   105	119	532	com/tencent/open/utils/HttpUtils$NetworkUnavailableException
    //   155	165	532	com/tencent/open/utils/HttpUtils$NetworkUnavailableException
    //   194	202	532	com/tencent/open/utils/HttpUtils$NetworkUnavailableException
    //   248	259	532	com/tencent/open/utils/HttpUtils$NetworkUnavailableException
    //   298	305	532	com/tencent/open/utils/HttpUtils$NetworkUnavailableException
    //   337	344	532	com/tencent/open/utils/HttpUtils$NetworkUnavailableException
    //   105	119	554	com/tencent/open/utils/HttpUtils$HttpStatusException
    //   155	165	554	com/tencent/open/utils/HttpUtils$HttpStatusException
    //   194	202	554	com/tencent/open/utils/HttpUtils$HttpStatusException
    //   248	259	554	com/tencent/open/utils/HttpUtils$HttpStatusException
    //   298	305	554	com/tencent/open/utils/HttpUtils$HttpStatusException
    //   560	576	591	java/lang/Exception
    //   105	119	610	java/io/IOException
    //   155	165	610	java/io/IOException
    //   194	202	610	java/io/IOException
    //   248	259	610	java/io/IOException
    //   298	305	610	java/io/IOException
    //   337	344	610	java/io/IOException
    //   337	344	656	com/tencent/open/utils/HttpUtils$HttpStatusException
    //   105	119	674	org/json/JSONException
    //   155	165	674	org/json/JSONException
    //   248	259	674	org/json/JSONException
    //   298	305	674	org/json/JSONException
    //   337	344	674	org/json/JSONException
    //   105	119	699	java/lang/Exception
    //   155	165	699	java/lang/Exception
    //   194	202	699	java/lang/Exception
    //   248	259	699	java/lang/Exception
    //   298	305	699	java/lang/Exception
    //   337	344	699	java/lang/Exception
  }
}

/* Location:           C:\crazyd\work\ustone\odm2016031702\baidu\android\nut-dex2jar.jar
 * Qualified Name:     com.tencent.open.b.l
 * JD-Core Version:    0.6.2
 */