package com.amap.api.services.core;

import android.text.TextUtils;
import java.io.IOException;
import java.util.Arrays;
import java.util.Iterator;
import java.util.Map;
import java.util.Map.Entry;
import java.util.Set;
import org.json.JSONObject;

public class as
{
  public static String a(String paramString)
  {
    int i = 0;
    try
    {
      if (TextUtils.isEmpty(paramString))
        return "";
      Object localObject = paramString.split("&");
      Arrays.sort((Object[])localObject);
      StringBuffer localStringBuffer = new StringBuffer();
      int j = localObject.length;
      while (i < j)
      {
        localStringBuffer.append(localObject[i]);
        localStringBuffer.append("&");
        i += 1;
      }
      localObject = localStringBuffer.toString();
      if (((String)localObject).length() > 1)
      {
        localObject = (String)((String)localObject).subSequence(0, ((String)localObject).length() - 1);
        return localObject;
      }
    }
    catch (Throwable localThrowable)
    {
      ay.a(localThrowable, "Utils", "sortParams");
    }
    return paramString;
  }

  // ERROR //
  public static String a(Throwable paramThrowable)
  {
    // Byte code:
    //   0: aconst_null
    //   1: astore 6
    //   3: aconst_null
    //   4: astore 7
    //   6: new 66	java/io/StringWriter
    //   9: dup
    //   10: invokespecial 67	java/io/StringWriter:<init>	()V
    //   13: astore_1
    //   14: new 69	java/io/PrintWriter
    //   17: dup
    //   18: aload_1
    //   19: invokespecial 72	java/io/PrintWriter:<init>	(Ljava/io/Writer;)V
    //   22: astore 5
    //   24: aload 5
    //   26: astore_3
    //   27: aload_1
    //   28: astore_2
    //   29: aload_0
    //   30: aload 5
    //   32: invokevirtual 76	java/lang/Throwable:printStackTrace	(Ljava/io/PrintWriter;)V
    //   35: aload 5
    //   37: astore_3
    //   38: aload_1
    //   39: astore_2
    //   40: aload_0
    //   41: invokevirtual 80	java/lang/Throwable:getCause	()Ljava/lang/Throwable;
    //   44: astore_0
    //   45: aload_0
    //   46: ifnull +27 -> 73
    //   49: aload 5
    //   51: astore_3
    //   52: aload_1
    //   53: astore_2
    //   54: aload_0
    //   55: aload 5
    //   57: invokevirtual 76	java/lang/Throwable:printStackTrace	(Ljava/io/PrintWriter;)V
    //   60: aload 5
    //   62: astore_3
    //   63: aload_1
    //   64: astore_2
    //   65: aload_0
    //   66: invokevirtual 80	java/lang/Throwable:getCause	()Ljava/lang/Throwable;
    //   69: astore_0
    //   70: goto -25 -> 45
    //   73: aload 5
    //   75: astore_3
    //   76: aload_1
    //   77: astore_2
    //   78: aload_1
    //   79: invokevirtual 81	java/lang/Object:toString	()Ljava/lang/String;
    //   82: astore_0
    //   83: aload_1
    //   84: ifnull +7 -> 91
    //   87: aload_1
    //   88: invokevirtual 86	java/io/Writer:close	()V
    //   91: aload_0
    //   92: astore_1
    //   93: aload 5
    //   95: ifnull +10 -> 105
    //   98: aload 5
    //   100: invokevirtual 87	java/io/PrintWriter:close	()V
    //   103: aload_0
    //   104: astore_1
    //   105: aload_1
    //   106: areturn
    //   107: astore 4
    //   109: aconst_null
    //   110: astore_0
    //   111: aconst_null
    //   112: astore_1
    //   113: aload_0
    //   114: astore_3
    //   115: aload_1
    //   116: astore_2
    //   117: aload 4
    //   119: invokevirtual 89	java/lang/Throwable:printStackTrace	()V
    //   122: aload_1
    //   123: ifnull +7 -> 130
    //   126: aload_1
    //   127: invokevirtual 86	java/io/Writer:close	()V
    //   130: aload 7
    //   132: astore_1
    //   133: aload_0
    //   134: ifnull -29 -> 105
    //   137: aload_0
    //   138: invokevirtual 87	java/io/PrintWriter:close	()V
    //   141: aconst_null
    //   142: areturn
    //   143: astore_1
    //   144: aload 6
    //   146: astore_0
    //   147: aload_1
    //   148: invokevirtual 89	java/lang/Throwable:printStackTrace	()V
    //   151: aload_0
    //   152: areturn
    //   153: astore_0
    //   154: aconst_null
    //   155: astore_3
    //   156: aconst_null
    //   157: astore_1
    //   158: aload_1
    //   159: ifnull +7 -> 166
    //   162: aload_1
    //   163: invokevirtual 86	java/io/Writer:close	()V
    //   166: aload_3
    //   167: ifnull +7 -> 174
    //   170: aload_3
    //   171: invokevirtual 87	java/io/PrintWriter:close	()V
    //   174: aload_0
    //   175: athrow
    //   176: astore_1
    //   177: aload_1
    //   178: invokevirtual 89	java/lang/Throwable:printStackTrace	()V
    //   181: goto -15 -> 166
    //   184: astore_1
    //   185: aload_1
    //   186: invokevirtual 89	java/lang/Throwable:printStackTrace	()V
    //   189: goto -15 -> 174
    //   192: astore_1
    //   193: aload_1
    //   194: invokevirtual 89	java/lang/Throwable:printStackTrace	()V
    //   197: goto -67 -> 130
    //   200: astore_1
    //   201: aload_1
    //   202: invokevirtual 89	java/lang/Throwable:printStackTrace	()V
    //   205: goto -114 -> 91
    //   208: astore_1
    //   209: goto -62 -> 147
    //   212: astore_0
    //   213: aconst_null
    //   214: astore_3
    //   215: goto -57 -> 158
    //   218: astore_0
    //   219: aload_2
    //   220: astore_1
    //   221: goto -63 -> 158
    //   224: astore 4
    //   226: aconst_null
    //   227: astore_0
    //   228: goto -115 -> 113
    //   231: astore 4
    //   233: aload 5
    //   235: astore_0
    //   236: goto -123 -> 113
    //
    // Exception table:
    //   from	to	target	type
    //   6	14	107	java/lang/Throwable
    //   137	141	143	java/lang/Throwable
    //   6	14	153	finally
    //   162	166	176	java/lang/Throwable
    //   170	174	184	java/lang/Throwable
    //   126	130	192	java/lang/Throwable
    //   87	91	200	java/lang/Throwable
    //   98	103	208	java/lang/Throwable
    //   14	24	212	finally
    //   29	35	218	finally
    //   40	45	218	finally
    //   54	60	218	finally
    //   65	70	218	finally
    //   78	83	218	finally
    //   117	122	218	finally
    //   14	24	224	java/lang/Throwable
    //   29	35	231	java/lang/Throwable
    //   40	45	231	java/lang/Throwable
    //   54	60	231	java/lang/Throwable
    //   65	70	231	java/lang/Throwable
    //   78	83	231	java/lang/Throwable
  }

  static String a(Map<String, String> paramMap)
  {
    if (paramMap != null)
    {
      StringBuilder localStringBuilder = new StringBuilder();
      paramMap = paramMap.entrySet().iterator();
      while (paramMap.hasNext())
      {
        Map.Entry localEntry = (Map.Entry)paramMap.next();
        if (localStringBuilder.length() > 0)
          localStringBuilder.append("&");
        localStringBuilder.append((String)localEntry.getKey());
        localStringBuilder.append("=");
        localStringBuilder.append((String)localEntry.getValue());
      }
      return localStringBuilder.toString();
    }
    return null;
  }

  // ERROR //
  static java.security.PublicKey a(android.content.Context paramContext)
    throws java.security.cert.CertificateException, java.security.spec.InvalidKeySpecException, java.security.NoSuchAlgorithmException, java.lang.NullPointerException, IOException
  {
    // Byte code:
    //   0: aconst_null
    //   1: astore 4
    //   3: aconst_null
    //   4: astore_3
    //   5: new 145	java/io/ByteArrayInputStream
    //   8: dup
    //   9: sipush 674
    //   12: newarray byte
    //   14: dup
    //   15: iconst_0
    //   16: ldc 146
    //   18: bastore
    //   19: dup
    //   20: iconst_1
    //   21: ldc 147
    //   23: bastore
    //   24: dup
    //   25: iconst_2
    //   26: ldc 148
    //   28: bastore
    //   29: dup
    //   30: iconst_3
    //   31: ldc 149
    //   33: bastore
    //   34: dup
    //   35: iconst_4
    //   36: ldc 146
    //   38: bastore
    //   39: dup
    //   40: iconst_5
    //   41: ldc 147
    //   43: bastore
    //   44: dup
    //   45: bipush 6
    //   47: ldc 148
    //   49: bastore
    //   50: dup
    //   51: bipush 7
    //   53: ldc 150
    //   55: bastore
    //   56: dup
    //   57: bipush 8
    //   59: ldc 151
    //   61: bastore
    //   62: dup
    //   63: bipush 9
    //   65: ldc 152
    //   67: bastore
    //   68: dup
    //   69: bipush 10
    //   71: ldc 148
    //   73: bastore
    //   74: dup
    //   75: bipush 11
    //   77: ldc 153
    //   79: bastore
    //   80: dup
    //   81: bipush 12
    //   83: ldc 148
    //   85: bastore
    //   86: dup
    //   87: bipush 13
    //   89: ldc 148
    //   91: bastore
    //   92: dup
    //   93: bipush 14
    //   95: ldc 154
    //   97: bastore
    //   98: dup
    //   99: bipush 15
    //   101: ldc 155
    //   103: bastore
    //   104: dup
    //   105: bipush 16
    //   107: ldc 156
    //   109: bastore
    //   110: dup
    //   111: bipush 17
    //   113: ldc 157
    //   115: bastore
    //   116: dup
    //   117: bipush 18
    //   119: ldc 158
    //   121: bastore
    //   122: dup
    //   123: bipush 19
    //   125: ldc 159
    //   127: bastore
    //   128: dup
    //   129: bipush 20
    //   131: ldc 160
    //   133: bastore
    //   134: dup
    //   135: bipush 21
    //   137: ldc 161
    //   139: bastore
    //   140: dup
    //   141: bipush 22
    //   143: ldc 162
    //   145: bastore
    //   146: dup
    //   147: bipush 23
    //   149: ldc 163
    //   151: bastore
    //   152: dup
    //   153: bipush 24
    //   155: ldc 146
    //   157: bastore
    //   158: dup
    //   159: bipush 25
    //   161: ldc 164
    //   163: bastore
    //   164: dup
    //   165: bipush 26
    //   167: ldc 165
    //   169: bastore
    //   170: dup
    //   171: bipush 27
    //   173: ldc 154
    //   175: bastore
    //   176: dup
    //   177: bipush 28
    //   179: ldc 166
    //   181: bastore
    //   182: dup
    //   183: bipush 29
    //   185: ldc 167
    //   187: bastore
    //   188: dup
    //   189: bipush 30
    //   191: ldc 168
    //   193: bastore
    //   194: dup
    //   195: bipush 31
    //   197: ldc 167
    //   199: bastore
    //   200: dup
    //   201: bipush 32
    //   203: ldc 169
    //   205: bastore
    //   206: dup
    //   207: bipush 33
    //   209: ldc 164
    //   211: bastore
    //   212: dup
    //   213: bipush 34
    //   215: ldc 153
    //   217: bastore
    //   218: dup
    //   219: bipush 35
    //   221: ldc 153
    //   223: bastore
    //   224: dup
    //   225: bipush 36
    //   227: ldc 170
    //   229: bastore
    //   230: dup
    //   231: bipush 37
    //   233: ldc 170
    //   235: bastore
    //   236: dup
    //   237: bipush 38
    //   239: ldc 155
    //   241: bastore
    //   242: dup
    //   243: bipush 39
    //   245: ldc 146
    //   247: bastore
    //   248: dup
    //   249: bipush 40
    //   251: ldc 171
    //   253: bastore
    //   254: dup
    //   255: bipush 41
    //   257: ldc 172
    //   259: bastore
    //   260: dup
    //   261: bipush 42
    //   263: ldc 173
    //   265: bastore
    //   266: dup
    //   267: bipush 43
    //   269: ldc 146
    //   271: bastore
    //   272: dup
    //   273: bipush 44
    //   275: ldc 154
    //   277: bastore
    //   278: dup
    //   279: bipush 45
    //   281: ldc 165
    //   283: bastore
    //   284: dup
    //   285: bipush 46
    //   287: ldc 152
    //   289: bastore
    //   290: dup
    //   291: bipush 47
    //   293: ldc 174
    //   295: bastore
    //   296: dup
    //   297: bipush 48
    //   299: ldc 175
    //   301: bastore
    //   302: dup
    //   303: bipush 49
    //   305: ldc 165
    //   307: bastore
    //   308: dup
    //   309: bipush 50
    //   311: ldc 176
    //   313: bastore
    //   314: dup
    //   315: bipush 51
    //   317: ldc 148
    //   319: bastore
    //   320: dup
    //   321: bipush 52
    //   323: ldc 177
    //   325: bastore
    //   326: dup
    //   327: bipush 53
    //   329: ldc 178
    //   331: bastore
    //   332: dup
    //   333: bipush 54
    //   335: ldc 172
    //   337: bastore
    //   338: dup
    //   339: bipush 55
    //   341: ldc 176
    //   343: bastore
    //   344: dup
    //   345: bipush 56
    //   347: ldc 146
    //   349: bastore
    //   350: dup
    //   351: bipush 57
    //   353: ldc 179
    //   355: bastore
    //   356: dup
    //   357: bipush 58
    //   359: ldc 165
    //   361: bastore
    //   362: dup
    //   363: bipush 59
    //   365: ldc 152
    //   367: bastore
    //   368: dup
    //   369: bipush 60
    //   371: ldc 174
    //   373: bastore
    //   374: dup
    //   375: bipush 61
    //   377: ldc 175
    //   379: bastore
    //   380: dup
    //   381: bipush 62
    //   383: ldc 180
    //   385: bastore
    //   386: dup
    //   387: bipush 63
    //   389: ldc 181
    //   391: bastore
    //   392: dup
    //   393: bipush 64
    //   395: ldc 182
    //   397: bastore
    //   398: dup
    //   399: bipush 65
    //   401: ldc 183
    //   403: bastore
    //   404: dup
    //   405: bipush 66
    //   407: ldc 184
    //   409: bastore
    //   410: dup
    //   411: bipush 67
    //   413: ldc 185
    //   415: bastore
    //   416: dup
    //   417: bipush 68
    //   419: ldc 186
    //   421: bastore
    //   422: dup
    //   423: bipush 69
    //   425: ldc 187
    //   427: bastore
    //   428: dup
    //   429: bipush 70
    //   431: ldc 183
    //   433: bastore
    //   434: dup
    //   435: bipush 71
    //   437: ldc 188
    //   439: bastore
    //   440: dup
    //   441: bipush 72
    //   443: ldc 189
    //   445: bastore
    //   446: dup
    //   447: bipush 73
    //   449: ldc 188
    //   451: bastore
    //   452: dup
    //   453: bipush 74
    //   455: ldc 186
    //   457: bastore
    //   458: dup
    //   459: bipush 75
    //   461: ldc 172
    //   463: bastore
    //   464: dup
    //   465: bipush 76
    //   467: ldc 190
    //   469: bastore
    //   470: dup
    //   471: bipush 77
    //   473: ldc 146
    //   475: bastore
    //   476: dup
    //   477: bipush 78
    //   479: ldc 191
    //   481: bastore
    //   482: dup
    //   483: bipush 79
    //   485: ldc 165
    //   487: bastore
    //   488: dup
    //   489: bipush 80
    //   491: ldc 152
    //   493: bastore
    //   494: dup
    //   495: bipush 81
    //   497: ldc 174
    //   499: bastore
    //   500: dup
    //   501: bipush 82
    //   503: ldc 175
    //   505: bastore
    //   506: dup
    //   507: bipush 83
    //   509: ldc 150
    //   511: bastore
    //   512: dup
    //   513: bipush 84
    //   515: ldc 181
    //   517: bastore
    //   518: dup
    //   519: bipush 85
    //   521: ldc 150
    //   523: bastore
    //   524: dup
    //   525: bipush 86
    //   527: ldc 192
    //   529: bastore
    //   530: dup
    //   531: bipush 87
    //   533: ldc 186
    //   535: bastore
    //   536: dup
    //   537: bipush 88
    //   539: ldc 193
    //   541: bastore
    //   542: dup
    //   543: bipush 89
    //   545: ldc 194
    //   547: bastore
    //   548: dup
    //   549: bipush 90
    //   551: ldc 193
    //   553: bastore
    //   554: dup
    //   555: bipush 91
    //   557: ldc 195
    //   559: bastore
    //   560: dup
    //   561: bipush 92
    //   563: ldc 196
    //   565: bastore
    //   566: dup
    //   567: bipush 93
    //   569: ldc 172
    //   571: bastore
    //   572: dup
    //   573: bipush 94
    //   575: ldc 179
    //   577: bastore
    //   578: dup
    //   579: bipush 95
    //   581: ldc 146
    //   583: bastore
    //   584: dup
    //   585: bipush 96
    //   587: ldc 157
    //   589: bastore
    //   590: dup
    //   591: bipush 97
    //   593: ldc 165
    //   595: bastore
    //   596: dup
    //   597: bipush 98
    //   599: ldc 152
    //   601: bastore
    //   602: dup
    //   603: bipush 99
    //   605: ldc 174
    //   607: bastore
    //   608: dup
    //   609: bipush 100
    //   611: ldc 175
    //   613: bastore
    //   614: dup
    //   615: bipush 101
    //   617: ldc 182
    //   619: bastore
    //   620: dup
    //   621: bipush 102
    //   623: ldc 181
    //   625: bastore
    //   626: dup
    //   627: bipush 103
    //   629: ldc 180
    //   631: bastore
    //   632: dup
    //   633: bipush 104
    //   635: ldc 197
    //   637: bastore
    //   638: dup
    //   639: bipush 105
    //   641: ldc 198
    //   643: bastore
    //   644: dup
    //   645: bipush 106
    //   647: ldc 188
    //   649: bastore
    //   650: dup
    //   651: bipush 107
    //   653: ldc 184
    //   655: bastore
    //   656: dup
    //   657: bipush 108
    //   659: ldc 195
    //   661: bastore
    //   662: dup
    //   663: bipush 109
    //   665: ldc 189
    //   667: bastore
    //   668: dup
    //   669: bipush 110
    //   671: ldc 199
    //   673: bastore
    //   674: dup
    //   675: bipush 111
    //   677: ldc 193
    //   679: bastore
    //   680: dup
    //   681: bipush 112
    //   683: ldc 172
    //   685: bastore
    //   686: dup
    //   687: bipush 113
    //   689: ldc 200
    //   691: bastore
    //   692: dup
    //   693: bipush 114
    //   695: ldc 146
    //   697: bastore
    //   698: dup
    //   699: bipush 115
    //   701: ldc 201
    //   703: bastore
    //   704: dup
    //   705: bipush 116
    //   707: ldc 165
    //   709: bastore
    //   710: dup
    //   711: bipush 117
    //   713: ldc 152
    //   715: bastore
    //   716: dup
    //   717: bipush 118
    //   719: ldc 174
    //   721: bastore
    //   722: dup
    //   723: bipush 119
    //   725: ldc 175
    //   727: bastore
    //   728: dup
    //   729: bipush 120
    //   731: ldc 152
    //   733: bastore
    //   734: dup
    //   735: bipush 121
    //   737: ldc 181
    //   739: bastore
    //   740: dup
    //   741: bipush 122
    //   743: ldc 202
    //   745: bastore
    //   746: dup
    //   747: bipush 123
    //   749: ldc 203
    //   751: bastore
    //   752: dup
    //   753: bipush 124
    //   755: ldc 184
    //   757: bastore
    //   758: dup
    //   759: bipush 125
    //   761: ldc 185
    //   763: bastore
    //   764: dup
    //   765: bipush 126
    //   767: ldc 204
    //   769: bastore
    //   770: dup
    //   771: bipush 127
    //   773: ldc 189
    //   775: bastore
    //   776: dup
    //   777: sipush 128
    //   780: ldc 198
    //   782: bastore
    //   783: dup
    //   784: sipush 129
    //   787: ldc 188
    //   789: bastore
    //   790: dup
    //   791: sipush 130
    //   794: ldc 184
    //   796: bastore
    //   797: dup
    //   798: sipush 131
    //   801: ldc 195
    //   803: bastore
    //   804: dup
    //   805: sipush 132
    //   808: ldc 189
    //   810: bastore
    //   811: dup
    //   812: sipush 133
    //   815: ldc 199
    //   817: bastore
    //   818: dup
    //   819: sipush 134
    //   822: ldc 193
    //   824: bastore
    //   825: dup
    //   826: sipush 135
    //   829: ldc 204
    //   831: bastore
    //   832: dup
    //   833: sipush 136
    //   836: ldc 189
    //   838: bastore
    //   839: dup
    //   840: sipush 137
    //   843: ldc 205
    //   845: bastore
    //   846: dup
    //   847: sipush 138
    //   850: ldc 193
    //   852: bastore
    //   853: dup
    //   854: sipush 139
    //   857: ldc 206
    //   859: bastore
    //   860: dup
    //   861: sipush 140
    //   864: ldc 186
    //   866: bastore
    //   867: dup
    //   868: sipush 141
    //   871: ldc 207
    //   873: bastore
    //   874: dup
    //   875: sipush 142
    //   878: ldc 199
    //   880: bastore
    //   881: dup
    //   882: sipush 143
    //   885: ldc 186
    //   887: bastore
    //   888: dup
    //   889: sipush 144
    //   892: ldc 207
    //   894: bastore
    //   895: dup
    //   896: sipush 145
    //   899: ldc 146
    //   901: bastore
    //   902: dup
    //   903: sipush 146
    //   906: ldc 208
    //   908: bastore
    //   909: dup
    //   910: sipush 147
    //   913: ldc 209
    //   915: bastore
    //   916: dup
    //   917: sipush 148
    //   920: ldc 164
    //   922: bastore
    //   923: dup
    //   924: sipush 149
    //   927: ldc 172
    //   929: bastore
    //   930: dup
    //   931: sipush 150
    //   934: ldc 210
    //   936: bastore
    //   937: dup
    //   938: sipush 151
    //   941: ldc 146
    //   943: bastore
    //   944: dup
    //   945: sipush 152
    //   948: ldc 211
    //   950: bastore
    //   951: dup
    //   952: sipush 153
    //   955: ldc 172
    //   957: bastore
    //   958: dup
    //   959: sipush 154
    //   962: ldc 212
    //   964: bastore
    //   965: dup
    //   966: sipush 155
    //   969: ldc 146
    //   971: bastore
    //   972: dup
    //   973: sipush 156
    //   976: ldc 213
    //   978: bastore
    //   979: dup
    //   980: sipush 157
    //   983: ldc 212
    //   985: bastore
    //   986: dup
    //   987: sipush 158
    //   990: ldc 214
    //   992: bastore
    //   993: dup
    //   994: sipush 159
    //   997: ldc 212
    //   999: bastore
    //   1000: dup
    //   1001: sipush 160
    //   1004: ldc 212
    //   1006: bastore
    //   1007: dup
    //   1008: sipush 161
    //   1011: ldc 215
    //   1013: bastore
    //   1014: dup
    //   1015: sipush 162
    //   1018: ldc 209
    //   1020: bastore
    //   1021: dup
    //   1022: sipush 163
    //   1025: ldc 164
    //   1027: bastore
    //   1028: dup
    //   1029: sipush 164
    //   1032: ldc 216
    //   1034: bastore
    //   1035: dup
    //   1036: sipush 165
    //   1039: ldc 210
    //   1041: bastore
    //   1042: dup
    //   1043: sipush 166
    //   1046: ldc 146
    //   1048: bastore
    //   1049: dup
    //   1050: sipush 167
    //   1053: ldc 211
    //   1055: bastore
    //   1056: dup
    //   1057: sipush 168
    //   1060: ldc 172
    //   1062: bastore
    //   1063: dup
    //   1064: sipush 169
    //   1067: ldc 210
    //   1069: bastore
    //   1070: dup
    //   1071: sipush 170
    //   1074: ldc 146
    //   1076: bastore
    //   1077: dup
    //   1078: sipush 171
    //   1081: ldc 213
    //   1083: bastore
    //   1084: dup
    //   1085: sipush 172
    //   1088: ldc 212
    //   1090: bastore
    //   1091: dup
    //   1092: sipush 173
    //   1095: ldc 214
    //   1097: bastore
    //   1098: dup
    //   1099: sipush 174
    //   1102: ldc 212
    //   1104: bastore
    //   1105: dup
    //   1106: sipush 175
    //   1109: ldc 212
    //   1111: bastore
    //   1112: dup
    //   1113: sipush 176
    //   1116: ldc 215
    //   1118: bastore
    //   1119: dup
    //   1120: sipush 177
    //   1123: ldc 146
    //   1125: bastore
    //   1126: dup
    //   1127: sipush 178
    //   1130: ldc 171
    //   1132: bastore
    //   1133: dup
    //   1134: sipush 179
    //   1137: ldc 172
    //   1139: bastore
    //   1140: dup
    //   1141: sipush 180
    //   1144: ldc 173
    //   1146: bastore
    //   1147: dup
    //   1148: sipush 181
    //   1151: ldc 146
    //   1153: bastore
    //   1154: dup
    //   1155: sipush 182
    //   1158: ldc 154
    //   1160: bastore
    //   1161: dup
    //   1162: sipush 183
    //   1165: ldc 165
    //   1167: bastore
    //   1168: dup
    //   1169: sipush 184
    //   1172: ldc 152
    //   1174: bastore
    //   1175: dup
    //   1176: sipush 185
    //   1179: ldc 174
    //   1181: bastore
    //   1182: dup
    //   1183: sipush 186
    //   1186: ldc 175
    //   1188: bastore
    //   1189: dup
    //   1190: sipush 187
    //   1193: ldc 165
    //   1195: bastore
    //   1196: dup
    //   1197: sipush 188
    //   1200: ldc 176
    //   1202: bastore
    //   1203: dup
    //   1204: sipush 189
    //   1207: ldc 148
    //   1209: bastore
    //   1210: dup
    //   1211: sipush 190
    //   1214: ldc 177
    //   1216: bastore
    //   1217: dup
    //   1218: sipush 191
    //   1221: ldc 178
    //   1223: bastore
    //   1224: dup
    //   1225: sipush 192
    //   1228: ldc 172
    //   1230: bastore
    //   1231: dup
    //   1232: sipush 193
    //   1235: ldc 176
    //   1237: bastore
    //   1238: dup
    //   1239: sipush 194
    //   1242: ldc 146
    //   1244: bastore
    //   1245: dup
    //   1246: sipush 195
    //   1249: ldc 179
    //   1251: bastore
    //   1252: dup
    //   1253: sipush 196
    //   1256: ldc 165
    //   1258: bastore
    //   1259: dup
    //   1260: sipush 197
    //   1263: ldc 152
    //   1265: bastore
    //   1266: dup
    //   1267: sipush 198
    //   1270: ldc 174
    //   1272: bastore
    //   1273: dup
    //   1274: sipush 199
    //   1277: ldc 175
    //   1279: bastore
    //   1280: dup
    //   1281: sipush 200
    //   1284: ldc 180
    //   1286: bastore
    //   1287: dup
    //   1288: sipush 201
    //   1291: ldc 181
    //   1293: bastore
    //   1294: dup
    //   1295: sipush 202
    //   1298: ldc 182
    //   1300: bastore
    //   1301: dup
    //   1302: sipush 203
    //   1305: ldc 183
    //   1307: bastore
    //   1308: dup
    //   1309: sipush 204
    //   1312: ldc 184
    //   1314: bastore
    //   1315: dup
    //   1316: sipush 205
    //   1319: ldc 185
    //   1321: bastore
    //   1322: dup
    //   1323: sipush 206
    //   1326: ldc 186
    //   1328: bastore
    //   1329: dup
    //   1330: sipush 207
    //   1333: ldc 187
    //   1335: bastore
    //   1336: dup
    //   1337: sipush 208
    //   1340: ldc 183
    //   1342: bastore
    //   1343: dup
    //   1344: sipush 209
    //   1347: ldc 188
    //   1349: bastore
    //   1350: dup
    //   1351: sipush 210
    //   1354: ldc 189
    //   1356: bastore
    //   1357: dup
    //   1358: sipush 211
    //   1361: ldc 188
    //   1363: bastore
    //   1364: dup
    //   1365: sipush 212
    //   1368: ldc 186
    //   1370: bastore
    //   1371: dup
    //   1372: sipush 213
    //   1375: ldc 172
    //   1377: bastore
    //   1378: dup
    //   1379: sipush 214
    //   1382: ldc 190
    //   1384: bastore
    //   1385: dup
    //   1386: sipush 215
    //   1389: ldc 146
    //   1391: bastore
    //   1392: dup
    //   1393: sipush 216
    //   1396: ldc 191
    //   1398: bastore
    //   1399: dup
    //   1400: sipush 217
    //   1403: ldc 165
    //   1405: bastore
    //   1406: dup
    //   1407: sipush 218
    //   1410: ldc 152
    //   1412: bastore
    //   1413: dup
    //   1414: sipush 219
    //   1417: ldc 174
    //   1419: bastore
    //   1420: dup
    //   1421: sipush 220
    //   1424: ldc 175
    //   1426: bastore
    //   1427: dup
    //   1428: sipush 221
    //   1431: ldc 150
    //   1433: bastore
    //   1434: dup
    //   1435: sipush 222
    //   1438: ldc 181
    //   1440: bastore
    //   1441: dup
    //   1442: sipush 223
    //   1445: ldc 150
    //   1447: bastore
    //   1448: dup
    //   1449: sipush 224
    //   1452: ldc 192
    //   1454: bastore
    //   1455: dup
    //   1456: sipush 225
    //   1459: ldc 186
    //   1461: bastore
    //   1462: dup
    //   1463: sipush 226
    //   1466: ldc 193
    //   1468: bastore
    //   1469: dup
    //   1470: sipush 227
    //   1473: ldc 194
    //   1475: bastore
    //   1476: dup
    //   1477: sipush 228
    //   1480: ldc 193
    //   1482: bastore
    //   1483: dup
    //   1484: sipush 229
    //   1487: ldc 195
    //   1489: bastore
    //   1490: dup
    //   1491: sipush 230
    //   1494: ldc 196
    //   1496: bastore
    //   1497: dup
    //   1498: sipush 231
    //   1501: ldc 172
    //   1503: bastore
    //   1504: dup
    //   1505: sipush 232
    //   1508: ldc 179
    //   1510: bastore
    //   1511: dup
    //   1512: sipush 233
    //   1515: ldc 146
    //   1517: bastore
    //   1518: dup
    //   1519: sipush 234
    //   1522: ldc 157
    //   1524: bastore
    //   1525: dup
    //   1526: sipush 235
    //   1529: ldc 165
    //   1531: bastore
    //   1532: dup
    //   1533: sipush 236
    //   1536: ldc 152
    //   1538: bastore
    //   1539: dup
    //   1540: sipush 237
    //   1543: ldc 174
    //   1545: bastore
    //   1546: dup
    //   1547: sipush 238
    //   1550: ldc 175
    //   1552: bastore
    //   1553: dup
    //   1554: sipush 239
    //   1557: ldc 182
    //   1559: bastore
    //   1560: dup
    //   1561: sipush 240
    //   1564: ldc 181
    //   1566: bastore
    //   1567: dup
    //   1568: sipush 241
    //   1571: ldc 180
    //   1573: bastore
    //   1574: dup
    //   1575: sipush 242
    //   1578: ldc 197
    //   1580: bastore
    //   1581: dup
    //   1582: sipush 243
    //   1585: ldc 198
    //   1587: bastore
    //   1588: dup
    //   1589: sipush 244
    //   1592: ldc 188
    //   1594: bastore
    //   1595: dup
    //   1596: sipush 245
    //   1599: ldc 184
    //   1601: bastore
    //   1602: dup
    //   1603: sipush 246
    //   1606: ldc 195
    //   1608: bastore
    //   1609: dup
    //   1610: sipush 247
    //   1613: ldc 189
    //   1615: bastore
    //   1616: dup
    //   1617: sipush 248
    //   1620: ldc 199
    //   1622: bastore
    //   1623: dup
    //   1624: sipush 249
    //   1627: ldc 193
    //   1629: bastore
    //   1630: dup
    //   1631: sipush 250
    //   1634: ldc 172
    //   1636: bastore
    //   1637: dup
    //   1638: sipush 251
    //   1641: ldc 200
    //   1643: bastore
    //   1644: dup
    //   1645: sipush 252
    //   1648: ldc 146
    //   1650: bastore
    //   1651: dup
    //   1652: sipush 253
    //   1655: ldc 201
    //   1657: bastore
    //   1658: dup
    //   1659: sipush 254
    //   1662: ldc 165
    //   1664: bastore
    //   1665: dup
    //   1666: sipush 255
    //   1669: ldc 152
    //   1671: bastore
    //   1672: dup
    //   1673: sipush 256
    //   1676: ldc 174
    //   1678: bastore
    //   1679: dup
    //   1680: sipush 257
    //   1683: ldc 175
    //   1685: bastore
    //   1686: dup
    //   1687: sipush 258
    //   1690: ldc 152
    //   1692: bastore
    //   1693: dup
    //   1694: sipush 259
    //   1697: ldc 181
    //   1699: bastore
    //   1700: dup
    //   1701: sipush 260
    //   1704: ldc 202
    //   1706: bastore
    //   1707: dup
    //   1708: sipush 261
    //   1711: ldc 203
    //   1713: bastore
    //   1714: dup
    //   1715: sipush 262
    //   1718: ldc 184
    //   1720: bastore
    //   1721: dup
    //   1722: sipush 263
    //   1725: ldc 185
    //   1727: bastore
    //   1728: dup
    //   1729: sipush 264
    //   1732: ldc 204
    //   1734: bastore
    //   1735: dup
    //   1736: sipush 265
    //   1739: ldc 189
    //   1741: bastore
    //   1742: dup
    //   1743: sipush 266
    //   1746: ldc 198
    //   1748: bastore
    //   1749: dup
    //   1750: sipush 267
    //   1753: ldc 188
    //   1755: bastore
    //   1756: dup
    //   1757: sipush 268
    //   1760: ldc 184
    //   1762: bastore
    //   1763: dup
    //   1764: sipush 269
    //   1767: ldc 195
    //   1769: bastore
    //   1770: dup
    //   1771: sipush 270
    //   1774: ldc 189
    //   1776: bastore
    //   1777: dup
    //   1778: sipush 271
    //   1781: ldc 199
    //   1783: bastore
    //   1784: dup
    //   1785: sipush 272
    //   1788: ldc 193
    //   1790: bastore
    //   1791: dup
    //   1792: sipush 273
    //   1795: ldc 204
    //   1797: bastore
    //   1798: dup
    //   1799: sipush 274
    //   1802: ldc 189
    //   1804: bastore
    //   1805: dup
    //   1806: sipush 275
    //   1809: ldc 205
    //   1811: bastore
    //   1812: dup
    //   1813: sipush 276
    //   1816: ldc 193
    //   1818: bastore
    //   1819: dup
    //   1820: sipush 277
    //   1823: ldc 206
    //   1825: bastore
    //   1826: dup
    //   1827: sipush 278
    //   1830: ldc 186
    //   1832: bastore
    //   1833: dup
    //   1834: sipush 279
    //   1837: ldc 207
    //   1839: bastore
    //   1840: dup
    //   1841: sipush 280
    //   1844: ldc 199
    //   1846: bastore
    //   1847: dup
    //   1848: sipush 281
    //   1851: ldc 186
    //   1853: bastore
    //   1854: dup
    //   1855: sipush 282
    //   1858: ldc 207
    //   1860: bastore
    //   1861: dup
    //   1862: sipush 283
    //   1865: ldc 146
    //   1867: bastore
    //   1868: dup
    //   1869: sipush 284
    //   1872: ldc 217
    //   1874: bastore
    //   1875: dup
    //   1876: sipush 285
    //   1879: ldc 218
    //   1881: bastore
    //   1882: dup
    //   1883: sipush 286
    //   1886: ldc 146
    //   1888: bastore
    //   1889: dup
    //   1890: sipush 287
    //   1893: ldc 164
    //   1895: bastore
    //   1896: dup
    //   1897: sipush 288
    //   1900: ldc 165
    //   1902: bastore
    //   1903: dup
    //   1904: sipush 289
    //   1907: ldc 154
    //   1909: bastore
    //   1910: dup
    //   1911: sipush 290
    //   1914: ldc 166
    //   1916: bastore
    //   1917: dup
    //   1918: sipush 291
    //   1921: ldc 167
    //   1923: bastore
    //   1924: dup
    //   1925: sipush 292
    //   1928: ldc 168
    //   1930: bastore
    //   1931: dup
    //   1932: sipush 293
    //   1935: ldc 167
    //   1937: bastore
    //   1938: dup
    //   1939: sipush 294
    //   1942: ldc 169
    //   1944: bastore
    //   1945: dup
    //   1946: sipush 295
    //   1949: ldc 164
    //   1951: bastore
    //   1952: dup
    //   1953: sipush 296
    //   1956: ldc 153
    //   1958: bastore
    //   1959: dup
    //   1960: sipush 297
    //   1963: ldc 153
    //   1965: bastore
    //   1966: dup
    //   1967: sipush 298
    //   1970: ldc 153
    //   1972: bastore
    //   1973: dup
    //   1974: sipush 299
    //   1977: ldc 170
    //   1979: bastore
    //   1980: dup
    //   1981: sipush 300
    //   1984: ldc 155
    //   1986: bastore
    //   1987: dup
    //   1988: sipush 301
    //   1991: ldc 152
    //   1993: bastore
    //   1994: dup
    //   1995: sipush 302
    //   1998: ldc 217
    //   2000: bastore
    //   2001: dup
    //   2002: sipush 303
    //   2005: ldc 219
    //   2007: bastore
    //   2008: dup
    //   2009: sipush 304
    //   2012: ldc 155
    //   2014: bastore
    //   2015: dup
    //   2016: sipush 305
    //   2019: ldc 146
    //   2021: bastore
    //   2022: dup
    //   2023: sipush 306
    //   2026: ldc 217
    //   2028: bastore
    //   2029: dup
    //   2030: sipush 307
    //   2033: ldc 220
    //   2035: bastore
    //   2036: dup
    //   2037: sipush 308
    //   2040: ldc 148
    //   2042: bastore
    //   2043: dup
    //   2044: sipush 309
    //   2047: ldc 217
    //   2049: bastore
    //   2050: dup
    //   2051: sipush 310
    //   2054: ldc 217
    //   2056: bastore
    //   2057: dup
    //   2058: sipush 311
    //   2061: ldc 155
    //   2063: bastore
    //   2064: dup
    //   2065: sipush 312
    //   2068: ldc 221
    //   2070: bastore
    //   2071: dup
    //   2072: sipush 313
    //   2075: ldc 222
    //   2077: bastore
    //   2078: dup
    //   2079: sipush 314
    //   2082: ldc 223
    //   2084: bastore
    //   2085: dup
    //   2086: sipush 315
    //   2089: ldc 224
    //   2091: bastore
    //   2092: dup
    //   2093: sipush 316
    //   2096: ldc 199
    //   2098: bastore
    //   2099: dup
    //   2100: sipush 317
    //   2103: ldc 225
    //   2105: bastore
    //   2106: dup
    //   2107: sipush 318
    //   2110: ldc 226
    //   2112: bastore
    //   2113: dup
    //   2114: sipush 319
    //   2117: ldc 217
    //   2119: bastore
    //   2120: dup
    //   2121: sipush 320
    //   2124: ldc 227
    //   2126: bastore
    //   2127: dup
    //   2128: sipush 321
    //   2131: ldc 228
    //   2133: bastore
    //   2134: dup
    //   2135: sipush 322
    //   2138: ldc 229
    //   2140: bastore
    //   2141: dup
    //   2142: sipush 323
    //   2145: ldc 230
    //   2147: bastore
    //   2148: dup
    //   2149: sipush 324
    //   2152: ldc 155
    //   2154: bastore
    //   2155: dup
    //   2156: sipush 325
    //   2159: ldc 231
    //   2161: bastore
    //   2162: dup
    //   2163: sipush 326
    //   2166: ldc 232
    //   2168: bastore
    //   2169: dup
    //   2170: sipush 327
    //   2173: ldc 233
    //   2175: bastore
    //   2176: dup
    //   2177: sipush 328
    //   2180: ldc 199
    //   2182: bastore
    //   2183: dup
    //   2184: sipush 329
    //   2187: ldc 170
    //   2189: bastore
    //   2190: dup
    //   2191: sipush 330
    //   2194: ldc 234
    //   2196: bastore
    //   2197: dup
    //   2198: sipush 331
    //   2201: ldc 235
    //   2203: bastore
    //   2204: dup
    //   2205: sipush 332
    //   2208: ldc 236
    //   2210: bastore
    //   2211: dup
    //   2212: sipush 333
    //   2215: ldc 237
    //   2217: bastore
    //   2218: dup
    //   2219: sipush 334
    //   2222: ldc 215
    //   2224: bastore
    //   2225: dup
    //   2226: sipush 335
    //   2229: ldc 238
    //   2231: bastore
    //   2232: dup
    //   2233: sipush 336
    //   2236: ldc 168
    //   2238: bastore
    //   2239: dup
    //   2240: sipush 337
    //   2243: ldc 147
    //   2245: bastore
    //   2246: dup
    //   2247: sipush 338
    //   2250: ldc 239
    //   2252: bastore
    //   2253: dup
    //   2254: sipush 339
    //   2257: ldc 240
    //   2259: bastore
    //   2260: dup
    //   2261: sipush 340
    //   2264: ldc 241
    //   2266: bastore
    //   2267: dup
    //   2268: sipush 341
    //   2271: ldc 242
    //   2273: bastore
    //   2274: dup
    //   2275: sipush 342
    //   2278: ldc 243
    //   2280: bastore
    //   2281: dup
    //   2282: sipush 343
    //   2285: ldc 244
    //   2287: bastore
    //   2288: dup
    //   2289: sipush 344
    //   2292: ldc 245
    //   2294: bastore
    //   2295: dup
    //   2296: sipush 345
    //   2299: ldc 209
    //   2301: bastore
    //   2302: dup
    //   2303: sipush 346
    //   2306: ldc 246
    //   2308: bastore
    //   2309: dup
    //   2310: sipush 347
    //   2313: ldc 235
    //   2315: bastore
    //   2316: dup
    //   2317: sipush 348
    //   2320: ldc 247
    //   2322: bastore
    //   2323: dup
    //   2324: sipush 349
    //   2327: ldc 238
    //   2329: bastore
    //   2330: dup
    //   2331: sipush 350
    //   2334: ldc 248
    //   2336: bastore
    //   2337: dup
    //   2338: sipush 351
    //   2341: ldc 202
    //   2343: bastore
    //   2344: dup
    //   2345: sipush 352
    //   2348: ldc 249
    //   2350: bastore
    //   2351: dup
    //   2352: sipush 353
    //   2355: ldc 250
    //   2357: bastore
    //   2358: dup
    //   2359: sipush 354
    //   2362: ldc 251
    //   2364: bastore
    //   2365: dup
    //   2366: sipush 355
    //   2369: ldc 252
    //   2371: bastore
    //   2372: dup
    //   2373: sipush 356
    //   2376: ldc 177
    //   2378: bastore
    //   2379: dup
    //   2380: sipush 357
    //   2383: ldc 253
    //   2385: bastore
    //   2386: dup
    //   2387: sipush 358
    //   2390: ldc 197
    //   2392: bastore
    //   2393: dup
    //   2394: sipush 359
    //   2397: ldc 254
    //   2399: bastore
    //   2400: dup
    //   2401: sipush 360
    //   2404: ldc 248
    //   2406: bastore
    //   2407: dup
    //   2408: sipush 361
    //   2411: ldc 173
    //   2413: bastore
    //   2414: dup
    //   2415: sipush 362
    //   2418: ldc 255
    //   2420: bastore
    //   2421: dup
    //   2422: sipush 363
    //   2425: ldc_w 256
    //   2428: bastore
    //   2429: dup
    //   2430: sipush 364
    //   2433: ldc_w 257
    //   2436: bastore
    //   2437: dup
    //   2438: sipush 365
    //   2441: ldc 190
    //   2443: bastore
    //   2444: dup
    //   2445: sipush 366
    //   2448: ldc_w 258
    //   2451: bastore
    //   2452: dup
    //   2453: sipush 367
    //   2456: ldc_w 259
    //   2459: bastore
    //   2460: dup
    //   2461: sipush 368
    //   2464: ldc_w 260
    //   2467: bastore
    //   2468: dup
    //   2469: sipush 369
    //   2472: ldc 159
    //   2474: bastore
    //   2475: dup
    //   2476: sipush 370
    //   2479: ldc_w 261
    //   2482: bastore
    //   2483: dup
    //   2484: sipush 371
    //   2487: ldc 191
    //   2489: bastore
    //   2490: dup
    //   2491: sipush 372
    //   2494: ldc 173
    //   2496: bastore
    //   2497: dup
    //   2498: sipush 373
    //   2501: ldc_w 262
    //   2504: bastore
    //   2505: dup
    //   2506: sipush 374
    //   2509: ldc_w 263
    //   2512: bastore
    //   2513: dup
    //   2514: sipush 375
    //   2517: ldc 164
    //   2519: bastore
    //   2520: dup
    //   2521: sipush 376
    //   2524: ldc 235
    //   2526: bastore
    //   2527: dup
    //   2528: sipush 377
    //   2531: ldc_w 264
    //   2534: bastore
    //   2535: dup
    //   2536: sipush 378
    //   2539: ldc 193
    //   2541: bastore
    //   2542: dup
    //   2543: sipush 379
    //   2546: ldc_w 265
    //   2549: bastore
    //   2550: dup
    //   2551: sipush 380
    //   2554: ldc 238
    //   2556: bastore
    //   2557: dup
    //   2558: sipush 381
    //   2561: ldc_w 266
    //   2564: bastore
    //   2565: dup
    //   2566: sipush 382
    //   2569: ldc 207
    //   2571: bastore
    //   2572: dup
    //   2573: sipush 383
    //   2576: ldc_w 267
    //   2579: bastore
    //   2580: dup
    //   2581: sipush 384
    //   2584: ldc 240
    //   2586: bastore
    //   2587: dup
    //   2588: sipush 385
    //   2591: ldc 181
    //   2593: bastore
    //   2594: dup
    //   2595: sipush 386
    //   2598: ldc_w 264
    //   2601: bastore
    //   2602: dup
    //   2603: sipush 387
    //   2606: ldc_w 268
    //   2609: bastore
    //   2610: dup
    //   2611: sipush 388
    //   2614: ldc 244
    //   2616: bastore
    //   2617: dup
    //   2618: sipush 389
    //   2621: ldc 231
    //   2623: bastore
    //   2624: dup
    //   2625: sipush 390
    //   2628: ldc_w 269
    //   2631: bastore
    //   2632: dup
    //   2633: sipush 391
    //   2636: ldc_w 257
    //   2639: bastore
    //   2640: dup
    //   2641: sipush 392
    //   2644: ldc 146
    //   2646: bastore
    //   2647: dup
    //   2648: sipush 393
    //   2651: ldc 213
    //   2653: bastore
    //   2654: dup
    //   2655: sipush 394
    //   2658: ldc_w 259
    //   2661: bastore
    //   2662: dup
    //   2663: sipush 395
    //   2666: ldc_w 270
    //   2669: bastore
    //   2670: dup
    //   2671: sipush 396
    //   2674: ldc_w 271
    //   2677: bastore
    //   2678: dup
    //   2679: sipush 397
    //   2682: ldc_w 272
    //   2685: bastore
    //   2686: dup
    //   2687: sipush 398
    //   2690: ldc 228
    //   2692: bastore
    //   2693: dup
    //   2694: sipush 399
    //   2697: ldc_w 273
    //   2700: bastore
    //   2701: dup
    //   2702: sipush 400
    //   2705: ldc 240
    //   2707: bastore
    //   2708: dup
    //   2709: sipush 401
    //   2712: ldc_w 274
    //   2715: bastore
    //   2716: dup
    //   2717: sipush 402
    //   2720: ldc 147
    //   2722: bastore
    //   2723: dup
    //   2724: sipush 403
    //   2727: ldc 199
    //   2729: bastore
    //   2730: dup
    //   2731: sipush 404
    //   2734: ldc_w 275
    //   2737: bastore
    //   2738: dup
    //   2739: sipush 405
    //   2742: ldc_w 276
    //   2745: bastore
    //   2746: dup
    //   2747: sipush 406
    //   2750: ldc 217
    //   2752: bastore
    //   2753: dup
    //   2754: sipush 407
    //   2757: ldc 154
    //   2759: bastore
    //   2760: dup
    //   2761: sipush 408
    //   2764: ldc_w 277
    //   2767: bastore
    //   2768: dup
    //   2769: sipush 409
    //   2772: ldc_w 278
    //   2775: bastore
    //   2776: dup
    //   2777: sipush 410
    //   2780: ldc_w 279
    //   2783: bastore
    //   2784: dup
    //   2785: sipush 411
    //   2788: ldc 161
    //   2790: bastore
    //   2791: dup
    //   2792: sipush 412
    //   2795: ldc 249
    //   2797: bastore
    //   2798: dup
    //   2799: sipush 413
    //   2802: ldc 240
    //   2804: bastore
    //   2805: dup
    //   2806: sipush 414
    //   2809: ldc 174
    //   2811: bastore
    //   2812: dup
    //   2813: sipush 415
    //   2816: ldc_w 280
    //   2819: bastore
    //   2820: dup
    //   2821: sipush 416
    //   2824: ldc_w 281
    //   2827: bastore
    //   2828: dup
    //   2829: sipush 417
    //   2832: ldc_w 270
    //   2835: bastore
    //   2836: dup
    //   2837: sipush 418
    //   2840: ldc 199
    //   2842: bastore
    //   2843: dup
    //   2844: sipush 419
    //   2847: ldc 168
    //   2849: bastore
    //   2850: dup
    //   2851: sipush 420
    //   2854: ldc_w 282
    //   2857: bastore
    //   2858: dup
    //   2859: sipush 421
    //   2862: ldc 228
    //   2864: bastore
    //   2865: dup
    //   2866: sipush 422
    //   2869: ldc 253
    //   2871: bastore
    //   2872: dup
    //   2873: sipush 423
    //   2876: ldc_w 283
    //   2879: bastore
    //   2880: dup
    //   2881: sipush 424
    //   2884: ldc_w 284
    //   2887: bastore
    //   2888: dup
    //   2889: sipush 425
    //   2892: ldc 231
    //   2894: bastore
    //   2895: dup
    //   2896: sipush 426
    //   2899: ldc_w 285
    //   2902: bastore
    //   2903: dup
    //   2904: sipush 427
    //   2907: ldc_w 286
    //   2910: bastore
    //   2911: dup
    //   2912: sipush 428
    //   2915: ldc_w 272
    //   2918: bastore
    //   2919: dup
    //   2920: sipush 429
    //   2923: ldc_w 287
    //   2926: bastore
    //   2927: dup
    //   2928: sipush 430
    //   2931: ldc_w 269
    //   2934: bastore
    //   2935: dup
    //   2936: sipush 431
    //   2939: ldc_w 288
    //   2942: bastore
    //   2943: dup
    //   2944: sipush 432
    //   2947: ldc 219
    //   2949: bastore
    //   2950: dup
    //   2951: sipush 433
    //   2954: ldc_w 263
    //   2957: bastore
    //   2958: dup
    //   2959: sipush 434
    //   2962: ldc 226
    //   2964: bastore
    //   2965: dup
    //   2966: sipush 435
    //   2969: ldc_w 289
    //   2972: bastore
    //   2973: dup
    //   2974: sipush 436
    //   2977: ldc_w 290
    //   2980: bastore
    //   2981: dup
    //   2982: sipush 437
    //   2985: ldc 153
    //   2987: bastore
    //   2988: dup
    //   2989: sipush 438
    //   2992: ldc 237
    //   2994: bastore
    //   2995: dup
    //   2996: sipush 439
    //   2999: ldc 176
    //   3001: bastore
    //   3002: dup
    //   3003: sipush 440
    //   3006: ldc 148
    //   3008: bastore
    //   3009: dup
    //   3010: sipush 441
    //   3013: ldc 152
    //   3015: bastore
    //   3016: dup
    //   3017: sipush 442
    //   3020: ldc 153
    //   3022: bastore
    //   3023: dup
    //   3024: sipush 443
    //   3027: ldc 155
    //   3029: bastore
    //   3030: dup
    //   3031: sipush 444
    //   3034: ldc 153
    //   3036: bastore
    //   3037: dup
    //   3038: sipush 445
    //   3041: ldc_w 291
    //   3044: bastore
    //   3045: dup
    //   3046: sipush 446
    //   3049: ldc_w 259
    //   3052: bastore
    //   3053: dup
    //   3054: sipush 447
    //   3057: ldc 146
    //   3059: bastore
    //   3060: dup
    //   3061: sipush 448
    //   3064: ldc 178
    //   3066: bastore
    //   3067: dup
    //   3068: sipush 449
    //   3071: ldc 146
    //   3073: bastore
    //   3074: dup
    //   3075: sipush 450
    //   3078: ldc 201
    //   3080: bastore
    //   3081: dup
    //   3082: sipush 451
    //   3085: ldc 165
    //   3087: bastore
    //   3088: dup
    //   3089: sipush 452
    //   3092: ldc 152
    //   3094: bastore
    //   3095: dup
    //   3096: sipush 453
    //   3099: ldc 174
    //   3101: bastore
    //   3102: dup
    //   3103: sipush 454
    //   3106: ldc 201
    //   3108: bastore
    //   3109: dup
    //   3110: sipush 455
    //   3113: ldc 191
    //   3115: bastore
    //   3116: dup
    //   3117: sipush 456
    //   3120: ldc 175
    //   3122: bastore
    //   3123: dup
    //   3124: sipush 457
    //   3127: ldc 202
    //   3129: bastore
    //   3130: dup
    //   3131: sipush 458
    //   3134: ldc 175
    //   3136: bastore
    //   3137: dup
    //   3138: sipush 459
    //   3141: ldc_w 292
    //   3144: bastore
    //   3145: dup
    //   3146: sipush 460
    //   3149: ldc 247
    //   3151: bastore
    //   3152: dup
    //   3153: sipush 461
    //   3156: ldc 231
    //   3158: bastore
    //   3159: dup
    //   3160: sipush 462
    //   3163: ldc 146
    //   3165: bastore
    //   3166: dup
    //   3167: sipush 463
    //   3170: ldc_w 293
    //   3173: bastore
    //   3174: dup
    //   3175: sipush 464
    //   3178: ldc_w 294
    //   3181: bastore
    //   3182: dup
    //   3183: sipush 465
    //   3186: ldc_w 295
    //   3189: bastore
    //   3190: dup
    //   3191: sipush 466
    //   3194: ldc_w 296
    //   3197: bastore
    //   3198: dup
    //   3199: sipush 467
    //   3202: ldc 174
    //   3204: bastore
    //   3205: dup
    //   3206: sipush 468
    //   3209: ldc 202
    //   3211: bastore
    //   3212: dup
    //   3213: sipush 469
    //   3216: ldc 222
    //   3218: bastore
    //   3219: dup
    //   3220: sipush 470
    //   3223: ldc_w 277
    //   3226: bastore
    //   3227: dup
    //   3228: sipush 471
    //   3231: ldc_w 297
    //   3234: bastore
    //   3235: dup
    //   3236: sipush 472
    //   3239: ldc_w 298
    //   3242: bastore
    //   3243: dup
    //   3244: sipush 473
    //   3247: ldc_w 280
    //   3250: bastore
    //   3251: dup
    //   3252: sipush 474
    //   3255: ldc_w 299
    //   3258: bastore
    //   3259: dup
    //   3260: sipush 475
    //   3263: ldc 191
    //   3265: bastore
    //   3266: dup
    //   3267: sipush 476
    //   3270: ldc_w 300
    //   3273: bastore
    //   3274: dup
    //   3275: sipush 477
    //   3278: ldc 165
    //   3280: bastore
    //   3281: dup
    //   3282: sipush 478
    //   3285: ldc_w 295
    //   3288: bastore
    //   3289: dup
    //   3290: sipush 479
    //   3293: ldc_w 299
    //   3296: bastore
    //   3297: dup
    //   3298: sipush 480
    //   3301: ldc 146
    //   3303: bastore
    //   3304: dup
    //   3305: sipush 481
    //   3308: ldc 200
    //   3310: bastore
    //   3311: dup
    //   3312: sipush 482
    //   3315: ldc 165
    //   3317: bastore
    //   3318: dup
    //   3319: sipush 483
    //   3322: ldc 152
    //   3324: bastore
    //   3325: dup
    //   3326: sipush 484
    //   3329: ldc 174
    //   3331: bastore
    //   3332: dup
    //   3333: sipush 485
    //   3336: ldc 201
    //   3338: bastore
    //   3339: dup
    //   3340: sipush 486
    //   3343: ldc_w 301
    //   3346: bastore
    //   3347: dup
    //   3348: sipush 487
    //   3351: ldc 175
    //   3353: bastore
    //   3354: dup
    //   3355: sipush 488
    //   3358: ldc_w 302
    //   3361: bastore
    //   3362: dup
    //   3363: sipush 489
    //   3366: ldc 146
    //   3368: bastore
    //   3369: dup
    //   3370: sipush 490
    //   3373: ldc 202
    //   3375: bastore
    //   3376: dup
    //   3377: sipush 491
    //   3380: ldc 223
    //   3382: bastore
    //   3383: dup
    //   3384: sipush 492
    //   3387: ldc_w 292
    //   3390: bastore
    //   3391: dup
    //   3392: sipush 493
    //   3395: ldc 247
    //   3397: bastore
    //   3398: dup
    //   3399: sipush 494
    //   3402: ldc 231
    //   3404: bastore
    //   3405: dup
    //   3406: sipush 495
    //   3409: ldc 146
    //   3411: bastore
    //   3412: dup
    //   3413: sipush 496
    //   3416: ldc_w 293
    //   3419: bastore
    //   3420: dup
    //   3421: sipush 497
    //   3424: ldc_w 294
    //   3427: bastore
    //   3428: dup
    //   3429: sipush 498
    //   3432: ldc_w 295
    //   3435: bastore
    //   3436: dup
    //   3437: sipush 499
    //   3440: ldc_w 296
    //   3443: bastore
    //   3444: dup
    //   3445: sipush 500
    //   3448: ldc 174
    //   3450: bastore
    //   3451: dup
    //   3452: sipush 501
    //   3455: ldc 202
    //   3457: bastore
    //   3458: dup
    //   3459: sipush 502
    //   3462: ldc 222
    //   3464: bastore
    //   3465: dup
    //   3466: sipush 503
    //   3469: ldc_w 277
    //   3472: bastore
    //   3473: dup
    //   3474: sipush 504
    //   3477: ldc_w 297
    //   3480: bastore
    //   3481: dup
    //   3482: sipush 505
    //   3485: ldc_w 298
    //   3488: bastore
    //   3489: dup
    //   3490: sipush 506
    //   3493: ldc_w 280
    //   3496: bastore
    //   3497: dup
    //   3498: sipush 507
    //   3501: ldc_w 299
    //   3504: bastore
    //   3505: dup
    //   3506: sipush 508
    //   3509: ldc 191
    //   3511: bastore
    //   3512: dup
    //   3513: sipush 509
    //   3516: ldc_w 300
    //   3519: bastore
    //   3520: dup
    //   3521: sipush 510
    //   3524: ldc 165
    //   3526: bastore
    //   3527: dup
    //   3528: sipush 511
    //   3531: ldc_w 295
    //   3534: bastore
    //   3535: dup
    //   3536: sipush 512
    //   3539: ldc_w 299
    //   3542: bastore
    //   3543: dup
    //   3544: sipush 513
    //   3547: ldc 146
    //   3549: bastore
    //   3550: dup
    //   3551: sipush 514
    //   3554: ldc 181
    //   3556: bastore
    //   3557: dup
    //   3558: sipush 515
    //   3561: ldc 165
    //   3563: bastore
    //   3564: dup
    //   3565: sipush 516
    //   3568: ldc 152
    //   3570: bastore
    //   3571: dup
    //   3572: sipush 517
    //   3575: ldc 174
    //   3577: bastore
    //   3578: dup
    //   3579: sipush 518
    //   3582: ldc 201
    //   3584: bastore
    //   3585: dup
    //   3586: sipush 519
    //   3589: ldc 176
    //   3591: bastore
    //   3592: dup
    //   3593: sipush 520
    //   3596: ldc 175
    //   3598: bastore
    //   3599: dup
    //   3600: sipush 521
    //   3603: ldc 170
    //   3605: bastore
    //   3606: dup
    //   3607: sipush 522
    //   3610: ldc 146
    //   3612: bastore
    //   3613: dup
    //   3614: sipush 523
    //   3617: ldc 152
    //   3619: bastore
    //   3620: dup
    //   3621: sipush 524
    //   3624: ldc 153
    //   3626: bastore
    //   3627: dup
    //   3628: sipush 525
    //   3631: ldc 153
    //   3633: bastore
    //   3634: dup
    //   3635: sipush 526
    //   3638: ldc_w 303
    //   3641: bastore
    //   3642: dup
    //   3643: sipush 527
    //   3646: ldc 146
    //   3648: bastore
    //   3649: dup
    //   3650: sipush 528
    //   3653: ldc 164
    //   3655: bastore
    //   3656: dup
    //   3657: sipush 529
    //   3660: ldc 165
    //   3662: bastore
    //   3663: dup
    //   3664: sipush 530
    //   3667: ldc 154
    //   3669: bastore
    //   3670: dup
    //   3671: sipush 531
    //   3674: ldc 166
    //   3676: bastore
    //   3677: dup
    //   3678: sipush 532
    //   3681: ldc 167
    //   3683: bastore
    //   3684: dup
    //   3685: sipush 533
    //   3688: ldc 168
    //   3690: bastore
    //   3691: dup
    //   3692: sipush 534
    //   3695: ldc 167
    //   3697: bastore
    //   3698: dup
    //   3699: sipush 535
    //   3702: ldc 169
    //   3704: bastore
    //   3705: dup
    //   3706: sipush 536
    //   3709: ldc 164
    //   3711: bastore
    //   3712: dup
    //   3713: sipush 537
    //   3716: ldc 153
    //   3718: bastore
    //   3719: dup
    //   3720: sipush 538
    //   3723: ldc 153
    //   3725: bastore
    //   3726: dup
    //   3727: sipush 539
    //   3730: ldc 170
    //   3732: bastore
    //   3733: dup
    //   3734: sipush 540
    //   3737: ldc 170
    //   3739: bastore
    //   3740: dup
    //   3741: sipush 541
    //   3744: ldc 155
    //   3746: bastore
    //   3747: dup
    //   3748: sipush 542
    //   3751: ldc 152
    //   3753: bastore
    //   3754: dup
    //   3755: sipush 543
    //   3758: ldc 217
    //   3760: bastore
    //   3761: dup
    //   3762: sipush 544
    //   3765: ldc 217
    //   3767: bastore
    //   3768: dup
    //   3769: sipush 545
    //   3772: ldc 155
    //   3774: bastore
    //   3775: dup
    //   3776: sipush 546
    //   3779: ldc_w 265
    //   3782: bastore
    //   3783: dup
    //   3784: sipush 547
    //   3787: ldc_w 304
    //   3790: bastore
    //   3791: dup
    //   3792: sipush 548
    //   3795: ldc 213
    //   3797: bastore
    //   3798: dup
    //   3799: sipush 549
    //   3802: ldc 232
    //   3804: bastore
    //   3805: dup
    //   3806: sipush 550
    //   3809: ldc_w 258
    //   3812: bastore
    //   3813: dup
    //   3814: sipush 551
    //   3817: ldc 223
    //   3819: bastore
    //   3820: dup
    //   3821: sipush 552
    //   3824: ldc 157
    //   3826: bastore
    //   3827: dup
    //   3828: sipush 553
    //   3831: ldc_w 305
    //   3834: bastore
    //   3835: dup
    //   3836: sipush 554
    //   3839: ldc_w 264
    //   3842: bastore
    //   3843: dup
    //   3844: sipush 555
    //   3847: ldc_w 306
    //   3850: bastore
    //   3851: dup
    //   3852: sipush 556
    //   3855: ldc 152
    //   3857: bastore
    //   3858: dup
    //   3859: sipush 557
    //   3862: ldc_w 289
    //   3865: bastore
    //   3866: dup
    //   3867: sipush 558
    //   3870: ldc_w 279
    //   3873: bastore
    //   3874: dup
    //   3875: sipush 559
    //   3878: ldc 205
    //   3880: bastore
    //   3881: dup
    //   3882: sipush 560
    //   3885: ldc_w 307
    //   3888: bastore
    //   3889: dup
    //   3890: sipush 561
    //   3893: ldc 224
    //   3895: bastore
    //   3896: dup
    //   3897: sipush 562
    //   3900: ldc_w 308
    //   3903: bastore
    //   3904: dup
    //   3905: sipush 563
    //   3908: ldc 147
    //   3910: bastore
    //   3911: dup
    //   3912: sipush 564
    //   3915: ldc 180
    //   3917: bastore
    //   3918: dup
    //   3919: sipush 565
    //   3922: ldc 203
    //   3924: bastore
    //   3925: dup
    //   3926: sipush 566
    //   3929: ldc_w 278
    //   3932: bastore
    //   3933: dup
    //   3934: sipush 567
    //   3937: ldc_w 286
    //   3940: bastore
    //   3941: dup
    //   3942: sipush 568
    //   3945: ldc_w 309
    //   3948: bastore
    //   3949: dup
    //   3950: sipush 569
    //   3953: ldc 224
    //   3955: bastore
    //   3956: dup
    //   3957: sipush 570
    //   3960: ldc 167
    //   3962: bastore
    //   3963: dup
    //   3964: sipush 571
    //   3967: ldc 228
    //   3969: bastore
    //   3970: dup
    //   3971: sipush 572
    //   3974: ldc 176
    //   3976: bastore
    //   3977: dup
    //   3978: sipush 573
    //   3981: ldc_w 310
    //   3984: bastore
    //   3985: dup
    //   3986: sipush 574
    //   3989: ldc_w 307
    //   3992: bastore
    //   3993: dup
    //   3994: sipush 575
    //   3997: ldc 215
    //   3999: bastore
    //   4000: dup
    //   4001: sipush 576
    //   4004: ldc 174
    //   4006: bastore
    //   4007: dup
    //   4008: sipush 577
    //   4011: ldc_w 311
    //   4014: bastore
    //   4015: dup
    //   4016: sipush 578
    //   4019: ldc_w 312
    //   4022: bastore
    //   4023: dup
    //   4024: sipush 579
    //   4027: ldc_w 257
    //   4030: bastore
    //   4031: dup
    //   4032: sipush 580
    //   4035: ldc_w 280
    //   4038: bastore
    //   4039: dup
    //   4040: sipush 581
    //   4043: ldc 193
    //   4045: bastore
    //   4046: dup
    //   4047: sipush 582
    //   4050: ldc_w 313
    //   4053: bastore
    //   4054: dup
    //   4055: sipush 583
    //   4058: ldc_w 265
    //   4061: bastore
    //   4062: dup
    //   4063: sipush 584
    //   4066: ldc_w 287
    //   4069: bastore
    //   4070: dup
    //   4071: sipush 585
    //   4074: ldc_w 305
    //   4077: bastore
    //   4078: dup
    //   4079: sipush 586
    //   4082: ldc_w 314
    //   4085: bastore
    //   4086: dup
    //   4087: sipush 587
    //   4090: ldc 177
    //   4092: bastore
    //   4093: dup
    //   4094: sipush 588
    //   4097: ldc_w 314
    //   4100: bastore
    //   4101: dup
    //   4102: sipush 589
    //   4105: ldc_w 315
    //   4108: bastore
    //   4109: dup
    //   4110: sipush 590
    //   4113: ldc 188
    //   4115: bastore
    //   4116: dup
    //   4117: sipush 591
    //   4120: ldc_w 316
    //   4123: bastore
    //   4124: dup
    //   4125: sipush 592
    //   4128: ldc_w 317
    //   4131: bastore
    //   4132: dup
    //   4133: sipush 593
    //   4136: ldc 246
    //   4138: bastore
    //   4139: dup
    //   4140: sipush 594
    //   4143: ldc_w 268
    //   4146: bastore
    //   4147: dup
    //   4148: sipush 595
    //   4151: ldc 164
    //   4153: bastore
    //   4154: dup
    //   4155: sipush 596
    //   4158: ldc_w 318
    //   4161: bastore
    //   4162: dup
    //   4163: sipush 597
    //   4166: ldc 204
    //   4168: bastore
    //   4169: dup
    //   4170: sipush 598
    //   4173: ldc_w 297
    //   4176: bastore
    //   4177: dup
    //   4178: sipush 599
    //   4181: ldc_w 319
    //   4184: bastore
    //   4185: dup
    //   4186: sipush 600
    //   4189: ldc 152
    //   4191: bastore
    //   4192: dup
    //   4193: sipush 601
    //   4196: ldc_w 267
    //   4199: bastore
    //   4200: dup
    //   4201: sipush 602
    //   4204: ldc 232
    //   4206: bastore
    //   4207: dup
    //   4208: sipush 603
    //   4211: ldc 219
    //   4213: bastore
    //   4214: dup
    //   4215: sipush 604
    //   4218: ldc_w 320
    //   4221: bastore
    //   4222: dup
    //   4223: sipush 605
    //   4226: ldc_w 321
    //   4229: bastore
    //   4230: dup
    //   4231: sipush 606
    //   4234: ldc 159
    //   4236: bastore
    //   4237: dup
    //   4238: sipush 607
    //   4241: ldc_w 259
    //   4244: bastore
    //   4245: dup
    //   4246: sipush 608
    //   4249: ldc_w 322
    //   4252: bastore
    //   4253: dup
    //   4254: sipush 609
    //   4257: ldc_w 323
    //   4260: bastore
    //   4261: dup
    //   4262: sipush 610
    //   4265: ldc_w 324
    //   4268: bastore
    //   4269: dup
    //   4270: sipush 611
    //   4273: ldc 165
    //   4275: bastore
    //   4276: dup
    //   4277: sipush 612
    //   4280: ldc_w 325
    //   4283: bastore
    //   4284: dup
    //   4285: sipush 613
    //   4288: ldc 237
    //   4290: bastore
    //   4291: dup
    //   4292: sipush 614
    //   4295: ldc_w 326
    //   4298: bastore
    //   4299: dup
    //   4300: sipush 615
    //   4303: ldc_w 303
    //   4306: bastore
    //   4307: dup
    //   4308: sipush 616
    //   4311: ldc 174
    //   4313: bastore
    //   4314: dup
    //   4315: sipush 617
    //   4318: ldc_w 258
    //   4321: bastore
    //   4322: dup
    //   4323: sipush 618
    //   4326: ldc_w 324
    //   4329: bastore
    //   4330: dup
    //   4331: sipush 619
    //   4334: ldc 219
    //   4336: bastore
    //   4337: dup
    //   4338: sipush 620
    //   4341: ldc 158
    //   4343: bastore
    //   4344: dup
    //   4345: sipush 621
    //   4348: ldc 164
    //   4350: bastore
    //   4351: dup
    //   4352: sipush 622
    //   4355: ldc_w 327
    //   4358: bastore
    //   4359: dup
    //   4360: sipush 623
    //   4363: ldc_w 265
    //   4366: bastore
    //   4367: dup
    //   4368: sipush 624
    //   4371: ldc 155
    //   4373: bastore
    //   4374: dup
    //   4375: sipush 625
    //   4378: ldc 149
    //   4380: bastore
    //   4381: dup
    //   4382: sipush 626
    //   4385: ldc_w 264
    //   4388: bastore
    //   4389: dup
    //   4390: sipush 627
    //   4393: ldc 240
    //   4395: bastore
    //   4396: dup
    //   4397: sipush 628
    //   4400: ldc_w 328
    //   4403: bastore
    //   4404: dup
    //   4405: sipush 629
    //   4408: ldc_w 329
    //   4411: bastore
    //   4412: dup
    //   4413: sipush 630
    //   4416: ldc_w 330
    //   4419: bastore
    //   4420: dup
    //   4421: sipush 631
    //   4424: ldc_w 280
    //   4427: bastore
    //   4428: dup
    //   4429: sipush 632
    //   4432: ldc_w 269
    //   4435: bastore
    //   4436: dup
    //   4437: sipush 633
    //   4440: ldc_w 290
    //   4443: bastore
    //   4444: dup
    //   4445: sipush 634
    //   4448: ldc 174
    //   4450: bastore
    //   4451: dup
    //   4452: sipush 635
    //   4455: ldc_w 331
    //   4458: bastore
    //   4459: dup
    //   4460: sipush 636
    //   4463: ldc 222
    //   4465: bastore
    //   4466: dup
    //   4467: sipush 637
    //   4470: ldc_w 263
    //   4473: bastore
    //   4474: dup
    //   4475: sipush 638
    //   4478: ldc 193
    //   4480: bastore
    //   4481: dup
    //   4482: sipush 639
    //   4485: ldc_w 271
    //   4488: bastore
    //   4489: dup
    //   4490: sipush 640
    //   4493: ldc 222
    //   4495: bastore
    //   4496: dup
    //   4497: sipush 641
    //   4500: ldc_w 332
    //   4503: bastore
    //   4504: dup
    //   4505: sipush 642
    //   4508: ldc 221
    //   4510: bastore
    //   4511: dup
    //   4512: sipush 643
    //   4515: ldc 149
    //   4517: bastore
    //   4518: dup
    //   4519: sipush 644
    //   4522: ldc 196
    //   4524: bastore
    //   4525: dup
    //   4526: sipush 645
    //   4529: ldc_w 333
    //   4532: bastore
    //   4533: dup
    //   4534: sipush 646
    //   4537: ldc_w 299
    //   4540: bastore
    //   4541: dup
    //   4542: sipush 647
    //   4545: ldc_w 301
    //   4548: bastore
    //   4549: dup
    //   4550: sipush 648
    //   4553: ldc 220
    //   4555: bastore
    //   4556: dup
    //   4557: sipush 649
    //   4560: ldc 222
    //   4562: bastore
    //   4563: dup
    //   4564: sipush 650
    //   4567: ldc_w 334
    //   4570: bastore
    //   4571: dup
    //   4572: sipush 651
    //   4575: ldc 167
    //   4577: bastore
    //   4578: dup
    //   4579: sipush 652
    //   4582: ldc_w 335
    //   4585: bastore
    //   4586: dup
    //   4587: sipush 653
    //   4590: ldc 231
    //   4592: bastore
    //   4593: dup
    //   4594: sipush 654
    //   4597: ldc_w 301
    //   4600: bastore
    //   4601: dup
    //   4602: sipush 655
    //   4605: ldc_w 261
    //   4608: bastore
    //   4609: dup
    //   4610: sipush 656
    //   4613: ldc_w 336
    //   4616: bastore
    //   4617: dup
    //   4618: sipush 657
    //   4621: ldc 209
    //   4623: bastore
    //   4624: dup
    //   4625: sipush 658
    //   4628: ldc_w 268
    //   4631: bastore
    //   4632: dup
    //   4633: sipush 659
    //   4636: ldc_w 337
    //   4639: bastore
    //   4640: dup
    //   4641: sipush 660
    //   4644: ldc 192
    //   4646: bastore
    //   4647: dup
    //   4648: sipush 661
    //   4651: ldc_w 338
    //   4654: bastore
    //   4655: dup
    //   4656: sipush 662
    //   4659: ldc 211
    //   4661: bastore
    //   4662: dup
    //   4663: sipush 663
    //   4666: ldc 205
    //   4668: bastore
    //   4669: dup
    //   4670: sipush 664
    //   4673: ldc 204
    //   4675: bastore
    //   4676: dup
    //   4677: sipush 665
    //   4680: ldc 234
    //   4682: bastore
    //   4683: dup
    //   4684: sipush 666
    //   4687: ldc_w 257
    //   4690: bastore
    //   4691: dup
    //   4692: sipush 667
    //   4695: ldc_w 257
    //   4698: bastore
    //   4699: dup
    //   4700: sipush 668
    //   4703: ldc_w 268
    //   4706: bastore
    //   4707: dup
    //   4708: sipush 669
    //   4711: ldc 199
    //   4713: bastore
    //   4714: dup
    //   4715: sipush 670
    //   4718: ldc_w 339
    //   4721: bastore
    //   4722: dup
    //   4723: sipush 671
    //   4726: ldc_w 340
    //   4729: bastore
    //   4730: dup
    //   4731: sipush 672
    //   4734: ldc 248
    //   4736: bastore
    //   4737: dup
    //   4738: sipush 673
    //   4741: ldc_w 280
    //   4744: bastore
    //   4745: invokespecial 343	java/io/ByteArrayInputStream:<init>	([B)V
    //   4748: astore_0
    //   4749: aload_0
    //   4750: astore_1
    //   4751: ldc_w 345
    //   4754: invokestatic 351	java/security/cert/CertificateFactory:getInstance	(Ljava/lang/String;)Ljava/security/cert/CertificateFactory;
    //   4757: astore 5
    //   4759: aload_0
    //   4760: astore_1
    //   4761: ldc_w 353
    //   4764: invokestatic 358	java/security/KeyFactory:getInstance	(Ljava/lang/String;)Ljava/security/KeyFactory;
    //   4767: astore_2
    //   4768: aload_0
    //   4769: astore_1
    //   4770: aload 5
    //   4772: aload_0
    //   4773: invokevirtual 362	java/security/cert/CertificateFactory:generateCertificate	(Ljava/io/InputStream;)Ljava/security/cert/Certificate;
    //   4776: astore 5
    //   4778: aload 5
    //   4780: ifnull +7 -> 4787
    //   4783: aload_2
    //   4784: ifnonnull +18 -> 4802
    //   4787: aload 4
    //   4789: astore_1
    //   4790: aload_0
    //   4791: ifnull +9 -> 4800
    //   4794: aload_3
    //   4795: astore_1
    //   4796: aload_0
    //   4797: invokevirtual 365	java/io/InputStream:close	()V
    //   4800: aload_1
    //   4801: areturn
    //   4802: aload_0
    //   4803: astore_1
    //   4804: aload_2
    //   4805: new 367	java/security/spec/X509EncodedKeySpec
    //   4808: dup
    //   4809: aload 5
    //   4811: invokevirtual 373	java/security/cert/Certificate:getPublicKey	()Ljava/security/PublicKey;
    //   4814: invokeinterface 379 1 0
    //   4819: invokespecial 380	java/security/spec/X509EncodedKeySpec:<init>	([B)V
    //   4822: invokevirtual 384	java/security/KeyFactory:generatePublic	(Ljava/security/spec/KeySpec;)Ljava/security/PublicKey;
    //   4825: astore_2
    //   4826: aload_2
    //   4827: astore_1
    //   4828: aload_0
    //   4829: ifnull -29 -> 4800
    //   4832: aload_2
    //   4833: astore_1
    //   4834: goto -38 -> 4796
    //   4837: astore_2
    //   4838: aconst_null
    //   4839: astore_0
    //   4840: aload_0
    //   4841: astore_1
    //   4842: aload_2
    //   4843: invokevirtual 89	java/lang/Throwable:printStackTrace	()V
    //   4846: aload 4
    //   4848: astore_1
    //   4849: aload_0
    //   4850: ifnull -50 -> 4800
    //   4853: aload_3
    //   4854: astore_1
    //   4855: goto -59 -> 4796
    //   4858: astore_0
    //   4859: aconst_null
    //   4860: astore_1
    //   4861: aload_1
    //   4862: ifnull +7 -> 4869
    //   4865: aload_1
    //   4866: invokevirtual 365	java/io/InputStream:close	()V
    //   4869: aload_0
    //   4870: athrow
    //   4871: astore_0
    //   4872: goto -11 -> 4861
    //   4875: astore_2
    //   4876: goto -36 -> 4840
    //
    // Exception table:
    //   from	to	target	type
    //   5	4749	4837	java/lang/Throwable
    //   5	4749	4858	finally
    //   4751	4759	4871	finally
    //   4761	4768	4871	finally
    //   4770	4778	4871	finally
    //   4804	4826	4871	finally
    //   4842	4846	4871	finally
    //   4751	4759	4875	java/lang/Throwable
    //   4761	4768	4875	java/lang/Throwable
    //   4770	4778	4875	java/lang/Throwable
    //   4804	4826	4875	java/lang/Throwable
  }

  public static boolean a(JSONObject paramJSONObject, String paramString)
  {
    return (paramJSONObject != null) && (paramJSONObject.has(paramString));
  }

  public static byte[] a()
  {
    int j = 0;
    try
    {
      Object localObject = new StringBuffer("16,16,18,77,15,911,121,77,121,911,38,77,911,99,86,67,611,96,48,77,84,911,38,67,021,301,86,67,611,98,48,77,511,77,48,97,511,58,48,97,511,84,501,87,511,96,48,77,221,911,38,77,121,37,86,67,25,301,86,67,021,96,86,67,021,701,86,67,35,56,86,67,611,37,221,87").reverse().toString().split(",");
      byte[] arrayOfByte2 = new byte[localObject.length];
      int i = 0;
      while (i < localObject.length)
      {
        arrayOfByte2[i] = Byte.parseByte(localObject[i]);
        i += 1;
      }
      String[] arrayOfString = new StringBuffer(new String(ao.b(new String(arrayOfByte2)))).reverse().toString().split(",");
      arrayOfByte2 = new byte[arrayOfString.length];
      i = j;
      while (true)
      {
        localObject = arrayOfByte2;
        if (i >= arrayOfString.length)
          break;
        arrayOfByte2[i] = Byte.parseByte(arrayOfString[i]);
        i += 1;
      }
    }
    catch (Throwable localThrowable)
    {
      ay.a(localThrowable, "Utils", "getIV");
      byte[] arrayOfByte1 = new byte[16];
      return arrayOfByte1;
    }
  }

  public static byte[] a(byte[] paramArrayOfByte)
  {
    try
    {
      paramArrayOfByte = f(paramArrayOfByte);
      return paramArrayOfByte;
    }
    catch (IOException paramArrayOfByte)
    {
      ay.a(paramArrayOfByte, "Utils", "gZip");
      return new byte[0];
    }
    catch (Throwable paramArrayOfByte)
    {
      while (true)
        ay.a(paramArrayOfByte, "Utils", "gZip");
    }
  }

  public static String b(Map<String, String> paramMap)
  {
    return a(a(paramMap));
  }

  // ERROR //
  public static byte[] b(byte[] paramArrayOfByte)
  {
    // Byte code:
    //   0: aconst_null
    //   1: astore 6
    //   3: aconst_null
    //   4: astore 7
    //   6: aload 7
    //   8: astore_2
    //   9: aload_0
    //   10: ifnull +11 -> 21
    //   13: aload_0
    //   14: arraylength
    //   15: ifne +8 -> 23
    //   18: aload 7
    //   20: astore_2
    //   21: aload_2
    //   22: areturn
    //   23: new 430	java/io/ByteArrayOutputStream
    //   26: dup
    //   27: invokespecial 431	java/io/ByteArrayOutputStream:<init>	()V
    //   30: astore_1
    //   31: new 433	java/util/zip/ZipOutputStream
    //   34: dup
    //   35: aload_1
    //   36: invokespecial 436	java/util/zip/ZipOutputStream:<init>	(Ljava/io/OutputStream;)V
    //   39: astore 5
    //   41: aload_1
    //   42: astore_3
    //   43: aload 5
    //   45: astore_2
    //   46: aload 5
    //   48: new 438	java/util/zip/ZipEntry
    //   51: dup
    //   52: ldc_w 440
    //   55: invokespecial 441	java/util/zip/ZipEntry:<init>	(Ljava/lang/String;)V
    //   58: invokevirtual 445	java/util/zip/ZipOutputStream:putNextEntry	(Ljava/util/zip/ZipEntry;)V
    //   61: aload_1
    //   62: astore_3
    //   63: aload 5
    //   65: astore_2
    //   66: aload 5
    //   68: aload_0
    //   69: invokevirtual 448	java/util/zip/ZipOutputStream:write	([B)V
    //   72: aload_1
    //   73: astore_3
    //   74: aload 5
    //   76: astore_2
    //   77: aload 5
    //   79: invokevirtual 451	java/util/zip/ZipOutputStream:closeEntry	()V
    //   82: aload_1
    //   83: astore_3
    //   84: aload 5
    //   86: astore_2
    //   87: aload 5
    //   89: invokevirtual 454	java/util/zip/ZipOutputStream:finish	()V
    //   92: aload_1
    //   93: astore_3
    //   94: aload 5
    //   96: astore_2
    //   97: aload_1
    //   98: invokevirtual 457	java/io/ByteArrayOutputStream:toByteArray	()[B
    //   101: astore_0
    //   102: aload 5
    //   104: ifnull +8 -> 112
    //   107: aload 5
    //   109: invokevirtual 458	java/util/zip/ZipOutputStream:close	()V
    //   112: aload_0
    //   113: astore_2
    //   114: aload_1
    //   115: ifnull -94 -> 21
    //   118: aload_1
    //   119: invokevirtual 459	java/io/ByteArrayOutputStream:close	()V
    //   122: aload_0
    //   123: areturn
    //   124: astore_1
    //   125: aload_1
    //   126: ldc 56
    //   128: ldc_w 461
    //   131: invokestatic 63	com/amap/api/services/core/ay:a	(Ljava/lang/Throwable;Ljava/lang/String;Ljava/lang/String;)V
    //   134: aload_1
    //   135: invokevirtual 89	java/lang/Throwable:printStackTrace	()V
    //   138: aload_0
    //   139: areturn
    //   140: astore 4
    //   142: aconst_null
    //   143: astore_1
    //   144: aconst_null
    //   145: astore_0
    //   146: aload_1
    //   147: astore_3
    //   148: aload_0
    //   149: astore_2
    //   150: aload 4
    //   152: ldc 56
    //   154: ldc_w 463
    //   157: invokestatic 63	com/amap/api/services/core/ay:a	(Ljava/lang/Throwable;Ljava/lang/String;Ljava/lang/String;)V
    //   160: aload_0
    //   161: ifnull +7 -> 168
    //   164: aload_0
    //   165: invokevirtual 458	java/util/zip/ZipOutputStream:close	()V
    //   168: aload 7
    //   170: astore_2
    //   171: aload_1
    //   172: ifnull -151 -> 21
    //   175: aload_1
    //   176: invokevirtual 459	java/io/ByteArrayOutputStream:close	()V
    //   179: aconst_null
    //   180: areturn
    //   181: astore_1
    //   182: aload_1
    //   183: ldc 56
    //   185: ldc_w 461
    //   188: invokestatic 63	com/amap/api/services/core/ay:a	(Ljava/lang/Throwable;Ljava/lang/String;Ljava/lang/String;)V
    //   191: aload 6
    //   193: astore_0
    //   194: goto -60 -> 134
    //   197: astore_0
    //   198: aconst_null
    //   199: astore_1
    //   200: aconst_null
    //   201: astore_2
    //   202: aload_2
    //   203: ifnull +7 -> 210
    //   206: aload_2
    //   207: invokevirtual 458	java/util/zip/ZipOutputStream:close	()V
    //   210: aload_1
    //   211: ifnull +7 -> 218
    //   214: aload_1
    //   215: invokevirtual 459	java/io/ByteArrayOutputStream:close	()V
    //   218: aload_0
    //   219: athrow
    //   220: astore_2
    //   221: aload_2
    //   222: ldc 56
    //   224: ldc_w 465
    //   227: invokestatic 63	com/amap/api/services/core/ay:a	(Ljava/lang/Throwable;Ljava/lang/String;Ljava/lang/String;)V
    //   230: aload_2
    //   231: invokevirtual 89	java/lang/Throwable:printStackTrace	()V
    //   234: goto -24 -> 210
    //   237: astore_1
    //   238: aload_1
    //   239: ldc 56
    //   241: ldc_w 461
    //   244: invokestatic 63	com/amap/api/services/core/ay:a	(Ljava/lang/Throwable;Ljava/lang/String;Ljava/lang/String;)V
    //   247: aload_1
    //   248: invokevirtual 89	java/lang/Throwable:printStackTrace	()V
    //   251: goto -33 -> 218
    //   254: astore_0
    //   255: aload_0
    //   256: ldc 56
    //   258: ldc_w 465
    //   261: invokestatic 63	com/amap/api/services/core/ay:a	(Ljava/lang/Throwable;Ljava/lang/String;Ljava/lang/String;)V
    //   264: aload_0
    //   265: invokevirtual 89	java/lang/Throwable:printStackTrace	()V
    //   268: goto -100 -> 168
    //   271: astore_2
    //   272: aload_2
    //   273: ldc 56
    //   275: ldc_w 465
    //   278: invokestatic 63	com/amap/api/services/core/ay:a	(Ljava/lang/Throwable;Ljava/lang/String;Ljava/lang/String;)V
    //   281: aload_2
    //   282: invokevirtual 89	java/lang/Throwable:printStackTrace	()V
    //   285: goto -173 -> 112
    //   288: astore_0
    //   289: aconst_null
    //   290: astore_2
    //   291: goto -89 -> 202
    //   294: astore_0
    //   295: aload_3
    //   296: astore_1
    //   297: goto -95 -> 202
    //   300: astore 4
    //   302: aconst_null
    //   303: astore_0
    //   304: goto -158 -> 146
    //   307: astore 4
    //   309: aload 5
    //   311: astore_0
    //   312: goto -166 -> 146
    //
    // Exception table:
    //   from	to	target	type
    //   118	122	124	java/lang/Throwable
    //   23	31	140	java/lang/Throwable
    //   175	179	181	java/lang/Throwable
    //   23	31	197	finally
    //   206	210	220	java/lang/Throwable
    //   214	218	237	java/lang/Throwable
    //   164	168	254	java/lang/Throwable
    //   107	112	271	java/lang/Throwable
    //   31	41	288	finally
    //   46	61	294	finally
    //   66	72	294	finally
    //   77	82	294	finally
    //   87	92	294	finally
    //   97	102	294	finally
    //   150	160	294	finally
    //   31	41	300	java/lang/Throwable
    //   46	61	307	java/lang/Throwable
    //   66	72	307	java/lang/Throwable
    //   77	82	307	java/lang/Throwable
    //   87	92	307	java/lang/Throwable
    //   97	102	307	java/lang/Throwable
  }

  static String c(byte[] paramArrayOfByte)
  {
    try
    {
      paramArrayOfByte = e(paramArrayOfByte);
      return paramArrayOfByte;
    }
    catch (Throwable paramArrayOfByte)
    {
      ay.a(paramArrayOfByte, "Utils", "HexString");
    }
    return null;
  }

  static String d(byte[] paramArrayOfByte)
  {
    try
    {
      paramArrayOfByte = e(paramArrayOfByte);
      return paramArrayOfByte;
    }
    catch (Throwable paramArrayOfByte)
    {
      paramArrayOfByte.printStackTrace();
    }
    return null;
  }

  public static String e(byte[] paramArrayOfByte)
  {
    StringBuilder localStringBuilder = new StringBuilder();
    if (paramArrayOfByte == null)
      return null;
    int i = 0;
    while (i < paramArrayOfByte.length)
    {
      String str2 = Integer.toHexString(paramArrayOfByte[i] & 0xFF);
      String str1 = str2;
      if (str2.length() == 1)
        str1 = "0" + str2;
      localStringBuilder.append(str1);
      i += 1;
    }
    return localStringBuilder.toString();
  }

  // ERROR //
  private static byte[] f(byte[] paramArrayOfByte)
    throws IOException, Throwable
  {
    // Byte code:
    //   0: aconst_null
    //   1: astore_2
    //   2: aload_0
    //   3: ifnonnull +5 -> 8
    //   6: aload_2
    //   7: areturn
    //   8: new 430	java/io/ByteArrayOutputStream
    //   11: dup
    //   12: invokespecial 431	java/io/ByteArrayOutputStream:<init>	()V
    //   15: astore_1
    //   16: new 484	java/util/zip/GZIPOutputStream
    //   19: dup
    //   20: aload_1
    //   21: invokespecial 485	java/util/zip/GZIPOutputStream:<init>	(Ljava/io/OutputStream;)V
    //   24: astore 4
    //   26: aload 4
    //   28: astore_2
    //   29: aload_1
    //   30: astore_3
    //   31: aload 4
    //   33: aload_0
    //   34: invokevirtual 486	java/util/zip/GZIPOutputStream:write	([B)V
    //   37: aload 4
    //   39: astore_2
    //   40: aload_1
    //   41: astore_3
    //   42: aload 4
    //   44: invokevirtual 487	java/util/zip/GZIPOutputStream:finish	()V
    //   47: aload 4
    //   49: astore_2
    //   50: aload_1
    //   51: astore_3
    //   52: aload_1
    //   53: invokevirtual 457	java/io/ByteArrayOutputStream:toByteArray	()[B
    //   56: astore_0
    //   57: aload 4
    //   59: ifnull +8 -> 67
    //   62: aload 4
    //   64: invokevirtual 488	java/util/zip/GZIPOutputStream:close	()V
    //   67: aload_0
    //   68: astore_2
    //   69: aload_1
    //   70: ifnull -64 -> 6
    //   73: aload_1
    //   74: invokevirtual 459	java/io/ByteArrayOutputStream:close	()V
    //   77: aload_0
    //   78: areturn
    //   79: astore_0
    //   80: aload_0
    //   81: athrow
    //   82: astore_0
    //   83: aconst_null
    //   84: astore_1
    //   85: aconst_null
    //   86: astore_2
    //   87: aload_1
    //   88: astore_3
    //   89: aload_0
    //   90: athrow
    //   91: astore_0
    //   92: aload_3
    //   93: astore_1
    //   94: aload_2
    //   95: ifnull +7 -> 102
    //   98: aload_2
    //   99: invokevirtual 488	java/util/zip/GZIPOutputStream:close	()V
    //   102: aload_1
    //   103: ifnull +7 -> 110
    //   106: aload_1
    //   107: invokevirtual 459	java/io/ByteArrayOutputStream:close	()V
    //   110: aload_0
    //   111: athrow
    //   112: astore_0
    //   113: aconst_null
    //   114: astore_1
    //   115: aconst_null
    //   116: astore_2
    //   117: aload_1
    //   118: astore_3
    //   119: aload_0
    //   120: athrow
    //   121: astore_0
    //   122: aload_0
    //   123: athrow
    //   124: astore_0
    //   125: aload_0
    //   126: athrow
    //   127: astore_0
    //   128: aload_0
    //   129: athrow
    //   130: astore_0
    //   131: aconst_null
    //   132: astore_1
    //   133: aconst_null
    //   134: astore_2
    //   135: goto -41 -> 94
    //   138: astore_0
    //   139: aconst_null
    //   140: astore_2
    //   141: goto -47 -> 94
    //   144: astore_0
    //   145: aconst_null
    //   146: astore_2
    //   147: goto -30 -> 117
    //   150: astore_0
    //   151: aload 4
    //   153: astore_2
    //   154: goto -37 -> 117
    //   157: astore_0
    //   158: aconst_null
    //   159: astore_2
    //   160: goto -73 -> 87
    //   163: astore_0
    //   164: aload 4
    //   166: astore_2
    //   167: goto -80 -> 87
    //
    // Exception table:
    //   from	to	target	type
    //   73	77	79	java/lang/Throwable
    //   8	16	82	java/io/IOException
    //   31	37	91	finally
    //   42	47	91	finally
    //   52	57	91	finally
    //   89	91	91	finally
    //   119	121	91	finally
    //   8	16	112	java/lang/Throwable
    //   98	102	121	java/lang/Throwable
    //   106	110	124	java/lang/Throwable
    //   62	67	127	java/lang/Throwable
    //   8	16	130	finally
    //   16	26	138	finally
    //   16	26	144	java/lang/Throwable
    //   31	37	150	java/lang/Throwable
    //   42	47	150	java/lang/Throwable
    //   52	57	150	java/lang/Throwable
    //   16	26	157	java/io/IOException
    //   31	37	163	java/io/IOException
    //   42	47	163	java/io/IOException
    //   52	57	163	java/io/IOException
  }
}

/* Location:           C:\crazyd\work\ustone\odm2016031702\baidu\android\nut-dex2jar.jar
 * Qualified Name:     com.amap.api.services.core.as
 * JD-Core Version:    0.6.2
 */