package com.amap.api.services.core;

import android.content.Context;

class av$1
  implements Runnable
{
  av$1(av paramav, Context paramContext, ar paramar, boolean paramBoolean)
  {
  }

  // ERROR //
  public void run()
  {
    // Byte code:
    //   0: invokestatic 37	android/os/Looper:getMainLooper	()Landroid/os/Looper;
    //   3: astore_1
    //   4: aload_1
    //   5: monitorenter
    //   6: new 39	com/amap/api/services/core/bt
    //   9: dup
    //   10: aload_0
    //   11: getfield 20	com/amap/api/services/core/av$1:a	Landroid/content/Context;
    //   14: iconst_1
    //   15: invokespecial 42	com/amap/api/services/core/bt:<init>	(Landroid/content/Context;Z)V
    //   18: aload_0
    //   19: getfield 22	com/amap/api/services/core/av$1:b	Lcom/amap/api/services/core/ar;
    //   22: invokevirtual 45	com/amap/api/services/core/bt:a	(Lcom/amap/api/services/core/ar;)V
    //   25: aload_1
    //   26: monitorexit
    //   27: aload_0
    //   28: getfield 24	com/amap/api/services/core/av$1:c	Z
    //   31: ifeq +61 -> 92
    //   34: invokestatic 37	android/os/Looper:getMainLooper	()Landroid/os/Looper;
    //   37: astore_1
    //   38: aload_1
    //   39: monitorenter
    //   40: new 47	com/amap/api/services/core/bv
    //   43: dup
    //   44: aload_0
    //   45: getfield 20	com/amap/api/services/core/av$1:a	Landroid/content/Context;
    //   48: invokespecial 50	com/amap/api/services/core/bv:<init>	(Landroid/content/Context;)V
    //   51: astore_2
    //   52: new 52	com/amap/api/services/core/bx
    //   55: dup
    //   56: invokespecial 53	com/amap/api/services/core/bx:<init>	()V
    //   59: astore_3
    //   60: aload_3
    //   61: iconst_1
    //   62: invokevirtual 56	com/amap/api/services/core/bx:c	(Z)V
    //   65: aload_3
    //   66: iconst_1
    //   67: invokevirtual 58	com/amap/api/services/core/bx:a	(Z)V
    //   70: aload_3
    //   71: iconst_1
    //   72: invokevirtual 60	com/amap/api/services/core/bx:b	(Z)V
    //   75: aload_2
    //   76: aload_3
    //   77: invokevirtual 63	com/amap/api/services/core/bv:a	(Lcom/amap/api/services/core/bx;)V
    //   80: aload_1
    //   81: monitorexit
    //   82: aload_0
    //   83: getfield 18	com/amap/api/services/core/av$1:d	Lcom/amap/api/services/core/av;
    //   86: invokestatic 68	com/amap/api/services/core/av:a	(Lcom/amap/api/services/core/av;)Landroid/content/Context;
    //   89: invokestatic 72	com/amap/api/services/core/bd:a	(Landroid/content/Context;)V
    //   92: return
    //   93: astore_2
    //   94: aload_1
    //   95: monitorexit
    //   96: aload_2
    //   97: athrow
    //   98: astore_1
    //   99: aload_1
    //   100: invokevirtual 75	java/lang/Throwable:printStackTrace	()V
    //   103: return
    //   104: astore_2
    //   105: aload_1
    //   106: monitorexit
    //   107: aload_2
    //   108: athrow
    //
    // Exception table:
    //   from	to	target	type
    //   6	27	93	finally
    //   94	96	93	finally
    //   0	6	98	java/lang/Throwable
    //   27	40	98	java/lang/Throwable
    //   82	92	98	java/lang/Throwable
    //   96	98	98	java/lang/Throwable
    //   107	109	98	java/lang/Throwable
    //   40	82	104	finally
    //   105	107	104	finally
  }
}

/* Location:           C:\crazyd\work\ustone\odm2016031702\baidu\android\nut-dex2jar.jar
 * Qualified Name:     com.amap.api.services.core.av.1
 * JD-Core Version:    0.6.2
 */