package com.amap.api.mapcore2d;

class f extends Thread
{
  f(b paramb)
  {
  }

  // ERROR //
  public void run()
  {
    // Byte code:
    //   0: new 21	android/os/Message
    //   3: dup
    //   4: invokespecial 22	android/os/Message:<init>	()V
    //   7: astore_1
    //   8: invokestatic 28	com/amap/api/maps2d/MapsInitializer:getNetworkEnable	()Z
    //   11: ifne +30 -> 41
    //   14: ldc2_w 29
    //   17: invokestatic 34	java/lang/Thread:sleep	(J)V
    //   20: goto -12 -> 8
    //   23: astore_2
    //   24: aload_2
    //   25: ldc 36
    //   27: ldc 37
    //   29: invokestatic 42	com/amap/api/mapcore2d/cz:a	(Ljava/lang/Throwable;Ljava/lang/String;Ljava/lang/String;)V
    //   32: invokestatic 46	java/lang/Thread:currentThread	()Ljava/lang/Thread;
    //   35: invokevirtual 49	java/lang/Thread:interrupt	()V
    //   38: goto -30 -> 8
    //   41: aload_1
    //   42: new 51	com/amap/api/mapcore2d/aw
    //   45: dup
    //   46: aload_0
    //   47: getfield 10	com/amap/api/mapcore2d/f:a	Lcom/amap/api/mapcore2d/b;
    //   50: invokestatic 57	com/amap/api/mapcore2d/b:d	(Lcom/amap/api/mapcore2d/b;)Landroid/content/Context;
    //   53: invokespecial 60	com/amap/api/mapcore2d/aw:<init>	(Landroid/content/Context;)V
    //   56: invokevirtual 63	com/amap/api/mapcore2d/aw:a	()Lcom/amap/api/mapcore2d/ax;
    //   59: putfield 67	android/os/Message:obj	Ljava/lang/Object;
    //   62: aload_1
    //   63: iconst_3
    //   64: putfield 71	android/os/Message:what	I
    //   67: aload_0
    //   68: getfield 10	com/amap/api/mapcore2d/f:a	Lcom/amap/api/mapcore2d/b;
    //   71: getfield 75	com/amap/api/mapcore2d/b:k	Landroid/os/Handler;
    //   74: aload_1
    //   75: invokevirtual 81	android/os/Handler:sendMessage	(Landroid/os/Message;)Z
    //   78: pop
    //   79: aload_0
    //   80: getfield 10	com/amap/api/mapcore2d/f:a	Lcom/amap/api/mapcore2d/b;
    //   83: invokestatic 57	com/amap/api/mapcore2d/b:d	(Lcom/amap/api/mapcore2d/b;)Landroid/content/Context;
    //   86: iconst_1
    //   87: invokestatic 86	com/amap/api/mapcore2d/v:a	(Z)Lcom/amap/api/mapcore2d/di;
    //   90: invokestatic 91	com/amap/api/mapcore2d/dc:a	(Landroid/content/Context;Lcom/amap/api/mapcore2d/di;)Z
    //   93: pop
    //   94: getstatic 93	com/amap/api/mapcore2d/dc:a	I
    //   97: ifne +15 -> 112
    //   100: aload_0
    //   101: getfield 10	com/amap/api/mapcore2d/f:a	Lcom/amap/api/mapcore2d/b;
    //   104: getfield 75	com/amap/api/mapcore2d/b:k	Landroid/os/Handler;
    //   107: iconst_2
    //   108: invokevirtual 97	android/os/Handler:sendEmptyMessage	(I)Z
    //   111: pop
    //   112: return
    //   113: astore_2
    //   114: aload_2
    //   115: ldc 36
    //   117: ldc 37
    //   119: invokestatic 42	com/amap/api/mapcore2d/cz:a	(Ljava/lang/Throwable;Ljava/lang/String;Ljava/lang/String;)V
    //   122: aload_1
    //   123: iconst_3
    //   124: putfield 71	android/os/Message:what	I
    //   127: aload_0
    //   128: getfield 10	com/amap/api/mapcore2d/f:a	Lcom/amap/api/mapcore2d/b;
    //   131: getfield 75	com/amap/api/mapcore2d/b:k	Landroid/os/Handler;
    //   134: aload_1
    //   135: invokevirtual 81	android/os/Handler:sendMessage	(Landroid/os/Message;)Z
    //   138: pop
    //   139: goto -60 -> 79
    //   142: astore_2
    //   143: aload_1
    //   144: iconst_3
    //   145: putfield 71	android/os/Message:what	I
    //   148: aload_0
    //   149: getfield 10	com/amap/api/mapcore2d/f:a	Lcom/amap/api/mapcore2d/b;
    //   152: getfield 75	com/amap/api/mapcore2d/b:k	Landroid/os/Handler;
    //   155: aload_1
    //   156: invokevirtual 81	android/os/Handler:sendMessage	(Landroid/os/Message;)Z
    //   159: pop
    //   160: aload_2
    //   161: athrow
    //   162: astore_1
    //   163: aload_0
    //   164: invokevirtual 98	com/amap/api/mapcore2d/f:interrupt	()V
    //   167: aload_1
    //   168: ldc 36
    //   170: ldc 37
    //   172: invokestatic 42	com/amap/api/mapcore2d/cz:a	(Ljava/lang/Throwable;Ljava/lang/String;Ljava/lang/String;)V
    //   175: return
    //
    // Exception table:
    //   from	to	target	type
    //   14	20	23	java/lang/Exception
    //   41	62	113	java/lang/Throwable
    //   41	62	142	finally
    //   114	122	142	finally
    //   79	112	162	java/lang/Exception
  }
}

/* Location:           C:\crazyd\work\ustone\odm2016031702\baidu\android\nut-dex2jar.jar
 * Qualified Name:     com.amap.api.mapcore2d.f
 * JD-Core Version:    0.6.2
 */