package com.google.zxing.a;

import com.google.zxing.l;

public final class b
  implements l
{
  // ERROR //
  public final com.google.zxing.m a(com.google.zxing.c paramc, java.util.Map<com.google.zxing.d, ?> paramMap)
    throws com.google.zxing.NotFoundException, com.google.zxing.FormatException
  {
    // Byte code:
    //   0: aconst_null
    //   1: astore 5
    //   3: new 19	com/google/zxing/a/b/a
    //   6: dup
    //   7: aload_1
    //   8: invokevirtual 24	com/google/zxing/c:a	()Lcom/google/zxing/common/b;
    //   11: invokespecial 27	com/google/zxing/a/b/a:<init>	(Lcom/google/zxing/common/b;)V
    //   14: astore 7
    //   16: aload 7
    //   18: iconst_0
    //   19: invokevirtual 30	com/google/zxing/a/b/a:a	(Z)Lcom/google/zxing/a/a;
    //   22: astore_1
    //   23: aload_1
    //   24: getfield 36	com/google/zxing/common/g:e	[Lcom/google/zxing/o;
    //   27: astore_3
    //   28: new 38	com/google/zxing/a/a/a
    //   31: dup
    //   32: invokespecial 39	com/google/zxing/a/a/a:<init>	()V
    //   35: aload_1
    //   36: invokevirtual 42	com/google/zxing/a/a/a:a	(Lcom/google/zxing/a/a;)Lcom/google/zxing/common/e;
    //   39: astore_1
    //   40: aconst_null
    //   41: astore 4
    //   43: aload_1
    //   44: astore 6
    //   46: aload_1
    //   47: ifnonnull +28 -> 75
    //   50: aload 7
    //   52: iconst_1
    //   53: invokevirtual 30	com/google/zxing/a/b/a:a	(Z)Lcom/google/zxing/a/a;
    //   56: astore_1
    //   57: aload_1
    //   58: getfield 36	com/google/zxing/common/g:e	[Lcom/google/zxing/o;
    //   61: astore_3
    //   62: new 38	com/google/zxing/a/a/a
    //   65: dup
    //   66: invokespecial 39	com/google/zxing/a/a/a:<init>	()V
    //   69: aload_1
    //   70: invokevirtual 42	com/google/zxing/a/a/a:a	(Lcom/google/zxing/a/a;)Lcom/google/zxing/common/e;
    //   73: astore 6
    //   75: aload_2
    //   76: ifnull +13 -> 89
    //   79: aload_2
    //   80: getstatic 48	com/google/zxing/d:j	Lcom/google/zxing/d;
    //   83: invokeinterface 54 2 0
    //   88: pop
    //   89: new 56	com/google/zxing/m
    //   92: dup
    //   93: aload 6
    //   95: getfield 62	com/google/zxing/common/e:b	Ljava/lang/String;
    //   98: aload 6
    //   100: getfield 65	com/google/zxing/common/e:a	[B
    //   103: aload_3
    //   104: getstatic 70	com/google/zxing/a:a	Lcom/google/zxing/a;
    //   107: invokespecial 73	com/google/zxing/m:<init>	(Ljava/lang/String;[B[Lcom/google/zxing/o;Lcom/google/zxing/a;)V
    //   110: astore_1
    //   111: aload 6
    //   113: getfield 77	com/google/zxing/common/e:c	Ljava/util/List;
    //   116: astore_2
    //   117: aload_2
    //   118: ifnull +11 -> 129
    //   121: aload_1
    //   122: getstatic 82	com/google/zxing/n:c	Lcom/google/zxing/n;
    //   125: aload_2
    //   126: invokevirtual 85	com/google/zxing/m:a	(Lcom/google/zxing/n;Ljava/lang/Object;)V
    //   129: aload 6
    //   131: getfield 88	com/google/zxing/common/e:d	Ljava/lang/String;
    //   134: astore_2
    //   135: aload_2
    //   136: ifnull +11 -> 147
    //   139: aload_1
    //   140: getstatic 90	com/google/zxing/n:d	Lcom/google/zxing/n;
    //   143: aload_2
    //   144: invokevirtual 85	com/google/zxing/m:a	(Lcom/google/zxing/n;Ljava/lang/Object;)V
    //   147: aload_1
    //   148: areturn
    //   149: astore_1
    //   150: aconst_null
    //   151: astore_3
    //   152: aload_1
    //   153: astore 4
    //   155: aconst_null
    //   156: astore_1
    //   157: goto -114 -> 43
    //   160: astore_1
    //   161: aconst_null
    //   162: astore_3
    //   163: aconst_null
    //   164: astore 4
    //   166: aconst_null
    //   167: astore 6
    //   169: aload_1
    //   170: astore 5
    //   172: aload 6
    //   174: astore_1
    //   175: goto -132 -> 43
    //   178: astore_1
    //   179: aload 4
    //   181: ifnull +6 -> 187
    //   184: aload 4
    //   186: athrow
    //   187: aload 5
    //   189: ifnull +6 -> 195
    //   192: aload 5
    //   194: athrow
    //   195: aload_1
    //   196: athrow
    //   197: astore_1
    //   198: goto -19 -> 179
    //   201: astore_1
    //   202: goto -39 -> 163
    //   205: astore_1
    //   206: goto -54 -> 152
    //
    // Exception table:
    //   from	to	target	type
    //   16	28	149	com/google/zxing/NotFoundException
    //   16	28	160	com/google/zxing/FormatException
    //   50	75	178	com/google/zxing/NotFoundException
    //   50	75	197	com/google/zxing/FormatException
    //   28	40	201	com/google/zxing/FormatException
    //   28	40	205	com/google/zxing/NotFoundException
  }

  public final void a()
  {
  }
}

/* Location:           C:\crazyd\work\ustone\odm2016031702\baidu\android\nut-dex2jar.jar
 * Qualified Name:     com.google.zxing.a.b
 * JD-Core Version:    0.6.2
 */