package u.aly;

import android.content.ContentValues;
import android.database.Cursor;
import android.database.SQLException;
import android.database.sqlite.SQLiteDatabase;
import android.text.TextUtils;
import java.util.Collection;
import java.util.HashMap;
import java.util.Iterator;
import java.util.Map;

public final class a
{
  private static ContentValues a(eh parameh)
  {
    ContentValues localContentValues = new ContentValues();
    localContentValues.put("key", TextUtils.join("!", parameh.a));
    localContentValues.put("label", TextUtils.join("!", parameh.b));
    localContentValues.put("count", Long.valueOf(parameh.e));
    localContentValues.put("value", Long.valueOf(parameh.d));
    localContentValues.put("totalTimestamp", Long.valueOf(parameh.c));
    localContentValues.put("timeWindowNum", parameh.f);
    return localContentValues;
  }

  // ERROR //
  public static String a(SQLiteDatabase paramSQLiteDatabase)
  {
    // Byte code:
    //   0: aload_0
    //   1: invokevirtual 76	android/database/sqlite/SQLiteDatabase:beginTransaction	()V
    //   4: aload_0
    //   5: ldc 78
    //   7: invokestatic 81	u/aly/a:b	(Landroid/database/sqlite/SQLiteDatabase;Ljava/lang/String;)I
    //   10: ifgt +10 -> 20
    //   13: aload_0
    //   14: invokevirtual 84	android/database/sqlite/SQLiteDatabase:endTransaction	()V
    //   17: ldc 86
    //   19: areturn
    //   20: aload_0
    //   21: ldc 88
    //   23: aconst_null
    //   24: invokevirtual 92	android/database/sqlite/SQLiteDatabase:rawQuery	(Ljava/lang/String;[Ljava/lang/String;)Landroid/database/Cursor;
    //   27: astore_1
    //   28: aload_1
    //   29: astore_2
    //   30: aload_1
    //   31: invokeinterface 98 1 0
    //   36: ifeq +124 -> 160
    //   39: aload_1
    //   40: astore_2
    //   41: aload_1
    //   42: aload_1
    //   43: ldc 63
    //   45: invokeinterface 102 2 0
    //   50: invokeinterface 106 2 0
    //   55: astore_3
    //   56: aload_1
    //   57: astore_2
    //   58: aload_0
    //   59: invokevirtual 109	android/database/sqlite/SQLiteDatabase:setTransactionSuccessful	()V
    //   62: aload_1
    //   63: ifnull +9 -> 72
    //   66: aload_1
    //   67: invokeinterface 112 1 0
    //   72: aload_0
    //   73: invokevirtual 84	android/database/sqlite/SQLiteDatabase:endTransaction	()V
    //   76: aload_3
    //   77: areturn
    //   78: astore 4
    //   80: aconst_null
    //   81: astore_1
    //   82: aconst_null
    //   83: astore_3
    //   84: aload_1
    //   85: astore_2
    //   86: new 114	java/lang/StringBuilder
    //   89: dup
    //   90: ldc 116
    //   92: invokespecial 119	java/lang/StringBuilder:<init>	(Ljava/lang/String;)V
    //   95: aload 4
    //   97: invokevirtual 123	android/database/SQLException:toString	()Ljava/lang/String;
    //   100: invokevirtual 127	java/lang/StringBuilder:append	(Ljava/lang/String;)Ljava/lang/StringBuilder;
    //   103: invokevirtual 128	java/lang/StringBuilder:toString	()Ljava/lang/String;
    //   106: invokestatic 132	u/aly/ct:d	(Ljava/lang/String;)V
    //   109: aload_1
    //   110: ifnull +9 -> 119
    //   113: aload_1
    //   114: invokeinterface 112 1 0
    //   119: aload_0
    //   120: invokevirtual 84	android/database/sqlite/SQLiteDatabase:endTransaction	()V
    //   123: aload_3
    //   124: areturn
    //   125: astore_1
    //   126: aconst_null
    //   127: astore_2
    //   128: aload_2
    //   129: ifnull +9 -> 138
    //   132: aload_2
    //   133: invokeinterface 112 1 0
    //   138: aload_0
    //   139: invokevirtual 84	android/database/sqlite/SQLiteDatabase:endTransaction	()V
    //   142: aload_1
    //   143: athrow
    //   144: astore_1
    //   145: goto -17 -> 128
    //   148: astore 4
    //   150: aconst_null
    //   151: astore_3
    //   152: goto -68 -> 84
    //   155: astore 4
    //   157: goto -73 -> 84
    //   160: aconst_null
    //   161: astore_3
    //   162: goto -106 -> 56
    //
    // Exception table:
    //   from	to	target	type
    //   0	13	78	android/database/SQLException
    //   20	28	78	android/database/SQLException
    //   0	13	125	finally
    //   20	28	125	finally
    //   30	39	144	finally
    //   41	56	144	finally
    //   58	62	144	finally
    //   86	109	144	finally
    //   30	39	148	android/database/SQLException
    //   41	56	148	android/database/SQLException
    //   58	62	155	android/database/SQLException
  }

  // ERROR //
  public static Map<String, java.util.List<ae>> a(ef paramef, SQLiteDatabase paramSQLiteDatabase)
  {
    // Byte code:
    //   0: new 135	java/util/HashMap
    //   3: dup
    //   4: invokespecial 136	java/util/HashMap:<init>	()V
    //   7: astore 4
    //   9: aload_1
    //   10: ldc 138
    //   12: invokestatic 81	u/aly/a:b	(Landroid/database/sqlite/SQLiteDatabase;Ljava/lang/String;)I
    //   15: ifle +258 -> 273
    //   18: aload_1
    //   19: ldc 140
    //   21: aconst_null
    //   22: invokevirtual 92	android/database/sqlite/SQLiteDatabase:rawQuery	(Ljava/lang/String;[Ljava/lang/String;)Landroid/database/Cursor;
    //   25: astore_1
    //   26: aload_1
    //   27: astore_2
    //   28: aload_1
    //   29: invokeinterface 143 1 0
    //   34: ifeq +214 -> 248
    //   37: aload_1
    //   38: astore_2
    //   39: aload_1
    //   40: aload_1
    //   41: ldc 14
    //   43: invokeinterface 102 2 0
    //   48: invokeinterface 106 2 0
    //   53: astore 5
    //   55: aload_1
    //   56: astore_2
    //   57: aload 4
    //   59: aload 5
    //   61: invokeinterface 149 2 0
    //   66: ifeq +156 -> 222
    //   69: aload_1
    //   70: astore_2
    //   71: aload 4
    //   73: aload 5
    //   75: invokeinterface 153 2 0
    //   80: checkcast 155	java/util/List
    //   83: astore_3
    //   84: aload_1
    //   85: astore_2
    //   86: aload 4
    //   88: aload 5
    //   90: invokeinterface 158 2 0
    //   95: pop
    //   96: aload_1
    //   97: astore_2
    //   98: new 160	u/aly/ae
    //   101: dup
    //   102: invokespecial 161	u/aly/ae:<init>	()V
    //   105: astore 6
    //   107: aload_1
    //   108: astore_2
    //   109: aload 6
    //   111: aload_1
    //   112: aload_1
    //   113: ldc 163
    //   115: invokeinterface 102 2 0
    //   120: invokeinterface 167 2 0
    //   125: putfield 169	u/aly/ae:b	J
    //   128: aload_1
    //   129: astore_2
    //   130: aload 6
    //   132: aload_1
    //   133: aload_1
    //   134: ldc 38
    //   136: invokeinterface 102 2 0
    //   141: invokeinterface 167 2 0
    //   146: l2i
    //   147: putfield 172	u/aly/ae:a	I
    //   150: aload_1
    //   151: astore_2
    //   152: aload_3
    //   153: aload 6
    //   155: invokeinterface 175 2 0
    //   160: pop
    //   161: aload_1
    //   162: astore_2
    //   163: aload 4
    //   165: aload 5
    //   167: aload_3
    //   168: invokeinterface 178 3 0
    //   173: pop
    //   174: goto -148 -> 26
    //   177: astore_3
    //   178: aload_1
    //   179: astore_2
    //   180: aload_0
    //   181: ldc 180
    //   183: invokevirtual 185	u/aly/ef:a	(Ljava/lang/Object;)V
    //   186: aload_1
    //   187: astore_2
    //   188: new 114	java/lang/StringBuilder
    //   191: dup
    //   192: ldc 187
    //   194: invokespecial 119	java/lang/StringBuilder:<init>	(Ljava/lang/String;)V
    //   197: aload_3
    //   198: invokevirtual 123	android/database/SQLException:toString	()Ljava/lang/String;
    //   201: invokevirtual 127	java/lang/StringBuilder:append	(Ljava/lang/String;)Ljava/lang/StringBuilder;
    //   204: invokevirtual 128	java/lang/StringBuilder:toString	()Ljava/lang/String;
    //   207: invokestatic 132	u/aly/ct:d	(Ljava/lang/String;)V
    //   210: aload_1
    //   211: ifnull +9 -> 220
    //   214: aload_1
    //   215: invokeinterface 112 1 0
    //   220: aconst_null
    //   221: areturn
    //   222: aload_1
    //   223: astore_2
    //   224: new 189	java/util/ArrayList
    //   227: dup
    //   228: invokespecial 190	java/util/ArrayList:<init>	()V
    //   231: astore_3
    //   232: goto -136 -> 96
    //   235: astore_0
    //   236: aload_2
    //   237: ifnull +9 -> 246
    //   240: aload_2
    //   241: invokeinterface 112 1 0
    //   246: aload_0
    //   247: athrow
    //   248: aload_1
    //   249: ifnull +9 -> 258
    //   252: aload_1
    //   253: invokeinterface 112 1 0
    //   258: aload 4
    //   260: areturn
    //   261: astore_0
    //   262: aconst_null
    //   263: astore_2
    //   264: goto -28 -> 236
    //   267: astore_3
    //   268: aconst_null
    //   269: astore_1
    //   270: goto -92 -> 178
    //   273: aconst_null
    //   274: astore_1
    //   275: goto -27 -> 248
    //
    // Exception table:
    //   from	to	target	type
    //   28	37	177	android/database/SQLException
    //   39	55	177	android/database/SQLException
    //   57	69	177	android/database/SQLException
    //   71	84	177	android/database/SQLException
    //   86	96	177	android/database/SQLException
    //   98	107	177	android/database/SQLException
    //   109	128	177	android/database/SQLException
    //   130	150	177	android/database/SQLException
    //   152	161	177	android/database/SQLException
    //   163	174	177	android/database/SQLException
    //   224	232	177	android/database/SQLException
    //   28	37	235	finally
    //   39	55	235	finally
    //   57	69	235	finally
    //   71	84	235	finally
    //   86	96	235	finally
    //   98	107	235	finally
    //   109	128	235	finally
    //   130	150	235	finally
    //   152	161	235	finally
    //   163	174	235	finally
    //   180	186	235	finally
    //   188	210	235	finally
    //   224	232	235	finally
    //   0	26	261	finally
    //   0	26	267	android/database/SQLException
  }

  public static boolean a(SQLiteDatabase paramSQLiteDatabase, String paramString)
  {
    try
    {
      if (b(paramSQLiteDatabase, paramString) >= 0)
        paramSQLiteDatabase.execSQL("delete from " + paramString);
      return true;
    }
    catch (SQLException paramSQLiteDatabase)
    {
      ct.d("cleanTableData faild!" + paramSQLiteDatabase.toString());
    }
    return false;
  }

  public static boolean a(SQLiteDatabase paramSQLiteDatabase, Collection<eh> paramCollection)
  {
    try
    {
      paramSQLiteDatabase.beginTransaction();
      if (b(paramSQLiteDatabase, "aggregated_cache") > 0)
        a(paramSQLiteDatabase, "aggregated_cache");
      paramCollection = paramCollection.iterator();
      while (paramCollection.hasNext())
        paramSQLiteDatabase.insert("aggregated_cache", null, a((eh)paramCollection.next()));
    }
    catch (SQLException paramCollection)
    {
      ct.d("insert to Aggregated cache table faild!");
      return false;
      paramSQLiteDatabase.setTransactionSuccessful();
      return true;
    }
    finally
    {
      paramSQLiteDatabase.endTransaction();
    }
    throw paramCollection;
  }

  public static boolean a(SQLiteDatabase paramSQLiteDatabase, ef paramef)
  {
    try
    {
      paramSQLiteDatabase.beginTransaction();
      if (b(paramSQLiteDatabase, "aggregated_cache") <= 0)
      {
        paramef.a("faild");
        return false;
      }
      paramSQLiteDatabase.execSQL("insert into aggregated(key, count, value, totalTimestamp, timeWindowNum, label) select key, count, value, totalTimestamp, timeWindowNum, label from aggregated_cache");
      paramSQLiteDatabase.setTransactionSuccessful();
      a(paramSQLiteDatabase, "aggregated_cache");
      paramef.a("success");
      return true;
    }
    catch (SQLException localSQLException)
    {
      paramef.a(Boolean.valueOf(false));
      ct.d("cacheToAggregatedTable happen " + localSQLException.toString());
      return false;
    }
    finally
    {
      paramSQLiteDatabase.endTransaction();
    }
    throw paramef;
  }

  public static boolean a(ef paramef, SQLiteDatabase paramSQLiteDatabase, Collection<eh> paramCollection)
  {
    try
    {
      paramSQLiteDatabase.beginTransaction();
      paramCollection = paramCollection.iterator();
      while (paramCollection.hasNext())
        paramSQLiteDatabase.insert("aggregated", null, a((eh)paramCollection.next()));
    }
    catch (SQLException paramef)
    {
      ct.d("insert to Aggregated cache table faild!");
      return false;
      paramSQLiteDatabase.setTransactionSuccessful();
      a(paramSQLiteDatabase, "aggregated_cache");
      paramef.a("success");
      return true;
    }
    finally
    {
      paramSQLiteDatabase.endTransaction();
    }
    throw paramef;
  }

  public static int b(SQLiteDatabase paramSQLiteDatabase, String paramString)
  {
    Object localObject = null;
    SQLiteDatabase localSQLiteDatabase = null;
    int j = 0;
    try
    {
      paramSQLiteDatabase = paramSQLiteDatabase.rawQuery("select * from " + paramString, null);
      localSQLiteDatabase = paramSQLiteDatabase;
      localObject = paramSQLiteDatabase;
      int i = paramSQLiteDatabase.getCount();
      j = i;
      if (paramSQLiteDatabase != null)
      {
        paramSQLiteDatabase.close();
        j = i;
      }
      return j;
    }
    catch (Exception paramSQLiteDatabase)
    {
      do
      {
        localObject = localSQLiteDatabase;
        ct.d("count error " + paramSQLiteDatabase.toString());
      }
      while (localSQLiteDatabase == null);
      localSQLiteDatabase.close();
      return 0;
    }
    finally
    {
      if (localObject != null)
        ((Cursor)localObject).close();
    }
    throw paramSQLiteDatabase;
  }

  // ERROR //
  public static Map<String, java.util.List<ad>> b(SQLiteDatabase paramSQLiteDatabase)
  {
    // Byte code:
    //   0: aload_0
    //   1: ldc 242
    //   3: invokestatic 81	u/aly/a:b	(Landroid/database/sqlite/SQLiteDatabase;Ljava/lang/String;)I
    //   6: ifle +239 -> 245
    //   9: aload_0
    //   10: ldc_w 257
    //   13: aconst_null
    //   14: invokevirtual 92	android/database/sqlite/SQLiteDatabase:rawQuery	(Ljava/lang/String;[Ljava/lang/String;)Landroid/database/Cursor;
    //   17: astore_0
    //   18: new 135	java/util/HashMap
    //   21: dup
    //   22: invokespecial 136	java/util/HashMap:<init>	()V
    //   25: astore_2
    //   26: aload_0
    //   27: invokeinterface 143 1 0
    //   32: ifeq +243 -> 275
    //   35: aload_0
    //   36: aload_0
    //   37: ldc 14
    //   39: invokeinterface 102 2 0
    //   44: invokeinterface 106 2 0
    //   49: astore_3
    //   50: aload_2
    //   51: aload_3
    //   52: invokeinterface 149 2 0
    //   57: ifeq +190 -> 247
    //   60: aload_2
    //   61: aload_3
    //   62: invokeinterface 153 2 0
    //   67: checkcast 155	java/util/List
    //   70: astore_1
    //   71: aload_2
    //   72: aload_3
    //   73: invokeinterface 158 2 0
    //   78: pop
    //   79: new 259	u/aly/ad
    //   82: dup
    //   83: invokespecial 260	u/aly/ad:<init>	()V
    //   86: astore 4
    //   88: aload 4
    //   90: aload_0
    //   91: aload_0
    //   92: ldc 33
    //   94: invokeinterface 102 2 0
    //   99: invokeinterface 106 2 0
    //   104: invokestatic 265	u/aly/ea:a	(Ljava/lang/String;)Ljava/util/List;
    //   107: putfield 267	u/aly/ad:e	Ljava/util/List;
    //   110: aload 4
    //   112: aload_0
    //   113: aload_0
    //   114: ldc 53
    //   116: invokeinterface 102 2 0
    //   121: invokeinterface 167 2 0
    //   126: putfield 269	u/aly/ad:a	J
    //   129: aload 4
    //   131: aload_0
    //   132: aload_0
    //   133: ldc 58
    //   135: invokeinterface 102 2 0
    //   140: invokeinterface 167 2 0
    //   145: putfield 270	u/aly/ad:b	J
    //   148: aload 4
    //   150: aload_0
    //   151: aload_0
    //   152: ldc 63
    //   154: invokeinterface 102 2 0
    //   159: invokeinterface 106 2 0
    //   164: invokestatic 275	java/lang/Integer:parseInt	(Ljava/lang/String;)I
    //   167: putfield 277	u/aly/ad:c	I
    //   170: aload 4
    //   172: aload_0
    //   173: aload_0
    //   174: ldc 38
    //   176: invokeinterface 102 2 0
    //   181: invokeinterface 167 2 0
    //   186: l2i
    //   187: putfield 279	u/aly/ad:d	I
    //   190: aload_1
    //   191: aload 4
    //   193: invokeinterface 175 2 0
    //   198: pop
    //   199: aload_2
    //   200: aload_3
    //   201: aload_1
    //   202: invokeinterface 178 3 0
    //   207: pop
    //   208: goto -182 -> 26
    //   211: astore_1
    //   212: new 114	java/lang/StringBuilder
    //   215: dup
    //   216: ldc_w 281
    //   219: invokespecial 119	java/lang/StringBuilder:<init>	(Ljava/lang/String;)V
    //   222: aload_1
    //   223: invokevirtual 123	android/database/SQLException:toString	()Ljava/lang/String;
    //   226: invokevirtual 127	java/lang/StringBuilder:append	(Ljava/lang/String;)Ljava/lang/StringBuilder;
    //   229: invokevirtual 128	java/lang/StringBuilder:toString	()Ljava/lang/String;
    //   232: invokestatic 132	u/aly/ct:d	(Ljava/lang/String;)V
    //   235: aload_0
    //   236: ifnull +9 -> 245
    //   239: aload_0
    //   240: invokeinterface 112 1 0
    //   245: aconst_null
    //   246: areturn
    //   247: new 189	java/util/ArrayList
    //   250: dup
    //   251: invokespecial 190	java/util/ArrayList:<init>	()V
    //   254: astore_1
    //   255: goto -176 -> 79
    //   258: astore_2
    //   259: aload_0
    //   260: astore_1
    //   261: aload_2
    //   262: astore_0
    //   263: aload_1
    //   264: ifnull +9 -> 273
    //   267: aload_1
    //   268: invokeinterface 112 1 0
    //   273: aload_0
    //   274: athrow
    //   275: aload_0
    //   276: ifnull +9 -> 285
    //   279: aload_0
    //   280: invokeinterface 112 1 0
    //   285: aload_2
    //   286: areturn
    //   287: astore_0
    //   288: aconst_null
    //   289: astore_1
    //   290: goto -27 -> 263
    //   293: astore_2
    //   294: aload_0
    //   295: astore_1
    //   296: aload_2
    //   297: astore_0
    //   298: goto -35 -> 263
    //   301: astore_1
    //   302: aconst_null
    //   303: astore_0
    //   304: goto -92 -> 212
    //
    // Exception table:
    //   from	to	target	type
    //   18	26	211	android/database/SQLException
    //   26	79	211	android/database/SQLException
    //   79	208	211	android/database/SQLException
    //   247	255	211	android/database/SQLException
    //   18	26	258	finally
    //   26	79	258	finally
    //   79	208	258	finally
    //   247	255	258	finally
    //   0	18	287	finally
    //   212	235	293	finally
    //   0	18	301	android/database/SQLException
  }

  public static boolean b(SQLiteDatabase paramSQLiteDatabase, ef paramef)
  {
    Object localObject3 = null;
    eh localeh = null;
    Object localObject2 = localeh;
    Object localObject1 = localObject3;
    try
    {
      localHashMap = new HashMap();
      localObject2 = localeh;
      localObject1 = localObject3;
      paramSQLiteDatabase = paramSQLiteDatabase.rawQuery("select * from aggregated_cache", null);
      while (true)
      {
        localObject2 = paramSQLiteDatabase;
        localObject1 = paramSQLiteDatabase;
        if (!paramSQLiteDatabase.moveToNext())
          break;
        localObject2 = paramSQLiteDatabase;
        localObject1 = paramSQLiteDatabase;
        localeh = new eh();
        localObject2 = paramSQLiteDatabase;
        localObject1 = paramSQLiteDatabase;
        localeh.a = ea.a(paramSQLiteDatabase.getString(paramSQLiteDatabase.getColumnIndex("key")));
        localObject2 = paramSQLiteDatabase;
        localObject1 = paramSQLiteDatabase;
        localeh.b = ea.a(paramSQLiteDatabase.getString(paramSQLiteDatabase.getColumnIndex("label")));
        localObject2 = paramSQLiteDatabase;
        localObject1 = paramSQLiteDatabase;
        localeh.e = paramSQLiteDatabase.getInt(paramSQLiteDatabase.getColumnIndex("count"));
        localObject2 = paramSQLiteDatabase;
        localObject1 = paramSQLiteDatabase;
        localeh.d = paramSQLiteDatabase.getInt(paramSQLiteDatabase.getColumnIndex("value"));
        localObject2 = paramSQLiteDatabase;
        localObject1 = paramSQLiteDatabase;
        localeh.f = paramSQLiteDatabase.getString(paramSQLiteDatabase.getColumnIndex("timeWindowNum"));
        localObject2 = paramSQLiteDatabase;
        localObject1 = paramSQLiteDatabase;
        localeh.c = Long.parseLong(paramSQLiteDatabase.getString(paramSQLiteDatabase.getColumnIndex("totalTimestamp")));
        localObject2 = paramSQLiteDatabase;
        localObject1 = paramSQLiteDatabase;
        localHashMap.put(ea.a(paramSQLiteDatabase.getString(paramSQLiteDatabase.getColumnIndex("key"))), localeh);
      }
    }
    catch (SQLException paramSQLiteDatabase)
    {
      HashMap localHashMap;
      localObject1 = localObject2;
      paramef.a(Boolean.valueOf(false));
      localObject1 = localObject2;
      ct.d("cacheToMemory happen " + paramSQLiteDatabase.toString());
      while (true)
      {
        return false;
        localObject2 = paramSQLiteDatabase;
        localObject1 = paramSQLiteDatabase;
        if (localHashMap.size() > 0)
        {
          localObject2 = paramSQLiteDatabase;
          localObject1 = paramSQLiteDatabase;
          paramef.a(localHashMap);
        }
        while (paramSQLiteDatabase != null)
        {
          paramSQLiteDatabase.close();
          return false;
          localObject2 = paramSQLiteDatabase;
          localObject1 = paramSQLiteDatabase;
          paramef.a("faild");
        }
      }
    }
    finally
    {
      if (localObject1 != null)
        ((Cursor)localObject1).close();
    }
    throw paramSQLiteDatabase;
  }

  // ERROR //
  public static java.util.List<String> c(SQLiteDatabase paramSQLiteDatabase)
  {
    // Byte code:
    //   0: aload_0
    //   1: ldc_w 299
    //   4: invokestatic 81	u/aly/a:b	(Landroid/database/sqlite/SQLiteDatabase;Ljava/lang/String;)I
    //   7: ifle +96 -> 103
    //   10: aload_0
    //   11: ldc_w 301
    //   14: aconst_null
    //   15: invokevirtual 92	android/database/sqlite/SQLiteDatabase:rawQuery	(Ljava/lang/String;[Ljava/lang/String;)Landroid/database/Cursor;
    //   18: astore_1
    //   19: aload_1
    //   20: astore_0
    //   21: new 189	java/util/ArrayList
    //   24: dup
    //   25: invokespecial 190	java/util/ArrayList:<init>	()V
    //   28: astore_2
    //   29: aload_1
    //   30: astore_0
    //   31: aload_1
    //   32: invokeinterface 143 1 0
    //   37: ifeq +70 -> 107
    //   40: aload_1
    //   41: astore_0
    //   42: aload_2
    //   43: aload_1
    //   44: aload_1
    //   45: ldc_w 303
    //   48: invokeinterface 102 2 0
    //   53: invokeinterface 106 2 0
    //   58: invokeinterface 175 2 0
    //   63: pop
    //   64: goto -35 -> 29
    //   67: astore_2
    //   68: aload_1
    //   69: astore_0
    //   70: new 114	java/lang/StringBuilder
    //   73: dup
    //   74: ldc_w 305
    //   77: invokespecial 119	java/lang/StringBuilder:<init>	(Ljava/lang/String;)V
    //   80: aload_2
    //   81: invokevirtual 123	android/database/SQLException:toString	()Ljava/lang/String;
    //   84: invokevirtual 127	java/lang/StringBuilder:append	(Ljava/lang/String;)Ljava/lang/StringBuilder;
    //   87: invokevirtual 128	java/lang/StringBuilder:toString	()Ljava/lang/String;
    //   90: invokestatic 132	u/aly/ct:d	(Ljava/lang/String;)V
    //   93: aload_1
    //   94: ifnull +9 -> 103
    //   97: aload_1
    //   98: invokeinterface 112 1 0
    //   103: aconst_null
    //   104: astore_0
    //   105: aload_0
    //   106: areturn
    //   107: aload_2
    //   108: astore_0
    //   109: aload_1
    //   110: ifnull -5 -> 105
    //   113: aload_1
    //   114: invokeinterface 112 1 0
    //   119: aload_2
    //   120: areturn
    //   121: astore_1
    //   122: aconst_null
    //   123: astore_0
    //   124: aload_0
    //   125: ifnull +9 -> 134
    //   128: aload_0
    //   129: invokeinterface 112 1 0
    //   134: aload_1
    //   135: athrow
    //   136: astore_1
    //   137: goto -13 -> 124
    //   140: astore_2
    //   141: aconst_null
    //   142: astore_1
    //   143: goto -75 -> 68
    //
    // Exception table:
    //   from	to	target	type
    //   21	29	67	android/database/SQLException
    //   31	40	67	android/database/SQLException
    //   42	64	67	android/database/SQLException
    //   0	19	121	finally
    //   21	29	136	finally
    //   31	40	136	finally
    //   42	64	136	finally
    //   70	93	136	finally
    //   0	19	140	android/database/SQLException
  }
}

/* Location:           C:\crazyd\work\ustone\odm2016031702\baidu\android\nut-dex2jar.jar
 * Qualified Name:     u.aly.a
 * JD-Core Version:    0.6.2
 */