package u.aly;

import com.umeng.analytics.z;

public final class es extends z
{
  public es(ej paramej, ef paramef)
  {
  }

  // ERROR //
  public final void a()
  {
    // Byte code:
    //   0: new 22	u/aly/et
    //   3: dup
    //   4: aload_0
    //   5: invokespecial 25	u/aly/et:<init>	(Lu/aly/es;)V
    //   8: astore 7
    //   10: getstatic 30	u/aly/ey:a	Landroid/content/Context;
    //   13: invokestatic 35	u/aly/as:a	(Landroid/content/Context;)Lu/aly/as;
    //   16: invokevirtual 38	u/aly/as:a	()Landroid/database/sqlite/SQLiteDatabase;
    //   19: astore 8
    //   21: aload 8
    //   23: invokestatic 43	u/aly/a:a	(Landroid/database/sqlite/SQLiteDatabase;)Ljava/lang/String;
    //   26: astore 9
    //   28: invokestatic 49	java/lang/System:currentTimeMillis	()J
    //   31: lstore_3
    //   32: invokestatic 55	java/util/Calendar:getInstance	()Ljava/util/Calendar;
    //   35: astore 10
    //   37: aload 10
    //   39: lload_3
    //   40: invokevirtual 59	java/util/Calendar:setTimeInMillis	(J)V
    //   43: aload 10
    //   45: bipush 11
    //   47: invokevirtual 63	java/util/Calendar:get	(I)I
    //   50: istore_1
    //   51: aload 10
    //   53: bipush 12
    //   55: invokevirtual 63	java/util/Calendar:get	(I)I
    //   58: bipush 6
    //   60: idiv
    //   61: istore_2
    //   62: lload_3
    //   63: invokestatic 68	u/aly/fb:a	(J)J
    //   66: lstore_3
    //   67: iload_2
    //   68: iconst_1
    //   69: iadd
    //   70: iload_1
    //   71: bipush 10
    //   73: imul
    //   74: iadd
    //   75: iconst_1
    //   76: isub
    //   77: i2l
    //   78: lstore 5
    //   80: aload 9
    //   82: ldc 70
    //   84: invokevirtual 76	java/lang/String:equals	(Ljava/lang/Object;)Z
    //   87: ifeq +59 -> 146
    //   90: aload 7
    //   92: ldc 78
    //   94: invokevirtual 83	u/aly/ef:a	(Ljava/lang/Object;)V
    //   97: getstatic 30	u/aly/ey:a	Landroid/content/Context;
    //   100: invokestatic 35	u/aly/as:a	(Landroid/content/Context;)Lu/aly/as;
    //   103: invokevirtual 86	u/aly/as:c	()V
    //   106: aload_0
    //   107: getfield 12	u/aly/es:b	Lu/aly/ej;
    //   110: invokevirtual 90	u/aly/ej:a	()V
    //   113: aload_0
    //   114: getfield 12	u/aly/es:b	Lu/aly/ej;
    //   117: astore 7
    //   119: invokestatic 93	u/aly/ey:b	()Ljava/util/List;
    //   122: astore 8
    //   124: aload 8
    //   126: ifnull +10 -> 136
    //   129: aload 7
    //   131: aload 8
    //   133: putfield 97	u/aly/ej:g	Ljava/util/List;
    //   136: aload_0
    //   137: getfield 14	u/aly/es:a	Lu/aly/ef;
    //   140: ldc 99
    //   142: invokevirtual 83	u/aly/ef:a	(Ljava/lang/Object;)V
    //   145: return
    //   146: aload 9
    //   148: lload_3
    //   149: ldc2_w 100
    //   152: lmul
    //   153: lload 5
    //   155: ladd
    //   156: invokestatic 105	java/lang/String:valueOf	(J)Ljava/lang/String;
    //   159: invokevirtual 76	java/lang/String:equals	(Ljava/lang/Object;)Z
    //   162: ifne +31 -> 193
    //   165: aload 8
    //   167: aload 7
    //   169: invokestatic 108	u/aly/a:a	(Landroid/database/sqlite/SQLiteDatabase;Lu/aly/ef;)Z
    //   172: pop
    //   173: getstatic 30	u/aly/ey:a	Landroid/content/Context;
    //   176: invokestatic 35	u/aly/as:a	(Landroid/content/Context;)Lu/aly/as;
    //   179: invokevirtual 86	u/aly/as:c	()V
    //   182: goto -76 -> 106
    //   185: astore 7
    //   187: aload 7
    //   189: invokevirtual 111	java/lang/Exception:printStackTrace	()V
    //   192: return
    //   193: aload 8
    //   195: aload 7
    //   197: invokestatic 113	u/aly/a:b	(Landroid/database/sqlite/SQLiteDatabase;Lu/aly/ef;)Z
    //   200: pop
    //   201: goto -28 -> 173
    //   204: astore 8
    //   206: aload 7
    //   208: iconst_0
    //   209: invokestatic 118	java/lang/Boolean:valueOf	(Z)Ljava/lang/Boolean;
    //   212: invokevirtual 83	u/aly/ef:a	(Ljava/lang/Object;)V
    //   215: ldc 120
    //   217: invokestatic 126	u/aly/ct:d	(Ljava/lang/String;)V
    //   220: getstatic 30	u/aly/ey:a	Landroid/content/Context;
    //   223: invokestatic 35	u/aly/as:a	(Landroid/content/Context;)Lu/aly/as;
    //   226: invokevirtual 86	u/aly/as:c	()V
    //   229: goto -123 -> 106
    //   232: astore 7
    //   234: getstatic 30	u/aly/ey:a	Landroid/content/Context;
    //   237: invokestatic 35	u/aly/as:a	(Landroid/content/Context;)Lu/aly/as;
    //   240: invokevirtual 86	u/aly/as:c	()V
    //   243: aload 7
    //   245: athrow
    //
    // Exception table:
    //   from	to	target	type
    //   0	10	185	java/lang/Exception
    //   97	106	185	java/lang/Exception
    //   106	124	185	java/lang/Exception
    //   129	136	185	java/lang/Exception
    //   136	145	185	java/lang/Exception
    //   173	182	185	java/lang/Exception
    //   220	229	185	java/lang/Exception
    //   234	246	185	java/lang/Exception
    //   10	67	204	java/lang/Exception
    //   80	97	204	java/lang/Exception
    //   146	173	204	java/lang/Exception
    //   193	201	204	java/lang/Exception
    //   10	67	232	finally
    //   80	97	232	finally
    //   146	173	232	finally
    //   193	201	232	finally
    //   206	220	232	finally
  }
}

/* Location:           C:\crazyd\work\ustone\odm2016031702\baidu\android\nut-dex2jar.jar
 * Qualified Name:     u.aly.es
 * JD-Core Version:    0.6.2
 */