package u.aly;

import android.content.ContentValues;
import android.content.Context;
import android.database.SQLException;
import android.database.sqlite.SQLiteDatabase;
import java.util.List;
import java.util.Map;

public final class ey
{
  public static Context a;

  public static Map<String, List<ad>> a()
  {
    try
    {
      Map localMap = a.b(as.a(a).a());
      return localMap;
    }
    catch (Exception localException)
    {
      ct.d("upload agg date error");
      return null;
    }
    finally
    {
      as.a(a).c();
    }
  }

  public static Map<String, List<ae>> a(ef paramef)
  {
    try
    {
      paramef = a.a(paramef, as.a(a).a());
      return paramef;
    }
    catch (Exception paramef)
    {
      paramef.printStackTrace();
      return null;
    }
    finally
    {
      as.a(a).c();
    }
    throw paramef;
  }

  public static void a(ef paramef, List<String> paramList)
  {
    try
    {
      localSQLiteDatabase = as.a(a).b();
    }
    catch (Exception paramef)
    {
    }
    finally
    {
      SQLiteDatabase localSQLiteDatabase;
      String str;
      ContentValues localContentValues;
      as.a(a).c();
    }
    throw paramef;
  }

  // ERROR //
  public static void a(ef paramef, Map<String, ei> paramMap)
  {
    // Byte code:
    //   0: aconst_null
    //   1: astore 12
    //   3: aconst_null
    //   4: astore 11
    //   6: getstatic 18	u/aly/ey:a	Landroid/content/Context;
    //   9: invokestatic 23	u/aly/as:a	(Landroid/content/Context;)Lu/aly/as;
    //   12: invokevirtual 58	u/aly/as:b	()Landroid/database/sqlite/SQLiteDatabase;
    //   15: astore 13
    //   17: aload 11
    //   19: astore 10
    //   21: aload 12
    //   23: astore 9
    //   25: aload_1
    //   26: ldc 136
    //   28: invokeinterface 142 2 0
    //   33: checkcast 144	u/aly/ei
    //   36: astore 14
    //   38: aload 14
    //   40: ifnonnull +13 -> 53
    //   43: getstatic 18	u/aly/ey:a	Landroid/content/Context;
    //   46: invokestatic 23	u/aly/as:a	(Landroid/content/Context;)Lu/aly/as;
    //   49: invokevirtual 35	u/aly/as:c	()V
    //   52: return
    //   53: aload 11
    //   55: astore 10
    //   57: aload 12
    //   59: astore 9
    //   61: aload 13
    //   63: new 104	java/lang/StringBuilder
    //   66: dup
    //   67: ldc 146
    //   69: invokespecial 108	java/lang/StringBuilder:<init>	(Ljava/lang/String;)V
    //   72: ldc 148
    //   74: invokevirtual 116	java/lang/StringBuilder:append	(Ljava/lang/String;)Ljava/lang/StringBuilder;
    //   77: invokevirtual 117	java/lang/StringBuilder:toString	()Ljava/lang/String;
    //   80: aconst_null
    //   81: invokevirtual 152	android/database/sqlite/SQLiteDatabase:rawQuery	(Ljava/lang/String;[Ljava/lang/String;)Landroid/database/Cursor;
    //   84: astore_1
    //   85: iconst_0
    //   86: istore_2
    //   87: aload_1
    //   88: astore 10
    //   90: aload_1
    //   91: astore 9
    //   93: aload_1
    //   94: invokeinterface 157 1 0
    //   99: pop
    //   100: lconst_0
    //   101: lstore_3
    //   102: aload_1
    //   103: astore 10
    //   105: aload_1
    //   106: astore 9
    //   108: aload_1
    //   109: invokeinterface 160 1 0
    //   114: ifne +162 -> 276
    //   117: aload_1
    //   118: astore 10
    //   120: aload_1
    //   121: astore 9
    //   123: aload_1
    //   124: invokeinterface 164 1 0
    //   129: ifle +73 -> 202
    //   132: aload_1
    //   133: astore 10
    //   135: aload_1
    //   136: astore 9
    //   138: aload_1
    //   139: aload_1
    //   140: ldc 166
    //   142: invokeinterface 170 2 0
    //   147: invokeinterface 174 2 0
    //   152: istore_2
    //   153: aload_1
    //   154: astore 10
    //   156: aload_1
    //   157: astore 9
    //   159: aload_1
    //   160: aload_1
    //   161: ldc 176
    //   163: invokeinterface 170 2 0
    //   168: invokeinterface 180 2 0
    //   173: lstore_3
    //   174: aload_1
    //   175: astore 10
    //   177: aload_1
    //   178: astore 9
    //   180: aload 13
    //   182: new 104	java/lang/StringBuilder
    //   185: dup
    //   186: ldc 182
    //   188: invokespecial 108	java/lang/StringBuilder:<init>	(Ljava/lang/String;)V
    //   191: ldc 148
    //   193: invokevirtual 116	java/lang/StringBuilder:append	(Ljava/lang/String;)Ljava/lang/StringBuilder;
    //   196: invokevirtual 117	java/lang/StringBuilder:toString	()Ljava/lang/String;
    //   199: invokevirtual 185	android/database/sqlite/SQLiteDatabase:execSQL	(Ljava/lang/String;)V
    //   202: aload_1
    //   203: astore 10
    //   205: aload_1
    //   206: astore 9
    //   208: aload_1
    //   209: invokeinterface 188 1 0
    //   214: pop
    //   215: goto -113 -> 102
    //   218: astore_0
    //   219: aload 10
    //   221: astore 9
    //   223: new 104	java/lang/StringBuilder
    //   226: dup
    //   227: ldc 190
    //   229: invokespecial 108	java/lang/StringBuilder:<init>	(Ljava/lang/String;)V
    //   232: aload_0
    //   233: invokevirtual 112	android/database/SQLException:toString	()Ljava/lang/String;
    //   236: invokevirtual 116	java/lang/StringBuilder:append	(Ljava/lang/String;)Ljava/lang/StringBuilder;
    //   239: invokevirtual 117	java/lang/StringBuilder:toString	()Ljava/lang/String;
    //   242: invokestatic 43	u/aly/ct:d	(Ljava/lang/String;)V
    //   245: aload 10
    //   247: ifnull -204 -> 43
    //   250: aload 10
    //   252: invokeinterface 193 1 0
    //   257: goto -214 -> 43
    //   260: astore_0
    //   261: ldc 195
    //   263: invokestatic 43	u/aly/ct:d	(Ljava/lang/String;)V
    //   266: getstatic 18	u/aly/ey:a	Landroid/content/Context;
    //   269: invokestatic 23	u/aly/as:a	(Landroid/content/Context;)Lu/aly/as;
    //   272: invokevirtual 35	u/aly/as:c	()V
    //   275: return
    //   276: aload_1
    //   277: astore 10
    //   279: aload_1
    //   280: astore 9
    //   282: new 91	android/content/ContentValues
    //   285: dup
    //   286: invokespecial 92	android/content/ContentValues:<init>	()V
    //   289: astore 11
    //   291: aload_1
    //   292: astore 10
    //   294: aload_1
    //   295: astore 9
    //   297: aload 11
    //   299: ldc 197
    //   301: aload 14
    //   303: getfield 200	u/aly/ei:a	Ljava/lang/String;
    //   306: invokevirtual 98	android/content/ContentValues:put	(Ljava/lang/String;Ljava/lang/String;)V
    //   309: iload_2
    //   310: ifne +128 -> 438
    //   313: aload_1
    //   314: astore 10
    //   316: aload_1
    //   317: astore 9
    //   319: aload 14
    //   321: getfield 203	u/aly/ei:c	J
    //   324: lstore 5
    //   326: aload_1
    //   327: astore 10
    //   329: aload_1
    //   330: astore 9
    //   332: aload 11
    //   334: ldc 166
    //   336: lload 5
    //   338: invokestatic 209	java/lang/Long:valueOf	(J)Ljava/lang/Long;
    //   341: invokevirtual 212	android/content/ContentValues:put	(Ljava/lang/String;Ljava/lang/Long;)V
    //   344: lload_3
    //   345: lstore 5
    //   347: lload_3
    //   348: lconst_0
    //   349: lcmp
    //   350: ifne +16 -> 366
    //   353: aload_1
    //   354: astore 10
    //   356: aload_1
    //   357: astore 9
    //   359: aload 14
    //   361: getfield 214	u/aly/ei:b	J
    //   364: lstore 5
    //   366: aload_1
    //   367: astore 10
    //   369: aload_1
    //   370: astore 9
    //   372: aload 11
    //   374: ldc 176
    //   376: lload 5
    //   378: invokestatic 209	java/lang/Long:valueOf	(J)Ljava/lang/Long;
    //   381: invokevirtual 212	android/content/ContentValues:put	(Ljava/lang/String;Ljava/lang/Long;)V
    //   384: aload_1
    //   385: astore 10
    //   387: aload_1
    //   388: astore 9
    //   390: aload 13
    //   392: ldc 216
    //   394: aconst_null
    //   395: aload 11
    //   397: invokevirtual 102	android/database/sqlite/SQLiteDatabase:insert	(Ljava/lang/String;Ljava/lang/String;Landroid/content/ContentValues;)J
    //   400: pop2
    //   401: aload_1
    //   402: astore 10
    //   404: aload_1
    //   405: astore 9
    //   407: aload_0
    //   408: ldc 125
    //   410: invokevirtual 130	u/aly/ef:a	(Ljava/lang/Object;)V
    //   413: aload_1
    //   414: ifnull -371 -> 43
    //   417: aload_1
    //   418: invokeinterface 193 1 0
    //   423: goto -380 -> 43
    //   426: astore_0
    //   427: getstatic 18	u/aly/ey:a	Landroid/content/Context;
    //   430: invokestatic 23	u/aly/as:a	(Landroid/content/Context;)Lu/aly/as;
    //   433: invokevirtual 35	u/aly/as:c	()V
    //   436: aload_0
    //   437: athrow
    //   438: iload_2
    //   439: i2l
    //   440: lstore 5
    //   442: aload_1
    //   443: astore 10
    //   445: aload_1
    //   446: astore 9
    //   448: aload 14
    //   450: getfield 203	u/aly/ei:c	J
    //   453: lstore 7
    //   455: lload 5
    //   457: lload 7
    //   459: ladd
    //   460: lstore 5
    //   462: goto -136 -> 326
    //   465: astore_0
    //   466: aload 9
    //   468: ifnull +10 -> 478
    //   471: aload 9
    //   473: invokeinterface 193 1 0
    //   478: aload_0
    //   479: athrow
    //
    // Exception table:
    //   from	to	target	type
    //   25	38	218	android/database/SQLException
    //   61	85	218	android/database/SQLException
    //   93	100	218	android/database/SQLException
    //   108	117	218	android/database/SQLException
    //   123	132	218	android/database/SQLException
    //   138	153	218	android/database/SQLException
    //   159	174	218	android/database/SQLException
    //   180	202	218	android/database/SQLException
    //   208	215	218	android/database/SQLException
    //   282	291	218	android/database/SQLException
    //   297	309	218	android/database/SQLException
    //   319	326	218	android/database/SQLException
    //   332	344	218	android/database/SQLException
    //   359	366	218	android/database/SQLException
    //   372	384	218	android/database/SQLException
    //   390	401	218	android/database/SQLException
    //   407	413	218	android/database/SQLException
    //   448	455	218	android/database/SQLException
    //   6	17	260	java/lang/Exception
    //   250	257	260	java/lang/Exception
    //   417	423	260	java/lang/Exception
    //   471	478	260	java/lang/Exception
    //   478	480	260	java/lang/Exception
    //   6	17	426	finally
    //   250	257	426	finally
    //   261	266	426	finally
    //   417	423	426	finally
    //   471	478	426	finally
    //   478	480	426	finally
    //   25	38	465	finally
    //   61	85	465	finally
    //   93	100	465	finally
    //   108	117	465	finally
    //   123	132	465	finally
    //   138	153	465	finally
    //   159	174	465	finally
    //   180	202	465	finally
    //   208	215	465	finally
    //   223	245	465	finally
    //   282	291	465	finally
    //   297	309	465	finally
    //   319	326	465	finally
    //   332	344	465	finally
    //   359	366	465	finally
    //   372	384	465	finally
    //   390	401	465	finally
    //   407	413	465	finally
    //   448	455	465	finally
  }

  public static List<String> b()
  {
    try
    {
      List localList = a.c(as.a(a).a());
      return localList;
    }
    catch (Exception localException)
    {
      ct.d("loadCKToMemory exception");
      return null;
    }
    finally
    {
      as.a(a).c();
    }
  }
}

/* Location:           C:\crazyd\work\ustone\odm2016031702\baidu\android\nut-dex2jar.jar
 * Qualified Name:     u.aly.ey
 * JD-Core Version:    0.6.2
 */