package u.aly;

import com.umeng.analytics.ah;

final class v
  implements ah
{
  v(u paramu)
  {
  }

  public final void a()
  {
    this.a.a.f();
  }

  // ERROR //
  public final boolean a(java.io.File paramFile)
  {
    // Byte code:
    //   0: new 31	java/io/FileInputStream
    //   3: dup
    //   4: aload_1
    //   5: invokespecial 34	java/io/FileInputStream:<init>	(Ljava/io/File;)V
    //   8: astore_3
    //   9: aload_3
    //   10: invokestatic 40	u/aly/cs:b	(Ljava/io/InputStream;)[B
    //   13: astore_1
    //   14: aload_3
    //   15: invokestatic 44	u/aly/cs:c	(Ljava/io/InputStream;)V
    //   18: aload_0
    //   19: getfield 12	u/aly/v:a	Lu/aly/u;
    //   22: getfield 47	u/aly/u:b	Lu/aly/r;
    //   25: aload_1
    //   26: invokevirtual 52	u/aly/r:a	([B)[B
    //   29: astore_1
    //   30: aload_1
    //   31: ifnonnull +51 -> 82
    //   34: iconst_1
    //   35: istore_2
    //   36: iload_2
    //   37: iconst_2
    //   38: if_icmpne +26 -> 64
    //   41: aload_0
    //   42: getfield 12	u/aly/v:a	Lu/aly/u;
    //   45: getfield 21	u/aly/u:a	Lu/aly/x;
    //   48: invokevirtual 56	u/aly/x:h	()Z
    //   51: ifeq +13 -> 64
    //   54: aload_0
    //   55: getfield 12	u/aly/v:a	Lu/aly/u;
    //   58: getfield 21	u/aly/u:a	Lu/aly/x;
    //   61: invokevirtual 59	u/aly/x:g	()V
    //   64: aload_0
    //   65: getfield 12	u/aly/v:a	Lu/aly/u;
    //   68: getfield 63	u/aly/u:e	Z
    //   71: ifeq +23 -> 94
    //   74: iconst_1
    //   75: ireturn
    //   76: aload_3
    //   77: invokestatic 44	u/aly/cs:c	(Ljava/io/InputStream;)V
    //   80: aload_1
    //   81: athrow
    //   82: aload_0
    //   83: getfield 12	u/aly/v:a	Lu/aly/u;
    //   86: aload_1
    //   87: invokevirtual 66	u/aly/u:a	([B)I
    //   90: istore_2
    //   91: goto -55 -> 36
    //   94: iload_2
    //   95: iconst_1
    //   96: if_icmpne +9 -> 105
    //   99: iconst_0
    //   100: ireturn
    //   101: astore_1
    //   102: goto -26 -> 76
    //   105: iconst_1
    //   106: ireturn
    //   107: astore_1
    //   108: aconst_null
    //   109: astore_3
    //   110: goto -34 -> 76
    //   113: astore_1
    //   114: iconst_0
    //   115: ireturn
    //
    // Exception table:
    //   from	to	target	type
    //   9	14	101	finally
    //   0	9	107	finally
    //   14	30	113	java/lang/Exception
    //   41	64	113	java/lang/Exception
    //   64	74	113	java/lang/Exception
    //   76	82	113	java/lang/Exception
    //   82	91	113	java/lang/Exception
  }
}

/* Location:           C:\crazyd\work\ustone\odm2016031702\baidu\android\nut-dex2jar.jar
 * Qualified Name:     u.aly.v
 * JD-Core Version:    0.6.2
 */