package rx;

import rx.b.a;

final class e
  implements a
{
  e(d paramd, g paramg, s params)
  {
  }

  // ERROR //
  public final void call()
  {
    // Byte code:
    //   0: aload_0
    //   1: getfield 16	rx/e:c	Lrx/d;
    //   4: getfield 34	rx/d:b	Lrx/a;
    //   7: astore_1
    //   8: aload_0
    //   9: getfield 18	rx/e:a	Lrx/g;
    //   12: astore_2
    //   13: aload_2
    //   14: invokestatic 39	rx/a:a	(Ljava/lang/Object;)Ljava/lang/Object;
    //   17: pop
    //   18: aload_1
    //   19: getfield 43	rx/a:d	Lrx/f;
    //   22: aload_2
    //   23: invokeinterface 48 2 0
    //   28: aload_0
    //   29: getfield 20	rx/e:b	Lrx/s;
    //   32: invokevirtual 53	rx/s:n_	()V
    //   35: return
    //   36: astore_1
    //   37: aload_1
    //   38: athrow
    //   39: astore_1
    //   40: aload_0
    //   41: getfield 20	rx/e:b	Lrx/s;
    //   44: invokevirtual 53	rx/s:n_	()V
    //   47: aload_1
    //   48: athrow
    //   49: astore_1
    //   50: aload_1
    //   51: invokestatic 56	rx/a:a	(Ljava/lang/Throwable;)Ljava/lang/NullPointerException;
    //   54: athrow
    //
    // Exception table:
    //   from	to	target	type
    //   18	28	36	java/lang/NullPointerException
    //   0	18	39	finally
    //   18	28	39	finally
    //   37	39	39	finally
    //   50	55	39	finally
    //   18	28	49	java/lang/Throwable
  }
}

/* Location:           C:\crazyd\work\ustone\odm2016031702\baidu\android\nut-dex2jar.jar
 * Qualified Name:     rx.e
 * JD-Core Version:    0.6.2
 */