package android.support.v7.widget;

import android.os.AsyncTask;

final class ac extends AsyncTask<Object, Void, Void>
{
  private ac(x paramx)
  {
  }

  // ERROR //
  private Void a(Object[] paramArrayOfObject)
  {
    // Byte code:
    //   0: iconst_0
    //   1: istore_2
    //   2: aload_1
    //   3: iconst_0
    //   4: aaload
    //   5: checkcast 29	java/util/List
    //   8: astore 4
    //   10: aload_1
    //   11: iconst_1
    //   12: aaload
    //   13: checkcast 31	java/lang/String
    //   16: astore 5
    //   18: aload_0
    //   19: getfield 11	android/support/v7/widget/ac:a	Landroid/support/v7/widget/x;
    //   22: invokestatic 36	android/support/v7/widget/x:a	(Landroid/support/v7/widget/x;)Landroid/content/Context;
    //   25: aload 5
    //   27: iconst_0
    //   28: invokevirtual 42	android/content/Context:openFileOutput	(Ljava/lang/String;I)Ljava/io/FileOutputStream;
    //   31: astore_1
    //   32: invokestatic 48	android/util/Xml:newSerializer	()Lorg/xmlpull/v1/XmlSerializer;
    //   35: astore 5
    //   37: aload 5
    //   39: aload_1
    //   40: aconst_null
    //   41: invokeinterface 54 3 0
    //   46: aload 5
    //   48: ldc 56
    //   50: iconst_1
    //   51: invokestatic 62	java/lang/Boolean:valueOf	(Z)Ljava/lang/Boolean;
    //   54: invokeinterface 66 3 0
    //   59: aload 5
    //   61: aconst_null
    //   62: ldc 68
    //   64: invokeinterface 72 3 0
    //   69: pop
    //   70: aload 4
    //   72: invokeinterface 76 1 0
    //   77: istore_3
    //   78: iload_2
    //   79: iload_3
    //   80: if_icmpge +130 -> 210
    //   83: aload 4
    //   85: iconst_0
    //   86: invokeinterface 80 2 0
    //   91: checkcast 82	android/support/v7/widget/aa
    //   94: astore 6
    //   96: aload 5
    //   98: aconst_null
    //   99: ldc 84
    //   101: invokeinterface 72 3 0
    //   106: pop
    //   107: aload 5
    //   109: aconst_null
    //   110: ldc 86
    //   112: aload 6
    //   114: getfield 89	android/support/v7/widget/aa:a	Landroid/content/ComponentName;
    //   117: invokevirtual 95	android/content/ComponentName:flattenToString	()Ljava/lang/String;
    //   120: invokeinterface 99 4 0
    //   125: pop
    //   126: aload 5
    //   128: aconst_null
    //   129: ldc 101
    //   131: aload 6
    //   133: getfield 105	android/support/v7/widget/aa:b	J
    //   136: invokestatic 108	java/lang/String:valueOf	(J)Ljava/lang/String;
    //   139: invokeinterface 99 4 0
    //   144: pop
    //   145: aload 5
    //   147: aconst_null
    //   148: ldc 110
    //   150: aload 6
    //   152: getfield 114	android/support/v7/widget/aa:c	F
    //   155: invokestatic 117	java/lang/String:valueOf	(F)Ljava/lang/String;
    //   158: invokeinterface 99 4 0
    //   163: pop
    //   164: aload 5
    //   166: aconst_null
    //   167: ldc 84
    //   169: invokeinterface 120 3 0
    //   174: pop
    //   175: iload_2
    //   176: iconst_1
    //   177: iadd
    //   178: istore_2
    //   179: goto -101 -> 78
    //   182: astore_1
    //   183: invokestatic 123	android/support/v7/widget/x:d	()Ljava/lang/String;
    //   186: new 125	java/lang/StringBuilder
    //   189: dup
    //   190: ldc 127
    //   192: invokespecial 130	java/lang/StringBuilder:<init>	(Ljava/lang/String;)V
    //   195: aload 5
    //   197: invokevirtual 134	java/lang/StringBuilder:append	(Ljava/lang/String;)Ljava/lang/StringBuilder;
    //   200: invokevirtual 137	java/lang/StringBuilder:toString	()Ljava/lang/String;
    //   203: aload_1
    //   204: invokestatic 143	android/util/Log:e	(Ljava/lang/String;Ljava/lang/String;Ljava/lang/Throwable;)I
    //   207: pop
    //   208: aconst_null
    //   209: areturn
    //   210: aload 5
    //   212: aconst_null
    //   213: ldc 68
    //   215: invokeinterface 120 3 0
    //   220: pop
    //   221: aload 5
    //   223: invokeinterface 146 1 0
    //   228: aload_0
    //   229: getfield 11	android/support/v7/widget/ac:a	Landroid/support/v7/widget/x;
    //   232: invokestatic 149	android/support/v7/widget/x:c	(Landroid/support/v7/widget/x;)Z
    //   235: pop
    //   236: aload_1
    //   237: ifnull -29 -> 208
    //   240: aload_1
    //   241: invokevirtual 154	java/io/FileOutputStream:close	()V
    //   244: aconst_null
    //   245: areturn
    //   246: astore_1
    //   247: aconst_null
    //   248: areturn
    //   249: astore 4
    //   251: invokestatic 123	android/support/v7/widget/x:d	()Ljava/lang/String;
    //   254: new 125	java/lang/StringBuilder
    //   257: dup
    //   258: ldc 127
    //   260: invokespecial 130	java/lang/StringBuilder:<init>	(Ljava/lang/String;)V
    //   263: aload_0
    //   264: getfield 11	android/support/v7/widget/ac:a	Landroid/support/v7/widget/x;
    //   267: invokestatic 157	android/support/v7/widget/x:b	(Landroid/support/v7/widget/x;)Ljava/lang/String;
    //   270: invokevirtual 134	java/lang/StringBuilder:append	(Ljava/lang/String;)Ljava/lang/StringBuilder;
    //   273: invokevirtual 137	java/lang/StringBuilder:toString	()Ljava/lang/String;
    //   276: aload 4
    //   278: invokestatic 143	android/util/Log:e	(Ljava/lang/String;Ljava/lang/String;Ljava/lang/Throwable;)I
    //   281: pop
    //   282: aload_0
    //   283: getfield 11	android/support/v7/widget/ac:a	Landroid/support/v7/widget/x;
    //   286: invokestatic 149	android/support/v7/widget/x:c	(Landroid/support/v7/widget/x;)Z
    //   289: pop
    //   290: aload_1
    //   291: ifnull -83 -> 208
    //   294: aload_1
    //   295: invokevirtual 154	java/io/FileOutputStream:close	()V
    //   298: aconst_null
    //   299: areturn
    //   300: astore_1
    //   301: aconst_null
    //   302: areturn
    //   303: astore 4
    //   305: invokestatic 123	android/support/v7/widget/x:d	()Ljava/lang/String;
    //   308: new 125	java/lang/StringBuilder
    //   311: dup
    //   312: ldc 127
    //   314: invokespecial 130	java/lang/StringBuilder:<init>	(Ljava/lang/String;)V
    //   317: aload_0
    //   318: getfield 11	android/support/v7/widget/ac:a	Landroid/support/v7/widget/x;
    //   321: invokestatic 157	android/support/v7/widget/x:b	(Landroid/support/v7/widget/x;)Ljava/lang/String;
    //   324: invokevirtual 134	java/lang/StringBuilder:append	(Ljava/lang/String;)Ljava/lang/StringBuilder;
    //   327: invokevirtual 137	java/lang/StringBuilder:toString	()Ljava/lang/String;
    //   330: aload 4
    //   332: invokestatic 143	android/util/Log:e	(Ljava/lang/String;Ljava/lang/String;Ljava/lang/Throwable;)I
    //   335: pop
    //   336: aload_0
    //   337: getfield 11	android/support/v7/widget/ac:a	Landroid/support/v7/widget/x;
    //   340: invokestatic 149	android/support/v7/widget/x:c	(Landroid/support/v7/widget/x;)Z
    //   343: pop
    //   344: aload_1
    //   345: ifnull -137 -> 208
    //   348: aload_1
    //   349: invokevirtual 154	java/io/FileOutputStream:close	()V
    //   352: aconst_null
    //   353: areturn
    //   354: astore_1
    //   355: aconst_null
    //   356: areturn
    //   357: astore 4
    //   359: invokestatic 123	android/support/v7/widget/x:d	()Ljava/lang/String;
    //   362: new 125	java/lang/StringBuilder
    //   365: dup
    //   366: ldc 127
    //   368: invokespecial 130	java/lang/StringBuilder:<init>	(Ljava/lang/String;)V
    //   371: aload_0
    //   372: getfield 11	android/support/v7/widget/ac:a	Landroid/support/v7/widget/x;
    //   375: invokestatic 157	android/support/v7/widget/x:b	(Landroid/support/v7/widget/x;)Ljava/lang/String;
    //   378: invokevirtual 134	java/lang/StringBuilder:append	(Ljava/lang/String;)Ljava/lang/StringBuilder;
    //   381: invokevirtual 137	java/lang/StringBuilder:toString	()Ljava/lang/String;
    //   384: aload 4
    //   386: invokestatic 143	android/util/Log:e	(Ljava/lang/String;Ljava/lang/String;Ljava/lang/Throwable;)I
    //   389: pop
    //   390: aload_0
    //   391: getfield 11	android/support/v7/widget/ac:a	Landroid/support/v7/widget/x;
    //   394: invokestatic 149	android/support/v7/widget/x:c	(Landroid/support/v7/widget/x;)Z
    //   397: pop
    //   398: aload_1
    //   399: ifnull -191 -> 208
    //   402: aload_1
    //   403: invokevirtual 154	java/io/FileOutputStream:close	()V
    //   406: aconst_null
    //   407: areturn
    //   408: astore_1
    //   409: aconst_null
    //   410: areturn
    //   411: astore 4
    //   413: aload_0
    //   414: getfield 11	android/support/v7/widget/ac:a	Landroid/support/v7/widget/x;
    //   417: invokestatic 149	android/support/v7/widget/x:c	(Landroid/support/v7/widget/x;)Z
    //   420: pop
    //   421: aload_1
    //   422: ifnull +7 -> 429
    //   425: aload_1
    //   426: invokevirtual 154	java/io/FileOutputStream:close	()V
    //   429: aload 4
    //   431: athrow
    //   432: astore_1
    //   433: goto -4 -> 429
    //
    // Exception table:
    //   from	to	target	type
    //   18	32	182	java/io/FileNotFoundException
    //   240	244	246	java/io/IOException
    //   37	78	249	java/lang/IllegalArgumentException
    //   83	175	249	java/lang/IllegalArgumentException
    //   210	228	249	java/lang/IllegalArgumentException
    //   294	298	300	java/io/IOException
    //   37	78	303	java/lang/IllegalStateException
    //   83	175	303	java/lang/IllegalStateException
    //   210	228	303	java/lang/IllegalStateException
    //   348	352	354	java/io/IOException
    //   37	78	357	java/io/IOException
    //   83	175	357	java/io/IOException
    //   210	228	357	java/io/IOException
    //   402	406	408	java/io/IOException
    //   37	78	411	finally
    //   83	175	411	finally
    //   210	228	411	finally
    //   251	282	411	finally
    //   305	336	411	finally
    //   359	390	411	finally
    //   425	429	432	java/io/IOException
  }
}

/* Location:           C:\crazyd\work\ustone\odm2016031702\baidu\android\nut-dex2jar.jar
 * Qualified Name:     android.support.v7.widget.ac
 * JD-Core Version:    0.6.2
 */