package com.loc;

public final class aa
{
  private ac a;
  private ad b;

  public aa(ad paramad)
  {
    this(paramad, (byte)0);
  }

  private aa(ad paramad, byte paramByte)
  {
    this.b = paramad;
    if (paramad.c == null);
    for (paramad = null; ; paramad = paramad.c)
    {
      this.a = new ac(this.b.a, this.b.b, paramad);
      this.a.b = -1L;
      this.a.c = 0L;
      return;
    }
  }

  // ERROR //
  public final void a(ab paramab)
  {
    // Byte code:
    //   0: aconst_null
    //   1: astore 6
    //   3: aconst_null
    //   4: astore 9
    //   6: aconst_null
    //   7: astore 7
    //   9: aconst_null
    //   10: astore 10
    //   12: aconst_null
    //   13: astore 14
    //   15: aconst_null
    //   16: astore 13
    //   18: aconst_null
    //   19: astore 12
    //   21: aconst_null
    //   22: astore 11
    //   24: aconst_null
    //   25: astore 8
    //   27: aconst_null
    //   28: astore 15
    //   30: aconst_null
    //   31: astore 16
    //   33: aconst_null
    //   34: astore 17
    //   36: aconst_null
    //   37: astore 5
    //   39: iconst_1
    //   40: istore_3
    //   41: aload_0
    //   42: getfield 37	com/loc/aa:a	Lcom/loc/ac;
    //   45: astore 19
    //   47: aload_0
    //   48: getfield 19	com/loc/aa:b	Lcom/loc/ad;
    //   51: invokevirtual 62	com/loc/ad:c	()Ljava/lang/String;
    //   54: astore 18
    //   56: aload_0
    //   57: getfield 19	com/loc/aa:b	Lcom/loc/ad;
    //   60: invokevirtual 65	com/loc/ad:b	()Ljava/util/Map;
    //   63: astore 20
    //   65: aload_0
    //   66: getfield 19	com/loc/aa:b	Lcom/loc/ad;
    //   69: invokevirtual 67	com/loc/ad:a	()Ljava/util/Map;
    //   72: astore 21
    //   74: aload_1
    //   75: ifnonnull +4 -> 79
    //   78: return
    //   79: aload 21
    //   81: invokestatic 70	com/loc/ac:a	(Ljava/util/Map;)Ljava/lang/String;
    //   84: astore 21
    //   86: new 72	java/lang/StringBuffer
    //   89: dup
    //   90: invokespecial 73	java/lang/StringBuffer:<init>	()V
    //   93: astore 22
    //   95: aload 22
    //   97: aload 18
    //   99: invokevirtual 77	java/lang/StringBuffer:append	(Ljava/lang/String;)Ljava/lang/StringBuffer;
    //   102: pop
    //   103: aload 21
    //   105: ifnull +16 -> 121
    //   108: aload 22
    //   110: ldc 79
    //   112: invokevirtual 77	java/lang/StringBuffer:append	(Ljava/lang/String;)Ljava/lang/StringBuffer;
    //   115: aload 21
    //   117: invokevirtual 77	java/lang/StringBuffer:append	(Ljava/lang/String;)Ljava/lang/StringBuffer;
    //   120: pop
    //   121: aload 19
    //   123: aload 22
    //   125: invokevirtual 82	java/lang/StringBuffer:toString	()Ljava/lang/String;
    //   128: aload 20
    //   130: iconst_0
    //   131: invokevirtual 85	com/loc/ac:a	(Ljava/lang/String;Ljava/util/Map;Z)Ljava/net/HttpURLConnection;
    //   134: astore 18
    //   136: aload 18
    //   138: astore 5
    //   140: aload 6
    //   142: astore 9
    //   144: aload 7
    //   146: astore 10
    //   148: aload 8
    //   150: astore 11
    //   152: aload 15
    //   154: astore 12
    //   156: aload 16
    //   158: astore 13
    //   160: aload 17
    //   162: astore 14
    //   164: aload 5
    //   166: ldc 87
    //   168: new 89	java/lang/StringBuilder
    //   171: dup
    //   172: ldc 91
    //   174: invokespecial 94	java/lang/StringBuilder:<init>	(Ljava/lang/String;)V
    //   177: aload 19
    //   179: getfield 44	com/loc/ac:c	J
    //   182: invokevirtual 97	java/lang/StringBuilder:append	(J)Ljava/lang/StringBuilder;
    //   185: ldc 99
    //   187: invokevirtual 102	java/lang/StringBuilder:append	(Ljava/lang/String;)Ljava/lang/StringBuilder;
    //   190: invokevirtual 103	java/lang/StringBuilder:toString	()Ljava/lang/String;
    //   193: invokevirtual 109	java/net/HttpURLConnection:setRequestProperty	(Ljava/lang/String;Ljava/lang/String;)V
    //   196: aload 6
    //   198: astore 9
    //   200: aload 7
    //   202: astore 10
    //   204: aload 8
    //   206: astore 11
    //   208: aload 15
    //   210: astore 12
    //   212: aload 16
    //   214: astore 13
    //   216: aload 17
    //   218: astore 14
    //   220: aload 5
    //   222: invokevirtual 112	java/net/HttpURLConnection:connect	()V
    //   225: aload 6
    //   227: astore 9
    //   229: aload 7
    //   231: astore 10
    //   233: aload 8
    //   235: astore 11
    //   237: aload 15
    //   239: astore 12
    //   241: aload 16
    //   243: astore 13
    //   245: aload 17
    //   247: astore 14
    //   249: aload 5
    //   251: invokevirtual 116	java/net/HttpURLConnection:getResponseCode	()I
    //   254: istore 4
    //   256: iload 4
    //   258: sipush 200
    //   261: if_icmpeq +531 -> 792
    //   264: iconst_1
    //   265: istore_2
    //   266: goto +1448 -> 1714
    //   269: iload_3
    //   270: iload_2
    //   271: iand
    //   272: ifeq +95 -> 367
    //   275: aload 6
    //   277: astore 9
    //   279: aload 7
    //   281: astore 10
    //   283: aload 8
    //   285: astore 11
    //   287: aload 15
    //   289: astore 12
    //   291: aload 16
    //   293: astore 13
    //   295: aload 17
    //   297: astore 14
    //   299: new 118	com/loc/l
    //   302: dup
    //   303: new 89	java/lang/StringBuilder
    //   306: dup
    //   307: ldc 120
    //   309: invokespecial 94	java/lang/StringBuilder:<init>	(Ljava/lang/String;)V
    //   312: aload 5
    //   314: invokevirtual 123	java/net/HttpURLConnection:getResponseMessage	()Ljava/lang/String;
    //   317: invokevirtual 102	java/lang/StringBuilder:append	(Ljava/lang/String;)Ljava/lang/StringBuilder;
    //   320: ldc 125
    //   322: invokevirtual 102	java/lang/StringBuilder:append	(Ljava/lang/String;)Ljava/lang/StringBuilder;
    //   325: iload 4
    //   327: invokevirtual 128	java/lang/StringBuilder:append	(I)Ljava/lang/StringBuilder;
    //   330: invokevirtual 103	java/lang/StringBuilder:toString	()Ljava/lang/String;
    //   333: invokespecial 129	com/loc/l:<init>	(Ljava/lang/String;)V
    //   336: pop
    //   337: aload 6
    //   339: astore 9
    //   341: aload 7
    //   343: astore 10
    //   345: aload 8
    //   347: astore 11
    //   349: aload 15
    //   351: astore 12
    //   353: aload 16
    //   355: astore 13
    //   357: aload 17
    //   359: astore 14
    //   361: aload_1
    //   362: invokeinterface 133 1 0
    //   367: aload 6
    //   369: astore 9
    //   371: aload 7
    //   373: astore 10
    //   375: aload 8
    //   377: astore 11
    //   379: aload 15
    //   381: astore 12
    //   383: aload 16
    //   385: astore 13
    //   387: aload 17
    //   389: astore 14
    //   391: aload 5
    //   393: invokevirtual 137	java/net/HttpURLConnection:getInputStream	()Ljava/io/InputStream;
    //   396: astore 6
    //   398: aload 6
    //   400: astore 9
    //   402: aload 6
    //   404: astore 10
    //   406: aload 6
    //   408: astore 8
    //   410: aload 5
    //   412: astore 7
    //   414: aload 6
    //   416: astore 11
    //   418: aload 6
    //   420: astore 12
    //   422: aload 6
    //   424: astore 13
    //   426: aload 6
    //   428: astore 14
    //   430: sipush 1024
    //   433: newarray byte
    //   435: astore 15
    //   437: aload 6
    //   439: astore 9
    //   441: aload 6
    //   443: astore 10
    //   445: aload 6
    //   447: astore 8
    //   449: aload 5
    //   451: astore 7
    //   453: aload 6
    //   455: astore 11
    //   457: aload 6
    //   459: astore 12
    //   461: aload 6
    //   463: astore 13
    //   465: aload 6
    //   467: astore 14
    //   469: invokestatic 143	java/lang/Thread:interrupted	()Z
    //   472: ifne +504 -> 976
    //   475: aload 6
    //   477: astore 9
    //   479: aload 6
    //   481: astore 10
    //   483: aload 6
    //   485: astore 8
    //   487: aload 5
    //   489: astore 7
    //   491: aload 6
    //   493: astore 11
    //   495: aload 6
    //   497: astore 12
    //   499: aload 6
    //   501: astore 13
    //   503: aload 6
    //   505: astore 14
    //   507: aload 19
    //   509: getfield 146	com/loc/ac:a	Z
    //   512: ifne +464 -> 976
    //   515: aload 6
    //   517: astore 9
    //   519: aload 6
    //   521: astore 10
    //   523: aload 6
    //   525: astore 8
    //   527: aload 5
    //   529: astore 7
    //   531: aload 6
    //   533: astore 11
    //   535: aload 6
    //   537: astore 12
    //   539: aload 6
    //   541: astore 13
    //   543: aload 6
    //   545: astore 14
    //   547: aload 6
    //   549: aload 15
    //   551: iconst_0
    //   552: sipush 1024
    //   555: invokevirtual 152	java/io/InputStream:read	([BII)I
    //   558: istore_2
    //   559: iload_2
    //   560: ifle +416 -> 976
    //   563: aload 6
    //   565: astore 9
    //   567: aload 6
    //   569: astore 10
    //   571: aload 6
    //   573: astore 8
    //   575: aload 5
    //   577: astore 7
    //   579: aload 6
    //   581: astore 11
    //   583: aload 6
    //   585: astore 12
    //   587: aload 6
    //   589: astore 13
    //   591: aload 6
    //   593: astore 14
    //   595: aload 19
    //   597: getfield 42	com/loc/ac:b	J
    //   600: ldc2_w 38
    //   603: lcmp
    //   604: ifeq +49 -> 653
    //   607: aload 6
    //   609: astore 9
    //   611: aload 6
    //   613: astore 10
    //   615: aload 6
    //   617: astore 8
    //   619: aload 5
    //   621: astore 7
    //   623: aload 6
    //   625: astore 11
    //   627: aload 6
    //   629: astore 12
    //   631: aload 6
    //   633: astore 13
    //   635: aload 6
    //   637: astore 14
    //   639: aload 19
    //   641: getfield 44	com/loc/ac:c	J
    //   644: aload 19
    //   646: getfield 42	com/loc/ac:b	J
    //   649: lcmp
    //   650: ifge +326 -> 976
    //   653: iload_2
    //   654: sipush 1024
    //   657: if_icmpne +145 -> 802
    //   660: aload 6
    //   662: astore 9
    //   664: aload 6
    //   666: astore 10
    //   668: aload 6
    //   670: astore 8
    //   672: aload 5
    //   674: astore 7
    //   676: aload 6
    //   678: astore 11
    //   680: aload 6
    //   682: astore 12
    //   684: aload 6
    //   686: astore 13
    //   688: aload 6
    //   690: astore 14
    //   692: aload_1
    //   693: aload 15
    //   695: aload 19
    //   697: getfield 44	com/loc/ac:c	J
    //   700: invokeinterface 155 4 0
    //   705: aload 6
    //   707: astore 9
    //   709: aload 6
    //   711: astore 10
    //   713: aload 6
    //   715: astore 8
    //   717: aload 5
    //   719: astore 7
    //   721: aload 6
    //   723: astore 11
    //   725: aload 6
    //   727: astore 12
    //   729: aload 6
    //   731: astore 13
    //   733: aload 6
    //   735: astore 14
    //   737: aload 19
    //   739: aload 19
    //   741: getfield 44	com/loc/ac:c	J
    //   744: iload_2
    //   745: i2l
    //   746: ladd
    //   747: putfield 44	com/loc/ac:c	J
    //   750: goto -313 -> 437
    //   753: astore 7
    //   755: aload_1
    //   756: invokeinterface 133 1 0
    //   761: aload 6
    //   763: ifnull +8 -> 771
    //   766: aload 6
    //   768: invokevirtual 158	java/io/InputStream:close	()V
    //   771: aload 5
    //   773: ifnull -695 -> 78
    //   776: aload 5
    //   778: invokevirtual 161	java/net/HttpURLConnection:disconnect	()V
    //   781: return
    //   782: astore_1
    //   783: aload_1
    //   784: invokevirtual 164	java/lang/Throwable:printStackTrace	()V
    //   787: aload_1
    //   788: invokevirtual 164	java/lang/Throwable:printStackTrace	()V
    //   791: return
    //   792: iconst_0
    //   793: istore_2
    //   794: goto +920 -> 1714
    //   797: iconst_0
    //   798: istore_3
    //   799: goto -530 -> 269
    //   802: aload 6
    //   804: astore 9
    //   806: aload 6
    //   808: astore 10
    //   810: aload 6
    //   812: astore 8
    //   814: aload 5
    //   816: astore 7
    //   818: aload 6
    //   820: astore 11
    //   822: aload 6
    //   824: astore 12
    //   826: aload 6
    //   828: astore 13
    //   830: aload 6
    //   832: astore 14
    //   834: iload_2
    //   835: newarray byte
    //   837: astore 16
    //   839: aload 6
    //   841: astore 9
    //   843: aload 6
    //   845: astore 10
    //   847: aload 6
    //   849: astore 8
    //   851: aload 5
    //   853: astore 7
    //   855: aload 6
    //   857: astore 11
    //   859: aload 6
    //   861: astore 12
    //   863: aload 6
    //   865: astore 13
    //   867: aload 6
    //   869: astore 14
    //   871: aload 15
    //   873: iconst_0
    //   874: aload 16
    //   876: iconst_0
    //   877: iload_2
    //   878: invokestatic 170	java/lang/System:arraycopy	(Ljava/lang/Object;ILjava/lang/Object;II)V
    //   881: aload 6
    //   883: astore 9
    //   885: aload 6
    //   887: astore 10
    //   889: aload 6
    //   891: astore 8
    //   893: aload 5
    //   895: astore 7
    //   897: aload 6
    //   899: astore 11
    //   901: aload 6
    //   903: astore 12
    //   905: aload 6
    //   907: astore 13
    //   909: aload 6
    //   911: astore 14
    //   913: aload_1
    //   914: aload 16
    //   916: aload 19
    //   918: getfield 44	com/loc/ac:c	J
    //   921: invokeinterface 155 4 0
    //   926: goto -221 -> 705
    //   929: astore 6
    //   931: aload 9
    //   933: astore 8
    //   935: aload 5
    //   937: astore 7
    //   939: aload_1
    //   940: invokeinterface 133 1 0
    //   945: aload 9
    //   947: ifnull +8 -> 955
    //   950: aload 9
    //   952: invokevirtual 158	java/io/InputStream:close	()V
    //   955: aload 5
    //   957: ifnull -879 -> 78
    //   960: aload 5
    //   962: invokevirtual 161	java/net/HttpURLConnection:disconnect	()V
    //   965: return
    //   966: astore_1
    //   967: aload_1
    //   968: invokevirtual 164	java/lang/Throwable:printStackTrace	()V
    //   971: aload_1
    //   972: invokevirtual 164	java/lang/Throwable:printStackTrace	()V
    //   975: return
    //   976: aload 6
    //   978: astore 9
    //   980: aload 6
    //   982: astore 10
    //   984: aload 6
    //   986: astore 8
    //   988: aload 5
    //   990: astore 7
    //   992: aload 6
    //   994: astore 11
    //   996: aload 6
    //   998: astore 12
    //   1000: aload 6
    //   1002: astore 13
    //   1004: aload 6
    //   1006: astore 14
    //   1008: aload 19
    //   1010: getfield 146	com/loc/ac:a	Z
    //   1013: ifeq +72 -> 1085
    //   1016: aload 6
    //   1018: astore 9
    //   1020: aload 6
    //   1022: astore 10
    //   1024: aload 6
    //   1026: astore 8
    //   1028: aload 5
    //   1030: astore 7
    //   1032: aload 6
    //   1034: astore 11
    //   1036: aload 6
    //   1038: astore 12
    //   1040: aload 6
    //   1042: astore 13
    //   1044: aload 6
    //   1046: astore 14
    //   1048: aload_1
    //   1049: invokeinterface 173 1 0
    //   1054: aload 6
    //   1056: ifnull +8 -> 1064
    //   1059: aload 6
    //   1061: invokevirtual 158	java/io/InputStream:close	()V
    //   1064: aload 5
    //   1066: ifnull -988 -> 78
    //   1069: aload 5
    //   1071: invokevirtual 161	java/net/HttpURLConnection:disconnect	()V
    //   1074: return
    //   1075: astore_1
    //   1076: aload_1
    //   1077: invokevirtual 164	java/lang/Throwable:printStackTrace	()V
    //   1080: aload_1
    //   1081: invokevirtual 164	java/lang/Throwable:printStackTrace	()V
    //   1084: return
    //   1085: aload 6
    //   1087: astore 9
    //   1089: aload 6
    //   1091: astore 10
    //   1093: aload 6
    //   1095: astore 8
    //   1097: aload 5
    //   1099: astore 7
    //   1101: aload 6
    //   1103: astore 11
    //   1105: aload 6
    //   1107: astore 12
    //   1109: aload 6
    //   1111: astore 13
    //   1113: aload 6
    //   1115: astore 14
    //   1117: aload_1
    //   1118: invokeinterface 175 1 0
    //   1123: goto -69 -> 1054
    //   1126: astore 6
    //   1128: aload 10
    //   1130: astore 8
    //   1132: aload 5
    //   1134: astore 7
    //   1136: aload_1
    //   1137: invokeinterface 133 1 0
    //   1142: aload 10
    //   1144: ifnull +8 -> 1152
    //   1147: aload 10
    //   1149: invokevirtual 158	java/io/InputStream:close	()V
    //   1152: aload 5
    //   1154: ifnull -1076 -> 78
    //   1157: aload 5
    //   1159: invokevirtual 161	java/net/HttpURLConnection:disconnect	()V
    //   1162: return
    //   1163: astore_1
    //   1164: aload_1
    //   1165: invokevirtual 164	java/lang/Throwable:printStackTrace	()V
    //   1168: aload_1
    //   1169: invokevirtual 164	java/lang/Throwable:printStackTrace	()V
    //   1172: return
    //   1173: astore_1
    //   1174: aload_1
    //   1175: invokevirtual 176	java/io/IOException:printStackTrace	()V
    //   1178: aload_1
    //   1179: invokevirtual 164	java/lang/Throwable:printStackTrace	()V
    //   1182: goto -118 -> 1064
    //   1185: astore_1
    //   1186: aload_1
    //   1187: invokevirtual 164	java/lang/Throwable:printStackTrace	()V
    //   1190: aload_1
    //   1191: invokevirtual 164	java/lang/Throwable:printStackTrace	()V
    //   1194: goto -130 -> 1064
    //   1197: astore_1
    //   1198: aload_1
    //   1199: invokevirtual 176	java/io/IOException:printStackTrace	()V
    //   1202: aload_1
    //   1203: invokevirtual 164	java/lang/Throwable:printStackTrace	()V
    //   1206: goto -435 -> 771
    //   1209: astore_1
    //   1210: aload_1
    //   1211: invokevirtual 164	java/lang/Throwable:printStackTrace	()V
    //   1214: aload_1
    //   1215: invokevirtual 164	java/lang/Throwable:printStackTrace	()V
    //   1218: goto -447 -> 771
    //   1221: astore_1
    //   1222: aload_1
    //   1223: invokevirtual 176	java/io/IOException:printStackTrace	()V
    //   1226: aload_1
    //   1227: invokevirtual 164	java/lang/Throwable:printStackTrace	()V
    //   1230: goto -275 -> 955
    //   1233: astore_1
    //   1234: aload_1
    //   1235: invokevirtual 164	java/lang/Throwable:printStackTrace	()V
    //   1238: aload_1
    //   1239: invokevirtual 164	java/lang/Throwable:printStackTrace	()V
    //   1242: goto -287 -> 955
    //   1245: astore_1
    //   1246: aload_1
    //   1247: invokevirtual 176	java/io/IOException:printStackTrace	()V
    //   1250: aload_1
    //   1251: invokevirtual 164	java/lang/Throwable:printStackTrace	()V
    //   1254: goto -102 -> 1152
    //   1257: astore_1
    //   1258: aload_1
    //   1259: invokevirtual 164	java/lang/Throwable:printStackTrace	()V
    //   1262: aload_1
    //   1263: invokevirtual 164	java/lang/Throwable:printStackTrace	()V
    //   1266: goto -114 -> 1152
    //   1269: astore 5
    //   1271: aconst_null
    //   1272: astore 5
    //   1274: aload 14
    //   1276: astore 8
    //   1278: aload 5
    //   1280: astore 7
    //   1282: aload_1
    //   1283: invokeinterface 133 1 0
    //   1288: aload 14
    //   1290: ifnull +8 -> 1298
    //   1293: aload 14
    //   1295: invokevirtual 158	java/io/InputStream:close	()V
    //   1298: aload 5
    //   1300: ifnull -1222 -> 78
    //   1303: aload 5
    //   1305: invokevirtual 161	java/net/HttpURLConnection:disconnect	()V
    //   1308: return
    //   1309: astore_1
    //   1310: aload_1
    //   1311: invokevirtual 164	java/lang/Throwable:printStackTrace	()V
    //   1314: aload_1
    //   1315: invokevirtual 164	java/lang/Throwable:printStackTrace	()V
    //   1318: return
    //   1319: astore_1
    //   1320: aload_1
    //   1321: invokevirtual 176	java/io/IOException:printStackTrace	()V
    //   1324: aload_1
    //   1325: invokevirtual 164	java/lang/Throwable:printStackTrace	()V
    //   1328: goto -30 -> 1298
    //   1331: astore_1
    //   1332: aload_1
    //   1333: invokevirtual 164	java/lang/Throwable:printStackTrace	()V
    //   1336: aload_1
    //   1337: invokevirtual 164	java/lang/Throwable:printStackTrace	()V
    //   1340: goto -42 -> 1298
    //   1343: astore 5
    //   1345: aconst_null
    //   1346: astore 5
    //   1348: aload 13
    //   1350: astore 8
    //   1352: aload 5
    //   1354: astore 7
    //   1356: aload_1
    //   1357: invokeinterface 133 1 0
    //   1362: aload 13
    //   1364: ifnull +8 -> 1372
    //   1367: aload 13
    //   1369: invokevirtual 158	java/io/InputStream:close	()V
    //   1372: aload 5
    //   1374: ifnull -1296 -> 78
    //   1377: aload 5
    //   1379: invokevirtual 161	java/net/HttpURLConnection:disconnect	()V
    //   1382: return
    //   1383: astore_1
    //   1384: aload_1
    //   1385: invokevirtual 164	java/lang/Throwable:printStackTrace	()V
    //   1388: aload_1
    //   1389: invokevirtual 164	java/lang/Throwable:printStackTrace	()V
    //   1392: return
    //   1393: astore_1
    //   1394: aload_1
    //   1395: invokevirtual 176	java/io/IOException:printStackTrace	()V
    //   1398: aload_1
    //   1399: invokevirtual 164	java/lang/Throwable:printStackTrace	()V
    //   1402: goto -30 -> 1372
    //   1405: astore_1
    //   1406: aload_1
    //   1407: invokevirtual 164	java/lang/Throwable:printStackTrace	()V
    //   1410: aload_1
    //   1411: invokevirtual 164	java/lang/Throwable:printStackTrace	()V
    //   1414: goto -42 -> 1372
    //   1417: astore 5
    //   1419: aconst_null
    //   1420: astore 5
    //   1422: aload 12
    //   1424: astore 8
    //   1426: aload 5
    //   1428: astore 7
    //   1430: aload_1
    //   1431: invokeinterface 133 1 0
    //   1436: aload 12
    //   1438: ifnull +8 -> 1446
    //   1441: aload 12
    //   1443: invokevirtual 158	java/io/InputStream:close	()V
    //   1446: aload 5
    //   1448: ifnull -1370 -> 78
    //   1451: aload 5
    //   1453: invokevirtual 161	java/net/HttpURLConnection:disconnect	()V
    //   1456: return
    //   1457: astore_1
    //   1458: aload_1
    //   1459: invokevirtual 164	java/lang/Throwable:printStackTrace	()V
    //   1462: aload_1
    //   1463: invokevirtual 164	java/lang/Throwable:printStackTrace	()V
    //   1466: return
    //   1467: astore_1
    //   1468: aload_1
    //   1469: invokevirtual 176	java/io/IOException:printStackTrace	()V
    //   1472: aload_1
    //   1473: invokevirtual 164	java/lang/Throwable:printStackTrace	()V
    //   1476: goto -30 -> 1446
    //   1479: astore_1
    //   1480: aload_1
    //   1481: invokevirtual 164	java/lang/Throwable:printStackTrace	()V
    //   1484: aload_1
    //   1485: invokevirtual 164	java/lang/Throwable:printStackTrace	()V
    //   1488: goto -42 -> 1446
    //   1491: astore 5
    //   1493: aconst_null
    //   1494: astore 5
    //   1496: aload 11
    //   1498: astore 8
    //   1500: aload 5
    //   1502: astore 7
    //   1504: aload_1
    //   1505: invokeinterface 133 1 0
    //   1510: aload 11
    //   1512: ifnull +8 -> 1520
    //   1515: aload 11
    //   1517: invokevirtual 158	java/io/InputStream:close	()V
    //   1520: aload 5
    //   1522: ifnull -1444 -> 78
    //   1525: aload 5
    //   1527: invokevirtual 161	java/net/HttpURLConnection:disconnect	()V
    //   1530: return
    //   1531: astore_1
    //   1532: aload_1
    //   1533: invokevirtual 164	java/lang/Throwable:printStackTrace	()V
    //   1536: aload_1
    //   1537: invokevirtual 164	java/lang/Throwable:printStackTrace	()V
    //   1540: return
    //   1541: astore_1
    //   1542: aload_1
    //   1543: invokevirtual 176	java/io/IOException:printStackTrace	()V
    //   1546: aload_1
    //   1547: invokevirtual 164	java/lang/Throwable:printStackTrace	()V
    //   1550: goto -30 -> 1520
    //   1553: astore_1
    //   1554: aload_1
    //   1555: invokevirtual 164	java/lang/Throwable:printStackTrace	()V
    //   1558: aload_1
    //   1559: invokevirtual 164	java/lang/Throwable:printStackTrace	()V
    //   1562: goto -42 -> 1520
    //   1565: astore_1
    //   1566: aconst_null
    //   1567: astore 6
    //   1569: aconst_null
    //   1570: astore 5
    //   1572: aload 6
    //   1574: ifnull +8 -> 1582
    //   1577: aload 6
    //   1579: invokevirtual 158	java/io/InputStream:close	()V
    //   1582: aload 5
    //   1584: ifnull +8 -> 1592
    //   1587: aload 5
    //   1589: invokevirtual 161	java/net/HttpURLConnection:disconnect	()V
    //   1592: aload_1
    //   1593: athrow
    //   1594: astore 6
    //   1596: aload 6
    //   1598: invokevirtual 176	java/io/IOException:printStackTrace	()V
    //   1601: aload 6
    //   1603: invokevirtual 164	java/lang/Throwable:printStackTrace	()V
    //   1606: goto -24 -> 1582
    //   1609: astore 6
    //   1611: aload 6
    //   1613: invokevirtual 164	java/lang/Throwable:printStackTrace	()V
    //   1616: aload 6
    //   1618: invokevirtual 164	java/lang/Throwable:printStackTrace	()V
    //   1621: goto -39 -> 1582
    //   1624: astore 5
    //   1626: aload 5
    //   1628: invokevirtual 164	java/lang/Throwable:printStackTrace	()V
    //   1631: aload 5
    //   1633: invokevirtual 164	java/lang/Throwable:printStackTrace	()V
    //   1636: goto -44 -> 1592
    //   1639: astore_1
    //   1640: aconst_null
    //   1641: astore 6
    //   1643: goto -71 -> 1572
    //   1646: astore_1
    //   1647: aload 8
    //   1649: astore 6
    //   1651: aload 7
    //   1653: astore 5
    //   1655: goto -83 -> 1572
    //   1658: astore_1
    //   1659: goto -87 -> 1572
    //   1662: astore 6
    //   1664: goto -168 -> 1496
    //   1667: astore 6
    //   1669: goto -247 -> 1422
    //   1672: astore 6
    //   1674: goto -326 -> 1348
    //   1677: astore 6
    //   1679: goto -405 -> 1274
    //   1682: astore 5
    //   1684: aconst_null
    //   1685: astore 5
    //   1687: goto -559 -> 1128
    //   1690: astore 5
    //   1692: aconst_null
    //   1693: astore 5
    //   1695: goto -764 -> 931
    //   1698: astore 6
    //   1700: aconst_null
    //   1701: astore 6
    //   1703: goto -948 -> 755
    //   1706: astore 6
    //   1708: aconst_null
    //   1709: astore 6
    //   1711: goto -956 -> 755
    //   1714: iload 4
    //   1716: sipush 206
    //   1719: if_icmpeq -922 -> 797
    //   1722: goto -1453 -> 269
    //
    // Exception table:
    //   from	to	target	type
    //   430	437	753	java/net/ConnectException
    //   469	475	753	java/net/ConnectException
    //   507	515	753	java/net/ConnectException
    //   547	559	753	java/net/ConnectException
    //   595	607	753	java/net/ConnectException
    //   639	653	753	java/net/ConnectException
    //   692	705	753	java/net/ConnectException
    //   737	750	753	java/net/ConnectException
    //   834	839	753	java/net/ConnectException
    //   871	881	753	java/net/ConnectException
    //   913	926	753	java/net/ConnectException
    //   1008	1016	753	java/net/ConnectException
    //   1048	1054	753	java/net/ConnectException
    //   1117	1123	753	java/net/ConnectException
    //   776	781	782	java/lang/Throwable
    //   164	196	929	java/net/MalformedURLException
    //   220	225	929	java/net/MalformedURLException
    //   249	256	929	java/net/MalformedURLException
    //   299	337	929	java/net/MalformedURLException
    //   361	367	929	java/net/MalformedURLException
    //   391	398	929	java/net/MalformedURLException
    //   430	437	929	java/net/MalformedURLException
    //   469	475	929	java/net/MalformedURLException
    //   507	515	929	java/net/MalformedURLException
    //   547	559	929	java/net/MalformedURLException
    //   595	607	929	java/net/MalformedURLException
    //   639	653	929	java/net/MalformedURLException
    //   692	705	929	java/net/MalformedURLException
    //   737	750	929	java/net/MalformedURLException
    //   834	839	929	java/net/MalformedURLException
    //   871	881	929	java/net/MalformedURLException
    //   913	926	929	java/net/MalformedURLException
    //   1008	1016	929	java/net/MalformedURLException
    //   1048	1054	929	java/net/MalformedURLException
    //   1117	1123	929	java/net/MalformedURLException
    //   960	965	966	java/lang/Throwable
    //   1069	1074	1075	java/lang/Throwable
    //   164	196	1126	java/net/UnknownHostException
    //   220	225	1126	java/net/UnknownHostException
    //   249	256	1126	java/net/UnknownHostException
    //   299	337	1126	java/net/UnknownHostException
    //   361	367	1126	java/net/UnknownHostException
    //   391	398	1126	java/net/UnknownHostException
    //   430	437	1126	java/net/UnknownHostException
    //   469	475	1126	java/net/UnknownHostException
    //   507	515	1126	java/net/UnknownHostException
    //   547	559	1126	java/net/UnknownHostException
    //   595	607	1126	java/net/UnknownHostException
    //   639	653	1126	java/net/UnknownHostException
    //   692	705	1126	java/net/UnknownHostException
    //   737	750	1126	java/net/UnknownHostException
    //   834	839	1126	java/net/UnknownHostException
    //   871	881	1126	java/net/UnknownHostException
    //   913	926	1126	java/net/UnknownHostException
    //   1008	1016	1126	java/net/UnknownHostException
    //   1048	1054	1126	java/net/UnknownHostException
    //   1117	1123	1126	java/net/UnknownHostException
    //   1157	1162	1163	java/lang/Throwable
    //   1059	1064	1173	java/io/IOException
    //   1059	1064	1185	java/lang/Throwable
    //   766	771	1197	java/io/IOException
    //   766	771	1209	java/lang/Throwable
    //   950	955	1221	java/io/IOException
    //   950	955	1233	java/lang/Throwable
    //   1147	1152	1245	java/io/IOException
    //   1147	1152	1257	java/lang/Throwable
    //   79	103	1269	java/net/SocketException
    //   108	121	1269	java/net/SocketException
    //   121	136	1269	java/net/SocketException
    //   1303	1308	1309	java/lang/Throwable
    //   1293	1298	1319	java/io/IOException
    //   1293	1298	1331	java/lang/Throwable
    //   79	103	1343	java/net/SocketTimeoutException
    //   108	121	1343	java/net/SocketTimeoutException
    //   121	136	1343	java/net/SocketTimeoutException
    //   1377	1382	1383	java/lang/Throwable
    //   1367	1372	1393	java/io/IOException
    //   1367	1372	1405	java/lang/Throwable
    //   79	103	1417	java/io/IOException
    //   108	121	1417	java/io/IOException
    //   121	136	1417	java/io/IOException
    //   1451	1456	1457	java/lang/Throwable
    //   1441	1446	1467	java/io/IOException
    //   1441	1446	1479	java/lang/Throwable
    //   79	103	1491	java/lang/Throwable
    //   108	121	1491	java/lang/Throwable
    //   121	136	1491	java/lang/Throwable
    //   1525	1530	1531	java/lang/Throwable
    //   1515	1520	1541	java/io/IOException
    //   1515	1520	1553	java/lang/Throwable
    //   79	103	1565	finally
    //   108	121	1565	finally
    //   121	136	1565	finally
    //   1577	1582	1594	java/io/IOException
    //   1577	1582	1609	java/lang/Throwable
    //   1587	1592	1624	java/lang/Throwable
    //   164	196	1639	finally
    //   220	225	1639	finally
    //   249	256	1639	finally
    //   299	337	1639	finally
    //   361	367	1639	finally
    //   391	398	1639	finally
    //   430	437	1646	finally
    //   469	475	1646	finally
    //   507	515	1646	finally
    //   547	559	1646	finally
    //   595	607	1646	finally
    //   639	653	1646	finally
    //   692	705	1646	finally
    //   737	750	1646	finally
    //   834	839	1646	finally
    //   871	881	1646	finally
    //   913	926	1646	finally
    //   939	945	1646	finally
    //   1008	1016	1646	finally
    //   1048	1054	1646	finally
    //   1117	1123	1646	finally
    //   1136	1142	1646	finally
    //   1282	1288	1646	finally
    //   1356	1362	1646	finally
    //   1430	1436	1646	finally
    //   1504	1510	1646	finally
    //   755	761	1658	finally
    //   164	196	1662	java/lang/Throwable
    //   220	225	1662	java/lang/Throwable
    //   249	256	1662	java/lang/Throwable
    //   299	337	1662	java/lang/Throwable
    //   361	367	1662	java/lang/Throwable
    //   391	398	1662	java/lang/Throwable
    //   430	437	1662	java/lang/Throwable
    //   469	475	1662	java/lang/Throwable
    //   507	515	1662	java/lang/Throwable
    //   547	559	1662	java/lang/Throwable
    //   595	607	1662	java/lang/Throwable
    //   639	653	1662	java/lang/Throwable
    //   692	705	1662	java/lang/Throwable
    //   737	750	1662	java/lang/Throwable
    //   834	839	1662	java/lang/Throwable
    //   871	881	1662	java/lang/Throwable
    //   913	926	1662	java/lang/Throwable
    //   1008	1016	1662	java/lang/Throwable
    //   1048	1054	1662	java/lang/Throwable
    //   1117	1123	1662	java/lang/Throwable
    //   164	196	1667	java/io/IOException
    //   220	225	1667	java/io/IOException
    //   249	256	1667	java/io/IOException
    //   299	337	1667	java/io/IOException
    //   361	367	1667	java/io/IOException
    //   391	398	1667	java/io/IOException
    //   430	437	1667	java/io/IOException
    //   469	475	1667	java/io/IOException
    //   507	515	1667	java/io/IOException
    //   547	559	1667	java/io/IOException
    //   595	607	1667	java/io/IOException
    //   639	653	1667	java/io/IOException
    //   692	705	1667	java/io/IOException
    //   737	750	1667	java/io/IOException
    //   834	839	1667	java/io/IOException
    //   871	881	1667	java/io/IOException
    //   913	926	1667	java/io/IOException
    //   1008	1016	1667	java/io/IOException
    //   1048	1054	1667	java/io/IOException
    //   1117	1123	1667	java/io/IOException
    //   164	196	1672	java/net/SocketTimeoutException
    //   220	225	1672	java/net/SocketTimeoutException
    //   249	256	1672	java/net/SocketTimeoutException
    //   299	337	1672	java/net/SocketTimeoutException
    //   361	367	1672	java/net/SocketTimeoutException
    //   391	398	1672	java/net/SocketTimeoutException
    //   430	437	1672	java/net/SocketTimeoutException
    //   469	475	1672	java/net/SocketTimeoutException
    //   507	515	1672	java/net/SocketTimeoutException
    //   547	559	1672	java/net/SocketTimeoutException
    //   595	607	1672	java/net/SocketTimeoutException
    //   639	653	1672	java/net/SocketTimeoutException
    //   692	705	1672	java/net/SocketTimeoutException
    //   737	750	1672	java/net/SocketTimeoutException
    //   834	839	1672	java/net/SocketTimeoutException
    //   871	881	1672	java/net/SocketTimeoutException
    //   913	926	1672	java/net/SocketTimeoutException
    //   1008	1016	1672	java/net/SocketTimeoutException
    //   1048	1054	1672	java/net/SocketTimeoutException
    //   1117	1123	1672	java/net/SocketTimeoutException
    //   164	196	1677	java/net/SocketException
    //   220	225	1677	java/net/SocketException
    //   249	256	1677	java/net/SocketException
    //   299	337	1677	java/net/SocketException
    //   361	367	1677	java/net/SocketException
    //   391	398	1677	java/net/SocketException
    //   430	437	1677	java/net/SocketException
    //   469	475	1677	java/net/SocketException
    //   507	515	1677	java/net/SocketException
    //   547	559	1677	java/net/SocketException
    //   595	607	1677	java/net/SocketException
    //   639	653	1677	java/net/SocketException
    //   692	705	1677	java/net/SocketException
    //   737	750	1677	java/net/SocketException
    //   834	839	1677	java/net/SocketException
    //   871	881	1677	java/net/SocketException
    //   913	926	1677	java/net/SocketException
    //   1008	1016	1677	java/net/SocketException
    //   1048	1054	1677	java/net/SocketException
    //   1117	1123	1677	java/net/SocketException
    //   79	103	1682	java/net/UnknownHostException
    //   108	121	1682	java/net/UnknownHostException
    //   121	136	1682	java/net/UnknownHostException
    //   79	103	1690	java/net/MalformedURLException
    //   108	121	1690	java/net/MalformedURLException
    //   121	136	1690	java/net/MalformedURLException
    //   79	103	1698	java/net/ConnectException
    //   108	121	1698	java/net/ConnectException
    //   121	136	1698	java/net/ConnectException
    //   164	196	1706	java/net/ConnectException
    //   220	225	1706	java/net/ConnectException
    //   249	256	1706	java/net/ConnectException
    //   299	337	1706	java/net/ConnectException
    //   361	367	1706	java/net/ConnectException
    //   391	398	1706	java/net/ConnectException
  }
}

/* Location:           C:\crazyd\work\ustone\odm2016031702\baidu\android\nut-dex2jar.jar
 * Qualified Name:     com.loc.aa
 * JD-Core Version:    0.6.2
 */