package com.loc;

import android.content.BroadcastReceiver;

final class ak extends BroadcastReceiver
{
  private ak(ag paramag)
  {
  }

  // ERROR //
  public final void onReceive(android.content.Context paramContext, android.content.Intent arg2)
  {
    // Byte code:
    //   0: iconst_4
    //   1: istore 4
    //   3: aload_1
    //   4: ifnull +7 -> 11
    //   7: aload_2
    //   8: ifnonnull +4 -> 12
    //   11: return
    //   12: aload_2
    //   13: invokevirtual 29	android/content/Intent:getAction	()Ljava/lang/String;
    //   16: astore_1
    //   17: aload_1
    //   18: invokestatic 35	android/text/TextUtils:isEmpty	(Ljava/lang/CharSequence;)Z
    //   21: ifne -10 -> 11
    //   24: aload_0
    //   25: getfield 10	com/loc/ak:a	Lcom/loc/ag;
    //   28: invokestatic 40	com/loc/ag:a	(Lcom/loc/ag;)Lcom/loc/be;
    //   31: astore_2
    //   32: aload_1
    //   33: ldc 42
    //   35: invokevirtual 48	java/lang/String:equals	(Ljava/lang/Object;)Z
    //   38: istore 5
    //   40: iload 5
    //   42: ifeq +77 -> 119
    //   45: aload_2
    //   46: ifnull -35 -> 11
    //   49: aconst_null
    //   50: astore_1
    //   51: aload_2
    //   52: invokevirtual 53	com/loc/be:a	()Ljava/util/List;
    //   55: astore_2
    //   56: aload_2
    //   57: astore_1
    //   58: aload_1
    //   59: ifnull +37 -> 96
    //   62: aload_0
    //   63: getfield 10	com/loc/ak:a	Lcom/loc/ag;
    //   66: getfield 57	com/loc/ag:k	Ljava/lang/Object;
    //   69: astore_2
    //   70: aload_2
    //   71: monitorenter
    //   72: aload_0
    //   73: getfield 10	com/loc/ak:a	Lcom/loc/ag;
    //   76: invokestatic 61	com/loc/ag:b	(Lcom/loc/ag;)Ljava/util/ArrayList;
    //   79: invokevirtual 66	java/util/ArrayList:clear	()V
    //   82: aload_0
    //   83: getfield 10	com/loc/ak:a	Lcom/loc/ag;
    //   86: invokestatic 61	com/loc/ag:b	(Lcom/loc/ag;)Ljava/util/ArrayList;
    //   89: aload_1
    //   90: invokevirtual 70	java/util/ArrayList:addAll	(Ljava/util/Collection;)Z
    //   93: pop
    //   94: aload_2
    //   95: monitorexit
    //   96: aload_0
    //   97: getfield 10	com/loc/ak:a	Lcom/loc/ag;
    //   100: invokestatic 75	com/loc/by:b	()J
    //   103: invokestatic 78	com/loc/ag:a	(Lcom/loc/ag;J)J
    //   106: pop2
    //   107: return
    //   108: astore_1
    //   109: aload_1
    //   110: invokevirtual 81	java/lang/Throwable:printStackTrace	()V
    //   113: return
    //   114: astore_1
    //   115: aload_2
    //   116: monitorexit
    //   117: aload_1
    //   118: athrow
    //   119: aload_1
    //   120: ldc 83
    //   122: invokevirtual 48	java/lang/String:equals	(Ljava/lang/Object;)Z
    //   125: ifeq +85 -> 210
    //   128: aload_0
    //   129: getfield 10	com/loc/ak:a	Lcom/loc/ag;
    //   132: invokestatic 40	com/loc/ag:a	(Lcom/loc/ag;)Lcom/loc/be;
    //   135: astore_1
    //   136: aload_1
    //   137: ifnull -126 -> 11
    //   140: iload 4
    //   142: istore_3
    //   143: aload_2
    //   144: getfield 86	com/loc/be:a	Landroid/net/wifi/WifiManager;
    //   147: ifnull +11 -> 158
    //   150: aload_2
    //   151: getfield 86	com/loc/be:a	Landroid/net/wifi/WifiManager;
    //   154: invokevirtual 92	android/net/wifi/WifiManager:getWifiState	()I
    //   157: istore_3
    //   158: aload_0
    //   159: getfield 10	com/loc/ak:a	Lcom/loc/ag;
    //   162: invokestatic 61	com/loc/ag:b	(Lcom/loc/ag;)Ljava/util/ArrayList;
    //   165: ifnonnull +155 -> 320
    //   168: aload_0
    //   169: getfield 10	com/loc/ak:a	Lcom/loc/ag;
    //   172: new 63	java/util/ArrayList
    //   175: dup
    //   176: invokespecial 93	java/util/ArrayList:<init>	()V
    //   179: invokestatic 96	com/loc/ag:a	(Lcom/loc/ag;Ljava/util/ArrayList;)Ljava/util/ArrayList;
    //   182: pop
    //   183: goto +137 -> 320
    //   186: aload_0
    //   187: getfield 10	com/loc/ak:a	Lcom/loc/ag;
    //   190: invokestatic 99	com/loc/ag:c	(Lcom/loc/ag;)V
    //   193: return
    //   194: aload_0
    //   195: getfield 10	com/loc/ak:a	Lcom/loc/ag;
    //   198: invokestatic 99	com/loc/ag:c	(Lcom/loc/ag;)V
    //   201: return
    //   202: aload_0
    //   203: getfield 10	com/loc/ak:a	Lcom/loc/ag;
    //   206: invokestatic 99	com/loc/ag:c	(Lcom/loc/ag;)V
    //   209: return
    //   210: aload_1
    //   211: ldc 101
    //   213: invokevirtual 48	java/lang/String:equals	(Ljava/lang/Object;)Z
    //   216: ifeq +12 -> 228
    //   219: aload_0
    //   220: getfield 10	com/loc/ak:a	Lcom/loc/ag;
    //   223: iconst_1
    //   224: putfield 105	com/loc/ag:n	Z
    //   227: return
    //   228: aload_1
    //   229: ldc 107
    //   231: invokevirtual 48	java/lang/String:equals	(Ljava/lang/Object;)Z
    //   234: ifeq +29 -> 263
    //   237: aload_0
    //   238: getfield 10	com/loc/ak:a	Lcom/loc/ag;
    //   241: iconst_0
    //   242: putfield 105	com/loc/ag:n	Z
    //   245: aload_0
    //   246: getfield 10	com/loc/ak:a	Lcom/loc/ag;
    //   249: invokestatic 111	com/loc/ag:d	(Lcom/loc/ag;)Lcom/loc/ce;
    //   252: ifnull -241 -> 11
    //   255: aload_0
    //   256: getfield 10	com/loc/ak:a	Lcom/loc/ag;
    //   259: invokestatic 114	com/loc/ag:e	(Lcom/loc/ag;)V
    //   262: return
    //   263: aload_1
    //   264: ldc 116
    //   266: invokevirtual 48	java/lang/String:equals	(Ljava/lang/Object;)Z
    //   269: ifne -258 -> 11
    //   272: aload_1
    //   273: ldc 118
    //   275: invokevirtual 48	java/lang/String:equals	(Ljava/lang/Object;)Z
    //   278: ifne -267 -> 11
    //   281: aload_1
    //   282: ldc 120
    //   284: invokevirtual 48	java/lang/String:equals	(Ljava/lang/Object;)Z
    //   287: ifeq -276 -> 11
    //   290: aload_0
    //   291: getfield 10	com/loc/ak:a	Lcom/loc/ag;
    //   294: invokestatic 124	com/loc/ag:f	(Lcom/loc/ag;)Z
    //   297: ifeq -286 -> 11
    //   300: aload_0
    //   301: getfield 10	com/loc/ak:a	Lcom/loc/ag;
    //   304: invokestatic 128	com/loc/ag:g	(Lcom/loc/ag;)I
    //   307: pop
    //   308: return
    //   309: astore_2
    //   310: goto -252 -> 58
    //   313: astore_1
    //   314: iload 4
    //   316: istore_3
    //   317: goto -159 -> 158
    //   320: iload_3
    //   321: tableswitch	default:+35 -> 356, 0:+-135->186, 1:+-127->194, 2:+35->356, 3:+35->356, 4:+-119->202
    //
    // Exception table:
    //   from	to	target	type
    //   12	40	108	java/lang/Throwable
    //   51	56	108	java/lang/Throwable
    //   62	72	108	java/lang/Throwable
    //   96	107	108	java/lang/Throwable
    //   117	119	108	java/lang/Throwable
    //   119	136	108	java/lang/Throwable
    //   143	158	108	java/lang/Throwable
    //   158	183	108	java/lang/Throwable
    //   186	193	108	java/lang/Throwable
    //   194	201	108	java/lang/Throwable
    //   202	209	108	java/lang/Throwable
    //   210	227	108	java/lang/Throwable
    //   228	262	108	java/lang/Throwable
    //   263	308	108	java/lang/Throwable
    //   72	96	114	finally
    //   115	117	114	finally
    //   51	56	309	java/lang/Exception
    //   143	158	313	java/lang/Exception
  }
}

/* Location:           C:\crazyd\work\ustone\odm2016031702\baidu\android\nut-dex2jar.jar
 * Qualified Name:     com.loc.ak
 * JD-Core Version:    0.6.2
 */