package com.loc;

final class cp extends Thread
{
  cp(co paramco, String paramString)
  {
    super(paramString);
  }

  // ERROR //
  public final void run()
  {
    // Byte code:
    //   0: invokestatic 23	android/os/Looper:prepare	()V
    //   3: aload_0
    //   4: getfield 10	com/loc/cp:a	Lcom/loc/co;
    //   7: invokestatic 27	android/os/Looper:myLooper	()Landroid/os/Looper;
    //   10: invokestatic 32	com/loc/co:a	(Lcom/loc/co;Landroid/os/Looper;)Landroid/os/Looper;
    //   13: pop
    //   14: aload_0
    //   15: getfield 10	com/loc/cp:a	Lcom/loc/co;
    //   18: new 34	java/util/Timer
    //   21: dup
    //   22: invokespecial 36	java/util/Timer:<init>	()V
    //   25: invokestatic 39	com/loc/co:a	(Lcom/loc/co;Ljava/util/Timer;)Ljava/util/Timer;
    //   28: pop
    //   29: aload_0
    //   30: getfield 10	com/loc/cp:a	Lcom/loc/co;
    //   33: new 41	com/loc/cq
    //   36: dup
    //   37: aload_0
    //   38: getfield 10	com/loc/cp:a	Lcom/loc/co;
    //   41: iconst_0
    //   42: invokespecial 44	com/loc/cq:<init>	(Lcom/loc/co;B)V
    //   45: invokestatic 47	com/loc/co:a	(Lcom/loc/co;Lcom/loc/cq;)Lcom/loc/cq;
    //   48: pop
    //   49: aload_0
    //   50: getfield 10	com/loc/cp:a	Lcom/loc/co;
    //   53: aload_0
    //   54: getfield 10	com/loc/cp:a	Lcom/loc/co;
    //   57: invokestatic 50	com/loc/co:a	(Lcom/loc/co;)Lcom/loc/cq;
    //   60: invokestatic 53	com/loc/co:a	(Lcom/loc/co;Landroid/telephony/PhoneStateListener;)V
    //   63: aload_0
    //   64: getfield 10	com/loc/cp:a	Lcom/loc/co;
    //   67: new 55	com/loc/cr
    //   70: dup
    //   71: aload_0
    //   72: getfield 10	com/loc/cp:a	Lcom/loc/co;
    //   75: iconst_0
    //   76: invokespecial 56	com/loc/cr:<init>	(Lcom/loc/co;B)V
    //   79: invokestatic 59	com/loc/co:a	(Lcom/loc/co;Lcom/loc/cr;)Lcom/loc/cr;
    //   82: pop
    //   83: aload_0
    //   84: getfield 10	com/loc/cp:a	Lcom/loc/co;
    //   87: aload_0
    //   88: getfield 10	com/loc/cp:a	Lcom/loc/co;
    //   91: invokestatic 63	com/loc/co:b	(Lcom/loc/co;)Lcom/loc/cr;
    //   94: invokestatic 66	com/loc/co:a	(Lcom/loc/co;Landroid/location/GpsStatus$NmeaListener;)V
    //   97: invokestatic 69	android/os/Looper:loop	()V
    //   100: return
    //   101: astore_1
    //   102: return
    //   103: astore_1
    //   104: goto -7 -> 97
    //
    // Exception table:
    //   from	to	target	type
    //   0	83	101	java/lang/Exception
    //   97	100	101	java/lang/Exception
    //   83	97	103	java/lang/Exception
  }
}

/* Location:           C:\crazyd\work\ustone\odm2016031702\baidu\android\nut-dex2jar.jar
 * Qualified Name:     com.loc.cp
 * JD-Core Version:    0.6.2
 */