package com.loc;

final class d extends Thread
{
  boolean a = false;

  public d(a parama, String paramString)
  {
    super(paramString);
  }

  // ERROR //
  public final void run()
  {
    // Byte code:
    //   0: aload_0
    //   1: iconst_1
    //   2: putfield 17	com/loc/d:a	Z
    //   5: aload_0
    //   6: getfield 17	com/loc/d:a	Z
    //   9: ifeq +87 -> 96
    //   12: invokestatic 28	java/lang/Thread:interrupted	()Z
    //   15: istore_1
    //   16: iload_1
    //   17: ifne +79 -> 96
    //   20: invokestatic 34	android/os/Message:obtain	()Landroid/os/Message;
    //   23: astore_2
    //   24: aload_2
    //   25: bipush 6
    //   27: putfield 38	android/os/Message:what	I
    //   30: aload_0
    //   31: getfield 12	com/loc/d:b	Lcom/loc/a;
    //   34: getfield 44	com/loc/a:h	Landroid/os/Messenger;
    //   37: ifnull +14 -> 51
    //   40: aload_0
    //   41: getfield 12	com/loc/d:b	Lcom/loc/a;
    //   44: getfield 44	com/loc/a:h	Landroid/os/Messenger;
    //   47: aload_2
    //   48: invokevirtual 50	android/os/Messenger:send	(Landroid/os/Message;)V
    //   51: getstatic 56	com/amap/api/location/AMapLocationClientOption$AMapLocationMode:Device_Sensors	Lcom/amap/api/location/AMapLocationClientOption$AMapLocationMode;
    //   54: aload_0
    //   55: getfield 12	com/loc/d:b	Lcom/loc/a;
    //   58: getfield 59	com/loc/a:a	Lcom/amap/api/location/AMapLocationClientOption;
    //   61: invokevirtual 65	com/amap/api/location/AMapLocationClientOption:getLocationMode	()Lcom/amap/api/location/AMapLocationClientOption$AMapLocationMode;
    //   64: invokevirtual 69	com/amap/api/location/AMapLocationClientOption$AMapLocationMode:equals	(Ljava/lang/Object;)Z
    //   67: istore_1
    //   68: iload_1
    //   69: ifeq +37 -> 106
    //   72: ldc2_w 70
    //   75: invokestatic 75	java/lang/Thread:sleep	(J)V
    //   78: goto -73 -> 5
    //   81: astore_2
    //   82: invokestatic 79	java/lang/Thread:currentThread	()Ljava/lang/Thread;
    //   85: invokevirtual 82	java/lang/Thread:interrupt	()V
    //   88: goto -83 -> 5
    //   91: astore_2
    //   92: aload_2
    //   93: invokevirtual 85	java/lang/Throwable:printStackTrace	()V
    //   96: aload_0
    //   97: getfield 12	com/loc/d:b	Lcom/loc/a;
    //   100: iconst_0
    //   101: invokestatic 88	com/loc/a:a	(Lcom/loc/a;Z)Z
    //   104: pop
    //   105: return
    //   106: getstatic 91	com/amap/api/location/AMapLocationClientOption$AMapLocationMode:Hight_Accuracy	Lcom/amap/api/location/AMapLocationClientOption$AMapLocationMode;
    //   109: aload_0
    //   110: getfield 12	com/loc/d:b	Lcom/loc/a;
    //   113: getfield 59	com/loc/a:a	Lcom/amap/api/location/AMapLocationClientOption;
    //   116: invokevirtual 65	com/amap/api/location/AMapLocationClientOption:getLocationMode	()Lcom/amap/api/location/AMapLocationClientOption$AMapLocationMode;
    //   119: invokevirtual 69	com/amap/api/location/AMapLocationClientOption$AMapLocationMode:equals	(Ljava/lang/Object;)Z
    //   122: ifeq +13 -> 135
    //   125: aload_0
    //   126: getfield 12	com/loc/d:b	Lcom/loc/a;
    //   129: invokestatic 94	com/loc/a:a	(Lcom/loc/a;)Z
    //   132: ifeq +51 -> 183
    //   135: aload_0
    //   136: getfield 12	com/loc/d:b	Lcom/loc/a;
    //   139: getfield 59	com/loc/a:a	Lcom/amap/api/location/AMapLocationClientOption;
    //   142: invokevirtual 97	com/amap/api/location/AMapLocationClientOption:isGpsFirst	()Z
    //   145: ifeq +98 -> 243
    //   148: aload_0
    //   149: getfield 12	com/loc/d:b	Lcom/loc/a;
    //   152: getfield 59	com/loc/a:a	Lcom/amap/api/location/AMapLocationClientOption;
    //   155: invokevirtual 100	com/amap/api/location/AMapLocationClientOption:isOnceLocation	()Z
    //   158: ifeq +85 -> 243
    //   161: aload_0
    //   162: getfield 12	com/loc/d:b	Lcom/loc/a;
    //   165: invokestatic 102	com/loc/a:b	(Lcom/loc/a;)Z
    //   168: ifne +75 -> 243
    //   171: aload_0
    //   172: getfield 12	com/loc/d:b	Lcom/loc/a;
    //   175: getfield 105	com/loc/a:p	Z
    //   178: istore_1
    //   179: iload_1
    //   180: ifne +63 -> 243
    //   183: aload_0
    //   184: getfield 12	com/loc/d:b	Lcom/loc/a;
    //   187: getfield 59	com/loc/a:a	Lcom/amap/api/location/AMapLocationClientOption;
    //   190: invokevirtual 100	com/amap/api/location/AMapLocationClientOption:isOnceLocation	()Z
    //   193: ifeq +25 -> 218
    //   196: aload_0
    //   197: getfield 12	com/loc/d:b	Lcom/loc/a;
    //   200: getfield 109	com/loc/a:n	J
    //   203: lconst_0
    //   204: lcmp
    //   205: ifne +13 -> 218
    //   208: aload_0
    //   209: getfield 12	com/loc/d:b	Lcom/loc/a;
    //   212: invokestatic 114	com/loc/by:b	()J
    //   215: putfield 109	com/loc/a:n	J
    //   218: ldc2_w 70
    //   221: invokestatic 75	java/lang/Thread:sleep	(J)V
    //   224: goto -219 -> 5
    //   227: astore_2
    //   228: invokestatic 79	java/lang/Thread:currentThread	()Ljava/lang/Thread;
    //   231: invokevirtual 82	java/lang/Thread:interrupt	()V
    //   234: goto -229 -> 5
    //   237: ldc2_w 115
    //   240: invokestatic 75	java/lang/Thread:sleep	(J)V
    //   243: aload_0
    //   244: getfield 12	com/loc/d:b	Lcom/loc/a;
    //   247: getfield 44	com/loc/a:h	Landroid/os/Messenger;
    //   250: astore_2
    //   251: aload_2
    //   252: ifnonnull +105 -> 357
    //   255: aload_0
    //   256: getfield 12	com/loc/d:b	Lcom/loc/a;
    //   259: astore_2
    //   260: aload_2
    //   261: aload_2
    //   262: getfield 119	com/loc/a:l	I
    //   265: iconst_1
    //   266: iadd
    //   267: putfield 119	com/loc/a:l	I
    //   270: aload_0
    //   271: getfield 12	com/loc/d:b	Lcom/loc/a;
    //   274: getfield 119	com/loc/a:l	I
    //   277: bipush 40
    //   279: if_icmple -42 -> 237
    //   282: invokestatic 34	android/os/Message:obtain	()Landroid/os/Message;
    //   285: astore_2
    //   286: new 121	android/os/Bundle
    //   289: dup
    //   290: invokespecial 123	android/os/Bundle:<init>	()V
    //   293: astore_3
    //   294: new 125	com/autonavi/aps/amapapi/model/AmapLoc
    //   297: dup
    //   298: invokespecial 126	com/autonavi/aps/amapapi/model/AmapLoc:<init>	()V
    //   301: astore 4
    //   303: aload 4
    //   305: bipush 10
    //   307: invokevirtual 129	com/autonavi/aps/amapapi/model/AmapLoc:b	(I)V
    //   310: aload 4
    //   312: ldc 131
    //   314: invokevirtual 133	com/autonavi/aps/amapapi/model/AmapLoc:b	(Ljava/lang/String;)V
    //   317: aload_3
    //   318: ldc 135
    //   320: aload 4
    //   322: invokevirtual 139	android/os/Bundle:putParcelable	(Ljava/lang/String;Landroid/os/Parcelable;)V
    //   325: aload_2
    //   326: aload_3
    //   327: invokevirtual 143	android/os/Message:setData	(Landroid/os/Bundle;)V
    //   330: aload_2
    //   331: iconst_1
    //   332: putfield 38	android/os/Message:what	I
    //   335: aload_0
    //   336: getfield 12	com/loc/d:b	Lcom/loc/a;
    //   339: getfield 146	com/loc/a:b	Lcom/loc/e;
    //   342: ifnull +15 -> 357
    //   345: aload_0
    //   346: getfield 12	com/loc/d:b	Lcom/loc/a;
    //   349: getfield 146	com/loc/a:b	Lcom/loc/e;
    //   352: aload_2
    //   353: invokevirtual 152	com/loc/e:sendMessage	(Landroid/os/Message;)Z
    //   356: pop
    //   357: aload_0
    //   358: getfield 12	com/loc/d:b	Lcom/loc/a;
    //   361: lconst_0
    //   362: putfield 109	com/loc/a:n	J
    //   365: aload_0
    //   366: getfield 12	com/loc/d:b	Lcom/loc/a;
    //   369: iconst_1
    //   370: invokestatic 88	com/loc/a:a	(Lcom/loc/a;Z)Z
    //   373: pop
    //   374: invokestatic 34	android/os/Message:obtain	()Landroid/os/Message;
    //   377: astore_2
    //   378: aload_2
    //   379: iconst_1
    //   380: putfield 38	android/os/Message:what	I
    //   383: new 121	android/os/Bundle
    //   386: dup
    //   387: invokespecial 123	android/os/Bundle:<init>	()V
    //   390: astore_3
    //   391: aload_3
    //   392: ldc 154
    //   394: aload_0
    //   395: getfield 12	com/loc/d:b	Lcom/loc/a;
    //   398: invokestatic 157	com/loc/a:c	(Lcom/loc/a;)Z
    //   401: invokevirtual 161	android/os/Bundle:putBoolean	(Ljava/lang/String;Z)V
    //   404: aload_3
    //   405: ldc 163
    //   407: aload_0
    //   408: getfield 12	com/loc/d:b	Lcom/loc/a;
    //   411: getfield 59	com/loc/a:a	Lcom/amap/api/location/AMapLocationClientOption;
    //   414: invokevirtual 166	com/amap/api/location/AMapLocationClientOption:isWifiActiveScan	()Z
    //   417: invokevirtual 161	android/os/Bundle:putBoolean	(Ljava/lang/String;Z)V
    //   420: aload_3
    //   421: ldc 168
    //   423: aload_0
    //   424: getfield 12	com/loc/d:b	Lcom/loc/a;
    //   427: getfield 59	com/loc/a:a	Lcom/amap/api/location/AMapLocationClientOption;
    //   430: invokevirtual 170	com/amap/api/location/AMapLocationClientOption:isNeedAddress	()Z
    //   433: invokevirtual 161	android/os/Bundle:putBoolean	(Ljava/lang/String;Z)V
    //   436: aload_3
    //   437: ldc 172
    //   439: aload_0
    //   440: getfield 12	com/loc/d:b	Lcom/loc/a;
    //   443: getfield 59	com/loc/a:a	Lcom/amap/api/location/AMapLocationClientOption;
    //   446: invokevirtual 174	com/amap/api/location/AMapLocationClientOption:isKillProcess	()Z
    //   449: invokevirtual 161	android/os/Bundle:putBoolean	(Ljava/lang/String;Z)V
    //   452: aload_3
    //   453: ldc 176
    //   455: aload_0
    //   456: getfield 12	com/loc/d:b	Lcom/loc/a;
    //   459: getfield 59	com/loc/a:a	Lcom/amap/api/location/AMapLocationClientOption;
    //   462: invokevirtual 178	com/amap/api/location/AMapLocationClientOption:isOffset	()Z
    //   465: invokevirtual 161	android/os/Bundle:putBoolean	(Ljava/lang/String;Z)V
    //   468: aload_3
    //   469: ldc 180
    //   471: aload_0
    //   472: getfield 12	com/loc/d:b	Lcom/loc/a;
    //   475: getfield 59	com/loc/a:a	Lcom/amap/api/location/AMapLocationClientOption;
    //   478: invokevirtual 183	com/amap/api/location/AMapLocationClientOption:getHttpTimeOut	()J
    //   481: invokevirtual 187	android/os/Bundle:putLong	(Ljava/lang/String;J)V
    //   484: aload_2
    //   485: aload_3
    //   486: invokevirtual 143	android/os/Message:setData	(Landroid/os/Bundle;)V
    //   489: aload_2
    //   490: aload_0
    //   491: getfield 12	com/loc/d:b	Lcom/loc/a;
    //   494: getfield 190	com/loc/a:i	Landroid/os/Messenger;
    //   497: putfield 193	android/os/Message:replyTo	Landroid/os/Messenger;
    //   500: aload_0
    //   501: getfield 12	com/loc/d:b	Lcom/loc/a;
    //   504: getfield 44	com/loc/a:h	Landroid/os/Messenger;
    //   507: ifnull +14 -> 521
    //   510: aload_0
    //   511: getfield 12	com/loc/d:b	Lcom/loc/a;
    //   514: getfield 44	com/loc/a:h	Landroid/os/Messenger;
    //   517: aload_2
    //   518: invokevirtual 50	android/os/Messenger:send	(Landroid/os/Message;)V
    //   521: aload_0
    //   522: getfield 12	com/loc/d:b	Lcom/loc/a;
    //   525: invokestatic 196	com/loc/a:d	(Lcom/loc/a;)Z
    //   528: pop
    //   529: aload_0
    //   530: getfield 12	com/loc/d:b	Lcom/loc/a;
    //   533: getfield 59	com/loc/a:a	Lcom/amap/api/location/AMapLocationClientOption;
    //   536: invokevirtual 199	com/amap/api/location/AMapLocationClientOption:getInterval	()J
    //   539: invokestatic 75	java/lang/Thread:sleep	(J)V
    //   542: goto -537 -> 5
    //   545: astore_2
    //   546: invokestatic 79	java/lang/Thread:currentThread	()Ljava/lang/Thread;
    //   549: invokevirtual 82	java/lang/Thread:interrupt	()V
    //   552: goto -547 -> 5
    //   555: astore_2
    //   556: aload_2
    //   557: invokevirtual 85	java/lang/Throwable:printStackTrace	()V
    //   560: goto -39 -> 521
    //   563: astore_2
    //   564: goto -321 -> 243
    //   567: astore_2
    //   568: goto -517 -> 51
    //
    // Exception table:
    //   from	to	target	type
    //   72	78	81	java/lang/InterruptedException
    //   5	16	91	java/lang/Throwable
    //   51	68	91	java/lang/Throwable
    //   72	78	91	java/lang/Throwable
    //   82	88	91	java/lang/Throwable
    //   106	135	91	java/lang/Throwable
    //   135	179	91	java/lang/Throwable
    //   183	218	91	java/lang/Throwable
    //   218	224	91	java/lang/Throwable
    //   228	234	91	java/lang/Throwable
    //   237	243	91	java/lang/Throwable
    //   243	251	91	java/lang/Throwable
    //   255	357	91	java/lang/Throwable
    //   357	500	91	java/lang/Throwable
    //   521	529	91	java/lang/Throwable
    //   529	542	91	java/lang/Throwable
    //   546	552	91	java/lang/Throwable
    //   556	560	91	java/lang/Throwable
    //   183	218	227	java/lang/InterruptedException
    //   218	224	227	java/lang/InterruptedException
    //   529	542	545	java/lang/InterruptedException
    //   500	521	555	java/lang/Throwable
    //   237	243	563	java/lang/InterruptedException
    //   255	357	563	java/lang/InterruptedException
    //   20	51	567	java/lang/Throwable
  }
}

/* Location:           C:\crazyd\work\ustone\odm2016031702\baidu\android\nut-dex2jar.jar
 * Qualified Name:     com.loc.d
 * JD-Core Version:    0.6.2
 */