package com.loc;

final class de extends Thread
{
  de(dd paramdd)
  {
  }

  // ERROR //
  public final void run()
  {
    // Byte code:
    //   0: aload_0
    //   1: getfield 10	com/loc/de:a	Lcom/loc/dd;
    //   4: invokestatic 26	com/loc/dd:d	(Lcom/loc/dd;)V
    //   7: aload_0
    //   8: getfield 10	com/loc/de:a	Lcom/loc/dd;
    //   11: getfield 30	com/loc/dd:h	Z
    //   14: ifeq +446 -> 460
    //   17: aload_0
    //   18: getfield 10	com/loc/de:a	Lcom/loc/dd;
    //   21: getfield 33	com/loc/dd:i	Z
    //   24: istore_2
    //   25: iload_2
    //   26: ifeq +392 -> 418
    //   29: aload_0
    //   30: getfield 10	com/loc/de:a	Lcom/loc/dd;
    //   33: aload_0
    //   34: getfield 10	com/loc/de:a	Lcom/loc/dd;
    //   37: aload_0
    //   38: getfield 10	com/loc/de:a	Lcom/loc/dd;
    //   41: getfield 36	com/loc/dd:f	Z
    //   44: invokestatic 39	com/loc/dd:a	(Lcom/loc/dd;Z)Lcom/autonavi/aps/amapapi/model/AmapLoc;
    //   47: putfield 43	com/loc/dd:l	Lcom/autonavi/aps/amapapi/model/AmapLoc;
    //   50: aload_0
    //   51: getfield 10	com/loc/de:a	Lcom/loc/dd;
    //   54: invokestatic 47	com/loc/dd:e	(Lcom/loc/dd;)Lcom/loc/ag;
    //   57: ifnull +20 -> 77
    //   60: aload_0
    //   61: getfield 10	com/loc/de:a	Lcom/loc/dd;
    //   64: aload_0
    //   65: getfield 10	com/loc/de:a	Lcom/loc/dd;
    //   68: getfield 43	com/loc/dd:l	Lcom/autonavi/aps/amapapi/model/AmapLoc;
    //   71: invokestatic 52	com/loc/ag:a	(Lcom/autonavi/aps/amapapi/model/AmapLoc;)Lcom/autonavi/aps/amapapi/model/AmapLoc;
    //   74: putfield 43	com/loc/dd:l	Lcom/autonavi/aps/amapapi/model/AmapLoc;
    //   77: aconst_null
    //   78: astore 5
    //   80: aconst_null
    //   81: astore 4
    //   83: aload_0
    //   84: getfield 10	com/loc/de:a	Lcom/loc/dd;
    //   87: getfield 56	com/loc/dd:j	Ljava/lang/Object;
    //   90: astore 6
    //   92: aload 6
    //   94: monitorenter
    //   95: aload_0
    //   96: getfield 10	com/loc/de:a	Lcom/loc/dd;
    //   99: getfield 43	com/loc/dd:l	Lcom/autonavi/aps/amapapi/model/AmapLoc;
    //   102: ifnull +26 -> 128
    //   105: aload_0
    //   106: getfield 10	com/loc/de:a	Lcom/loc/dd;
    //   109: getfield 43	com/loc/dd:l	Lcom/autonavi/aps/amapapi/model/AmapLoc;
    //   112: invokevirtual 61	com/autonavi/aps/amapapi/model/AmapLoc:a	()I
    //   115: ifne +13 -> 128
    //   118: aload_0
    //   119: getfield 10	com/loc/de:a	Lcom/loc/dd;
    //   122: invokestatic 67	com/loc/by:b	()J
    //   125: putfield 71	com/loc/dd:m	J
    //   128: aload_0
    //   129: getfield 10	com/loc/de:a	Lcom/loc/dd;
    //   132: iconst_0
    //   133: putfield 33	com/loc/dd:i	Z
    //   136: aload 5
    //   138: astore_3
    //   139: aload_0
    //   140: getfield 10	com/loc/de:a	Lcom/loc/dd;
    //   143: getfield 75	com/loc/dd:g	Ljava/util/Vector;
    //   146: ifnull +199 -> 345
    //   149: aload 5
    //   151: astore_3
    //   152: aload_0
    //   153: getfield 10	com/loc/de:a	Lcom/loc/dd;
    //   156: getfield 75	com/loc/dd:g	Ljava/util/Vector;
    //   159: invokevirtual 80	java/util/Vector:size	()I
    //   162: ifle +183 -> 345
    //   165: aload_0
    //   166: getfield 10	com/loc/de:a	Lcom/loc/dd;
    //   169: getfield 75	com/loc/dd:g	Ljava/util/Vector;
    //   172: invokevirtual 80	java/util/Vector:size	()I
    //   175: istore_1
    //   176: aload 4
    //   178: astore_3
    //   179: iload_1
    //   180: ifle +165 -> 345
    //   183: invokestatic 86	android/os/Message:obtain	()Landroid/os/Message;
    //   186: astore 4
    //   188: new 88	android/os/Bundle
    //   191: dup
    //   192: invokespecial 89	android/os/Bundle:<init>	()V
    //   195: astore_3
    //   196: aload_3
    //   197: ldc 91
    //   199: aload_0
    //   200: getfield 10	com/loc/de:a	Lcom/loc/dd;
    //   203: getfield 43	com/loc/dd:l	Lcom/autonavi/aps/amapapi/model/AmapLoc;
    //   206: invokevirtual 95	android/os/Bundle:putParcelable	(Ljava/lang/String;Landroid/os/Parcelable;)V
    //   209: aload 4
    //   211: aload_3
    //   212: invokevirtual 99	android/os/Message:setData	(Landroid/os/Bundle;)V
    //   215: aload 4
    //   217: iconst_1
    //   218: putfield 103	android/os/Message:what	I
    //   221: aload_0
    //   222: getfield 10	com/loc/de:a	Lcom/loc/dd;
    //   225: getfield 75	com/loc/dd:g	Ljava/util/Vector;
    //   228: iconst_0
    //   229: invokevirtual 107	java/util/Vector:get	(I)Ljava/lang/Object;
    //   232: checkcast 109	android/os/Messenger
    //   235: astore_3
    //   236: aload_3
    //   237: aload 4
    //   239: invokevirtual 113	android/os/Messenger:send	(Landroid/os/Message;)V
    //   242: aload_0
    //   243: getfield 10	com/loc/de:a	Lcom/loc/dd;
    //   246: getfield 75	com/loc/dd:g	Ljava/util/Vector;
    //   249: iconst_0
    //   250: invokevirtual 116	java/util/Vector:remove	(I)Ljava/lang/Object;
    //   253: pop
    //   254: iload_1
    //   255: iconst_1
    //   256: isub
    //   257: istore_1
    //   258: goto -79 -> 179
    //   261: astore_3
    //   262: aload_0
    //   263: getfield 10	com/loc/de:a	Lcom/loc/dd;
    //   266: bipush 9
    //   268: aload_3
    //   269: invokevirtual 120	java/lang/Throwable:getMessage	()Ljava/lang/String;
    //   272: invokestatic 123	com/loc/dd:a	(ILjava/lang/String;)Lcom/autonavi/aps/amapapi/model/AmapLoc;
    //   275: putfield 43	com/loc/dd:l	Lcom/autonavi/aps/amapapi/model/AmapLoc;
    //   278: goto -271 -> 7
    //   281: astore_3
    //   282: aload_0
    //   283: getfield 10	com/loc/de:a	Lcom/loc/dd;
    //   286: invokestatic 126	com/loc/dd:h	(Lcom/loc/dd;)Z
    //   289: ifne +10 -> 299
    //   292: aload_0
    //   293: getfield 10	com/loc/de:a	Lcom/loc/dd;
    //   296: invokestatic 128	com/loc/dd:i	(Lcom/loc/dd;)V
    //   299: return
    //   300: astore_3
    //   301: aload_0
    //   302: getfield 10	com/loc/de:a	Lcom/loc/dd;
    //   305: bipush 8
    //   307: aload_3
    //   308: invokevirtual 120	java/lang/Throwable:getMessage	()Ljava/lang/String;
    //   311: invokestatic 123	com/loc/dd:a	(ILjava/lang/String;)Lcom/autonavi/aps/amapapi/model/AmapLoc;
    //   314: putfield 43	com/loc/dd:l	Lcom/autonavi/aps/amapapi/model/AmapLoc;
    //   317: goto -240 -> 77
    //   320: astore_3
    //   321: invokestatic 132	java/lang/Thread:currentThread	()Ljava/lang/Thread;
    //   324: invokevirtual 135	java/lang/Thread:interrupt	()V
    //   327: aload_0
    //   328: getfield 10	com/loc/de:a	Lcom/loc/dd;
    //   331: invokestatic 126	com/loc/dd:h	(Lcom/loc/dd;)Z
    //   334: ifne -35 -> 299
    //   337: aload_0
    //   338: getfield 10	com/loc/de:a	Lcom/loc/dd;
    //   341: invokestatic 128	com/loc/dd:i	(Lcom/loc/dd;)V
    //   344: return
    //   345: aload 6
    //   347: monitorexit
    //   348: aload_0
    //   349: getfield 10	com/loc/de:a	Lcom/loc/dd;
    //   352: invokestatic 137	com/loc/dd:f	(Lcom/loc/dd;)V
    //   355: aload_0
    //   356: getfield 10	com/loc/de:a	Lcom/loc/dd;
    //   359: invokestatic 139	com/loc/dd:g	(Lcom/loc/dd;)V
    //   362: aload_0
    //   363: getfield 10	com/loc/de:a	Lcom/loc/dd;
    //   366: aload_3
    //   367: invokestatic 142	com/loc/dd:a	(Lcom/loc/dd;Landroid/os/Messenger;)V
    //   370: goto -363 -> 7
    //   373: astore_3
    //   374: aload_0
    //   375: getfield 10	com/loc/de:a	Lcom/loc/dd;
    //   378: invokestatic 126	com/loc/dd:h	(Lcom/loc/dd;)Z
    //   381: ifne -82 -> 299
    //   384: aload_0
    //   385: getfield 10	com/loc/de:a	Lcom/loc/dd;
    //   388: invokestatic 128	com/loc/dd:i	(Lcom/loc/dd;)V
    //   391: return
    //   392: astore_3
    //   393: aload 6
    //   395: monitorexit
    //   396: aload_3
    //   397: athrow
    //   398: astore_3
    //   399: aload_0
    //   400: getfield 10	com/loc/de:a	Lcom/loc/dd;
    //   403: invokestatic 126	com/loc/dd:h	(Lcom/loc/dd;)Z
    //   406: ifne +10 -> 416
    //   409: aload_0
    //   410: getfield 10	com/loc/de:a	Lcom/loc/dd;
    //   413: invokestatic 128	com/loc/dd:i	(Lcom/loc/dd;)V
    //   416: aload_3
    //   417: athrow
    //   418: aload_0
    //   419: getfield 10	com/loc/de:a	Lcom/loc/dd;
    //   422: getfield 56	com/loc/dd:j	Ljava/lang/Object;
    //   425: astore_3
    //   426: aload_3
    //   427: monitorenter
    //   428: aload_0
    //   429: getfield 10	com/loc/de:a	Lcom/loc/dd;
    //   432: invokestatic 126	com/loc/dd:h	(Lcom/loc/dd;)Z
    //   435: ifeq +13 -> 448
    //   438: aload_0
    //   439: getfield 10	com/loc/de:a	Lcom/loc/dd;
    //   442: getfield 56	com/loc/dd:j	Ljava/lang/Object;
    //   445: invokevirtual 147	java/lang/Object:wait	()V
    //   448: aload_3
    //   449: monitorexit
    //   450: goto -443 -> 7
    //   453: astore 4
    //   455: aload_3
    //   456: monitorexit
    //   457: aload 4
    //   459: athrow
    //   460: aload_0
    //   461: getfield 10	com/loc/de:a	Lcom/loc/dd;
    //   464: invokestatic 126	com/loc/dd:h	(Lcom/loc/dd;)Z
    //   467: ifne -168 -> 299
    //   470: aload_0
    //   471: getfield 10	com/loc/de:a	Lcom/loc/dd;
    //   474: invokestatic 128	com/loc/dd:i	(Lcom/loc/dd;)V
    //   477: return
    //
    // Exception table:
    //   from	to	target	type
    //   0	7	261	java/lang/Throwable
    //   0	7	281	android/os/RemoteException
    //   7	25	281	android/os/RemoteException
    //   29	77	281	android/os/RemoteException
    //   83	95	281	android/os/RemoteException
    //   262	278	281	android/os/RemoteException
    //   301	317	281	android/os/RemoteException
    //   348	370	281	android/os/RemoteException
    //   396	398	281	android/os/RemoteException
    //   418	428	281	android/os/RemoteException
    //   457	460	281	android/os/RemoteException
    //   29	77	300	java/lang/Throwable
    //   0	7	320	java/lang/InterruptedException
    //   7	25	320	java/lang/InterruptedException
    //   29	77	320	java/lang/InterruptedException
    //   83	95	320	java/lang/InterruptedException
    //   262	278	320	java/lang/InterruptedException
    //   301	317	320	java/lang/InterruptedException
    //   348	370	320	java/lang/InterruptedException
    //   396	398	320	java/lang/InterruptedException
    //   418	428	320	java/lang/InterruptedException
    //   457	460	320	java/lang/InterruptedException
    //   7	25	373	java/lang/Throwable
    //   83	95	373	java/lang/Throwable
    //   262	278	373	java/lang/Throwable
    //   301	317	373	java/lang/Throwable
    //   348	370	373	java/lang/Throwable
    //   396	398	373	java/lang/Throwable
    //   418	428	373	java/lang/Throwable
    //   457	460	373	java/lang/Throwable
    //   95	128	392	finally
    //   128	136	392	finally
    //   139	149	392	finally
    //   152	176	392	finally
    //   183	254	392	finally
    //   345	348	392	finally
    //   393	396	392	finally
    //   0	7	398	finally
    //   7	25	398	finally
    //   29	77	398	finally
    //   83	95	398	finally
    //   262	278	398	finally
    //   301	317	398	finally
    //   321	327	398	finally
    //   348	370	398	finally
    //   396	398	398	finally
    //   418	428	398	finally
    //   457	460	398	finally
    //   428	448	453	finally
    //   448	450	453	finally
    //   455	457	453	finally
  }
}

/* Location:           C:\crazyd\work\ustone\odm2016031702\baidu\android\nut-dex2jar.jar
 * Qualified Name:     com.loc.de
 * JD-Core Version:    0.6.2
 */