package com.loc;

import java.io.ByteArrayInputStream;
import java.io.ByteArrayOutputStream;
import java.io.File;
import java.io.IOException;
import java.io.RandomAccessFile;
import java.util.ArrayList;
import java.util.BitSet;
import java.util.zip.GZIPInputStream;

public final class dl
{
  private RandomAccessFile a;
  private cl b;
  private File c = null;

  protected dl(cl paramcl)
  {
    this.b = paramcl;
  }

  private static byte a(byte[] paramArrayOfByte)
  {
    Object localObject2 = null;
    Object localObject1 = localObject2;
    ByteArrayInputStream localByteArrayInputStream;
    GZIPInputStream localGZIPInputStream;
    ByteArrayOutputStream localByteArrayOutputStream;
    try
    {
      localByteArrayInputStream = new ByteArrayInputStream(paramArrayOfByte);
      localObject1 = localObject2;
      localGZIPInputStream = new GZIPInputStream(localByteArrayInputStream);
      localObject1 = localObject2;
      paramArrayOfByte = new byte[1024];
      localObject1 = localObject2;
      localByteArrayOutputStream = new ByteArrayOutputStream();
      while (true)
      {
        localObject1 = localObject2;
        int i = localGZIPInputStream.read(paramArrayOfByte, 0, 1024);
        if (i == -1)
          break;
        localObject1 = localObject2;
        localByteArrayOutputStream.write(paramArrayOfByte, 0, i);
      }
    }
    catch (Exception paramArrayOfByte)
    {
      paramArrayOfByte = (byte[])localObject1;
    }
    while (true)
    {
      return paramArrayOfByte[0];
      localObject1 = localObject2;
      paramArrayOfByte = localByteArrayOutputStream.toByteArray();
      localObject1 = paramArrayOfByte;
      localByteArrayOutputStream.flush();
      localObject1 = paramArrayOfByte;
      localByteArrayOutputStream.close();
      localObject1 = paramArrayOfByte;
      localGZIPInputStream.close();
      localObject1 = paramArrayOfByte;
      localByteArrayInputStream.close();
    }
  }

  private static int a(int paramInt1, int paramInt2, int paramInt3)
  {
    paramInt1 = (paramInt3 - 1) * 1500 + paramInt1;
    while (paramInt1 >= paramInt2)
      paramInt1 -= 1500;
    return paramInt1;
  }

  private int a(BitSet paramBitSet)
  {
    int k = 0;
    int i = 0;
    while (true)
    {
      int j = k;
      if (i < paramBitSet.length())
      {
        if (paramBitSet.get(i))
          j = this.b.a + (i * 1500 + 4);
      }
      else
        return j;
      i += 1;
    }
  }

  private ArrayList a(int paramInt1, int paramInt2)
  {
    ArrayList localArrayList = new ArrayList();
    while (true)
    {
      if (paramInt1 <= paramInt2);
      try
      {
        this.a.seek(paramInt1);
        int i = this.a.readInt();
        this.a.readLong();
        if (i > 0)
        {
          if (i > 1500)
            return null;
          byte[] arrayOfByte = new byte[i];
          this.a.read(arrayOfByte);
          i = a(arrayOfByte);
          if ((i == 3) || (i == 4) || (i == 41))
          {
            localArrayList.add(arrayOfByte);
            label97: paramInt1 += 1500;
            continue;
            return localArrayList;
          }
        }
      }
      catch (IOException localIOException)
      {
        break label97;
      }
    }
    return null;
  }

  private BitSet b()
  {
    Object localObject = new byte[this.b.a];
    try
    {
      this.a.read((byte[])localObject);
      localObject = cl.b((byte[])localObject);
      return localObject;
    }
    catch (IOException localIOException)
    {
    }
    return null;
  }

  // ERROR //
  protected final int a()
  {
    // Byte code:
    //   0: iconst_0
    //   1: istore_2
    //   2: iconst_0
    //   3: istore 6
    //   5: iconst_0
    //   6: istore 7
    //   8: iconst_0
    //   9: istore 8
    //   11: iconst_0
    //   12: istore_1
    //   13: aload_0
    //   14: monitorenter
    //   15: aload_0
    //   16: aload_0
    //   17: getfield 19	com/loc/dl:b	Lcom/loc/cl;
    //   20: invokevirtual 114	com/loc/cl:b	()Ljava/io/File;
    //   23: putfield 17	com/loc/dl:c	Ljava/io/File;
    //   26: iload 6
    //   28: istore_3
    //   29: iload 7
    //   31: istore 4
    //   33: iload 8
    //   35: istore 5
    //   37: aload_0
    //   38: getfield 17	com/loc/dl:c	Ljava/io/File;
    //   41: ifnull +234 -> 275
    //   44: iload 6
    //   46: istore_3
    //   47: iload 7
    //   49: istore 4
    //   51: iload 8
    //   53: istore 5
    //   55: aload_0
    //   56: new 83	java/io/RandomAccessFile
    //   59: dup
    //   60: aload_0
    //   61: getfield 19	com/loc/dl:b	Lcom/loc/cl;
    //   64: invokevirtual 114	com/loc/cl:b	()Ljava/io/File;
    //   67: ldc 116
    //   69: invokespecial 119	java/io/RandomAccessFile:<init>	(Ljava/io/File;Ljava/lang/String;)V
    //   72: putfield 81	com/loc/dl:a	Ljava/io/RandomAccessFile;
    //   75: iload 6
    //   77: istore_3
    //   78: iload 7
    //   80: istore 4
    //   82: iload 8
    //   84: istore 5
    //   86: aload_0
    //   87: getfield 19	com/loc/dl:b	Lcom/loc/cl;
    //   90: getfield 73	com/loc/cl:a	I
    //   93: newarray byte
    //   95: astore 10
    //   97: iload 6
    //   99: istore_3
    //   100: iload 7
    //   102: istore 4
    //   104: iload 8
    //   106: istore 5
    //   108: getstatic 125	com/loc/co:t	Z
    //   111: ifeq +63 -> 174
    //   114: iload 6
    //   116: istore_3
    //   117: iload 7
    //   119: istore 4
    //   121: iload 8
    //   123: istore 5
    //   125: aload_0
    //   126: getfield 81	com/loc/dl:a	Ljava/io/RandomAccessFile;
    //   129: astore 11
    //   131: aload 11
    //   133: ifnull +41 -> 174
    //   136: iload 6
    //   138: istore_3
    //   139: iload 8
    //   141: istore 5
    //   143: aload_0
    //   144: getfield 81	com/loc/dl:a	Ljava/io/RandomAccessFile;
    //   147: invokevirtual 126	java/io/RandomAccessFile:close	()V
    //   150: aload_0
    //   151: getfield 81	com/loc/dl:a	Ljava/io/RandomAccessFile;
    //   154: astore 10
    //   156: aload 10
    //   158: ifnull +10 -> 168
    //   161: aload_0
    //   162: getfield 81	com/loc/dl:a	Ljava/io/RandomAccessFile;
    //   165: invokevirtual 126	java/io/RandomAccessFile:close	()V
    //   168: aload_0
    //   169: monitorexit
    //   170: iconst_0
    //   171: ireturn
    //   172: astore 11
    //   174: iload 6
    //   176: istore_3
    //   177: iload 7
    //   179: istore 4
    //   181: iload 8
    //   183: istore 5
    //   185: aload_0
    //   186: getfield 81	com/loc/dl:a	Ljava/io/RandomAccessFile;
    //   189: aload 10
    //   191: invokevirtual 97	java/io/RandomAccessFile:read	([B)I
    //   194: pop
    //   195: iload 6
    //   197: istore_3
    //   198: iload 7
    //   200: istore 4
    //   202: iload 8
    //   204: istore 5
    //   206: aload 10
    //   208: invokestatic 107	com/loc/cl:b	([B)Ljava/util/BitSet;
    //   211: astore 10
    //   213: iconst_0
    //   214: istore 6
    //   216: iload_1
    //   217: istore_2
    //   218: iload_1
    //   219: istore_3
    //   220: iload_1
    //   221: istore 4
    //   223: iload_1
    //   224: istore 5
    //   226: iload 6
    //   228: aload 10
    //   230: invokevirtual 129	java/util/BitSet:size	()I
    //   233: if_icmpge +42 -> 275
    //   236: iload_1
    //   237: istore_3
    //   238: iload_1
    //   239: istore 4
    //   241: iload_1
    //   242: istore 5
    //   244: aload 10
    //   246: iload 6
    //   248: invokevirtual 68	java/util/BitSet:get	(I)Z
    //   251: istore 9
    //   253: iload_1
    //   254: istore_2
    //   255: iload 9
    //   257: ifeq +7 -> 264
    //   260: iload_1
    //   261: iconst_1
    //   262: iadd
    //   263: istore_2
    //   264: iload 6
    //   266: iconst_1
    //   267: iadd
    //   268: istore 6
    //   270: iload_2
    //   271: istore_1
    //   272: goto -56 -> 216
    //   275: aload_0
    //   276: getfield 81	com/loc/dl:a	Ljava/io/RandomAccessFile;
    //   279: astore 10
    //   281: iload_2
    //   282: istore_1
    //   283: aload 10
    //   285: ifnull +12 -> 297
    //   288: aload_0
    //   289: getfield 81	com/loc/dl:a	Ljava/io/RandomAccessFile;
    //   292: invokevirtual 126	java/io/RandomAccessFile:close	()V
    //   295: iload_2
    //   296: istore_1
    //   297: aload_0
    //   298: aconst_null
    //   299: putfield 17	com/loc/dl:c	Ljava/io/File;
    //   302: aload_0
    //   303: monitorexit
    //   304: iload_1
    //   305: ireturn
    //   306: astore 10
    //   308: aload_0
    //   309: monitorexit
    //   310: aload 10
    //   312: athrow
    //   313: astore 10
    //   315: aload_0
    //   316: getfield 81	com/loc/dl:a	Ljava/io/RandomAccessFile;
    //   319: astore 10
    //   321: iload_3
    //   322: istore_1
    //   323: aload 10
    //   325: ifnull -28 -> 297
    //   328: aload_0
    //   329: getfield 81	com/loc/dl:a	Ljava/io/RandomAccessFile;
    //   332: invokevirtual 126	java/io/RandomAccessFile:close	()V
    //   335: iload_3
    //   336: istore_1
    //   337: goto -40 -> 297
    //   340: astore 10
    //   342: iload_3
    //   343: istore_1
    //   344: goto -47 -> 297
    //   347: astore 10
    //   349: aload_0
    //   350: getfield 81	com/loc/dl:a	Ljava/io/RandomAccessFile;
    //   353: astore 10
    //   355: iload 4
    //   357: istore_1
    //   358: aload 10
    //   360: ifnull -63 -> 297
    //   363: aload_0
    //   364: getfield 81	com/loc/dl:a	Ljava/io/RandomAccessFile;
    //   367: invokevirtual 126	java/io/RandomAccessFile:close	()V
    //   370: iload 4
    //   372: istore_1
    //   373: goto -76 -> 297
    //   376: astore 10
    //   378: iload 4
    //   380: istore_1
    //   381: goto -84 -> 297
    //   384: astore 10
    //   386: aload_0
    //   387: getfield 81	com/loc/dl:a	Ljava/io/RandomAccessFile;
    //   390: astore 10
    //   392: iload 5
    //   394: istore_1
    //   395: aload 10
    //   397: ifnull -100 -> 297
    //   400: aload_0
    //   401: getfield 81	com/loc/dl:a	Ljava/io/RandomAccessFile;
    //   404: invokevirtual 126	java/io/RandomAccessFile:close	()V
    //   407: iload 5
    //   409: istore_1
    //   410: goto -113 -> 297
    //   413: astore 10
    //   415: iload 5
    //   417: istore_1
    //   418: goto -121 -> 297
    //   421: astore 10
    //   423: aload_0
    //   424: getfield 81	com/loc/dl:a	Ljava/io/RandomAccessFile;
    //   427: astore 11
    //   429: aload 11
    //   431: ifnull +10 -> 441
    //   434: aload_0
    //   435: getfield 81	com/loc/dl:a	Ljava/io/RandomAccessFile;
    //   438: invokevirtual 126	java/io/RandomAccessFile:close	()V
    //   441: aload 10
    //   443: athrow
    //   444: astore 11
    //   446: goto -5 -> 441
    //   449: astore 10
    //   451: iload_2
    //   452: istore_1
    //   453: goto -156 -> 297
    //   456: astore 10
    //   458: goto -290 -> 168
    //
    // Exception table:
    //   from	to	target	type
    //   143	150	172	java/io/IOException
    //   15	26	306	finally
    //   150	156	306	finally
    //   161	168	306	finally
    //   168	170	306	finally
    //   275	281	306	finally
    //   288	295	306	finally
    //   297	304	306	finally
    //   315	321	306	finally
    //   328	335	306	finally
    //   349	355	306	finally
    //   363	370	306	finally
    //   386	392	306	finally
    //   400	407	306	finally
    //   423	429	306	finally
    //   434	441	306	finally
    //   441	444	306	finally
    //   37	44	313	java/io/FileNotFoundException
    //   55	75	313	java/io/FileNotFoundException
    //   86	97	313	java/io/FileNotFoundException
    //   108	114	313	java/io/FileNotFoundException
    //   125	131	313	java/io/FileNotFoundException
    //   143	150	313	java/io/FileNotFoundException
    //   185	195	313	java/io/FileNotFoundException
    //   206	213	313	java/io/FileNotFoundException
    //   226	236	313	java/io/FileNotFoundException
    //   244	253	313	java/io/FileNotFoundException
    //   328	335	340	java/io/IOException
    //   37	44	347	java/io/IOException
    //   55	75	347	java/io/IOException
    //   86	97	347	java/io/IOException
    //   108	114	347	java/io/IOException
    //   125	131	347	java/io/IOException
    //   185	195	347	java/io/IOException
    //   206	213	347	java/io/IOException
    //   226	236	347	java/io/IOException
    //   244	253	347	java/io/IOException
    //   363	370	376	java/io/IOException
    //   37	44	384	java/lang/NullPointerException
    //   55	75	384	java/lang/NullPointerException
    //   86	97	384	java/lang/NullPointerException
    //   108	114	384	java/lang/NullPointerException
    //   125	131	384	java/lang/NullPointerException
    //   143	150	384	java/lang/NullPointerException
    //   185	195	384	java/lang/NullPointerException
    //   206	213	384	java/lang/NullPointerException
    //   226	236	384	java/lang/NullPointerException
    //   244	253	384	java/lang/NullPointerException
    //   400	407	413	java/io/IOException
    //   37	44	421	finally
    //   55	75	421	finally
    //   86	97	421	finally
    //   108	114	421	finally
    //   125	131	421	finally
    //   143	150	421	finally
    //   185	195	421	finally
    //   206	213	421	finally
    //   226	236	421	finally
    //   244	253	421	finally
    //   434	441	444	java/io/IOException
    //   288	295	449	java/io/IOException
    //   161	168	456	java/io/IOException
  }

  // ERROR //
  protected final ck a(int paramInt)
  {
    // Byte code:
    //   0: aconst_null
    //   1: astore 4
    //   3: aload_0
    //   4: monitorenter
    //   5: aload_0
    //   6: getfield 19	com/loc/dl:b	Lcom/loc/cl;
    //   9: astore_3
    //   10: aload_3
    //   11: ifnonnull +10 -> 21
    //   14: aload 4
    //   16: astore_3
    //   17: aload_0
    //   18: monitorexit
    //   19: aload_3
    //   20: areturn
    //   21: aload_0
    //   22: monitorenter
    //   23: aload_0
    //   24: aload_0
    //   25: getfield 19	com/loc/dl:b	Lcom/loc/cl;
    //   28: invokevirtual 114	com/loc/cl:b	()Ljava/io/File;
    //   31: putfield 17	com/loc/dl:c	Ljava/io/File;
    //   34: aload_0
    //   35: getfield 17	com/loc/dl:c	Ljava/io/File;
    //   38: ifnonnull +21 -> 59
    //   41: aload_0
    //   42: monitorexit
    //   43: aload 4
    //   45: astore_3
    //   46: goto -29 -> 17
    //   49: astore_3
    //   50: aload_0
    //   51: monitorexit
    //   52: aload_3
    //   53: athrow
    //   54: astore_3
    //   55: aload_0
    //   56: monitorexit
    //   57: aload_3
    //   58: athrow
    //   59: aload_0
    //   60: new 83	java/io/RandomAccessFile
    //   63: dup
    //   64: aload_0
    //   65: getfield 17	com/loc/dl:c	Ljava/io/File;
    //   68: ldc 116
    //   70: invokespecial 119	java/io/RandomAccessFile:<init>	(Ljava/io/File;Ljava/lang/String;)V
    //   73: putfield 81	com/loc/dl:a	Ljava/io/RandomAccessFile;
    //   76: getstatic 125	com/loc/co:t	Z
    //   79: ifeq +44 -> 123
    //   82: aload_0
    //   83: getfield 81	com/loc/dl:a	Ljava/io/RandomAccessFile;
    //   86: astore_3
    //   87: aload_3
    //   88: ifnull +35 -> 123
    //   91: aload_0
    //   92: getfield 81	com/loc/dl:a	Ljava/io/RandomAccessFile;
    //   95: invokevirtual 126	java/io/RandomAccessFile:close	()V
    //   98: aload_0
    //   99: getfield 81	com/loc/dl:a	Ljava/io/RandomAccessFile;
    //   102: astore_3
    //   103: aload_3
    //   104: ifnull +10 -> 114
    //   107: aload_0
    //   108: getfield 81	com/loc/dl:a	Ljava/io/RandomAccessFile;
    //   111: invokevirtual 126	java/io/RandomAccessFile:close	()V
    //   114: aload_0
    //   115: monitorexit
    //   116: aload 4
    //   118: astore_3
    //   119: goto -102 -> 17
    //   122: astore_3
    //   123: aload_0
    //   124: invokespecial 132	com/loc/dl:b	()Ljava/util/BitSet;
    //   127: astore_3
    //   128: aload_3
    //   129: ifnonnull +35 -> 164
    //   132: aload_0
    //   133: getfield 17	com/loc/dl:c	Ljava/io/File;
    //   136: invokevirtual 138	java/io/File:delete	()Z
    //   139: pop
    //   140: aload_0
    //   141: getfield 81	com/loc/dl:a	Ljava/io/RandomAccessFile;
    //   144: astore_3
    //   145: aload_3
    //   146: ifnull +10 -> 156
    //   149: aload_0
    //   150: getfield 81	com/loc/dl:a	Ljava/io/RandomAccessFile;
    //   153: invokevirtual 126	java/io/RandomAccessFile:close	()V
    //   156: aload_0
    //   157: monitorexit
    //   158: aload 4
    //   160: astore_3
    //   161: goto -144 -> 17
    //   164: aload_0
    //   165: aload_3
    //   166: invokespecial 140	com/loc/dl:a	(Ljava/util/BitSet;)I
    //   169: istore_2
    //   170: iload_2
    //   171: aload_0
    //   172: getfield 17	com/loc/dl:c	Ljava/io/File;
    //   175: invokevirtual 142	java/io/File:length	()J
    //   178: l2i
    //   179: iload_1
    //   180: invokestatic 144	com/loc/dl:a	(III)I
    //   183: istore_1
    //   184: aload_0
    //   185: iload_2
    //   186: iload_1
    //   187: invokespecial 146	com/loc/dl:a	(II)Ljava/util/ArrayList;
    //   190: astore_3
    //   191: aload_3
    //   192: ifnonnull +35 -> 227
    //   195: aload_0
    //   196: getfield 17	com/loc/dl:c	Ljava/io/File;
    //   199: invokevirtual 138	java/io/File:delete	()Z
    //   202: pop
    //   203: aload_0
    //   204: getfield 81	com/loc/dl:a	Ljava/io/RandomAccessFile;
    //   207: astore_3
    //   208: aload_3
    //   209: ifnull +10 -> 219
    //   212: aload_0
    //   213: getfield 81	com/loc/dl:a	Ljava/io/RandomAccessFile;
    //   216: invokevirtual 126	java/io/RandomAccessFile:close	()V
    //   219: aload_0
    //   220: monitorexit
    //   221: aload 4
    //   223: astore_3
    //   224: goto -207 -> 17
    //   227: iload_2
    //   228: aload_0
    //   229: getfield 19	com/loc/dl:b	Lcom/loc/cl;
    //   232: getfield 73	com/loc/cl:a	I
    //   235: isub
    //   236: iconst_4
    //   237: isub
    //   238: sipush 1500
    //   241: idiv
    //   242: istore_2
    //   243: iload_1
    //   244: aload_0
    //   245: getfield 19	com/loc/dl:b	Lcom/loc/cl;
    //   248: getfield 73	com/loc/cl:a	I
    //   251: isub
    //   252: iconst_4
    //   253: isub
    //   254: sipush 1500
    //   257: idiv
    //   258: istore_1
    //   259: new 148	com/loc/ck
    //   262: dup
    //   263: aload_0
    //   264: getfield 17	com/loc/dl:c	Ljava/io/File;
    //   267: aload_3
    //   268: iconst_2
    //   269: newarray int
    //   271: dup
    //   272: iconst_0
    //   273: iload_2
    //   274: iastore
    //   275: dup
    //   276: iconst_1
    //   277: iload_1
    //   278: iastore
    //   279: invokespecial 151	com/loc/ck:<init>	(Ljava/io/File;Ljava/util/ArrayList;[I)V
    //   282: astore 5
    //   284: aload_0
    //   285: getfield 81	com/loc/dl:a	Ljava/io/RandomAccessFile;
    //   288: astore 6
    //   290: aload 5
    //   292: astore_3
    //   293: aload 6
    //   295: ifnull +13 -> 308
    //   298: aload_0
    //   299: getfield 81	com/loc/dl:a	Ljava/io/RandomAccessFile;
    //   302: invokevirtual 126	java/io/RandomAccessFile:close	()V
    //   305: aload 5
    //   307: astore_3
    //   308: aload_3
    //   309: ifnull +21 -> 330
    //   312: aload_3
    //   313: invokevirtual 153	com/loc/ck:b	()I
    //   316: bipush 100
    //   318: if_icmple +12 -> 330
    //   321: aload_3
    //   322: invokevirtual 153	com/loc/ck:b	()I
    //   325: ldc 154
    //   327: if_icmplt +101 -> 428
    //   330: aload_0
    //   331: getfield 17	com/loc/dl:c	Ljava/io/File;
    //   334: invokevirtual 138	java/io/File:delete	()Z
    //   337: pop
    //   338: aload_0
    //   339: aconst_null
    //   340: putfield 17	com/loc/dl:c	Ljava/io/File;
    //   343: aload_0
    //   344: monitorexit
    //   345: aload 4
    //   347: astore_3
    //   348: goto -331 -> 17
    //   351: astore_3
    //   352: aload_0
    //   353: getfield 81	com/loc/dl:a	Ljava/io/RandomAccessFile;
    //   356: astore_3
    //   357: aload_3
    //   358: ifnull +99 -> 457
    //   361: aload_0
    //   362: getfield 81	com/loc/dl:a	Ljava/io/RandomAccessFile;
    //   365: invokevirtual 126	java/io/RandomAccessFile:close	()V
    //   368: aconst_null
    //   369: astore_3
    //   370: goto -62 -> 308
    //   373: astore_3
    //   374: aconst_null
    //   375: astore_3
    //   376: goto -68 -> 308
    //   379: astore_3
    //   380: aload_0
    //   381: getfield 81	com/loc/dl:a	Ljava/io/RandomAccessFile;
    //   384: astore_3
    //   385: aload_3
    //   386: ifnull +71 -> 457
    //   389: aload_0
    //   390: getfield 81	com/loc/dl:a	Ljava/io/RandomAccessFile;
    //   393: invokevirtual 126	java/io/RandomAccessFile:close	()V
    //   396: aconst_null
    //   397: astore_3
    //   398: goto -90 -> 308
    //   401: astore_3
    //   402: aconst_null
    //   403: astore_3
    //   404: goto -96 -> 308
    //   407: astore_3
    //   408: aload_0
    //   409: getfield 81	com/loc/dl:a	Ljava/io/RandomAccessFile;
    //   412: astore 4
    //   414: aload 4
    //   416: ifnull +10 -> 426
    //   419: aload_0
    //   420: getfield 81	com/loc/dl:a	Ljava/io/RandomAccessFile;
    //   423: invokevirtual 126	java/io/RandomAccessFile:close	()V
    //   426: aload_3
    //   427: athrow
    //   428: aload_0
    //   429: monitorexit
    //   430: goto -413 -> 17
    //   433: astore 4
    //   435: goto -9 -> 426
    //   438: astore_3
    //   439: aload 5
    //   441: astore_3
    //   442: goto -134 -> 308
    //   445: astore_3
    //   446: goto -227 -> 219
    //   449: astore_3
    //   450: goto -294 -> 156
    //   453: astore_3
    //   454: goto -340 -> 114
    //   457: aconst_null
    //   458: astore_3
    //   459: goto -151 -> 308
    //
    // Exception table:
    //   from	to	target	type
    //   23	43	49	finally
    //   98	103	49	finally
    //   107	114	49	finally
    //   114	116	49	finally
    //   140	145	49	finally
    //   149	156	49	finally
    //   156	158	49	finally
    //   203	208	49	finally
    //   212	219	49	finally
    //   219	221	49	finally
    //   284	290	49	finally
    //   298	305	49	finally
    //   312	330	49	finally
    //   330	345	49	finally
    //   352	357	49	finally
    //   361	368	49	finally
    //   380	385	49	finally
    //   389	396	49	finally
    //   408	414	49	finally
    //   419	426	49	finally
    //   426	428	49	finally
    //   5	10	54	finally
    //   21	23	54	finally
    //   50	54	54	finally
    //   428	430	54	finally
    //   91	98	122	java/io/IOException
    //   59	87	351	java/io/FileNotFoundException
    //   91	98	351	java/io/FileNotFoundException
    //   123	128	351	java/io/FileNotFoundException
    //   132	140	351	java/io/FileNotFoundException
    //   164	191	351	java/io/FileNotFoundException
    //   195	203	351	java/io/FileNotFoundException
    //   227	284	351	java/io/FileNotFoundException
    //   361	368	373	java/lang/Exception
    //   59	87	379	java/lang/Exception
    //   91	98	379	java/lang/Exception
    //   123	128	379	java/lang/Exception
    //   132	140	379	java/lang/Exception
    //   164	191	379	java/lang/Exception
    //   195	203	379	java/lang/Exception
    //   227	284	379	java/lang/Exception
    //   389	396	401	java/lang/Exception
    //   59	87	407	finally
    //   91	98	407	finally
    //   123	128	407	finally
    //   132	140	407	finally
    //   164	191	407	finally
    //   195	203	407	finally
    //   227	284	407	finally
    //   419	426	433	java/lang/Exception
    //   298	305	438	java/lang/Exception
    //   212	219	445	java/lang/Exception
    //   149	156	449	java/lang/Exception
    //   107	114	453	java/lang/Exception
  }

  // ERROR //
  protected final void a(ck paramck)
  {
    // Byte code:
    //   0: aconst_null
    //   1: astore 6
    //   3: aconst_null
    //   4: astore 5
    //   6: aload_0
    //   7: monitorenter
    //   8: aload_0
    //   9: monitorenter
    //   10: aload_0
    //   11: aload_1
    //   12: getfield 157	com/loc/ck:a	Ljava/io/File;
    //   15: putfield 17	com/loc/dl:c	Ljava/io/File;
    //   18: aload_0
    //   19: getfield 17	com/loc/dl:c	Ljava/io/File;
    //   22: ifnonnull +8 -> 30
    //   25: aload_0
    //   26: monitorexit
    //   27: aload_0
    //   28: monitorexit
    //   29: return
    //   30: aload 5
    //   32: astore_3
    //   33: aload 6
    //   35: astore 4
    //   37: aload_0
    //   38: new 83	java/io/RandomAccessFile
    //   41: dup
    //   42: aload_0
    //   43: getfield 17	com/loc/dl:c	Ljava/io/File;
    //   46: ldc 116
    //   48: invokespecial 119	java/io/RandomAccessFile:<init>	(Ljava/io/File;Ljava/lang/String;)V
    //   51: putfield 81	com/loc/dl:a	Ljava/io/RandomAccessFile;
    //   54: aload 5
    //   56: astore_3
    //   57: aload 6
    //   59: astore 4
    //   61: aload_0
    //   62: getfield 19	com/loc/dl:b	Lcom/loc/cl;
    //   65: getfield 73	com/loc/cl:a	I
    //   68: newarray byte
    //   70: astore 7
    //   72: aload 5
    //   74: astore_3
    //   75: aload 6
    //   77: astore 4
    //   79: getstatic 125	com/loc/co:t	Z
    //   82: ifeq +63 -> 145
    //   85: aload 5
    //   87: astore_3
    //   88: aload 6
    //   90: astore 4
    //   92: aload_0
    //   93: getfield 81	com/loc/dl:a	Ljava/io/RandomAccessFile;
    //   96: astore 8
    //   98: aload 8
    //   100: ifnull +45 -> 145
    //   103: aload 5
    //   105: astore_3
    //   106: aload_0
    //   107: getfield 81	com/loc/dl:a	Ljava/io/RandomAccessFile;
    //   110: invokevirtual 126	java/io/RandomAccessFile:close	()V
    //   113: aload_0
    //   114: getfield 81	com/loc/dl:a	Ljava/io/RandomAccessFile;
    //   117: astore_1
    //   118: aload_1
    //   119: ifnull +10 -> 129
    //   122: aload_0
    //   123: getfield 81	com/loc/dl:a	Ljava/io/RandomAccessFile;
    //   126: invokevirtual 126	java/io/RandomAccessFile:close	()V
    //   129: aload_0
    //   130: monitorexit
    //   131: goto -104 -> 27
    //   134: astore_1
    //   135: aload_0
    //   136: monitorexit
    //   137: aload_1
    //   138: athrow
    //   139: astore_1
    //   140: aload_0
    //   141: monitorexit
    //   142: aload_1
    //   143: athrow
    //   144: astore_3
    //   145: aload 5
    //   147: astore_3
    //   148: aload 6
    //   150: astore 4
    //   152: aload_0
    //   153: getfield 81	com/loc/dl:a	Ljava/io/RandomAccessFile;
    //   156: aload 7
    //   158: invokevirtual 97	java/io/RandomAccessFile:read	([B)I
    //   161: pop
    //   162: aload 5
    //   164: astore_3
    //   165: aload 6
    //   167: astore 4
    //   169: aload 7
    //   171: invokestatic 107	com/loc/cl:b	([B)Ljava/util/BitSet;
    //   174: astore 5
    //   176: aload 5
    //   178: astore_3
    //   179: aload 5
    //   181: astore 4
    //   183: aload_1
    //   184: getfield 159	com/loc/ck:c	Z
    //   187: ifeq +89 -> 276
    //   190: aload 5
    //   192: astore_3
    //   193: aload 5
    //   195: astore 4
    //   197: aload_1
    //   198: getfield 162	com/loc/ck:b	[I
    //   201: iconst_0
    //   202: iaload
    //   203: istore_2
    //   204: aload 5
    //   206: astore_3
    //   207: aload 5
    //   209: astore 4
    //   211: iload_2
    //   212: aload_1
    //   213: getfield 162	com/loc/ck:b	[I
    //   216: iconst_1
    //   217: iaload
    //   218: if_icmpgt +24 -> 242
    //   221: aload 5
    //   223: astore_3
    //   224: aload 5
    //   226: astore 4
    //   228: aload 5
    //   230: iload_2
    //   231: iconst_0
    //   232: invokevirtual 166	java/util/BitSet:set	(IZ)V
    //   235: iload_2
    //   236: iconst_1
    //   237: iadd
    //   238: istore_2
    //   239: goto -35 -> 204
    //   242: aload 5
    //   244: astore_3
    //   245: aload 5
    //   247: astore 4
    //   249: aload_0
    //   250: getfield 81	com/loc/dl:a	Ljava/io/RandomAccessFile;
    //   253: lconst_0
    //   254: invokevirtual 87	java/io/RandomAccessFile:seek	(J)V
    //   257: aload 5
    //   259: astore_3
    //   260: aload 5
    //   262: astore 4
    //   264: aload_0
    //   265: getfield 81	com/loc/dl:a	Ljava/io/RandomAccessFile;
    //   268: aload 5
    //   270: invokestatic 169	com/loc/cl:a	(Ljava/util/BitSet;)[B
    //   273: invokevirtual 171	java/io/RandomAccessFile:write	([B)V
    //   276: aload_0
    //   277: getfield 81	com/loc/dl:a	Ljava/io/RandomAccessFile;
    //   280: astore_3
    //   281: aload 5
    //   283: astore_1
    //   284: aload_3
    //   285: ifnull +13 -> 298
    //   288: aload_0
    //   289: getfield 81	com/loc/dl:a	Ljava/io/RandomAccessFile;
    //   292: invokevirtual 126	java/io/RandomAccessFile:close	()V
    //   295: aload 5
    //   297: astore_1
    //   298: aload_1
    //   299: invokevirtual 174	java/util/BitSet:isEmpty	()Z
    //   302: ifeq +11 -> 313
    //   305: aload_0
    //   306: getfield 17	com/loc/dl:c	Ljava/io/File;
    //   309: invokevirtual 138	java/io/File:delete	()Z
    //   312: pop
    //   313: aload_0
    //   314: aconst_null
    //   315: putfield 17	com/loc/dl:c	Ljava/io/File;
    //   318: aload_0
    //   319: monitorexit
    //   320: goto -293 -> 27
    //   323: astore_1
    //   324: aload_0
    //   325: getfield 81	com/loc/dl:a	Ljava/io/RandomAccessFile;
    //   328: astore 4
    //   330: aload_3
    //   331: astore_1
    //   332: aload 4
    //   334: ifnull -36 -> 298
    //   337: aload_0
    //   338: getfield 81	com/loc/dl:a	Ljava/io/RandomAccessFile;
    //   341: invokevirtual 126	java/io/RandomAccessFile:close	()V
    //   344: aload_3
    //   345: astore_1
    //   346: goto -48 -> 298
    //   349: astore_1
    //   350: aload_3
    //   351: astore_1
    //   352: goto -54 -> 298
    //   355: astore_1
    //   356: aload_0
    //   357: getfield 81	com/loc/dl:a	Ljava/io/RandomAccessFile;
    //   360: astore_3
    //   361: aload 4
    //   363: astore_1
    //   364: aload_3
    //   365: ifnull -67 -> 298
    //   368: aload_0
    //   369: getfield 81	com/loc/dl:a	Ljava/io/RandomAccessFile;
    //   372: invokevirtual 126	java/io/RandomAccessFile:close	()V
    //   375: aload 4
    //   377: astore_1
    //   378: goto -80 -> 298
    //   381: astore_1
    //   382: aload 4
    //   384: astore_1
    //   385: goto -87 -> 298
    //   388: astore_1
    //   389: aload_0
    //   390: getfield 81	com/loc/dl:a	Ljava/io/RandomAccessFile;
    //   393: astore_3
    //   394: aload_3
    //   395: ifnull +10 -> 405
    //   398: aload_0
    //   399: getfield 81	com/loc/dl:a	Ljava/io/RandomAccessFile;
    //   402: invokevirtual 126	java/io/RandomAccessFile:close	()V
    //   405: aload_1
    //   406: athrow
    //   407: astore_3
    //   408: goto -3 -> 405
    //   411: astore_1
    //   412: aload 5
    //   414: astore_1
    //   415: goto -117 -> 298
    //   418: astore_1
    //   419: goto -290 -> 129
    //
    // Exception table:
    //   from	to	target	type
    //   10	27	134	finally
    //   113	118	134	finally
    //   122	129	134	finally
    //   129	131	134	finally
    //   276	281	134	finally
    //   288	295	134	finally
    //   298	313	134	finally
    //   313	320	134	finally
    //   324	330	134	finally
    //   337	344	134	finally
    //   356	361	134	finally
    //   368	375	134	finally
    //   389	394	134	finally
    //   398	405	134	finally
    //   405	407	134	finally
    //   8	10	139	finally
    //   135	139	139	finally
    //   106	113	144	java/io/IOException
    //   37	54	323	java/io/FileNotFoundException
    //   61	72	323	java/io/FileNotFoundException
    //   79	85	323	java/io/FileNotFoundException
    //   92	98	323	java/io/FileNotFoundException
    //   106	113	323	java/io/FileNotFoundException
    //   152	162	323	java/io/FileNotFoundException
    //   169	176	323	java/io/FileNotFoundException
    //   183	190	323	java/io/FileNotFoundException
    //   197	204	323	java/io/FileNotFoundException
    //   211	221	323	java/io/FileNotFoundException
    //   228	235	323	java/io/FileNotFoundException
    //   249	257	323	java/io/FileNotFoundException
    //   264	276	323	java/io/FileNotFoundException
    //   337	344	349	java/io/IOException
    //   37	54	355	java/io/IOException
    //   61	72	355	java/io/IOException
    //   79	85	355	java/io/IOException
    //   92	98	355	java/io/IOException
    //   152	162	355	java/io/IOException
    //   169	176	355	java/io/IOException
    //   183	190	355	java/io/IOException
    //   197	204	355	java/io/IOException
    //   211	221	355	java/io/IOException
    //   228	235	355	java/io/IOException
    //   249	257	355	java/io/IOException
    //   264	276	355	java/io/IOException
    //   368	375	381	java/io/IOException
    //   37	54	388	finally
    //   61	72	388	finally
    //   79	85	388	finally
    //   92	98	388	finally
    //   106	113	388	finally
    //   152	162	388	finally
    //   169	176	388	finally
    //   183	190	388	finally
    //   197	204	388	finally
    //   211	221	388	finally
    //   228	235	388	finally
    //   249	257	388	finally
    //   264	276	388	finally
    //   398	405	407	java/io/IOException
    //   288	295	411	java/io/IOException
    //   122	129	418	java/io/IOException
  }
}

/* Location:           C:\crazyd\work\ustone\odm2016031702\baidu\android\nut-dex2jar.jar
 * Qualified Name:     com.loc.dl
 * JD-Core Version:    0.6.2
 */