package com.loc;

import android.os.Handler;
import android.os.Looper;

public final class e extends Handler
{
  a a = null;

  public e(a parama)
  {
    this.a = parama;
  }

  public e(a parama, Looper paramLooper)
  {
    super(paramLooper);
    this.a = parama;
  }

  // ERROR //
  public final void handleMessage(android.os.Message paramMessage)
  {
    // Byte code:
    //   0: aload_0
    //   1: aload_1
    //   2: invokespecial 28	android/os/Handler:handleMessage	(Landroid/os/Message;)V
    //   5: aconst_null
    //   6: astore 7
    //   8: aload_1
    //   9: getfield 34	android/os/Message:what	I
    //   12: lookupswitch	default:+60->72, 1:+61->73, 2:+533->545, 5:+575->587, 100:+594->606, 101:+604->616, 102:+687->699
    //   73: aload_1
    //   74: invokevirtual 38	android/os/Message:getData	()Landroid/os/Bundle;
    //   77: astore_1
    //   78: aload_1
    //   79: ifnull +1113 -> 1192
    //   82: aload_1
    //   83: ldc 40
    //   85: invokevirtual 46	java/lang/Class:getClassLoader	()Ljava/lang/ClassLoader;
    //   88: invokevirtual 52	android/os/Bundle:setClassLoader	(Ljava/lang/ClassLoader;)V
    //   91: aload_1
    //   92: ldc 54
    //   94: invokevirtual 58	android/os/Bundle:getParcelable	(Ljava/lang/String;)Landroid/os/Parcelable;
    //   97: checkcast 40	com/autonavi/aps/amapapi/model/AmapLoc
    //   100: invokestatic 63	com/loc/dp:a	(Lcom/autonavi/aps/amapapi/model/AmapLoc;)Lcom/amap/api/location/AMapLocation;
    //   103: astore_1
    //   104: aload_1
    //   105: ldc 65
    //   107: invokevirtual 71	com/amap/api/location/AMapLocation:setProvider	(Ljava/lang/String;)V
    //   110: aload_0
    //   111: getfield 13	com/loc/e:a	Lcom/loc/a;
    //   114: getfield 77	com/loc/a:e	Lcom/loc/dq;
    //   117: ifnull +278 -> 395
    //   120: aload_0
    //   121: getfield 13	com/loc/e:a	Lcom/loc/a;
    //   124: getfield 77	com/loc/a:e	Lcom/loc/dq;
    //   127: astore 7
    //   129: aload 7
    //   131: getfield 83	com/loc/dq:b	Ljava/util/Hashtable;
    //   134: invokevirtual 89	java/util/Hashtable:isEmpty	()Z
    //   137: ifne +258 -> 395
    //   140: aload 7
    //   142: getfield 83	com/loc/dq:b	Ljava/util/Hashtable;
    //   145: invokevirtual 93	java/util/Hashtable:entrySet	()Ljava/util/Set;
    //   148: invokeinterface 99 1 0
    //   153: astore 8
    //   155: aload 8
    //   157: ifnull +238 -> 395
    //   160: aload 8
    //   162: invokeinterface 104 1 0
    //   167: ifeq +228 -> 395
    //   170: aload 8
    //   172: invokeinterface 108 1 0
    //   177: checkcast 110	java/util/Map$Entry
    //   180: astore 9
    //   182: aload 9
    //   184: invokeinterface 113 1 0
    //   189: checkcast 115	java/util/ArrayList
    //   192: invokevirtual 116	java/util/ArrayList:iterator	()Ljava/util/Iterator;
    //   195: astore 10
    //   197: aload 10
    //   199: invokeinterface 104 1 0
    //   204: ifeq -49 -> 155
    //   207: aload 10
    //   209: invokeinterface 108 1 0
    //   214: checkcast 118	com/amap/api/fence/Fence
    //   217: astore 11
    //   219: aload 11
    //   221: invokestatic 121	com/loc/dq:a	(Lcom/amap/api/fence/Fence;)Z
    //   224: ifne -27 -> 197
    //   227: iconst_4
    //   228: newarray double
    //   230: dup
    //   231: iconst_0
    //   232: aload 11
    //   234: getfield 125	com/amap/api/fence/Fence:d	D
    //   237: dastore
    //   238: dup
    //   239: iconst_1
    //   240: aload 11
    //   242: getfield 128	com/amap/api/fence/Fence:c	D
    //   245: dastore
    //   246: dup
    //   247: iconst_2
    //   248: aload_1
    //   249: invokevirtual 132	com/amap/api/location/AMapLocation:getLatitude	()D
    //   252: dastore
    //   253: dup
    //   254: iconst_3
    //   255: aload_1
    //   256: invokevirtual 135	com/amap/api/location/AMapLocation:getLongitude	()D
    //   259: dastore
    //   260: invokestatic 140	com/loc/by:a	([D)F
    //   263: fstore_2
    //   264: aload_1
    //   265: invokevirtual 144	com/amap/api/location/AMapLocation:getAccuracy	()F
    //   268: fstore_3
    //   269: fload_3
    //   270: ldc 145
    //   272: fcmpl
    //   273: iflt +509 -> 782
    //   276: fload_2
    //   277: aload 11
    //   279: getfield 148	com/amap/api/fence/Fence:e	F
    //   282: ldc 145
    //   284: fadd
    //   285: fsub
    //   286: fstore_2
    //   287: iconst_0
    //   288: istore 5
    //   290: iconst_0
    //   291: istore 4
    //   293: fload_2
    //   294: fconst_0
    //   295: fcmpl
    //   296: ifle +499 -> 795
    //   299: aload 11
    //   301: getfield 151	com/amap/api/fence/Fence:g	I
    //   304: ifeq +6 -> 310
    //   307: iconst_1
    //   308: istore 4
    //   310: aload 11
    //   312: iconst_0
    //   313: putfield 151	com/amap/api/fence/Fence:g	I
    //   316: iload 4
    //   318: ifeq +542 -> 860
    //   321: aload 11
    //   323: getfield 151	com/amap/api/fence/Fence:g	I
    //   326: tableswitch	default:+871 -> 1197, 0:+22->348, 1:+494->820
    //   349: fconst_0
    //   350: ldc2_w 152
    //   353: putfield 157	com/amap/api/fence/Fence:h	J
    //   356: aload 11
    //   358: invokevirtual 160	com/amap/api/fence/Fence:a	()I
    //   361: iconst_2
    //   362: iand
    //   363: iconst_2
    //   364: if_icmpne -167 -> 197
    //   367: aload 7
    //   369: aload 9
    //   371: invokeinterface 163 1 0
    //   376: checkcast 165	android/app/PendingIntent
    //   379: aload 11
    //   381: iconst_2
    //   382: invokevirtual 168	com/loc/dq:a	(Landroid/app/PendingIntent;Lcom/amap/api/fence/Fence;I)V
    //   385: goto -188 -> 197
    //   388: astore 7
    //   390: aload 7
    //   392: invokevirtual 171	java/lang/Throwable:printStackTrace	()V
    //   395: aload_1
    //   396: ifnull +15 -> 411
    //   399: ldc 173
    //   401: aload_1
    //   402: invokevirtual 177	com/amap/api/location/AMapLocation:getProvider	()Ljava/lang/String;
    //   405: invokevirtual 183	java/lang/String:equals	(Ljava/lang/Object;)Z
    //   408: ifne +13 -> 421
    //   411: aload_0
    //   412: getfield 13	com/loc/e:a	Lcom/loc/a;
    //   415: invokestatic 186	com/loc/a:a	(Lcom/loc/a;)Z
    //   418: ifeq +93 -> 511
    //   421: aload_0
    //   422: getfield 13	com/loc/e:a	Lcom/loc/a;
    //   425: invokestatic 189	com/loc/a:f	(Lcom/loc/a;)Z
    //   428: ifne +83 -> 511
    //   431: aload_0
    //   432: getfield 13	com/loc/e:a	Lcom/loc/a;
    //   435: getfield 192	com/loc/a:g	Lcom/loc/dt;
    //   438: ifnull +27 -> 465
    //   441: aload_0
    //   442: getfield 13	com/loc/e:a	Lcom/loc/a;
    //   445: getfield 192	com/loc/a:g	Lcom/loc/dt;
    //   448: astore 8
    //   450: aload 8
    //   452: getfield 197	com/loc/dt:a	Landroid/content/Context;
    //   455: ifnull +10 -> 465
    //   458: aload_1
    //   459: invokestatic 200	com/loc/by:a	(Lcom/amap/api/location/AMapLocation;)Z
    //   462: ifne +466 -> 928
    //   465: aload_0
    //   466: getfield 13	com/loc/e:a	Lcom/loc/a;
    //   469: getfield 203	com/loc/a:d	Ljava/util/ArrayList;
    //   472: invokevirtual 116	java/util/ArrayList:iterator	()Ljava/util/Iterator;
    //   475: astore 7
    //   477: aload 7
    //   479: invokeinterface 104 1 0
    //   484: ifeq +27 -> 511
    //   487: aload 7
    //   489: invokeinterface 108 1 0
    //   494: checkcast 205	com/amap/api/location/AMapLocationListener
    //   497: aload_1
    //   498: invokeinterface 209 2 0
    //   503: goto -26 -> 477
    //   506: astore_1
    //   507: aload_1
    //   508: invokevirtual 171	java/lang/Throwable:printStackTrace	()V
    //   511: aload_0
    //   512: getfield 13	com/loc/e:a	Lcom/loc/a;
    //   515: getfield 212	com/loc/a:a	Lcom/amap/api/location/AMapLocationClientOption;
    //   518: invokevirtual 217	com/amap/api/location/AMapLocationClientOption:isOnceLocation	()Z
    //   521: ifeq -449 -> 72
    //   524: aload_0
    //   525: getfield 13	com/loc/e:a	Lcom/loc/a;
    //   528: invokevirtual 220	com/loc/a:stopLocation	()V
    //   531: return
    //   532: astore_1
    //   533: aload_1
    //   534: invokevirtual 171	java/lang/Throwable:printStackTrace	()V
    //   537: return
    //   538: astore_1
    //   539: aload 7
    //   541: astore_1
    //   542: goto -432 -> 110
    //   545: aload_1
    //   546: getfield 224	android/os/Message:obj	Ljava/lang/Object;
    //   549: checkcast 67	com/amap/api/location/AMapLocation
    //   552: astore_1
    //   553: aload_1
    //   554: invokevirtual 227	com/amap/api/location/AMapLocation:getErrorCode	()I
    //   557: ifne +21 -> 578
    //   560: aload_0
    //   561: getfield 13	com/loc/e:a	Lcom/loc/a;
    //   564: invokestatic 230	com/loc/by:b	()J
    //   567: putfield 233	com/loc/a:m	J
    //   570: aload_0
    //   571: getfield 13	com/loc/e:a	Lcom/loc/a;
    //   574: iconst_1
    //   575: putfield 237	com/loc/a:p	Z
    //   578: goto -468 -> 110
    //   581: astore_1
    //   582: aconst_null
    //   583: astore_1
    //   584: goto -474 -> 110
    //   587: aload_0
    //   588: getfield 13	com/loc/e:a	Lcom/loc/a;
    //   591: invokestatic 230	com/loc/by:b	()J
    //   594: putfield 233	com/loc/a:m	J
    //   597: aload_0
    //   598: getfield 13	com/loc/e:a	Lcom/loc/a;
    //   601: iconst_1
    //   602: putfield 237	com/loc/a:p	Z
    //   605: return
    //   606: aload_0
    //   607: getfield 13	com/loc/e:a	Lcom/loc/a;
    //   610: invokestatic 239	com/loc/a:e	(Lcom/loc/a;)V
    //   613: return
    //   614: astore_1
    //   615: return
    //   616: invokestatic 243	android/os/Message:obtain	()Landroid/os/Message;
    //   619: astore_1
    //   620: aload_1
    //   621: iconst_2
    //   622: putfield 34	android/os/Message:what	I
    //   625: aload_0
    //   626: getfield 13	com/loc/e:a	Lcom/loc/a;
    //   629: getfield 246	com/loc/a:h	Landroid/os/Messenger;
    //   632: ifnull +23 -> 655
    //   635: aload_0
    //   636: getfield 13	com/loc/e:a	Lcom/loc/a;
    //   639: iconst_0
    //   640: putfield 249	com/loc/a:o	I
    //   643: aload_0
    //   644: getfield 13	com/loc/e:a	Lcom/loc/a;
    //   647: getfield 246	com/loc/a:h	Landroid/os/Messenger;
    //   650: aload_1
    //   651: invokevirtual 254	android/os/Messenger:send	(Landroid/os/Message;)V
    //   654: return
    //   655: aload_0
    //   656: getfield 13	com/loc/e:a	Lcom/loc/a;
    //   659: astore_1
    //   660: aload_1
    //   661: aload_1
    //   662: getfield 249	com/loc/a:o	I
    //   665: iconst_1
    //   666: iadd
    //   667: putfield 249	com/loc/a:o	I
    //   670: aload_0
    //   671: getfield 13	com/loc/e:a	Lcom/loc/a;
    //   674: getfield 249	com/loc/a:o	I
    //   677: bipush 10
    //   679: if_icmpge -607 -> 72
    //   682: aload_0
    //   683: getfield 13	com/loc/e:a	Lcom/loc/a;
    //   686: getfield 257	com/loc/a:b	Lcom/loc/e;
    //   689: bipush 101
    //   691: ldc2_w 258
    //   694: invokevirtual 263	com/loc/e:sendEmptyMessageDelayed	(IJ)Z
    //   697: pop
    //   698: return
    //   699: invokestatic 243	android/os/Message:obtain	()Landroid/os/Message;
    //   702: astore_1
    //   703: aload_1
    //   704: iconst_3
    //   705: putfield 34	android/os/Message:what	I
    //   708: aload_0
    //   709: getfield 13	com/loc/e:a	Lcom/loc/a;
    //   712: getfield 246	com/loc/a:h	Landroid/os/Messenger;
    //   715: ifnull +23 -> 738
    //   718: aload_0
    //   719: getfield 13	com/loc/e:a	Lcom/loc/a;
    //   722: iconst_0
    //   723: putfield 249	com/loc/a:o	I
    //   726: aload_0
    //   727: getfield 13	com/loc/e:a	Lcom/loc/a;
    //   730: getfield 246	com/loc/a:h	Landroid/os/Messenger;
    //   733: aload_1
    //   734: invokevirtual 254	android/os/Messenger:send	(Landroid/os/Message;)V
    //   737: return
    //   738: aload_0
    //   739: getfield 13	com/loc/e:a	Lcom/loc/a;
    //   742: astore_1
    //   743: aload_1
    //   744: aload_1
    //   745: getfield 249	com/loc/a:o	I
    //   748: iconst_1
    //   749: iadd
    //   750: putfield 249	com/loc/a:o	I
    //   753: aload_0
    //   754: getfield 13	com/loc/e:a	Lcom/loc/a;
    //   757: getfield 249	com/loc/a:o	I
    //   760: bipush 10
    //   762: if_icmpge -690 -> 72
    //   765: aload_0
    //   766: getfield 13	com/loc/e:a	Lcom/loc/a;
    //   769: getfield 257	com/loc/a:b	Lcom/loc/e;
    //   772: bipush 102
    //   774: ldc2_w 258
    //   777: invokevirtual 263	com/loc/e:sendEmptyMessageDelayed	(IJ)Z
    //   780: pop
    //   781: return
    //   782: fload_2
    //   783: fload_3
    //   784: aload 11
    //   786: getfield 148	com/amap/api/fence/Fence:e	F
    //   789: fadd
    //   790: fsub
    //   791: fstore_2
    //   792: goto -505 -> 287
    //   795: iload 5
    //   797: istore 4
    //   799: aload 11
    //   801: getfield 151	com/amap/api/fence/Fence:g	I
    //   804: iconst_1
    //   805: if_icmpeq +6 -> 811
    //   808: iconst_1
    //   809: istore 4
    //   811: aload 11
    //   813: iconst_1
    //   814: putfield 151	com/amap/api/fence/Fence:g	I
    //   817: goto -501 -> 316
    //   820: aload 11
    //   822: invokestatic 230	com/loc/by:b	()J
    //   825: putfield 157	com/amap/api/fence/Fence:h	J
    //   828: aload 11
    //   830: invokevirtual 160	com/amap/api/fence/Fence:a	()I
    //   833: iconst_1
    //   834: iand
    //   835: iconst_1
    //   836: if_icmpne -639 -> 197
    //   839: aload 7
    //   841: aload 9
    //   843: invokeinterface 163 1 0
    //   848: checkcast 165	android/app/PendingIntent
    //   851: aload 11
    //   853: iconst_1
    //   854: invokevirtual 168	com/loc/dq:a	(Landroid/app/PendingIntent;Lcom/amap/api/fence/Fence;I)V
    //   857: goto -660 -> 197
    //   860: aload 11
    //   862: invokevirtual 160	com/amap/api/fence/Fence:a	()I
    //   865: iconst_4
    //   866: iand
    //   867: iconst_4
    //   868: if_icmpne -671 -> 197
    //   871: aload 11
    //   873: getfield 157	com/amap/api/fence/Fence:h	J
    //   876: lconst_0
    //   877: lcmp
    //   878: ifle -681 -> 197
    //   881: invokestatic 230	com/loc/by:b	()J
    //   884: aload 11
    //   886: getfield 157	com/amap/api/fence/Fence:h	J
    //   889: lsub
    //   890: aload 11
    //   892: invokevirtual 265	com/amap/api/fence/Fence:c	()J
    //   895: lcmp
    //   896: ifle -699 -> 197
    //   899: aload 11
    //   901: invokestatic 230	com/loc/by:b	()J
    //   904: putfield 157	com/amap/api/fence/Fence:h	J
    //   907: aload 7
    //   909: aload 9
    //   911: invokeinterface 163 1 0
    //   916: checkcast 165	android/app/PendingIntent
    //   919: aload 11
    //   921: iconst_4
    //   922: invokevirtual 168	com/loc/dq:a	(Landroid/app/PendingIntent;Lcom/amap/api/fence/Fence;I)V
    //   925: goto -728 -> 197
    //   928: aload_1
    //   929: invokevirtual 268	com/amap/api/location/AMapLocation:getLocationType	()I
    //   932: iconst_2
    //   933: if_icmpeq -468 -> 465
    //   936: aload 8
    //   938: getfield 271	com/loc/dt:d	Landroid/content/SharedPreferences;
    //   941: ifnonnull +20 -> 961
    //   944: aload 8
    //   946: aload 8
    //   948: getfield 197	com/loc/dt:a	Landroid/content/Context;
    //   951: ldc_w 273
    //   954: iconst_0
    //   955: invokevirtual 279	android/content/Context:getSharedPreferences	(Ljava/lang/String;I)Landroid/content/SharedPreferences;
    //   958: putfield 271	com/loc/dt:d	Landroid/content/SharedPreferences;
    //   961: aload 8
    //   963: getfield 282	com/loc/dt:e	Landroid/content/SharedPreferences$Editor;
    //   966: ifnonnull +18 -> 984
    //   969: aload 8
    //   971: aload 8
    //   973: getfield 271	com/loc/dt:d	Landroid/content/SharedPreferences;
    //   976: invokeinterface 288 1 0
    //   981: putfield 282	com/loc/dt:e	Landroid/content/SharedPreferences$Editor;
    //   984: aconst_null
    //   985: astore 7
    //   987: aload_1
    //   988: invokevirtual 291	com/amap/api/location/AMapLocation:toStr	()Ljava/lang/String;
    //   991: invokestatic 296	android/text/TextUtils:isEmpty	(Ljava/lang/CharSequence;)Z
    //   994: istore 6
    //   996: iload 6
    //   998: ifne +30 -> 1028
    //   1001: aload_1
    //   1002: invokevirtual 291	com/amap/api/location/AMapLocation:toStr	()Ljava/lang/String;
    //   1005: ldc_w 298
    //   1008: invokevirtual 302	java/lang/String:getBytes	(Ljava/lang/String;)[B
    //   1011: aload 8
    //   1013: getfield 305	com/loc/dt:b	Ljava/lang/String;
    //   1016: invokestatic 310	com/loc/bf:c	([BLjava/lang/String;)[B
    //   1019: astore 7
    //   1021: aload 7
    //   1023: invokestatic 315	com/loc/ej:a	([B)Ljava/lang/String;
    //   1026: astore 7
    //   1028: aload 7
    //   1030: invokestatic 296	android/text/TextUtils:isEmpty	(Ljava/lang/CharSequence;)Z
    //   1033: ifne -568 -> 465
    //   1036: new 317	java/lang/StringBuilder
    //   1039: dup
    //   1040: ldc_w 319
    //   1043: invokespecial 321	java/lang/StringBuilder:<init>	(Ljava/lang/String;)V
    //   1046: getstatic 323	com/loc/dp:f	Ljava/lang/String;
    //   1049: invokevirtual 327	java/lang/StringBuilder:append	(Ljava/lang/String;)Ljava/lang/StringBuilder;
    //   1052: invokevirtual 330	java/lang/StringBuilder:toString	()Ljava/lang/String;
    //   1055: astore 9
    //   1057: aload 8
    //   1059: getfield 282	com/loc/dt:e	Landroid/content/SharedPreferences$Editor;
    //   1062: aload 9
    //   1064: aload 7
    //   1066: invokeinterface 336 3 0
    //   1071: pop
    //   1072: aload 8
    //   1074: getfield 282	com/loc/dt:e	Landroid/content/SharedPreferences$Editor;
    //   1077: astore 7
    //   1079: aload 7
    //   1081: ifnull -616 -> 465
    //   1084: getstatic 341	android/os/Build$VERSION:SDK_INT	I
    //   1087: istore 4
    //   1089: iload 4
    //   1091: bipush 9
    //   1093: if_icmplt +78 -> 1171
    //   1096: aload 8
    //   1098: getfield 344	com/loc/dt:f	Ljava/lang/reflect/Method;
    //   1101: ifnonnull +21 -> 1122
    //   1104: aload 8
    //   1106: ldc_w 332
    //   1109: ldc_w 346
    //   1112: iconst_0
    //   1113: anewarray 42	java/lang/Class
    //   1116: invokevirtual 350	java/lang/Class:getDeclaredMethod	(Ljava/lang/String;[Ljava/lang/Class;)Ljava/lang/reflect/Method;
    //   1119: putfield 344	com/loc/dt:f	Ljava/lang/reflect/Method;
    //   1122: aload 8
    //   1124: getfield 344	com/loc/dt:f	Ljava/lang/reflect/Method;
    //   1127: aload 7
    //   1129: iconst_0
    //   1130: anewarray 352	java/lang/Object
    //   1133: invokevirtual 358	java/lang/reflect/Method:invoke	(Ljava/lang/Object;[Ljava/lang/Object;)Ljava/lang/Object;
    //   1136: pop
    //   1137: goto -672 -> 465
    //   1140: astore 8
    //   1142: aload 8
    //   1144: invokevirtual 171	java/lang/Throwable:printStackTrace	()V
    //   1147: aload 7
    //   1149: invokeinterface 361 1 0
    //   1154: pop
    //   1155: goto -690 -> 465
    //   1158: astore 7
    //   1160: aload 7
    //   1162: invokevirtual 362	java/io/UnsupportedEncodingException:printStackTrace	()V
    //   1165: aconst_null
    //   1166: astore 7
    //   1168: goto -147 -> 1021
    //   1171: aload 7
    //   1173: invokeinterface 361 1 0
    //   1178: pop
    //   1179: goto -714 -> 465
    //   1182: astore 7
    //   1184: goto -600 -> 584
    //   1187: astore 7
    //   1189: goto -647 -> 542
    //   1192: aconst_null
    //   1193: astore_1
    //   1194: goto -1084 -> 110
    //   1197: goto -1000 -> 197
    //   1200: astore_1
    //   1201: return
    //   1202: astore_1
    //   1203: return
    //
    // Exception table:
    //   from	to	target	type
    //   110	155	388	java/lang/Throwable
    //   160	197	388	java/lang/Throwable
    //   197	269	388	java/lang/Throwable
    //   276	287	388	java/lang/Throwable
    //   299	307	388	java/lang/Throwable
    //   310	316	388	java/lang/Throwable
    //   321	348	388	java/lang/Throwable
    //   348	385	388	java/lang/Throwable
    //   782	792	388	java/lang/Throwable
    //   799	808	388	java/lang/Throwable
    //   811	817	388	java/lang/Throwable
    //   820	857	388	java/lang/Throwable
    //   860	925	388	java/lang/Throwable
    //   399	411	506	java/lang/Throwable
    //   411	421	506	java/lang/Throwable
    //   421	465	506	java/lang/Throwable
    //   465	477	506	java/lang/Throwable
    //   477	503	506	java/lang/Throwable
    //   928	961	506	java/lang/Throwable
    //   961	984	506	java/lang/Throwable
    //   987	996	506	java/lang/Throwable
    //   1001	1021	506	java/lang/Throwable
    //   1021	1028	506	java/lang/Throwable
    //   1028	1079	506	java/lang/Throwable
    //   1084	1089	506	java/lang/Throwable
    //   1142	1155	506	java/lang/Throwable
    //   1160	1165	506	java/lang/Throwable
    //   1171	1179	506	java/lang/Throwable
    //   511	531	532	java/lang/Throwable
    //   73	78	538	java/lang/Throwable
    //   82	104	538	java/lang/Throwable
    //   545	553	581	java/lang/Throwable
    //   606	613	614	java/lang/Throwable
    //   1096	1122	1140	java/lang/Throwable
    //   1122	1137	1140	java/lang/Throwable
    //   1001	1021	1158	java/io/UnsupportedEncodingException
    //   553	578	1182	java/lang/Throwable
    //   104	110	1187	java/lang/Throwable
    //   616	654	1200	android/os/RemoteException
    //   655	698	1200	android/os/RemoteException
    //   699	737	1202	android/os/RemoteException
    //   738	781	1202	android/os/RemoteException
  }
}

/* Location:           C:\crazyd\work\ustone\odm2016031702\baidu\android\nut-dex2jar.jar
 * Qualified Name:     com.loc.e
 * JD-Core Version:    0.6.2
 */