package com.loc;

import android.content.Context;
import org.json.JSONException;
import org.json.JSONObject;

public final class eb
{
  public static ec a(Context paramContext, eo parameo, String paramString)
  {
    try
    {
      new z();
      paramContext = a(z.a(new eg(paramContext, parameo, paramString)));
      return paramContext;
    }
    catch (l paramContext)
    {
      paramContext.printStackTrace();
      return new ec();
    }
    catch (Throwable paramContext)
    {
      while (true)
        paramContext.printStackTrace();
    }
  }

  // ERROR //
  private static ec a(byte[] paramArrayOfByte)
  {
    // Byte code:
    //   0: iconst_0
    //   1: istore_2
    //   2: new 32	com/loc/ec
    //   5: dup
    //   6: invokespecial 33	com/loc/ec:<init>	()V
    //   9: astore_3
    //   10: aload_0
    //   11: ifnull +473 -> 484
    //   14: aload_0
    //   15: arraylength
    //   16: ifne +5 -> 21
    //   19: aload_3
    //   20: areturn
    //   21: new 40	org/json/JSONObject
    //   24: dup
    //   25: new 42	java/lang/String
    //   28: dup
    //   29: aload_0
    //   30: ldc 44
    //   32: invokespecial 47	java/lang/String:<init>	([BLjava/lang/String;)V
    //   35: invokespecial 50	org/json/JSONObject:<init>	(Ljava/lang/String;)V
    //   38: astore_0
    //   39: ldc 52
    //   41: aload_0
    //   42: ldc 54
    //   44: invokestatic 57	com/loc/eb:a	(Lorg/json/JSONObject;Ljava/lang/String;)Ljava/lang/String;
    //   47: invokevirtual 61	java/lang/String:equals	(Ljava/lang/Object;)Z
    //   50: ifeq +434 -> 484
    //   53: aload_0
    //   54: ldc 63
    //   56: invokevirtual 67	org/json/JSONObject:has	(Ljava/lang/String;)Z
    //   59: ifeq +425 -> 484
    //   62: aload_0
    //   63: ldc 63
    //   65: invokevirtual 71	org/json/JSONObject:getJSONObject	(Ljava/lang/String;)Lorg/json/JSONObject;
    //   68: astore_0
    //   69: aload_0
    //   70: ifnull +414 -> 484
    //   73: aload_0
    //   74: ldc 73
    //   76: invokestatic 78	com/loc/eq:a	(Lorg/json/JSONObject;Ljava/lang/String;)Z
    //   79: ifeq +400 -> 479
    //   82: aload_0
    //   83: ldc 73
    //   85: invokevirtual 71	org/json/JSONObject:getJSONObject	(Ljava/lang/String;)Lorg/json/JSONObject;
    //   88: invokestatic 82	com/loc/eb:b	(Lorg/json/JSONObject;)Z
    //   91: istore_1
    //   92: aload_0
    //   93: ldc 84
    //   95: invokestatic 78	com/loc/eq:a	(Lorg/json/JSONObject;Ljava/lang/String;)Z
    //   98: ifeq +13 -> 111
    //   101: aload_0
    //   102: ldc 84
    //   104: invokevirtual 71	org/json/JSONObject:getJSONObject	(Ljava/lang/String;)Lorg/json/JSONObject;
    //   107: invokestatic 86	com/loc/eb:a	(Lorg/json/JSONObject;)Z
    //   110: istore_2
    //   111: new 88	com/loc/ed
    //   114: dup
    //   115: invokespecial 89	com/loc/ed:<init>	()V
    //   118: astore 4
    //   120: aload 4
    //   122: iload_1
    //   123: putfield 92	com/loc/ed:a	Z
    //   126: aload 4
    //   128: iload_2
    //   129: putfield 94	com/loc/ed:b	Z
    //   132: aload_3
    //   133: aload 4
    //   135: putfield 98	com/loc/ec:f	Lcom/loc/ed;
    //   138: aload_0
    //   139: ldc 100
    //   141: invokevirtual 67	org/json/JSONObject:has	(Ljava/lang/String;)Z
    //   144: ifeq +84 -> 228
    //   147: aload_0
    //   148: ldc 100
    //   150: invokevirtual 71	org/json/JSONObject:getJSONObject	(Ljava/lang/String;)Lorg/json/JSONObject;
    //   153: astore 7
    //   155: new 102	com/loc/ef
    //   158: dup
    //   159: invokespecial 103	com/loc/ef:<init>	()V
    //   162: astore 4
    //   164: aload 7
    //   166: ifnull +56 -> 222
    //   169: aload 7
    //   171: ldc 105
    //   173: invokestatic 57	com/loc/eb:a	(Lorg/json/JSONObject;Ljava/lang/String;)Ljava/lang/String;
    //   176: astore 5
    //   178: aload 7
    //   180: ldc 107
    //   182: invokestatic 57	com/loc/eb:a	(Lorg/json/JSONObject;Ljava/lang/String;)Ljava/lang/String;
    //   185: astore 6
    //   187: aload 7
    //   189: ldc 109
    //   191: invokestatic 57	com/loc/eb:a	(Lorg/json/JSONObject;Ljava/lang/String;)Ljava/lang/String;
    //   194: astore 7
    //   196: aload 5
    //   198: invokestatic 115	android/text/TextUtils:isEmpty	(Ljava/lang/CharSequence;)Z
    //   201: ifne +21 -> 222
    //   204: aload 6
    //   206: invokestatic 115	android/text/TextUtils:isEmpty	(Ljava/lang/CharSequence;)Z
    //   209: ifne +13 -> 222
    //   212: aload 7
    //   214: invokestatic 115	android/text/TextUtils:isEmpty	(Ljava/lang/CharSequence;)Z
    //   217: istore_1
    //   218: iload_1
    //   219: ifeq +182 -> 401
    //   222: aload_3
    //   223: aload 4
    //   225: putfield 119	com/loc/ec:g	Lcom/loc/ef;
    //   228: aload_0
    //   229: ldc 121
    //   231: invokestatic 78	com/loc/eq:a	(Lorg/json/JSONObject;Ljava/lang/String;)Z
    //   234: ifeq +63 -> 297
    //   237: aload_0
    //   238: ldc 121
    //   240: invokevirtual 71	org/json/JSONObject:getJSONObject	(Ljava/lang/String;)Lorg/json/JSONObject;
    //   243: astore 6
    //   245: new 123	com/loc/ee
    //   248: dup
    //   249: invokespecial 124	com/loc/ee:<init>	()V
    //   252: astore 4
    //   254: aload 6
    //   256: ifnull +35 -> 291
    //   259: aload 6
    //   261: ldc 105
    //   263: invokestatic 57	com/loc/eb:a	(Lorg/json/JSONObject;Ljava/lang/String;)Ljava/lang/String;
    //   266: astore 5
    //   268: aload 6
    //   270: ldc 107
    //   272: invokestatic 57	com/loc/eb:a	(Lorg/json/JSONObject;Ljava/lang/String;)Ljava/lang/String;
    //   275: astore 6
    //   277: aload 4
    //   279: aload 5
    //   281: putfield 127	com/loc/ee:b	Ljava/lang/String;
    //   284: aload 4
    //   286: aload 6
    //   288: putfield 129	com/loc/ee:a	Ljava/lang/String;
    //   291: aload_3
    //   292: aload 4
    //   294: putfield 133	com/loc/ec:h	Lcom/loc/ee;
    //   297: aload_0
    //   298: ldc 135
    //   300: invokestatic 78	com/loc/eq:a	(Lorg/json/JSONObject;Ljava/lang/String;)Z
    //   303: ifeq +13 -> 316
    //   306: aload_3
    //   307: aload_0
    //   308: ldc 135
    //   310: invokevirtual 71	org/json/JSONObject:getJSONObject	(Ljava/lang/String;)Lorg/json/JSONObject;
    //   313: putfield 139	com/loc/ec:d	Lorg/json/JSONObject;
    //   316: aload_0
    //   317: ldc 141
    //   319: invokestatic 78	com/loc/eq:a	(Lorg/json/JSONObject;Ljava/lang/String;)Z
    //   322: ifeq +13 -> 335
    //   325: aload_3
    //   326: aload_0
    //   327: ldc 141
    //   329: invokevirtual 71	org/json/JSONObject:getJSONObject	(Ljava/lang/String;)Lorg/json/JSONObject;
    //   332: putfield 144	com/loc/ec:e	Lorg/json/JSONObject;
    //   335: aload_0
    //   336: ldc 146
    //   338: invokestatic 78	com/loc/eq:a	(Lorg/json/JSONObject;Ljava/lang/String;)Z
    //   341: ifeq +13 -> 354
    //   344: aload_3
    //   345: aload_0
    //   346: ldc 146
    //   348: invokevirtual 71	org/json/JSONObject:getJSONObject	(Ljava/lang/String;)Lorg/json/JSONObject;
    //   351: putfield 149	com/loc/ec:c	Lorg/json/JSONObject;
    //   354: aload_0
    //   355: ldc 151
    //   357: invokestatic 78	com/loc/eq:a	(Lorg/json/JSONObject;Ljava/lang/String;)Z
    //   360: ifeq +13 -> 373
    //   363: aload_3
    //   364: aload_0
    //   365: ldc 151
    //   367: invokevirtual 71	org/json/JSONObject:getJSONObject	(Ljava/lang/String;)Lorg/json/JSONObject;
    //   370: putfield 153	com/loc/ec:b	Lorg/json/JSONObject;
    //   373: aload_0
    //   374: ldc 155
    //   376: invokestatic 78	com/loc/eq:a	(Lorg/json/JSONObject;Ljava/lang/String;)Z
    //   379: ifeq +105 -> 484
    //   382: aload_3
    //   383: aload_0
    //   384: ldc 155
    //   386: invokevirtual 71	org/json/JSONObject:getJSONObject	(Ljava/lang/String;)Lorg/json/JSONObject;
    //   389: putfield 157	com/loc/ec:a	Lorg/json/JSONObject;
    //   392: aload_3
    //   393: areturn
    //   394: astore_0
    //   395: aload_0
    //   396: invokevirtual 30	java/lang/Throwable:printStackTrace	()V
    //   399: aload_3
    //   400: areturn
    //   401: aload 4
    //   403: aload 6
    //   405: putfield 158	com/loc/ef:a	Ljava/lang/String;
    //   408: aload 4
    //   410: aload 5
    //   412: putfield 159	com/loc/ef:b	Ljava/lang/String;
    //   415: aload 4
    //   417: aload 7
    //   419: putfield 161	com/loc/ef:c	Ljava/lang/String;
    //   422: goto -200 -> 222
    //   425: astore 5
    //   427: aload 5
    //   429: invokevirtual 30	java/lang/Throwable:printStackTrace	()V
    //   432: goto -210 -> 222
    //   435: astore_0
    //   436: aload_0
    //   437: invokevirtual 30	java/lang/Throwable:printStackTrace	()V
    //   440: aload_3
    //   441: areturn
    //   442: astore 5
    //   444: aload 5
    //   446: invokevirtual 30	java/lang/Throwable:printStackTrace	()V
    //   449: goto -227 -> 222
    //   452: astore_0
    //   453: aload_0
    //   454: invokevirtual 30	java/lang/Throwable:printStackTrace	()V
    //   457: aload_3
    //   458: areturn
    //   459: astore 5
    //   461: aload 5
    //   463: invokevirtual 30	java/lang/Throwable:printStackTrace	()V
    //   466: goto -175 -> 291
    //   469: astore 5
    //   471: aload 5
    //   473: invokevirtual 30	java/lang/Throwable:printStackTrace	()V
    //   476: goto -185 -> 291
    //   479: iconst_0
    //   480: istore_1
    //   481: goto -389 -> 92
    //   484: aload_3
    //   485: areturn
    //
    // Exception table:
    //   from	to	target	type
    //   14	19	394	org/json/JSONException
    //   21	69	394	org/json/JSONException
    //   73	92	394	org/json/JSONException
    //   92	111	394	org/json/JSONException
    //   111	164	394	org/json/JSONException
    //   222	228	394	org/json/JSONException
    //   228	254	394	org/json/JSONException
    //   291	297	394	org/json/JSONException
    //   297	316	394	org/json/JSONException
    //   316	335	394	org/json/JSONException
    //   335	354	394	org/json/JSONException
    //   354	373	394	org/json/JSONException
    //   373	392	394	org/json/JSONException
    //   427	432	394	org/json/JSONException
    //   444	449	394	org/json/JSONException
    //   461	466	394	org/json/JSONException
    //   471	476	394	org/json/JSONException
    //   169	218	425	org/json/JSONException
    //   401	422	425	org/json/JSONException
    //   14	19	435	java/io/UnsupportedEncodingException
    //   21	69	435	java/io/UnsupportedEncodingException
    //   73	92	435	java/io/UnsupportedEncodingException
    //   92	111	435	java/io/UnsupportedEncodingException
    //   111	164	435	java/io/UnsupportedEncodingException
    //   169	218	435	java/io/UnsupportedEncodingException
    //   222	228	435	java/io/UnsupportedEncodingException
    //   228	254	435	java/io/UnsupportedEncodingException
    //   259	291	435	java/io/UnsupportedEncodingException
    //   291	297	435	java/io/UnsupportedEncodingException
    //   297	316	435	java/io/UnsupportedEncodingException
    //   316	335	435	java/io/UnsupportedEncodingException
    //   335	354	435	java/io/UnsupportedEncodingException
    //   354	373	435	java/io/UnsupportedEncodingException
    //   373	392	435	java/io/UnsupportedEncodingException
    //   401	422	435	java/io/UnsupportedEncodingException
    //   427	432	435	java/io/UnsupportedEncodingException
    //   444	449	435	java/io/UnsupportedEncodingException
    //   461	466	435	java/io/UnsupportedEncodingException
    //   471	476	435	java/io/UnsupportedEncodingException
    //   169	218	442	java/lang/Throwable
    //   401	422	442	java/lang/Throwable
    //   14	19	452	java/lang/Throwable
    //   21	69	452	java/lang/Throwable
    //   73	92	452	java/lang/Throwable
    //   92	111	452	java/lang/Throwable
    //   111	164	452	java/lang/Throwable
    //   222	228	452	java/lang/Throwable
    //   228	254	452	java/lang/Throwable
    //   291	297	452	java/lang/Throwable
    //   297	316	452	java/lang/Throwable
    //   316	335	452	java/lang/Throwable
    //   335	354	452	java/lang/Throwable
    //   354	373	452	java/lang/Throwable
    //   373	392	452	java/lang/Throwable
    //   427	432	452	java/lang/Throwable
    //   444	449	452	java/lang/Throwable
    //   461	466	452	java/lang/Throwable
    //   471	476	452	java/lang/Throwable
    //   259	291	459	org/json/JSONException
    //   259	291	469	java/lang/Throwable
  }

  private static String a(JSONObject paramJSONObject, String paramString)
    throws JSONException
  {
    if (paramJSONObject == null);
    while ((!paramJSONObject.has(paramString)) || (paramJSONObject.getString(paramString).equals("[]")))
      return "";
    return paramJSONObject.optString(paramString);
  }

  private static boolean a(String paramString)
  {
    if (paramString == null);
    while (!paramString.equals("1"))
      return false;
    return true;
  }

  private static boolean a(JSONObject paramJSONObject)
  {
    if (paramJSONObject == null)
      return false;
    try
    {
      boolean bool = a(a(paramJSONObject.getJSONObject("commoninfo"), "com_isupload"));
      return bool;
    }
    catch (JSONException paramJSONObject)
    {
      paramJSONObject.printStackTrace();
      return false;
    }
    catch (Throwable paramJSONObject)
    {
      paramJSONObject.printStackTrace();
    }
    return false;
  }

  private static boolean b(JSONObject paramJSONObject)
  {
    if (paramJSONObject == null)
      return false;
    try
    {
      boolean bool = a(a(paramJSONObject.getJSONObject("exceptinfo"), "ex_isupload"));
      return bool;
    }
    catch (JSONException paramJSONObject)
    {
      paramJSONObject.printStackTrace();
      return false;
    }
    catch (Throwable paramJSONObject)
    {
      paramJSONObject.printStackTrace();
    }
    return false;
  }
}

/* Location:           C:\crazyd\work\ustone\odm2016031702\baidu\android\nut-dex2jar.jar
 * Qualified Name:     com.loc.eb
 * JD-Core Version:    0.6.2
 */