package com.loc;

public final class k
{
  // ERROR //
  public static <T> T a(android.content.Context paramContext, eo parameo, java.lang.String paramString, java.lang.Class paramClass, java.lang.Class[] paramArrayOfClass, Object[] paramArrayOfObject)
    throws l
  {
    // Byte code:
    //   0: aconst_null
    //   1: astore 7
    //   3: aload_0
    //   4: aload_1
    //   5: aload_0
    //   6: aload_1
    //   7: getfield 28	com/loc/eo:c	Ljava/lang/String;
    //   10: aload_1
    //   11: getfield 30	com/loc/eo:a	Ljava/lang/String;
    //   14: invokestatic 35	com/loc/n:a	(Landroid/content/Context;Ljava/lang/String;Ljava/lang/String;)Ljava/lang/String;
    //   17: aload_0
    //   18: invokestatic 38	com/loc/n:a	(Landroid/content/Context;)Ljava/lang/String;
    //   21: aload_0
    //   22: invokevirtual 44	android/content/Context:getClassLoader	()Ljava/lang/ClassLoader;
    //   25: invokestatic 49	com/loc/q:a	(Landroid/content/Context;Lcom/loc/eo;Ljava/lang/String;Ljava/lang/String;Ljava/lang/ClassLoader;)Lcom/loc/q;
    //   28: astore_0
    //   29: aload_0
    //   30: ifnull +71 -> 101
    //   33: aload_0
    //   34: getfield 52	com/loc/q:a	Ldalvik/system/DexFile;
    //   37: ifnull +53 -> 90
    //   40: iconst_1
    //   41: istore 6
    //   43: iload 6
    //   45: ifeq +56 -> 101
    //   48: aload_0
    //   49: getfield 56	com/loc/q:b	Z
    //   52: ifeq +49 -> 101
    //   55: aload_0
    //   56: aload_2
    //   57: invokevirtual 60	com/loc/q:loadClass	(Ljava/lang/String;)Ljava/lang/Class;
    //   60: astore_0
    //   61: aload_0
    //   62: ifnull +39 -> 101
    //   65: aload_0
    //   66: aload 4
    //   68: invokevirtual 66	java/lang/Class:getConstructor	([Ljava/lang/Class;)Ljava/lang/reflect/Constructor;
    //   71: aload 5
    //   73: invokevirtual 72	java/lang/reflect/Constructor:newInstance	([Ljava/lang/Object;)Ljava/lang/Object;
    //   76: astore_0
    //   77: aload_0
    //   78: areturn
    //   79: astore_0
    //   80: aload_0
    //   81: invokevirtual 76	java/lang/Throwable:printStackTrace	()V
    //   84: aload 7
    //   86: astore_0
    //   87: goto -58 -> 29
    //   90: iconst_0
    //   91: istore 6
    //   93: goto -50 -> 43
    //   96: astore_0
    //   97: aload_0
    //   98: invokevirtual 77	java/lang/ClassNotFoundException:printStackTrace	()V
    //   101: aload_3
    //   102: aload 4
    //   104: invokevirtual 66	java/lang/Class:getConstructor	([Ljava/lang/Class;)Ljava/lang/reflect/Constructor;
    //   107: astore_0
    //   108: aload_0
    //   109: iconst_1
    //   110: invokevirtual 81	java/lang/reflect/Constructor:setAccessible	(Z)V
    //   113: aload_0
    //   114: aload 5
    //   116: invokevirtual 72	java/lang/reflect/Constructor:newInstance	([Ljava/lang/Object;)Ljava/lang/Object;
    //   119: astore_0
    //   120: aload_0
    //   121: areturn
    //   122: astore_0
    //   123: aload_0
    //   124: invokevirtual 82	java/lang/NoSuchMethodException:printStackTrace	()V
    //   127: goto -26 -> 101
    //   130: astore_0
    //   131: aload_0
    //   132: invokevirtual 83	java/lang/InstantiationException:printStackTrace	()V
    //   135: goto -34 -> 101
    //   138: astore_0
    //   139: aload_0
    //   140: invokevirtual 84	java/lang/IllegalAccessException:printStackTrace	()V
    //   143: goto -42 -> 101
    //   146: astore_0
    //   147: aload_0
    //   148: invokevirtual 85	java/lang/IllegalArgumentException:printStackTrace	()V
    //   151: goto -50 -> 101
    //   154: astore_0
    //   155: aload_0
    //   156: invokevirtual 86	java/lang/reflect/InvocationTargetException:printStackTrace	()V
    //   159: goto -58 -> 101
    //   162: astore_0
    //   163: aload_0
    //   164: invokevirtual 76	java/lang/Throwable:printStackTrace	()V
    //   167: goto -66 -> 101
    //   170: astore_0
    //   171: aload_0
    //   172: invokevirtual 82	java/lang/NoSuchMethodException:printStackTrace	()V
    //   175: new 8	com/loc/l
    //   178: dup
    //   179: ldc 88
    //   181: invokespecial 92	com/loc/l:<init>	(Ljava/lang/String;)V
    //   184: athrow
    //   185: astore_0
    //   186: aload_0
    //   187: invokevirtual 83	java/lang/InstantiationException:printStackTrace	()V
    //   190: goto -15 -> 175
    //   193: astore_0
    //   194: aload_0
    //   195: invokevirtual 84	java/lang/IllegalAccessException:printStackTrace	()V
    //   198: goto -23 -> 175
    //   201: astore_0
    //   202: aload_0
    //   203: invokevirtual 85	java/lang/IllegalArgumentException:printStackTrace	()V
    //   206: goto -31 -> 175
    //   209: astore_0
    //   210: aload_0
    //   211: invokevirtual 86	java/lang/reflect/InvocationTargetException:printStackTrace	()V
    //   214: goto -39 -> 175
    //   217: astore_0
    //   218: aload_0
    //   219: invokevirtual 76	java/lang/Throwable:printStackTrace	()V
    //   222: goto -47 -> 175
    //
    // Exception table:
    //   from	to	target	type
    //   3	29	79	java/lang/Throwable
    //   33	40	96	java/lang/ClassNotFoundException
    //   48	61	96	java/lang/ClassNotFoundException
    //   65	77	96	java/lang/ClassNotFoundException
    //   33	40	122	java/lang/NoSuchMethodException
    //   48	61	122	java/lang/NoSuchMethodException
    //   65	77	122	java/lang/NoSuchMethodException
    //   33	40	130	java/lang/InstantiationException
    //   48	61	130	java/lang/InstantiationException
    //   65	77	130	java/lang/InstantiationException
    //   33	40	138	java/lang/IllegalAccessException
    //   48	61	138	java/lang/IllegalAccessException
    //   65	77	138	java/lang/IllegalAccessException
    //   33	40	146	java/lang/IllegalArgumentException
    //   48	61	146	java/lang/IllegalArgumentException
    //   65	77	146	java/lang/IllegalArgumentException
    //   33	40	154	java/lang/reflect/InvocationTargetException
    //   48	61	154	java/lang/reflect/InvocationTargetException
    //   65	77	154	java/lang/reflect/InvocationTargetException
    //   33	40	162	java/lang/Throwable
    //   48	61	162	java/lang/Throwable
    //   65	77	162	java/lang/Throwable
    //   101	120	170	java/lang/NoSuchMethodException
    //   101	120	185	java/lang/InstantiationException
    //   101	120	193	java/lang/IllegalAccessException
    //   101	120	201	java/lang/IllegalArgumentException
    //   101	120	209	java/lang/reflect/InvocationTargetException
    //   101	120	217	java/lang/Throwable
  }
}

/* Location:           C:\crazyd\work\ustone\odm2016031702\baidu\android\nut-dex2jar.jar
 * Qualified Name:     com.loc.k
 * JD-Core Version:    0.6.2
 */