package com.loc;

import java.util.List;

final class p
{
  static v a(f paramf, String paramString)
  {
    paramf = paramf.a(u.a(paramString), new u());
    if (paramf.size() > 0)
      return (v)paramf.get(0);
    return null;
  }

  // ERROR //
  static void a(f arg0, v paramv, String paramString)
  {
    // Byte code:
    //   0: new 8	com/loc/u
    //   3: dup
    //   4: invokespecial 15	com/loc/u:<init>	()V
    //   7: astore_3
    //   8: aload_3
    //   9: aload_1
    //   10: putfield 39	com/loc/u:a	Lcom/loc/v;
    //   13: aload_0
    //   14: getfield 43	com/loc/f:b	Lcom/loc/es;
    //   17: astore_1
    //   18: aload_1
    //   19: monitorenter
    //   20: aload_0
    //   21: aload_2
    //   22: aload_3
    //   23: invokevirtual 20	com/loc/f:a	(Ljava/lang/String;Lcom/loc/g;)Ljava/util/List;
    //   26: invokeinterface 26 1 0
    //   31: ifne +169 -> 200
    //   34: aload_0
    //   35: getfield 43	com/loc/f:b	Lcom/loc/es;
    //   38: astore_2
    //   39: aload_2
    //   40: monitorenter
    //   41: aload_0
    //   42: getfield 46	com/loc/f:a	Landroid/database/sqlite/SQLiteDatabase;
    //   45: ifnull +13 -> 58
    //   48: aload_0
    //   49: getfield 46	com/loc/f:a	Landroid/database/sqlite/SQLiteDatabase;
    //   52: invokevirtual 52	android/database/sqlite/SQLiteDatabase:isReadOnly	()Z
    //   55: ifeq +11 -> 66
    //   58: aload_0
    //   59: aload_0
    //   60: invokevirtual 55	com/loc/f:a	()Landroid/database/sqlite/SQLiteDatabase;
    //   63: putfield 46	com/loc/f:a	Landroid/database/sqlite/SQLiteDatabase;
    //   66: aload_0
    //   67: getfield 46	com/loc/f:a	Landroid/database/sqlite/SQLiteDatabase;
    //   70: ifnonnull +8 -> 78
    //   73: aload_2
    //   74: monitorexit
    //   75: aload_1
    //   76: monitorexit
    //   77: return
    //   78: aload_0
    //   79: getfield 46	com/loc/f:a	Landroid/database/sqlite/SQLiteDatabase;
    //   82: astore 4
    //   84: aload 4
    //   86: ifnull +31 -> 117
    //   89: aload_3
    //   90: invokeinterface 60 1 0
    //   95: astore 5
    //   97: aload 5
    //   99: ifnull +18 -> 117
    //   102: aload 4
    //   104: aload_3
    //   105: invokeinterface 63 1 0
    //   110: aconst_null
    //   111: aload 5
    //   113: invokevirtual 67	android/database/sqlite/SQLiteDatabase:insert	(Ljava/lang/String;Ljava/lang/String;Landroid/content/ContentValues;)J
    //   116: pop2
    //   117: aload_0
    //   118: getfield 46	com/loc/f:a	Landroid/database/sqlite/SQLiteDatabase;
    //   121: ifnull +15 -> 136
    //   124: aload_0
    //   125: getfield 46	com/loc/f:a	Landroid/database/sqlite/SQLiteDatabase;
    //   128: invokevirtual 70	android/database/sqlite/SQLiteDatabase:close	()V
    //   131: aload_0
    //   132: aconst_null
    //   133: putfield 46	com/loc/f:a	Landroid/database/sqlite/SQLiteDatabase;
    //   136: aload_2
    //   137: monitorexit
    //   138: goto -63 -> 75
    //   141: astore_0
    //   142: aload_2
    //   143: monitorexit
    //   144: aload_0
    //   145: athrow
    //   146: astore_0
    //   147: aload_1
    //   148: monitorexit
    //   149: aload_0
    //   150: athrow
    //   151: astore_3
    //   152: aload_3
    //   153: invokevirtual 73	java/lang/Throwable:printStackTrace	()V
    //   156: aload_0
    //   157: getfield 46	com/loc/f:a	Landroid/database/sqlite/SQLiteDatabase;
    //   160: ifnull -24 -> 136
    //   163: aload_0
    //   164: getfield 46	com/loc/f:a	Landroid/database/sqlite/SQLiteDatabase;
    //   167: invokevirtual 70	android/database/sqlite/SQLiteDatabase:close	()V
    //   170: aload_0
    //   171: aconst_null
    //   172: putfield 46	com/loc/f:a	Landroid/database/sqlite/SQLiteDatabase;
    //   175: goto -39 -> 136
    //   178: astore_3
    //   179: aload_0
    //   180: getfield 46	com/loc/f:a	Landroid/database/sqlite/SQLiteDatabase;
    //   183: ifnull +15 -> 198
    //   186: aload_0
    //   187: getfield 46	com/loc/f:a	Landroid/database/sqlite/SQLiteDatabase;
    //   190: invokevirtual 70	android/database/sqlite/SQLiteDatabase:close	()V
    //   193: aload_0
    //   194: aconst_null
    //   195: putfield 46	com/loc/f:a	Landroid/database/sqlite/SQLiteDatabase;
    //   198: aload_3
    //   199: athrow
    //   200: aload_0
    //   201: getfield 43	com/loc/f:b	Lcom/loc/es;
    //   204: astore 4
    //   206: aload 4
    //   208: monitorenter
    //   209: aload_2
    //   210: ifnonnull +15 -> 225
    //   213: aload 4
    //   215: monitorexit
    //   216: goto -141 -> 75
    //   219: astore_0
    //   220: aload 4
    //   222: monitorexit
    //   223: aload_0
    //   224: athrow
    //   225: aload_3
    //   226: invokeinterface 60 1 0
    //   231: astore 5
    //   233: aload 5
    //   235: ifnonnull +9 -> 244
    //   238: aload 4
    //   240: monitorexit
    //   241: goto -166 -> 75
    //   244: aload_0
    //   245: getfield 46	com/loc/f:a	Landroid/database/sqlite/SQLiteDatabase;
    //   248: ifnull +13 -> 261
    //   251: aload_0
    //   252: getfield 46	com/loc/f:a	Landroid/database/sqlite/SQLiteDatabase;
    //   255: invokevirtual 52	android/database/sqlite/SQLiteDatabase:isReadOnly	()Z
    //   258: ifeq +11 -> 269
    //   261: aload_0
    //   262: aload_0
    //   263: invokevirtual 55	com/loc/f:a	()Landroid/database/sqlite/SQLiteDatabase;
    //   266: putfield 46	com/loc/f:a	Landroid/database/sqlite/SQLiteDatabase;
    //   269: aload_0
    //   270: getfield 46	com/loc/f:a	Landroid/database/sqlite/SQLiteDatabase;
    //   273: ifnonnull +9 -> 282
    //   276: aload 4
    //   278: monitorexit
    //   279: goto -204 -> 75
    //   282: aload_0
    //   283: getfield 46	com/loc/f:a	Landroid/database/sqlite/SQLiteDatabase;
    //   286: aload_3
    //   287: invokeinterface 63 1 0
    //   292: aload 5
    //   294: aload_2
    //   295: aconst_null
    //   296: invokevirtual 77	android/database/sqlite/SQLiteDatabase:update	(Ljava/lang/String;Landroid/content/ContentValues;Ljava/lang/String;[Ljava/lang/String;)I
    //   299: pop
    //   300: aload_0
    //   301: getfield 46	com/loc/f:a	Landroid/database/sqlite/SQLiteDatabase;
    //   304: ifnull +15 -> 319
    //   307: aload_0
    //   308: getfield 46	com/loc/f:a	Landroid/database/sqlite/SQLiteDatabase;
    //   311: invokevirtual 70	android/database/sqlite/SQLiteDatabase:close	()V
    //   314: aload_0
    //   315: aconst_null
    //   316: putfield 46	com/loc/f:a	Landroid/database/sqlite/SQLiteDatabase;
    //   319: aload 4
    //   321: monitorexit
    //   322: goto -247 -> 75
    //   325: astore_2
    //   326: aload_2
    //   327: invokevirtual 73	java/lang/Throwable:printStackTrace	()V
    //   330: aload_0
    //   331: getfield 46	com/loc/f:a	Landroid/database/sqlite/SQLiteDatabase;
    //   334: ifnull -15 -> 319
    //   337: aload_0
    //   338: getfield 46	com/loc/f:a	Landroid/database/sqlite/SQLiteDatabase;
    //   341: invokevirtual 70	android/database/sqlite/SQLiteDatabase:close	()V
    //   344: aload_0
    //   345: aconst_null
    //   346: putfield 46	com/loc/f:a	Landroid/database/sqlite/SQLiteDatabase;
    //   349: goto -30 -> 319
    //   352: astore_2
    //   353: aload_0
    //   354: getfield 46	com/loc/f:a	Landroid/database/sqlite/SQLiteDatabase;
    //   357: ifnull +15 -> 372
    //   360: aload_0
    //   361: getfield 46	com/loc/f:a	Landroid/database/sqlite/SQLiteDatabase;
    //   364: invokevirtual 70	android/database/sqlite/SQLiteDatabase:close	()V
    //   367: aload_0
    //   368: aconst_null
    //   369: putfield 46	com/loc/f:a	Landroid/database/sqlite/SQLiteDatabase;
    //   372: aload_2
    //   373: athrow
    //
    // Exception table:
    //   from	to	target	type
    //   41	58	141	finally
    //   58	66	141	finally
    //   66	75	141	finally
    //   117	136	141	finally
    //   136	138	141	finally
    //   142	144	141	finally
    //   156	175	141	finally
    //   179	198	141	finally
    //   198	200	141	finally
    //   20	41	146	finally
    //   75	77	146	finally
    //   144	146	146	finally
    //   147	149	146	finally
    //   200	209	146	finally
    //   223	225	146	finally
    //   78	84	151	java/lang/Throwable
    //   89	97	151	java/lang/Throwable
    //   102	117	151	java/lang/Throwable
    //   78	84	178	finally
    //   89	97	178	finally
    //   102	117	178	finally
    //   152	156	178	finally
    //   213	216	219	finally
    //   220	223	219	finally
    //   225	233	219	finally
    //   238	241	219	finally
    //   244	261	219	finally
    //   261	269	219	finally
    //   269	279	219	finally
    //   300	319	219	finally
    //   319	322	219	finally
    //   330	349	219	finally
    //   353	372	219	finally
    //   372	374	219	finally
    //   282	300	325	java/lang/Throwable
    //   282	300	352	finally
    //   326	330	352	finally
  }
}

/* Location:           C:\crazyd\work\ustone\odm2016031702\baidu\android\nut-dex2jar.jar
 * Qualified Name:     com.loc.p
 * JD-Core Version:    0.6.2
 */