package com.crashlytics.android.core;

import android.app.ActivityManager.RunningAppProcessInfo;
import android.content.Context;
import android.content.res.Configuration;
import android.content.res.Resources;
import android.os.Environment;
import io.fabric.sdk.android.o;
import io.fabric.sdk.android.r;
import io.fabric.sdk.android.services.b.l;
import io.fabric.sdk.android.services.b.x;
import io.fabric.sdk.android.services.d.a;
import java.io.File;
import java.io.FilenameFilter;
import java.io.IOException;
import java.io.InputStream;
import java.io.OutputStream;
import java.util.Arrays;
import java.util.Collections;
import java.util.Comparator;
import java.util.Date;
import java.util.Iterator;
import java.util.LinkedList;
import java.util.List;
import java.util.Locale;
import java.util.Map;
import java.util.Map.Entry;
import java.util.Set;
import java.util.TreeMap;
import java.util.concurrent.atomic.AtomicBoolean;
import java.util.concurrent.atomic.AtomicInteger;
import java.util.regex.Pattern;

public final class ab
  implements Thread.UncaughtExceptionHandler
{
  static final FilenameFilter a = new ac();
  static final Comparator<File> b = new ah();
  static final Comparator<File> c = new ai();
  static final FilenameFilter d = new aj();
  private static final Pattern h = Pattern.compile("([\\d|A-Z|a-z]{12}\\-[\\d|A-Z|a-z]{4}\\-[\\d|A-Z|a-z]{4}\\-[\\d|A-Z|a-z]{12}).+");
  private static final Map<String, String> i = Collections.singletonMap("X-CRASHLYTICS-SEND-FLAGS", "1");
  private static final String[] j = { "SessionUser", "SessionApp", "SessionOS", "SessionDevice" };
  final AtomicBoolean e;
  public final v f;
  final h g;
  private final AtomicInteger k = new AtomicInteger(0);
  private final Thread.UncaughtExceptionHandler l;
  private final a m;
  private final x n;
  private final az o;
  private final at p;
  private final String q;

  ab(Thread.UncaughtExceptionHandler paramUncaughtExceptionHandler, v paramv, x paramx, ca paramca, a parama, h paramh)
  {
    this.l = paramUncaughtExceptionHandler;
    this.f = paramv;
    this.n = paramx;
    this.g = paramh;
    this.q = paramca.a();
    this.m = parama;
    this.e = new AtomicBoolean(false);
    paramUncaughtExceptionHandler = paramh.q;
    this.o = new az(paramUncaughtExceptionHandler, parama);
    this.p = new at(paramUncaughtExceptionHandler);
  }

  static String a(File paramFile)
  {
    return paramFile.getName().substring(0, 35);
  }

  // ERROR //
  private static void a(f paramf, File paramFile)
    throws IOException
  {
    // Byte code:
    //   0: aload_1
    //   1: invokevirtual 288	java/io/File:exists	()Z
    //   4: ifne +35 -> 39
    //   7: invokestatic 178	io/fabric/sdk/android/f:b	()Lio/fabric/sdk/android/r;
    //   10: ldc 180
    //   12: new 211	java/lang/StringBuilder
    //   15: dup
    //   16: ldc_w 290
    //   19: invokespecial 292	java/lang/StringBuilder:<init>	(Ljava/lang/String;)V
    //   22: aload_1
    //   23: invokevirtual 157	java/io/File:getName	()Ljava/lang/String;
    //   26: invokevirtual 216	java/lang/StringBuilder:append	(Ljava/lang/String;)Ljava/lang/StringBuilder;
    //   29: invokevirtual 221	java/lang/StringBuilder:toString	()Ljava/lang/String;
    //   32: aconst_null
    //   33: invokeinterface 187 4 0
    //   38: return
    //   39: new 294	java/io/FileInputStream
    //   42: dup
    //   43: aload_1
    //   44: invokespecial 295	java/io/FileInputStream:<init>	(Ljava/io/File;)V
    //   47: astore_2
    //   48: aload_2
    //   49: aload_0
    //   50: aload_1
    //   51: invokevirtual 299	java/io/File:length	()J
    //   54: l2i
    //   55: invokestatic 302	com/crashlytics/android/core/ab:a	(Ljava/io/InputStream;Lcom/crashlytics/android/core/f;I)V
    //   58: aload_2
    //   59: ldc_w 304
    //   62: invokestatic 199	io/fabric/sdk/android/services/b/l:a	(Ljava/io/Closeable;Ljava/lang/String;)V
    //   65: return
    //   66: astore_0
    //   67: aconst_null
    //   68: astore_1
    //   69: aload_1
    //   70: ldc_w 304
    //   73: invokestatic 199	io/fabric/sdk/android/services/b/l:a	(Ljava/io/Closeable;Ljava/lang/String;)V
    //   76: aload_0
    //   77: athrow
    //   78: astore_0
    //   79: aload_2
    //   80: astore_1
    //   81: goto -12 -> 69
    //
    // Exception table:
    //   from	to	target	type
    //   39	48	66	finally
    //   48	58	78	finally
  }

  private void a(f paramf, String paramString)
    throws IOException
  {
    String[] arrayOfString = j;
    int i2 = arrayOfString.length;
    int i1 = 0;
    if (i1 < i2)
    {
      String str = arrayOfString[i1];
      File[] arrayOfFile = a(new an(paramString + str));
      if (arrayOfFile.length == 0)
        io.fabric.sdk.android.f.b().c("CrashlyticsCore", "Can't find " + str + " data for session ID " + paramString, null);
      while (true)
      {
        i1 += 1;
        break;
        io.fabric.sdk.android.f.b().a("CrashlyticsCore", "Collecting " + str + " data for session ID " + paramString);
        a(paramf, arrayOfFile[0]);
      }
    }
  }

  private void a(f paramf, Date paramDate, Thread paramThread, Throwable paramThrowable, String paramString)
    throws Exception
  {
    Context localContext = this.g.q;
    long l1 = paramDate.getTime() / 1000L;
    float f1 = l.c(localContext);
    int i2 = l.a(localContext, this.p.e);
    boolean bool = l.d(localContext);
    int i3 = localContext.getResources().getConfiguration().orientation;
    long l2 = l.b();
    long l3 = l.b(localContext);
    long l4 = l.b(Environment.getDataDirectory().getPath());
    ActivityManager.RunningAppProcessInfo localRunningAppProcessInfo = l.a(localContext.getPackageName(), localContext);
    LinkedList localLinkedList = new LinkedList();
    StackTraceElement[] arrayOfStackTraceElement = paramThrowable.getStackTrace();
    String str1 = this.g.h;
    String str2 = this.n.c;
    paramDate = Thread.getAllStackTraces();
    Thread[] arrayOfThread = new Thread[paramDate.size()];
    paramDate = paramDate.entrySet().iterator();
    int i1 = 0;
    while (paramDate.hasNext())
    {
      Map.Entry localEntry = (Map.Entry)paramDate.next();
      arrayOfThread[i1] = ((Thread)localEntry.getKey());
      localLinkedList.add(localEntry.getValue());
      i1 += 1;
    }
    if (!l.a(localContext, "com.crashlytics.CollectCustomKeys", true))
      paramDate = new TreeMap();
    while (true)
    {
      by.a(paramf, l1, paramString, paramThrowable, paramThread, arrayOfStackTraceElement, arrayOfThread, localLinkedList, paramDate, this.o, localRunningAppProcessInfo, i3, str2, str1, f1, i2, bool, l2 - l3, l4);
      return;
      paramDate = Collections.unmodifiableMap(this.g.b);
      if ((paramDate != null) && (paramDate.size() > 1))
        paramDate = new TreeMap(paramDate);
    }
  }

  private static void a(f paramf, File[] paramArrayOfFile, String paramString)
  {
    Arrays.sort(paramArrayOfFile, l.a);
    int i2 = paramArrayOfFile.length;
    int i1 = 0;
    while (true)
      if (i1 < i2)
      {
        File localFile = paramArrayOfFile[i1];
        try
        {
          io.fabric.sdk.android.f.b().a("CrashlyticsCore", String.format(Locale.US, "Found Non Fatal for session ID %s in %s ", new Object[] { paramString, localFile.getName() }));
          a(paramf, localFile);
          i1 += 1;
        }
        catch (Exception localException)
        {
          while (true)
            io.fabric.sdk.android.f.b().c("CrashlyticsCore", "Error writting non-fatal to session.", localException);
        }
      }
  }

  private static void a(InputStream paramInputStream, f paramf, int paramInt)
    throws IOException
  {
    byte[] arrayOfByte = new byte[paramInt];
    paramInt = 0;
    while (paramInt < arrayOfByte.length)
    {
      i1 = paramInputStream.read(arrayOfByte, paramInt, arrayOfByte.length - paramInt);
      if (i1 < 0)
        break;
      paramInt += i1;
    }
    int i1 = arrayOfByte.length;
    if (paramf.b - paramf.c >= i1)
    {
      System.arraycopy(arrayOfByte, 0, paramf.a, paramf.c, i1);
      paramf.c = (i1 + paramf.c);
      return;
    }
    int i2 = paramf.b - paramf.c;
    System.arraycopy(arrayOfByte, 0, paramf.a, paramf.c, i2);
    paramInt = i2 + 0;
    i1 -= i2;
    paramf.c = paramf.b;
    paramf.b();
    if (i1 <= paramf.b)
    {
      System.arraycopy(arrayOfByte, paramInt, paramf.a, 0, i1);
      paramf.c = i1;
      return;
    }
    paramf.d.write(arrayOfByte, paramInt, i1);
  }

  private void a(String paramString)
  {
    paramString = a(new ap(paramString));
    int i2 = paramString.length;
    int i1 = 0;
    while (i1 < i2)
    {
      paramString[i1].delete();
      i1 += 1;
    }
  }

  // ERROR //
  private void a(boolean paramBoolean)
    throws Exception
  {
    // Byte code:
    //   0: iconst_1
    //   1: istore 4
    //   3: aconst_null
    //   4: astore 7
    //   6: aconst_null
    //   7: astore 10
    //   9: iload_1
    //   10: ifeq +62 -> 72
    //   13: iconst_1
    //   14: istore_2
    //   15: new 525	java/util/HashSet
    //   18: dup
    //   19: invokespecial 526	java/util/HashSet:<init>	()V
    //   22: astore 6
    //   24: aload_0
    //   25: invokespecial 171	com/crashlytics/android/core/ab:d	()[Ljava/io/File;
    //   28: astore 8
    //   30: iload_2
    //   31: bipush 8
    //   33: iadd
    //   34: aload 8
    //   36: arraylength
    //   37: invokestatic 532	java/lang/Math:min	(II)I
    //   40: istore 5
    //   42: iconst_0
    //   43: istore_3
    //   44: iload_3
    //   45: iload 5
    //   47: if_icmpge +30 -> 77
    //   50: aload 6
    //   52: aload 8
    //   54: iload_3
    //   55: aaload
    //   56: invokestatic 173	com/crashlytics/android/core/ab:a	(Ljava/io/File;)Ljava/lang/String;
    //   59: invokeinterface 533 2 0
    //   64: pop
    //   65: iload_3
    //   66: iconst_1
    //   67: iadd
    //   68: istore_3
    //   69: goto -25 -> 44
    //   72: iconst_0
    //   73: istore_2
    //   74: goto -59 -> 15
    //   77: aload_0
    //   78: getfield 144	com/crashlytics/android/core/ab:o	Lcom/crashlytics/android/core/az;
    //   81: aload 6
    //   83: invokevirtual 536	com/crashlytics/android/core/az:a	(Ljava/util/Set;)V
    //   86: aload_0
    //   87: new 538	com/crashlytics/android/core/am
    //   90: dup
    //   91: iconst_0
    //   92: invokespecial 541	com/crashlytics/android/core/am:<init>	(B)V
    //   95: invokevirtual 311	com/crashlytics/android/core/ab:a	(Ljava/io/FilenameFilter;)[Ljava/io/File;
    //   98: astore 8
    //   100: aload 8
    //   102: arraylength
    //   103: istore 5
    //   105: iconst_0
    //   106: istore_3
    //   107: iload_3
    //   108: iload 5
    //   110: if_icmpge +89 -> 199
    //   113: aload 8
    //   115: iload_3
    //   116: aaload
    //   117: astore 9
    //   119: aload 9
    //   121: invokevirtual 157	java/io/File:getName	()Ljava/lang/String;
    //   124: astore 11
    //   126: getstatic 74	com/crashlytics/android/core/ab:h	Ljava/util/regex/Pattern;
    //   129: aload 11
    //   131: invokevirtual 545	java/util/regex/Pattern:matcher	(Ljava/lang/CharSequence;)Ljava/util/regex/Matcher;
    //   134: astore 12
    //   136: aload 12
    //   138: invokevirtual 550	java/util/regex/Matcher:matches	()Z
    //   141: pop
    //   142: aload 6
    //   144: aload 12
    //   146: iconst_1
    //   147: invokevirtual 554	java/util/regex/Matcher:group	(I)Ljava/lang/String;
    //   150: invokeinterface 557 2 0
    //   155: ifne +37 -> 192
    //   158: invokestatic 178	io/fabric/sdk/android/f:b	()Lio/fabric/sdk/android/r;
    //   161: ldc 180
    //   163: new 211	java/lang/StringBuilder
    //   166: dup
    //   167: ldc_w 559
    //   170: invokespecial 292	java/lang/StringBuilder:<init>	(Ljava/lang/String;)V
    //   173: aload 11
    //   175: invokevirtual 216	java/lang/StringBuilder:append	(Ljava/lang/String;)Ljava/lang/StringBuilder;
    //   178: invokevirtual 221	java/lang/StringBuilder:toString	()Ljava/lang/String;
    //   181: invokeinterface 320 3 0
    //   186: aload 9
    //   188: invokevirtual 523	java/io/File:delete	()Z
    //   191: pop
    //   192: iload_3
    //   193: iconst_1
    //   194: iadd
    //   195: istore_3
    //   196: goto -89 -> 107
    //   199: aload_0
    //   200: invokespecial 171	com/crashlytics/android/core/ab:d	()[Ljava/io/File;
    //   203: astore 11
    //   205: aload 11
    //   207: arraylength
    //   208: iload_2
    //   209: if_icmpgt +17 -> 226
    //   212: invokestatic 178	io/fabric/sdk/android/f:b	()Lio/fabric/sdk/android/r;
    //   215: ldc 180
    //   217: ldc_w 561
    //   220: invokeinterface 320 3 0
    //   225: return
    //   226: aload 11
    //   228: iload_2
    //   229: aaload
    //   230: invokestatic 173	com/crashlytics/android/core/ab:a	(Ljava/io/File;)Ljava/lang/String;
    //   233: astore 6
    //   235: new 206	com/crashlytics/android/core/d
    //   238: dup
    //   239: aload_0
    //   240: invokespecial 209	com/crashlytics/android/core/ab:f	()Ljava/io/File;
    //   243: new 211	java/lang/StringBuilder
    //   246: dup
    //   247: invokespecial 212	java/lang/StringBuilder:<init>	()V
    //   250: aload 6
    //   252: invokevirtual 216	java/lang/StringBuilder:append	(Ljava/lang/String;)Ljava/lang/StringBuilder;
    //   255: ldc 90
    //   257: invokevirtual 216	java/lang/StringBuilder:append	(Ljava/lang/String;)Ljava/lang/StringBuilder;
    //   260: invokevirtual 221	java/lang/StringBuilder:toString	()Ljava/lang/String;
    //   263: invokespecial 224	com/crashlytics/android/core/d:<init>	(Ljava/io/File;Ljava/lang/String;)V
    //   266: astore 8
    //   268: aload 8
    //   270: invokestatic 229	com/crashlytics/android/core/f:a	(Ljava/io/OutputStream;)Lcom/crashlytics/android/core/f;
    //   273: astore 7
    //   275: aload_0
    //   276: getfield 132	com/crashlytics/android/core/ab:e	Ljava/util/concurrent/atomic/AtomicBoolean;
    //   279: invokevirtual 564	java/util/concurrent/atomic/AtomicBoolean:get	()Z
    //   282: ifeq +177 -> 459
    //   285: aload_0
    //   286: getfield 116	com/crashlytics/android/core/ab:g	Lcom/crashlytics/android/core/h;
    //   289: astore 6
    //   291: aload 6
    //   293: getfield 567	io/fabric/sdk/android/o:s	Lio/fabric/sdk/android/services/b/x;
    //   296: getfield 569	io/fabric/sdk/android/services/b/x:b	Z
    //   299: ifeq +148 -> 447
    //   302: aload 6
    //   304: getfield 571	com/crashlytics/android/core/h:e	Ljava/lang/String;
    //   307: astore 6
    //   309: aload_0
    //   310: getfield 116	com/crashlytics/android/core/ab:g	Lcom/crashlytics/android/core/h;
    //   313: astore 9
    //   315: aload 9
    //   317: getfield 567	io/fabric/sdk/android/o:s	Lio/fabric/sdk/android/services/b/x;
    //   320: getfield 569	io/fabric/sdk/android/services/b/x:b	Z
    //   323: ifeq +130 -> 453
    //   326: aload 9
    //   328: getfield 573	com/crashlytics/android/core/h:g	Ljava/lang/String;
    //   331: astore 9
    //   333: aload_0
    //   334: getfield 116	com/crashlytics/android/core/ab:g	Lcom/crashlytics/android/core/h;
    //   337: astore 12
    //   339: aload 12
    //   341: getfield 567	io/fabric/sdk/android/o:s	Lio/fabric/sdk/android/services/b/x;
    //   344: getfield 569	io/fabric/sdk/android/services/b/x:b	Z
    //   347: ifeq +10 -> 357
    //   350: aload 12
    //   352: getfield 575	com/crashlytics/android/core/h:f	Ljava/lang/String;
    //   355: astore 10
    //   357: new 577	com/crashlytics/android/core/cb
    //   360: dup
    //   361: aload 6
    //   363: aload 9
    //   365: aload 10
    //   367: invokespecial 580	com/crashlytics/android/core/cb:<init>	(Ljava/lang/String;Ljava/lang/String;Ljava/lang/String;)V
    //   370: astore 6
    //   372: aload 6
    //   374: getfield 582	com/crashlytics/android/core/cb:b	Ljava/lang/String;
    //   377: ifnonnull +260 -> 637
    //   380: aload 6
    //   382: getfield 583	com/crashlytics/android/core/cb:c	Ljava/lang/String;
    //   385: ifnonnull +252 -> 637
    //   388: aload 6
    //   390: getfield 585	com/crashlytics/android/core/cb:d	Ljava/lang/String;
    //   393: astore 9
    //   395: aload 9
    //   397: ifnonnull +240 -> 637
    //   400: iload 4
    //   402: istore_3
    //   403: iload_3
    //   404: ifeq +76 -> 480
    //   407: aload 7
    //   409: ldc_w 587
    //   412: invokestatic 194	io/fabric/sdk/android/services/b/l:a	(Ljava/io/Flushable;Ljava/lang/String;)V
    //   415: aload 8
    //   417: ldc_w 589
    //   420: invokestatic 199	io/fabric/sdk/android/services/b/l:a	(Ljava/io/Closeable;Ljava/lang/String;)V
    //   423: invokestatic 592	com/crashlytics/android/core/h:i	()Lio/fabric/sdk/android/services/e/p;
    //   426: astore 6
    //   428: aload 6
    //   430: ifnonnull +137 -> 567
    //   433: invokestatic 178	io/fabric/sdk/android/f:b	()Lio/fabric/sdk/android/r;
    //   436: ldc 180
    //   438: ldc_w 594
    //   441: invokeinterface 320 3 0
    //   446: return
    //   447: aconst_null
    //   448: astore 6
    //   450: goto -141 -> 309
    //   453: aconst_null
    //   454: astore 9
    //   456: goto -123 -> 333
    //   459: new 231	com/crashlytics/android/core/bc
    //   462: dup
    //   463: aload_0
    //   464: invokespecial 209	com/crashlytics/android/core/ab:f	()Ljava/io/File;
    //   467: invokespecial 234	com/crashlytics/android/core/bc:<init>	(Ljava/io/File;)V
    //   470: aload 6
    //   472: invokevirtual 597	com/crashlytics/android/core/bc:a	(Ljava/lang/String;)Lcom/crashlytics/android/core/cb;
    //   475: astore 6
    //   477: goto -105 -> 372
    //   480: aload 7
    //   482: aload 6
    //   484: getfield 582	com/crashlytics/android/core/cb:b	Ljava/lang/String;
    //   487: aload 6
    //   489: getfield 583	com/crashlytics/android/core/cb:c	Ljava/lang/String;
    //   492: aload 6
    //   494: getfield 585	com/crashlytics/android/core/cb:d	Ljava/lang/String;
    //   497: invokestatic 600	com/crashlytics/android/core/by:a	(Lcom/crashlytics/android/core/f;Ljava/lang/String;Ljava/lang/String;Ljava/lang/String;)V
    //   500: aload 7
    //   502: ldc_w 587
    //   505: invokestatic 194	io/fabric/sdk/android/services/b/l:a	(Ljava/io/Flushable;Ljava/lang/String;)V
    //   508: aload 8
    //   510: ldc_w 589
    //   513: invokestatic 199	io/fabric/sdk/android/services/b/l:a	(Ljava/io/Closeable;Ljava/lang/String;)V
    //   516: goto -93 -> 423
    //   519: astore 8
    //   521: aconst_null
    //   522: astore 6
    //   524: aload 8
    //   526: aload 7
    //   528: invokestatic 252	com/crashlytics/android/core/ax:a	(Ljava/lang/Throwable;Ljava/io/OutputStream;)V
    //   531: aload 8
    //   533: athrow
    //   534: astore 9
    //   536: aload 7
    //   538: astore 8
    //   540: aload 6
    //   542: astore 7
    //   544: aload 9
    //   546: astore 6
    //   548: aload 7
    //   550: ldc_w 587
    //   553: invokestatic 194	io/fabric/sdk/android/services/b/l:a	(Ljava/io/Flushable;Ljava/lang/String;)V
    //   556: aload 8
    //   558: ldc_w 589
    //   561: invokestatic 199	io/fabric/sdk/android/services/b/l:a	(Ljava/io/Closeable;Ljava/lang/String;)V
    //   564: aload 6
    //   566: athrow
    //   567: aload_0
    //   568: aload 11
    //   570: iload_2
    //   571: aload 6
    //   573: getfield 603	io/fabric/sdk/android/services/e/p:c	I
    //   576: invokespecial 606	com/crashlytics/android/core/ab:a	([Ljava/io/File;II)V
    //   579: return
    //   580: astore 6
    //   582: aconst_null
    //   583: astore 7
    //   585: aconst_null
    //   586: astore 8
    //   588: goto -40 -> 548
    //   591: astore 6
    //   593: aconst_null
    //   594: astore 7
    //   596: goto -48 -> 548
    //   599: astore 6
    //   601: goto -53 -> 548
    //   604: astore 9
    //   606: aconst_null
    //   607: astore 6
    //   609: aload 8
    //   611: astore 7
    //   613: aload 9
    //   615: astore 8
    //   617: goto -93 -> 524
    //   620: astore 9
    //   622: aload 7
    //   624: astore 6
    //   626: aload 8
    //   628: astore 7
    //   630: aload 9
    //   632: astore 8
    //   634: goto -110 -> 524
    //   637: iconst_0
    //   638: istore_3
    //   639: goto -236 -> 403
    //
    // Exception table:
    //   from	to	target	type
    //   235	268	519	java/lang/Exception
    //   524	534	534	finally
    //   235	268	580	finally
    //   268	275	591	finally
    //   275	309	599	finally
    //   309	333	599	finally
    //   333	339	599	finally
    //   339	357	599	finally
    //   357	372	599	finally
    //   372	395	599	finally
    //   459	477	599	finally
    //   480	500	599	finally
    //   268	275	604	java/lang/Exception
    //   275	309	620	java/lang/Exception
    //   309	333	620	java/lang/Exception
    //   333	339	620	java/lang/Exception
    //   339	357	620	java/lang/Exception
    //   357	372	620	java/lang/Exception
    //   372	395	620	java/lang/Exception
    //   459	477	620	java/lang/Exception
    //   480	500	620	java/lang/Exception
  }

  // ERROR //
  private void a(File[] paramArrayOfFile, int paramInt1, int paramInt2)
  {
    // Byte code:
    //   0: invokestatic 178	io/fabric/sdk/android/f:b	()Lio/fabric/sdk/android/r;
    //   3: ldc 180
    //   5: ldc_w 608
    //   8: invokeinterface 320 3 0
    //   13: iload_2
    //   14: aload_1
    //   15: arraylength
    //   16: if_icmpge +872 -> 888
    //   19: aload_1
    //   20: iload_2
    //   21: aaload
    //   22: astore 14
    //   24: aload 14
    //   26: invokestatic 173	com/crashlytics/android/core/ab:a	(Ljava/io/File;)Ljava/lang/String;
    //   29: astore 13
    //   31: invokestatic 178	io/fabric/sdk/android/f:b	()Lio/fabric/sdk/android/r;
    //   34: ldc 180
    //   36: new 211	java/lang/StringBuilder
    //   39: dup
    //   40: ldc_w 610
    //   43: invokespecial 292	java/lang/StringBuilder:<init>	(Ljava/lang/String;)V
    //   46: aload 13
    //   48: invokevirtual 216	java/lang/StringBuilder:append	(Ljava/lang/String;)Ljava/lang/StringBuilder;
    //   51: invokevirtual 221	java/lang/StringBuilder:toString	()Ljava/lang/String;
    //   54: invokeinterface 320 3 0
    //   59: invokestatic 178	io/fabric/sdk/android/f:b	()Lio/fabric/sdk/android/r;
    //   62: ldc 180
    //   64: new 211	java/lang/StringBuilder
    //   67: dup
    //   68: ldc_w 612
    //   71: invokespecial 292	java/lang/StringBuilder:<init>	(Ljava/lang/String;)V
    //   74: aload 13
    //   76: invokevirtual 216	java/lang/StringBuilder:append	(Ljava/lang/String;)Ljava/lang/StringBuilder;
    //   79: invokevirtual 221	java/lang/StringBuilder:toString	()Ljava/lang/String;
    //   82: invokeinterface 320 3 0
    //   87: aload_0
    //   88: new 307	com/crashlytics/android/core/an
    //   91: dup
    //   92: new 211	java/lang/StringBuilder
    //   95: dup
    //   96: invokespecial 212	java/lang/StringBuilder:<init>	()V
    //   99: aload 13
    //   101: invokevirtual 216	java/lang/StringBuilder:append	(Ljava/lang/String;)Ljava/lang/StringBuilder;
    //   104: ldc 218
    //   106: invokevirtual 216	java/lang/StringBuilder:append	(Ljava/lang/String;)Ljava/lang/StringBuilder;
    //   109: invokevirtual 221	java/lang/StringBuilder:toString	()Ljava/lang/String;
    //   112: invokespecial 308	com/crashlytics/android/core/an:<init>	(Ljava/lang/String;)V
    //   115: invokevirtual 311	com/crashlytics/android/core/ab:a	(Ljava/io/FilenameFilter;)[Ljava/io/File;
    //   118: astore 6
    //   120: aload 6
    //   122: ifnull +590 -> 712
    //   125: aload 6
    //   127: arraylength
    //   128: ifle +584 -> 712
    //   131: iconst_1
    //   132: istore 4
    //   134: invokestatic 178	io/fabric/sdk/android/f:b	()Lio/fabric/sdk/android/r;
    //   137: ldc 180
    //   139: getstatic 479	java/util/Locale:US	Ljava/util/Locale;
    //   142: ldc_w 614
    //   145: iconst_2
    //   146: anewarray 4	java/lang/Object
    //   149: dup
    //   150: iconst_0
    //   151: aload 13
    //   153: aastore
    //   154: dup
    //   155: iconst_1
    //   156: iload 4
    //   158: invokestatic 620	java/lang/Boolean:valueOf	(Z)Ljava/lang/Boolean;
    //   161: aastore
    //   162: invokestatic 485	java/lang/String:format	(Ljava/util/Locale;Ljava/lang/String;[Ljava/lang/Object;)Ljava/lang/String;
    //   165: invokeinterface 320 3 0
    //   170: aload_0
    //   171: new 307	com/crashlytics/android/core/an
    //   174: dup
    //   175: new 211	java/lang/StringBuilder
    //   178: dup
    //   179: invokespecial 212	java/lang/StringBuilder:<init>	()V
    //   182: aload 13
    //   184: invokevirtual 216	java/lang/StringBuilder:append	(Ljava/lang/String;)Ljava/lang/StringBuilder;
    //   187: ldc_w 622
    //   190: invokevirtual 216	java/lang/StringBuilder:append	(Ljava/lang/String;)Ljava/lang/StringBuilder;
    //   193: invokevirtual 221	java/lang/StringBuilder:toString	()Ljava/lang/String;
    //   196: invokespecial 308	com/crashlytics/android/core/an:<init>	(Ljava/lang/String;)V
    //   199: invokevirtual 311	com/crashlytics/android/core/ab:a	(Ljava/io/FilenameFilter;)[Ljava/io/File;
    //   202: astore 9
    //   204: aload 9
    //   206: ifnull +512 -> 718
    //   209: aload 9
    //   211: arraylength
    //   212: ifle +506 -> 718
    //   215: iconst_1
    //   216: istore 5
    //   218: invokestatic 178	io/fabric/sdk/android/f:b	()Lio/fabric/sdk/android/r;
    //   221: ldc 180
    //   223: getstatic 479	java/util/Locale:US	Ljava/util/Locale;
    //   226: ldc_w 624
    //   229: iconst_2
    //   230: anewarray 4	java/lang/Object
    //   233: dup
    //   234: iconst_0
    //   235: aload 13
    //   237: aastore
    //   238: dup
    //   239: iconst_1
    //   240: iload 5
    //   242: invokestatic 620	java/lang/Boolean:valueOf	(Z)Ljava/lang/Boolean;
    //   245: aastore
    //   246: invokestatic 485	java/lang/String:format	(Ljava/util/Locale;Ljava/lang/String;[Ljava/lang/Object;)Ljava/lang/String;
    //   249: invokeinterface 320 3 0
    //   254: iload 4
    //   256: ifne +8 -> 264
    //   259: iload 5
    //   261: ifeq +596 -> 857
    //   264: aload 9
    //   266: arraylength
    //   267: iload_3
    //   268: if_icmple +634 -> 902
    //   271: invokestatic 178	io/fabric/sdk/android/f:b	()Lio/fabric/sdk/android/r;
    //   274: ldc 180
    //   276: getstatic 479	java/util/Locale:US	Ljava/util/Locale;
    //   279: ldc_w 626
    //   282: iconst_1
    //   283: anewarray 4	java/lang/Object
    //   286: dup
    //   287: iconst_0
    //   288: iload_3
    //   289: invokestatic 631	java/lang/Integer:valueOf	(I)Ljava/lang/Integer;
    //   292: aastore
    //   293: invokestatic 485	java/lang/String:format	(Ljava/util/Locale;Ljava/lang/String;[Ljava/lang/Object;)Ljava/lang/String;
    //   296: invokeinterface 320 3 0
    //   301: aload_0
    //   302: invokespecial 209	com/crashlytics/android/core/ab:f	()Ljava/io/File;
    //   305: new 307	com/crashlytics/android/core/an
    //   308: dup
    //   309: new 211	java/lang/StringBuilder
    //   312: dup
    //   313: invokespecial 212	java/lang/StringBuilder:<init>	()V
    //   316: aload 13
    //   318: invokevirtual 216	java/lang/StringBuilder:append	(Ljava/lang/String;)Ljava/lang/StringBuilder;
    //   321: ldc_w 622
    //   324: invokevirtual 216	java/lang/StringBuilder:append	(Ljava/lang/String;)Ljava/lang/StringBuilder;
    //   327: invokevirtual 221	java/lang/StringBuilder:toString	()Ljava/lang/String;
    //   330: invokespecial 308	com/crashlytics/android/core/an:<init>	(Ljava/lang/String;)V
    //   333: iload_3
    //   334: getstatic 59	com/crashlytics/android/core/ab:c	Ljava/util/Comparator;
    //   337: invokestatic 273	com/crashlytics/android/core/cc:a	(Ljava/io/File;Ljava/io/FilenameFilter;ILjava/util/Comparator;)V
    //   340: aload_0
    //   341: new 307	com/crashlytics/android/core/an
    //   344: dup
    //   345: new 211	java/lang/StringBuilder
    //   348: dup
    //   349: invokespecial 212	java/lang/StringBuilder:<init>	()V
    //   352: aload 13
    //   354: invokevirtual 216	java/lang/StringBuilder:append	(Ljava/lang/String;)Ljava/lang/StringBuilder;
    //   357: ldc_w 622
    //   360: invokevirtual 216	java/lang/StringBuilder:append	(Ljava/lang/String;)Ljava/lang/StringBuilder;
    //   363: invokevirtual 221	java/lang/StringBuilder:toString	()Ljava/lang/String;
    //   366: invokespecial 308	com/crashlytics/android/core/an:<init>	(Ljava/lang/String;)V
    //   369: invokevirtual 311	com/crashlytics/android/core/ab:a	(Ljava/io/FilenameFilter;)[Ljava/io/File;
    //   372: astore 9
    //   374: iload 4
    //   376: ifeq +348 -> 724
    //   379: aload 6
    //   381: iconst_0
    //   382: aaload
    //   383: astore 11
    //   385: aload 11
    //   387: ifnull +343 -> 730
    //   390: iconst_1
    //   391: istore 4
    //   393: aconst_null
    //   394: astore 6
    //   396: aconst_null
    //   397: astore 7
    //   399: aconst_null
    //   400: astore 12
    //   402: aconst_null
    //   403: astore 8
    //   405: new 206	com/crashlytics/android/core/d
    //   408: dup
    //   409: aload_0
    //   410: invokespecial 209	com/crashlytics/android/core/ab:f	()Ljava/io/File;
    //   413: aload 13
    //   415: invokespecial 224	com/crashlytics/android/core/d:<init>	(Ljava/io/File;Ljava/lang/String;)V
    //   418: astore 10
    //   420: aload 7
    //   422: astore 6
    //   424: aload 10
    //   426: astore 7
    //   428: aload 12
    //   430: astore 8
    //   432: aload 10
    //   434: invokestatic 229	com/crashlytics/android/core/f:a	(Ljava/io/OutputStream;)Lcom/crashlytics/android/core/f;
    //   437: astore 12
    //   439: aload 12
    //   441: astore 6
    //   443: aload 10
    //   445: astore 7
    //   447: aload 12
    //   449: astore 8
    //   451: invokestatic 178	io/fabric/sdk/android/f:b	()Lio/fabric/sdk/android/r;
    //   454: ldc 180
    //   456: new 211	java/lang/StringBuilder
    //   459: dup
    //   460: ldc_w 633
    //   463: invokespecial 292	java/lang/StringBuilder:<init>	(Ljava/lang/String;)V
    //   466: aload 13
    //   468: invokevirtual 216	java/lang/StringBuilder:append	(Ljava/lang/String;)Ljava/lang/StringBuilder;
    //   471: invokevirtual 221	java/lang/StringBuilder:toString	()Ljava/lang/String;
    //   474: invokeinterface 320 3 0
    //   479: aload 12
    //   481: astore 6
    //   483: aload 10
    //   485: astore 7
    //   487: aload 12
    //   489: astore 8
    //   491: aload 12
    //   493: aload 14
    //   495: invokestatic 322	com/crashlytics/android/core/ab:a	(Lcom/crashlytics/android/core/f;Ljava/io/File;)V
    //   498: aload 12
    //   500: astore 6
    //   502: aload 10
    //   504: astore 7
    //   506: aload 12
    //   508: astore 8
    //   510: aload 12
    //   512: iconst_4
    //   513: new 324	java/util/Date
    //   516: dup
    //   517: invokespecial 634	java/util/Date:<init>	()V
    //   520: invokevirtual 327	java/util/Date:getTime	()J
    //   523: ldc2_w 328
    //   526: ldiv
    //   527: invokevirtual 637	com/crashlytics/android/core/f:a	(IJ)V
    //   530: aload 12
    //   532: astore 6
    //   534: aload 10
    //   536: astore 7
    //   538: aload 12
    //   540: astore 8
    //   542: aload 12
    //   544: iconst_5
    //   545: iload 4
    //   547: invokevirtual 640	com/crashlytics/android/core/f:a	(IZ)V
    //   550: aload 12
    //   552: astore 6
    //   554: aload 10
    //   556: astore 7
    //   558: aload 12
    //   560: astore 8
    //   562: aload_0
    //   563: aload 12
    //   565: aload 13
    //   567: invokespecial 642	com/crashlytics/android/core/ab:a	(Lcom/crashlytics/android/core/f;Ljava/lang/String;)V
    //   570: aload 12
    //   572: astore 6
    //   574: aload 10
    //   576: astore 7
    //   578: aload 12
    //   580: astore 8
    //   582: aload 12
    //   584: aload 9
    //   586: aload 13
    //   588: invokestatic 644	com/crashlytics/android/core/ab:a	(Lcom/crashlytics/android/core/f;[Ljava/io/File;Ljava/lang/String;)V
    //   591: iload 4
    //   593: ifeq +22 -> 615
    //   596: aload 12
    //   598: astore 6
    //   600: aload 10
    //   602: astore 7
    //   604: aload 12
    //   606: astore 8
    //   608: aload 12
    //   610: aload 11
    //   612: invokestatic 322	com/crashlytics/android/core/ab:a	(Lcom/crashlytics/android/core/f;Ljava/io/File;)V
    //   615: aload 12
    //   617: astore 6
    //   619: aload 10
    //   621: astore 7
    //   623: aload 12
    //   625: astore 8
    //   627: aload 12
    //   629: bipush 11
    //   631: iconst_1
    //   632: invokevirtual 647	com/crashlytics/android/core/f:a	(II)V
    //   635: aload 12
    //   637: astore 6
    //   639: aload 10
    //   641: astore 7
    //   643: aload 12
    //   645: astore 8
    //   647: aload 12
    //   649: bipush 12
    //   651: iconst_3
    //   652: invokevirtual 649	com/crashlytics/android/core/f:b	(II)V
    //   655: aload 12
    //   657: ldc_w 651
    //   660: invokestatic 194	io/fabric/sdk/android/services/b/l:a	(Ljava/io/Flushable;Ljava/lang/String;)V
    //   663: aload 10
    //   665: ldc_w 653
    //   668: invokestatic 199	io/fabric/sdk/android/services/b/l:a	(Ljava/io/Closeable;Ljava/lang/String;)V
    //   671: invokestatic 178	io/fabric/sdk/android/f:b	()Lio/fabric/sdk/android/r;
    //   674: ldc 180
    //   676: new 211	java/lang/StringBuilder
    //   679: dup
    //   680: ldc_w 655
    //   683: invokespecial 292	java/lang/StringBuilder:<init>	(Ljava/lang/String;)V
    //   686: aload 13
    //   688: invokevirtual 216	java/lang/StringBuilder:append	(Ljava/lang/String;)Ljava/lang/StringBuilder;
    //   691: invokevirtual 221	java/lang/StringBuilder:toString	()Ljava/lang/String;
    //   694: invokeinterface 320 3 0
    //   699: aload_0
    //   700: aload 13
    //   702: invokespecial 656	com/crashlytics/android/core/ab:a	(Ljava/lang/String;)V
    //   705: iload_2
    //   706: iconst_1
    //   707: iadd
    //   708: istore_2
    //   709: goto -696 -> 13
    //   712: iconst_0
    //   713: istore 4
    //   715: goto -581 -> 134
    //   718: iconst_0
    //   719: istore 5
    //   721: goto -503 -> 218
    //   724: aconst_null
    //   725: astore 11
    //   727: goto -342 -> 385
    //   730: iconst_0
    //   731: istore 4
    //   733: goto -340 -> 393
    //   736: astore 11
    //   738: aconst_null
    //   739: astore 9
    //   741: aload 8
    //   743: astore 6
    //   745: aload 9
    //   747: astore 7
    //   749: invokestatic 178	io/fabric/sdk/android/f:b	()Lio/fabric/sdk/android/r;
    //   752: ldc 180
    //   754: new 211	java/lang/StringBuilder
    //   757: dup
    //   758: ldc_w 658
    //   761: invokespecial 292	java/lang/StringBuilder:<init>	(Ljava/lang/String;)V
    //   764: aload 13
    //   766: invokevirtual 216	java/lang/StringBuilder:append	(Ljava/lang/String;)Ljava/lang/StringBuilder;
    //   769: invokevirtual 221	java/lang/StringBuilder:toString	()Ljava/lang/String;
    //   772: aload 11
    //   774: invokeinterface 187 4 0
    //   779: aload 8
    //   781: astore 6
    //   783: aload 9
    //   785: astore 7
    //   787: aload 11
    //   789: aload 9
    //   791: invokestatic 252	com/crashlytics/android/core/ax:a	(Ljava/lang/Throwable;Ljava/io/OutputStream;)V
    //   794: aload 8
    //   796: ldc_w 651
    //   799: invokestatic 194	io/fabric/sdk/android/services/b/l:a	(Ljava/io/Flushable;Ljava/lang/String;)V
    //   802: aload 9
    //   804: ifnull -133 -> 671
    //   807: aload 9
    //   809: invokevirtual 660	com/crashlytics/android/core/d:a	()V
    //   812: goto -141 -> 671
    //   815: astore 6
    //   817: invokestatic 178	io/fabric/sdk/android/f:b	()Lio/fabric/sdk/android/r;
    //   820: ldc 180
    //   822: ldc_w 662
    //   825: aload 6
    //   827: invokeinterface 187 4 0
    //   832: goto -161 -> 671
    //   835: astore_1
    //   836: aconst_null
    //   837: astore 7
    //   839: aload 6
    //   841: ldc_w 651
    //   844: invokestatic 194	io/fabric/sdk/android/services/b/l:a	(Ljava/io/Flushable;Ljava/lang/String;)V
    //   847: aload 7
    //   849: ldc_w 653
    //   852: invokestatic 199	io/fabric/sdk/android/services/b/l:a	(Ljava/io/Closeable;Ljava/lang/String;)V
    //   855: aload_1
    //   856: athrow
    //   857: invokestatic 178	io/fabric/sdk/android/f:b	()Lio/fabric/sdk/android/r;
    //   860: ldc 180
    //   862: new 211	java/lang/StringBuilder
    //   865: dup
    //   866: ldc_w 664
    //   869: invokespecial 292	java/lang/StringBuilder:<init>	(Ljava/lang/String;)V
    //   872: aload 13
    //   874: invokevirtual 216	java/lang/StringBuilder:append	(Ljava/lang/String;)Ljava/lang/StringBuilder;
    //   877: invokevirtual 221	java/lang/StringBuilder:toString	()Ljava/lang/String;
    //   880: invokeinterface 320 3 0
    //   885: goto -214 -> 671
    //   888: return
    //   889: astore_1
    //   890: goto -51 -> 839
    //   893: astore 11
    //   895: aload 10
    //   897: astore 9
    //   899: goto -158 -> 741
    //   902: goto -528 -> 374
    //
    // Exception table:
    //   from	to	target	type
    //   405	420	736	java/lang/Exception
    //   807	812	815	java/io/IOException
    //   405	420	835	finally
    //   432	439	889	finally
    //   451	479	889	finally
    //   491	498	889	finally
    //   510	530	889	finally
    //   542	550	889	finally
    //   562	570	889	finally
    //   582	591	889	finally
    //   608	615	889	finally
    //   627	635	889	finally
    //   647	655	889	finally
    //   749	779	889	finally
    //   787	794	889	finally
    //   432	439	893	java/lang/Exception
    //   451	479	893	java/lang/Exception
    //   491	498	893	java/lang/Exception
    //   510	530	893	java/lang/Exception
    //   542	550	893	java/lang/Exception
    //   562	570	893	java/lang/Exception
    //   582	591	893	java/lang/Exception
    //   608	615	893	java/lang/Exception
    //   627	635	893	java/lang/Exception
    //   647	655	893	java/lang/Exception
  }

  // ERROR //
  private void c()
    throws Exception
  {
    // Byte code:
    //   0: new 324	java/util/Date
    //   3: dup
    //   4: invokespecial 634	java/util/Date:<init>	()V
    //   7: astore 16
    //   9: new 668	com/crashlytics/android/core/c
    //   12: dup
    //   13: aload_0
    //   14: getfield 114	com/crashlytics/android/core/ab:n	Lio/fabric/sdk/android/services/b/x;
    //   17: invokespecial 671	com/crashlytics/android/core/c:<init>	(Lio/fabric/sdk/android/services/b/x;)V
    //   20: invokevirtual 672	com/crashlytics/android/core/c:toString	()Ljava/lang/String;
    //   23: astore 17
    //   25: invokestatic 178	io/fabric/sdk/android/f:b	()Lio/fabric/sdk/android/r;
    //   28: ldc 180
    //   30: new 211	java/lang/StringBuilder
    //   33: dup
    //   34: ldc_w 674
    //   37: invokespecial 292	java/lang/StringBuilder:<init>	(Ljava/lang/String;)V
    //   40: aload 17
    //   42: invokevirtual 216	java/lang/StringBuilder:append	(Ljava/lang/String;)Ljava/lang/StringBuilder;
    //   45: invokevirtual 221	java/lang/StringBuilder:toString	()Ljava/lang/String;
    //   48: invokeinterface 320 3 0
    //   53: aconst_null
    //   54: astore 11
    //   56: aconst_null
    //   57: astore 12
    //   59: aconst_null
    //   60: astore 15
    //   62: aconst_null
    //   63: astore 13
    //   65: new 206	com/crashlytics/android/core/d
    //   68: dup
    //   69: aload_0
    //   70: invokespecial 209	com/crashlytics/android/core/ab:f	()Ljava/io/File;
    //   73: new 211	java/lang/StringBuilder
    //   76: dup
    //   77: invokespecial 212	java/lang/StringBuilder:<init>	()V
    //   80: aload 17
    //   82: invokevirtual 216	java/lang/StringBuilder:append	(Ljava/lang/String;)Ljava/lang/StringBuilder;
    //   85: ldc_w 676
    //   88: invokevirtual 216	java/lang/StringBuilder:append	(Ljava/lang/String;)Ljava/lang/StringBuilder;
    //   91: invokevirtual 221	java/lang/StringBuilder:toString	()Ljava/lang/String;
    //   94: invokespecial 224	com/crashlytics/android/core/d:<init>	(Ljava/io/File;Ljava/lang/String;)V
    //   97: astore 14
    //   99: aload 14
    //   101: astore 12
    //   103: aload 15
    //   105: astore 13
    //   107: aload 14
    //   109: invokestatic 229	com/crashlytics/android/core/f:a	(Ljava/io/OutputStream;)Lcom/crashlytics/android/core/f;
    //   112: astore 15
    //   114: aload 15
    //   116: astore 11
    //   118: aload 14
    //   120: astore 12
    //   122: aload 15
    //   124: astore 13
    //   126: aload 15
    //   128: aload 17
    //   130: getstatic 479	java/util/Locale:US	Ljava/util/Locale;
    //   133: ldc_w 678
    //   136: iconst_1
    //   137: anewarray 4	java/lang/Object
    //   140: dup
    //   141: iconst_0
    //   142: ldc_w 680
    //   145: aastore
    //   146: invokestatic 485	java/lang/String:format	(Ljava/util/Locale;Ljava/lang/String;[Ljava/lang/Object;)Ljava/lang/String;
    //   149: aload 16
    //   151: invokevirtual 327	java/util/Date:getTime	()J
    //   154: ldc2_w 328
    //   157: ldiv
    //   158: invokestatic 683	com/crashlytics/android/core/by:a	(Lcom/crashlytics/android/core/f;Ljava/lang/String;Ljava/lang/String;J)V
    //   161: aload 15
    //   163: ldc 189
    //   165: invokestatic 194	io/fabric/sdk/android/services/b/l:a	(Ljava/io/Flushable;Ljava/lang/String;)V
    //   168: aload 14
    //   170: ldc_w 685
    //   173: invokestatic 199	io/fabric/sdk/android/services/b/l:a	(Ljava/io/Closeable;Ljava/lang/String;)V
    //   176: aconst_null
    //   177: astore 11
    //   179: aconst_null
    //   180: astore 13
    //   182: aconst_null
    //   183: astore 14
    //   185: new 206	com/crashlytics/android/core/d
    //   188: dup
    //   189: aload_0
    //   190: invokespecial 209	com/crashlytics/android/core/ab:f	()Ljava/io/File;
    //   193: new 211	java/lang/StringBuilder
    //   196: dup
    //   197: invokespecial 212	java/lang/StringBuilder:<init>	()V
    //   200: aload 17
    //   202: invokevirtual 216	java/lang/StringBuilder:append	(Ljava/lang/String;)Ljava/lang/StringBuilder;
    //   205: ldc 92
    //   207: invokevirtual 216	java/lang/StringBuilder:append	(Ljava/lang/String;)Ljava/lang/StringBuilder;
    //   210: invokevirtual 221	java/lang/StringBuilder:toString	()Ljava/lang/String;
    //   213: invokespecial 224	com/crashlytics/android/core/d:<init>	(Ljava/io/File;Ljava/lang/String;)V
    //   216: astore 12
    //   218: aload 12
    //   220: invokestatic 229	com/crashlytics/android/core/f:a	(Ljava/io/OutputStream;)Lcom/crashlytics/android/core/f;
    //   223: astore 11
    //   225: aload 11
    //   227: aload_0
    //   228: getfield 114	com/crashlytics/android/core/ab:n	Lio/fabric/sdk/android/services/b/x;
    //   231: getfield 396	io/fabric/sdk/android/services/b/x:c	Ljava/lang/String;
    //   234: aload_0
    //   235: getfield 116	com/crashlytics/android/core/ab:g	Lcom/crashlytics/android/core/h;
    //   238: getfield 687	com/crashlytics/android/core/h:i	Ljava/lang/String;
    //   241: aload_0
    //   242: getfield 116	com/crashlytics/android/core/ab:g	Lcom/crashlytics/android/core/h;
    //   245: getfield 689	com/crashlytics/android/core/h:k	Ljava/lang/String;
    //   248: aload_0
    //   249: getfield 116	com/crashlytics/android/core/ab:g	Lcom/crashlytics/android/core/h;
    //   252: getfield 691	com/crashlytics/android/core/h:l	Ljava/lang/String;
    //   255: aload_0
    //   256: getfield 114	com/crashlytics/android/core/ab:n	Lio/fabric/sdk/android/services/b/x;
    //   259: invokevirtual 692	io/fabric/sdk/android/services/b/x:a	()Ljava/lang/String;
    //   262: aload_0
    //   263: getfield 116	com/crashlytics/android/core/ab:g	Lcom/crashlytics/android/core/h;
    //   266: getfield 694	com/crashlytics/android/core/h:j	Ljava/lang/String;
    //   269: invokestatic 699	io/fabric/sdk/android/services/b/r:a	(Ljava/lang/String;)Lio/fabric/sdk/android/services/b/r;
    //   272: getfield 701	io/fabric/sdk/android/services/b/r:e	I
    //   275: aload_0
    //   276: getfield 123	com/crashlytics/android/core/ab:q	Ljava/lang/String;
    //   279: invokestatic 704	com/crashlytics/android/core/by:a	(Lcom/crashlytics/android/core/f;Ljava/lang/String;Ljava/lang/String;Ljava/lang/String;Ljava/lang/String;Ljava/lang/String;ILjava/lang/String;)V
    //   282: aload 11
    //   284: ldc_w 706
    //   287: invokestatic 194	io/fabric/sdk/android/services/b/l:a	(Ljava/io/Flushable;Ljava/lang/String;)V
    //   290: aload 12
    //   292: ldc_w 708
    //   295: invokestatic 199	io/fabric/sdk/android/services/b/l:a	(Ljava/io/Closeable;Ljava/lang/String;)V
    //   298: aconst_null
    //   299: astore 13
    //   301: aconst_null
    //   302: astore 16
    //   304: aconst_null
    //   305: astore 12
    //   307: aconst_null
    //   308: astore 15
    //   310: aconst_null
    //   311: astore 11
    //   313: new 206	com/crashlytics/android/core/d
    //   316: dup
    //   317: aload_0
    //   318: invokespecial 209	com/crashlytics/android/core/ab:f	()Ljava/io/File;
    //   321: new 211	java/lang/StringBuilder
    //   324: dup
    //   325: invokespecial 212	java/lang/StringBuilder:<init>	()V
    //   328: aload 17
    //   330: invokevirtual 216	java/lang/StringBuilder:append	(Ljava/lang/String;)Ljava/lang/StringBuilder;
    //   333: ldc 94
    //   335: invokevirtual 216	java/lang/StringBuilder:append	(Ljava/lang/String;)Ljava/lang/StringBuilder;
    //   338: invokevirtual 221	java/lang/StringBuilder:toString	()Ljava/lang/String;
    //   341: invokespecial 224	com/crashlytics/android/core/d:<init>	(Ljava/io/File;Ljava/lang/String;)V
    //   344: astore 14
    //   346: aload 16
    //   348: astore 11
    //   350: aload 14
    //   352: astore 12
    //   354: aload 15
    //   356: astore 13
    //   358: aload 14
    //   360: invokestatic 229	com/crashlytics/android/core/f:a	(Ljava/io/OutputStream;)Lcom/crashlytics/android/core/f;
    //   363: astore 15
    //   365: aload 15
    //   367: astore 11
    //   369: aload 14
    //   371: astore 12
    //   373: aload 15
    //   375: astore 13
    //   377: aload 15
    //   379: aload_0
    //   380: getfield 116	com/crashlytics/android/core/ab:g	Lcom/crashlytics/android/core/h;
    //   383: getfield 137	io/fabric/sdk/android/o:q	Landroid/content/Context;
    //   386: invokestatic 710	io/fabric/sdk/android/services/b/l:f	(Landroid/content/Context;)Z
    //   389: invokestatic 713	com/crashlytics/android/core/by:a	(Lcom/crashlytics/android/core/f;Z)V
    //   392: aload 15
    //   394: ldc_w 715
    //   397: invokestatic 194	io/fabric/sdk/android/services/b/l:a	(Ljava/io/Flushable;Ljava/lang/String;)V
    //   400: aload 14
    //   402: ldc_w 717
    //   405: invokestatic 199	io/fabric/sdk/android/services/b/l:a	(Ljava/io/Closeable;Ljava/lang/String;)V
    //   408: aconst_null
    //   409: astore 14
    //   411: aconst_null
    //   412: astore 11
    //   414: aconst_null
    //   415: astore 16
    //   417: aconst_null
    //   418: astore 15
    //   420: aconst_null
    //   421: astore 12
    //   423: new 206	com/crashlytics/android/core/d
    //   426: dup
    //   427: aload_0
    //   428: invokespecial 209	com/crashlytics/android/core/ab:f	()Ljava/io/File;
    //   431: new 211	java/lang/StringBuilder
    //   434: dup
    //   435: invokespecial 212	java/lang/StringBuilder:<init>	()V
    //   438: aload 17
    //   440: invokevirtual 216	java/lang/StringBuilder:append	(Ljava/lang/String;)Ljava/lang/StringBuilder;
    //   443: ldc 96
    //   445: invokevirtual 216	java/lang/StringBuilder:append	(Ljava/lang/String;)Ljava/lang/StringBuilder;
    //   448: invokevirtual 221	java/lang/StringBuilder:toString	()Ljava/lang/String;
    //   451: invokespecial 224	com/crashlytics/android/core/d:<init>	(Ljava/io/File;Ljava/lang/String;)V
    //   454: astore 13
    //   456: aload 16
    //   458: astore 11
    //   460: aload 15
    //   462: astore 12
    //   464: aload 13
    //   466: invokestatic 229	com/crashlytics/android/core/f:a	(Ljava/io/OutputStream;)Lcom/crashlytics/android/core/f;
    //   469: astore 14
    //   471: aload 14
    //   473: astore 11
    //   475: aload 14
    //   477: astore 12
    //   479: aload_0
    //   480: getfield 116	com/crashlytics/android/core/ab:g	Lcom/crashlytics/android/core/h;
    //   483: getfield 137	io/fabric/sdk/android/o:q	Landroid/content/Context;
    //   486: astore 15
    //   488: aload 14
    //   490: astore 11
    //   492: aload 14
    //   494: astore 12
    //   496: new 719	android/os/StatFs
    //   499: dup
    //   500: invokestatic 369	android/os/Environment:getDataDirectory	()Ljava/io/File;
    //   503: invokevirtual 372	java/io/File:getPath	()Ljava/lang/String;
    //   506: invokespecial 720	android/os/StatFs:<init>	(Ljava/lang/String;)V
    //   509: astore 18
    //   511: aload 14
    //   513: astore 11
    //   515: aload 14
    //   517: astore 12
    //   519: aload_0
    //   520: getfield 114	com/crashlytics/android/core/ab:n	Lio/fabric/sdk/android/services/b/x;
    //   523: invokevirtual 722	io/fabric/sdk/android/services/b/x:c	()Ljava/lang/String;
    //   526: astore 16
    //   528: aload 14
    //   530: astore 11
    //   532: aload 14
    //   534: astore 12
    //   536: invokestatic 724	io/fabric/sdk/android/services/b/l:a	()I
    //   539: istore_1
    //   540: aload 14
    //   542: astore 11
    //   544: aload 14
    //   546: astore 12
    //   548: invokestatic 730	java/lang/Runtime:getRuntime	()Ljava/lang/Runtime;
    //   551: invokevirtual 733	java/lang/Runtime:availableProcessors	()I
    //   554: istore_2
    //   555: aload 14
    //   557: astore 11
    //   559: aload 14
    //   561: astore 12
    //   563: invokestatic 361	io/fabric/sdk/android/services/b/l:b	()J
    //   566: lstore 4
    //   568: aload 14
    //   570: astore 11
    //   572: aload 14
    //   574: astore 12
    //   576: aload 18
    //   578: invokevirtual 736	android/os/StatFs:getBlockCount	()I
    //   581: i2l
    //   582: lstore 6
    //   584: aload 14
    //   586: astore 11
    //   588: aload 14
    //   590: astore 12
    //   592: aload 18
    //   594: invokevirtual 739	android/os/StatFs:getBlockSize	()I
    //   597: i2l
    //   598: lstore 8
    //   600: aload 14
    //   602: astore 11
    //   604: aload 14
    //   606: astore 12
    //   608: aload 15
    //   610: invokestatic 741	io/fabric/sdk/android/services/b/l:e	(Landroid/content/Context;)Z
    //   613: istore 10
    //   615: aload 14
    //   617: astore 11
    //   619: aload 14
    //   621: astore 12
    //   623: aload_0
    //   624: getfield 114	com/crashlytics/android/core/ab:n	Lio/fabric/sdk/android/services/b/x;
    //   627: invokevirtual 743	io/fabric/sdk/android/services/b/x:d	()Ljava/util/Map;
    //   630: astore 18
    //   632: aload 14
    //   634: astore 11
    //   636: aload 14
    //   638: astore 12
    //   640: aload 15
    //   642: invokestatic 746	io/fabric/sdk/android/services/b/l:g	(Landroid/content/Context;)I
    //   645: istore_3
    //   646: aload 14
    //   648: astore 11
    //   650: aload 14
    //   652: astore 12
    //   654: aload 14
    //   656: aload 16
    //   658: iload_1
    //   659: getstatic 751	android/os/Build:MODEL	Ljava/lang/String;
    //   662: iload_2
    //   663: lload 4
    //   665: lload 6
    //   667: lload 8
    //   669: lmul
    //   670: iload 10
    //   672: aload 18
    //   674: iload_3
    //   675: getstatic 754	android/os/Build:MANUFACTURER	Ljava/lang/String;
    //   678: getstatic 757	android/os/Build:PRODUCT	Ljava/lang/String;
    //   681: invokestatic 760	com/crashlytics/android/core/by:a	(Lcom/crashlytics/android/core/f;Ljava/lang/String;ILjava/lang/String;IJJZLjava/util/Map;ILjava/lang/String;Ljava/lang/String;)V
    //   684: aload 14
    //   686: ldc_w 762
    //   689: invokestatic 194	io/fabric/sdk/android/services/b/l:a	(Ljava/io/Flushable;Ljava/lang/String;)V
    //   692: aload 13
    //   694: ldc_w 764
    //   697: invokestatic 199	io/fabric/sdk/android/services/b/l:a	(Ljava/io/Closeable;Ljava/lang/String;)V
    //   700: aload_0
    //   701: getfield 144	com/crashlytics/android/core/ab:o	Lcom/crashlytics/android/core/az;
    //   704: aload 17
    //   706: invokevirtual 765	com/crashlytics/android/core/az:a	(Ljava/lang/String;)V
    //   709: return
    //   710: astore 15
    //   712: aconst_null
    //   713: astore 14
    //   715: aload 13
    //   717: astore 11
    //   719: aload 14
    //   721: astore 12
    //   723: aload 15
    //   725: aload 14
    //   727: invokestatic 252	com/crashlytics/android/core/ax:a	(Ljava/lang/Throwable;Ljava/io/OutputStream;)V
    //   730: aload 13
    //   732: astore 11
    //   734: aload 14
    //   736: astore 12
    //   738: aload 15
    //   740: athrow
    //   741: astore 14
    //   743: aload 12
    //   745: astore 13
    //   747: aload 11
    //   749: astore 12
    //   751: aload 14
    //   753: astore 11
    //   755: aload 12
    //   757: ldc 189
    //   759: invokestatic 194	io/fabric/sdk/android/services/b/l:a	(Ljava/io/Flushable;Ljava/lang/String;)V
    //   762: aload 13
    //   764: ldc_w 685
    //   767: invokestatic 199	io/fabric/sdk/android/services/b/l:a	(Ljava/io/Closeable;Ljava/lang/String;)V
    //   770: aload 11
    //   772: athrow
    //   773: astore 13
    //   775: aload 14
    //   777: astore 12
    //   779: aload 13
    //   781: aload 11
    //   783: invokestatic 252	com/crashlytics/android/core/ax:a	(Ljava/lang/Throwable;Ljava/io/OutputStream;)V
    //   786: aload 13
    //   788: athrow
    //   789: astore 15
    //   791: aload 11
    //   793: astore 14
    //   795: aload 12
    //   797: astore 13
    //   799: aload 15
    //   801: astore 11
    //   803: aload 13
    //   805: ldc_w 706
    //   808: invokestatic 194	io/fabric/sdk/android/services/b/l:a	(Ljava/io/Flushable;Ljava/lang/String;)V
    //   811: aload 14
    //   813: ldc_w 708
    //   816: invokestatic 199	io/fabric/sdk/android/services/b/l:a	(Ljava/io/Closeable;Ljava/lang/String;)V
    //   819: aload 11
    //   821: athrow
    //   822: astore 15
    //   824: aconst_null
    //   825: astore 14
    //   827: aload 11
    //   829: astore 13
    //   831: aload 13
    //   833: astore 11
    //   835: aload 14
    //   837: astore 12
    //   839: aload 15
    //   841: aload 14
    //   843: invokestatic 252	com/crashlytics/android/core/ax:a	(Ljava/lang/Throwable;Ljava/io/OutputStream;)V
    //   846: aload 13
    //   848: astore 11
    //   850: aload 14
    //   852: astore 12
    //   854: aload 15
    //   856: athrow
    //   857: astore 14
    //   859: aload 12
    //   861: astore 13
    //   863: aload 11
    //   865: astore 12
    //   867: aload 14
    //   869: astore 11
    //   871: aload 12
    //   873: ldc_w 715
    //   876: invokestatic 194	io/fabric/sdk/android/services/b/l:a	(Ljava/io/Flushable;Ljava/lang/String;)V
    //   879: aload 13
    //   881: ldc_w 717
    //   884: invokestatic 199	io/fabric/sdk/android/services/b/l:a	(Ljava/io/Closeable;Ljava/lang/String;)V
    //   887: aload 11
    //   889: athrow
    //   890: astore 13
    //   892: aload 14
    //   894: astore 11
    //   896: aload 13
    //   898: aload 11
    //   900: invokestatic 252	com/crashlytics/android/core/ax:a	(Ljava/lang/Throwable;Ljava/io/OutputStream;)V
    //   903: aload 13
    //   905: athrow
    //   906: astore 14
    //   908: aload 11
    //   910: astore 13
    //   912: aload 12
    //   914: astore 11
    //   916: aload 14
    //   918: astore 12
    //   920: aload 11
    //   922: ldc_w 762
    //   925: invokestatic 194	io/fabric/sdk/android/services/b/l:a	(Ljava/io/Flushable;Ljava/lang/String;)V
    //   928: aload 13
    //   930: ldc_w 764
    //   933: invokestatic 199	io/fabric/sdk/android/services/b/l:a	(Ljava/io/Closeable;Ljava/lang/String;)V
    //   936: aload 12
    //   938: athrow
    //   939: astore 12
    //   941: aconst_null
    //   942: astore 13
    //   944: goto -24 -> 920
    //   947: astore 12
    //   949: goto -29 -> 920
    //   952: astore 14
    //   954: aload 13
    //   956: astore 11
    //   958: aload 14
    //   960: astore 13
    //   962: goto -66 -> 896
    //   965: astore 11
    //   967: goto -96 -> 871
    //   970: astore 15
    //   972: goto -141 -> 831
    //   975: astore 11
    //   977: aconst_null
    //   978: astore 14
    //   980: goto -177 -> 803
    //   983: astore 11
    //   985: aload 12
    //   987: astore 14
    //   989: goto -186 -> 803
    //   992: astore 14
    //   994: aload 11
    //   996: astore 13
    //   998: aload 14
    //   1000: astore 11
    //   1002: aload 12
    //   1004: astore 14
    //   1006: goto -203 -> 803
    //   1009: astore 13
    //   1011: aload 12
    //   1013: astore 11
    //   1015: aload 14
    //   1017: astore 12
    //   1019: goto -240 -> 779
    //   1022: astore 13
    //   1024: aload 12
    //   1026: astore 14
    //   1028: aload 11
    //   1030: astore 12
    //   1032: aload 14
    //   1034: astore 11
    //   1036: goto -257 -> 779
    //   1039: astore 11
    //   1041: aconst_null
    //   1042: astore 13
    //   1044: goto -289 -> 755
    //   1047: astore 15
    //   1049: goto -334 -> 715
    //
    // Exception table:
    //   from	to	target	type
    //   65	99	710	java/lang/Exception
    //   107	114	741	finally
    //   126	161	741	finally
    //   723	730	741	finally
    //   738	741	741	finally
    //   185	218	773	java/lang/Exception
    //   779	789	789	finally
    //   313	346	822	java/lang/Exception
    //   358	365	857	finally
    //   377	392	857	finally
    //   839	846	857	finally
    //   854	857	857	finally
    //   423	456	890	java/lang/Exception
    //   896	906	906	finally
    //   423	456	939	finally
    //   464	471	947	finally
    //   479	488	947	finally
    //   496	511	947	finally
    //   519	528	947	finally
    //   536	540	947	finally
    //   548	555	947	finally
    //   563	568	947	finally
    //   576	584	947	finally
    //   592	600	947	finally
    //   608	615	947	finally
    //   623	632	947	finally
    //   640	646	947	finally
    //   654	684	947	finally
    //   464	471	952	java/lang/Exception
    //   479	488	952	java/lang/Exception
    //   496	511	952	java/lang/Exception
    //   519	528	952	java/lang/Exception
    //   536	540	952	java/lang/Exception
    //   548	555	952	java/lang/Exception
    //   563	568	952	java/lang/Exception
    //   576	584	952	java/lang/Exception
    //   592	600	952	java/lang/Exception
    //   608	615	952	java/lang/Exception
    //   623	632	952	java/lang/Exception
    //   640	646	952	java/lang/Exception
    //   654	684	952	java/lang/Exception
    //   313	346	965	finally
    //   358	365	970	java/lang/Exception
    //   377	392	970	java/lang/Exception
    //   185	218	975	finally
    //   218	225	983	finally
    //   225	282	992	finally
    //   218	225	1009	java/lang/Exception
    //   225	282	1022	java/lang/Exception
    //   65	99	1039	finally
    //   107	114	1047	java/lang/Exception
    //   126	161	1047	java/lang/Exception
  }

  private File[] d()
  {
    File[] arrayOfFile = a(new an("BeginSession"));
    Arrays.sort(arrayOfFile, b);
    return arrayOfFile;
  }

  private void e()
  {
    File[] arrayOfFile = a(a);
    int i2 = arrayOfFile.length;
    int i1 = 0;
    while (i1 < i2)
    {
      File localFile = arrayOfFile[i1];
      this.f.a(new ao(this.g, localFile));
      i1 += 1;
    }
  }

  private File f()
  {
    return this.m.a();
  }

  final File[] a(FilenameFilter paramFilenameFilter)
  {
    File[] arrayOfFile = f().listFiles(paramFilenameFilter);
    paramFilenameFilter = arrayOfFile;
    if (arrayOfFile == null)
      paramFilenameFilter = new File[0];
    return paramFilenameFilter;
  }

  // ERROR //
  public final void uncaughtException(Thread paramThread, Throwable paramThrowable)
  {
    // Byte code:
    //   0: aload_0
    //   1: monitorenter
    //   2: aload_0
    //   3: getfield 132	com/crashlytics/android/core/ab:e	Ljava/util/concurrent/atomic/AtomicBoolean;
    //   6: iconst_1
    //   7: invokevirtual 789	java/util/concurrent/atomic/AtomicBoolean:set	(Z)V
    //   10: invokestatic 178	io/fabric/sdk/android/f:b	()Lio/fabric/sdk/android/r;
    //   13: ldc 180
    //   15: new 211	java/lang/StringBuilder
    //   18: dup
    //   19: ldc_w 791
    //   22: invokespecial 292	java/lang/StringBuilder:<init>	(Ljava/lang/String;)V
    //   25: aload_2
    //   26: invokevirtual 794	java/lang/StringBuilder:append	(Ljava/lang/Object;)Ljava/lang/StringBuilder;
    //   29: ldc_w 796
    //   32: invokevirtual 216	java/lang/StringBuilder:append	(Ljava/lang/String;)Ljava/lang/StringBuilder;
    //   35: aload_1
    //   36: invokevirtual 797	java/lang/Thread:getName	()Ljava/lang/String;
    //   39: invokevirtual 216	java/lang/StringBuilder:append	(Ljava/lang/String;)Ljava/lang/StringBuilder;
    //   42: invokevirtual 221	java/lang/StringBuilder:toString	()Ljava/lang/String;
    //   45: invokeinterface 320 3 0
    //   50: aload_0
    //   51: getfield 151	com/crashlytics/android/core/ab:p	Lcom/crashlytics/android/core/at;
    //   54: astore_3
    //   55: aload_3
    //   56: getfield 799	com/crashlytics/android/core/at:a	Ljava/util/concurrent/atomic/AtomicBoolean;
    //   59: iconst_0
    //   60: invokevirtual 803	java/util/concurrent/atomic/AtomicBoolean:getAndSet	(Z)Z
    //   63: ifeq +25 -> 88
    //   66: aload_3
    //   67: getfield 805	com/crashlytics/android/core/at:b	Landroid/content/Context;
    //   70: aload_3
    //   71: getfield 808	com/crashlytics/android/core/at:d	Landroid/content/BroadcastReceiver;
    //   74: invokevirtual 812	android/content/Context:unregisterReceiver	(Landroid/content/BroadcastReceiver;)V
    //   77: aload_3
    //   78: getfield 805	com/crashlytics/android/core/at:b	Landroid/content/Context;
    //   81: aload_3
    //   82: getfield 814	com/crashlytics/android/core/at:c	Landroid/content/BroadcastReceiver;
    //   85: invokevirtual 812	android/content/Context:unregisterReceiver	(Landroid/content/BroadcastReceiver;)V
    //   88: new 324	java/util/Date
    //   91: dup
    //   92: invokespecial 634	java/util/Date:<init>	()V
    //   95: astore_3
    //   96: aload_0
    //   97: getfield 112	com/crashlytics/android/core/ab:f	Lcom/crashlytics/android/core/v;
    //   100: new 816	com/crashlytics/android/core/ak
    //   103: dup
    //   104: aload_0
    //   105: aload_3
    //   106: aload_1
    //   107: aload_2
    //   108: invokespecial 818	com/crashlytics/android/core/ak:<init>	(Lcom/crashlytics/android/core/ab;Ljava/util/Date;Ljava/lang/Thread;Ljava/lang/Throwable;)V
    //   111: invokevirtual 821	com/crashlytics/android/core/v:a	(Ljava/util/concurrent/Callable;)Ljava/lang/Object;
    //   114: pop
    //   115: invokestatic 178	io/fabric/sdk/android/f:b	()Lio/fabric/sdk/android/r;
    //   118: ldc 180
    //   120: ldc_w 823
    //   123: invokeinterface 320 3 0
    //   128: aload_0
    //   129: getfield 110	com/crashlytics/android/core/ab:l	Ljava/lang/Thread$UncaughtExceptionHandler;
    //   132: aload_1
    //   133: aload_2
    //   134: invokeinterface 825 3 0
    //   139: aload_0
    //   140: getfield 132	com/crashlytics/android/core/ab:e	Ljava/util/concurrent/atomic/AtomicBoolean;
    //   143: iconst_0
    //   144: invokevirtual 789	java/util/concurrent/atomic/AtomicBoolean:set	(Z)V
    //   147: aload_0
    //   148: monitorexit
    //   149: return
    //   150: astore_3
    //   151: invokestatic 178	io/fabric/sdk/android/f:b	()Lio/fabric/sdk/android/r;
    //   154: ldc 180
    //   156: ldc_w 827
    //   159: aload_3
    //   160: invokeinterface 187 4 0
    //   165: invokestatic 178	io/fabric/sdk/android/f:b	()Lio/fabric/sdk/android/r;
    //   168: ldc 180
    //   170: ldc_w 823
    //   173: invokeinterface 320 3 0
    //   178: aload_0
    //   179: getfield 110	com/crashlytics/android/core/ab:l	Ljava/lang/Thread$UncaughtExceptionHandler;
    //   182: aload_1
    //   183: aload_2
    //   184: invokeinterface 825 3 0
    //   189: aload_0
    //   190: getfield 132	com/crashlytics/android/core/ab:e	Ljava/util/concurrent/atomic/AtomicBoolean;
    //   193: iconst_0
    //   194: invokevirtual 789	java/util/concurrent/atomic/AtomicBoolean:set	(Z)V
    //   197: goto -50 -> 147
    //   200: astore_1
    //   201: aload_0
    //   202: monitorexit
    //   203: aload_1
    //   204: athrow
    //   205: astore_3
    //   206: invokestatic 178	io/fabric/sdk/android/f:b	()Lio/fabric/sdk/android/r;
    //   209: ldc 180
    //   211: ldc_w 823
    //   214: invokeinterface 320 3 0
    //   219: aload_0
    //   220: getfield 110	com/crashlytics/android/core/ab:l	Ljava/lang/Thread$UncaughtExceptionHandler;
    //   223: aload_1
    //   224: aload_2
    //   225: invokeinterface 825 3 0
    //   230: aload_0
    //   231: getfield 132	com/crashlytics/android/core/ab:e	Ljava/util/concurrent/atomic/AtomicBoolean;
    //   234: iconst_0
    //   235: invokevirtual 789	java/util/concurrent/atomic/AtomicBoolean:set	(Z)V
    //   238: aload_3
    //   239: athrow
    //
    // Exception table:
    //   from	to	target	type
    //   10	88	150	java/lang/Exception
    //   88	115	150	java/lang/Exception
    //   2	10	200	finally
    //   115	147	200	finally
    //   165	197	200	finally
    //   206	240	200	finally
    //   10	88	205	finally
    //   88	115	205	finally
    //   151	165	205	finally
  }
}

/* Location:           C:\crazyd\work\ustone\odm2016031702\baidu\android\nut-dex2jar.jar
 * Qualified Name:     com.crashlytics.android.core.ab
 * JD-Core Version:    0.6.2
 */