package rx.c.a;

import java.util.ArrayList;
import java.util.List;
import java.util.Queue;
import java.util.concurrent.ConcurrentLinkedQueue;
import rx.c.d.s;
import rx.exceptions.CompositeException;
import rx.f.c;
import rx.h;
import rx.z;

final class o<T> extends z<h<? extends T>>
{
  static final m<?>[] r = new m[0];
  final z<? super T> a;
  final boolean b;
  final int d;
  n<T> e;
  volatile Queue<Object> f;
  volatile c g;
  volatile ConcurrentLinkedQueue<Throwable> h;
  final b<T> i;
  volatile boolean j;
  boolean k;
  boolean l;
  final Object m;
  volatile m<?>[] n;
  long o;
  long p;
  int q;

  public o(z<? super T> paramz, boolean paramBoolean, int paramInt)
  {
    this.a = paramz;
    this.b = paramBoolean;
    this.d = paramInt;
    this.i = b.a();
    this.m = new Object();
    this.n = r;
    if (paramInt == 2147483647);
    for (long l1 = 9223372036854775807L; ; l1 = paramInt)
    {
      a(l1);
      return;
    }
  }

  private c g()
  {
    c localc1 = this.g;
    c localc2 = localc1;
    if (localc1 == null);
    while (true)
    {
      try
      {
        localc1 = this.g;
        if (localc1 == null)
        {
          localc1 = new c();
          this.g = localc1;
          i1 = 1;
          localc2 = localc1;
          if (i1 != 0)
          {
            a(localc1);
            localc2 = localc1;
          }
          return localc2;
        }
      }
      finally
      {
      }
      int i1 = 0;
    }
  }

  private void h()
  {
    ArrayList localArrayList = new ArrayList(this.h);
    if (localArrayList.size() == 1)
    {
      this.a.a((Throwable)localArrayList.get(0));
      return;
    }
    this.a.a(new CompositeException(localArrayList, (byte)0));
  }

  private boolean i()
  {
    if (this.a.c.b)
      return true;
    ConcurrentLinkedQueue localConcurrentLinkedQueue = this.h;
    if ((!this.b) && (localConcurrentLinkedQueue != null) && (!localConcurrentLinkedQueue.isEmpty()))
      try
      {
        h();
        return true;
      }
      finally
      {
        this.c.n_();
      }
    return false;
  }

  public final void a()
  {
    this.j = true;
    e();
  }

  public final void a(Throwable paramThrowable)
  {
    d().offer(paramThrowable);
    this.j = true;
    e();
  }

  final Queue<Throwable> d()
  {
    Object localObject = this.h;
    if (localObject == null)
      try
      {
        ConcurrentLinkedQueue localConcurrentLinkedQueue = this.h;
        localObject = localConcurrentLinkedQueue;
        if (localConcurrentLinkedQueue == null)
        {
          localObject = new ConcurrentLinkedQueue();
          this.h = ((ConcurrentLinkedQueue)localObject);
        }
        return localObject;
      }
      finally
      {
      }
    return localQueue;
  }

  final void e()
  {
    try
    {
      if (this.k)
      {
        this.l = true;
        return;
      }
      this.k = true;
      f();
      return;
    }
    finally
    {
    }
  }

  // ERROR //
  final void f()
  {
    // Byte code:
    //   0: iconst_0
    //   1: istore 11
    //   3: iconst_0
    //   4: istore 10
    //   6: iload 10
    //   8: istore_1
    //   9: aload_0
    //   10: getfield 52	rx/c/a/o:a	Lrx/z;
    //   13: astore 20
    //   15: iload 10
    //   17: istore_1
    //   18: aload_0
    //   19: invokespecial 229	rx/c/a/o:i	()Z
    //   22: ifeq +4 -> 26
    //   25: return
    //   26: iload 10
    //   28: istore_1
    //   29: aload_0
    //   30: getfield 177	rx/c/a/o:f	Ljava/util/Queue;
    //   33: astore 21
    //   35: iload 10
    //   37: istore_1
    //   38: aload_0
    //   39: getfield 145	rx/c/a/o:e	Lrx/c/a/n;
    //   42: invokevirtual 150	rx/c/a/n:get	()J
    //   45: lstore 13
    //   47: lload 13
    //   49: ldc2_w 72
    //   52: lcmp
    //   53: ifne +88 -> 141
    //   56: iconst_1
    //   57: istore 7
    //   59: goto +1003 -> 1062
    //   62: aload 18
    //   64: astore 19
    //   66: lload 13
    //   68: lconst_0
    //   69: lcmp
    //   70: ifle +1023 -> 1093
    //   73: iload 10
    //   75: istore_1
    //   76: aload 21
    //   78: invokeinterface 233 1 0
    //   83: astore 18
    //   85: iload 10
    //   87: istore_1
    //   88: aload_0
    //   89: invokespecial 229	rx/c/a/o:i	()Z
    //   92: ifne +969 -> 1061
    //   95: aload 18
    //   97: astore 19
    //   99: aload 18
    //   101: ifnull +992 -> 1093
    //   104: iload 10
    //   106: istore_1
    //   107: aload 18
    //   109: invokestatic 236	rx/c/a/b:b	(Ljava/lang/Object;)Ljava/lang/Object;
    //   112: astore 19
    //   114: iload 10
    //   116: istore_1
    //   117: aload 20
    //   119: aload 19
    //   121: invokevirtual 154	rx/z:a	(Ljava/lang/Object;)V
    //   124: lload 13
    //   126: lconst_1
    //   127: lsub
    //   128: lstore 13
    //   130: iload_2
    //   131: iconst_1
    //   132: iadd
    //   133: istore_2
    //   134: iload_3
    //   135: iconst_1
    //   136: iadd
    //   137: istore_3
    //   138: goto -76 -> 62
    //   141: iconst_0
    //   142: istore 7
    //   144: goto +918 -> 1062
    //   147: astore 19
    //   149: iload 10
    //   151: istore_1
    //   152: aload_0
    //   153: getfield 54	rx/c/a/o:b	Z
    //   156: ifne +50 -> 206
    //   159: iload 10
    //   161: istore_1
    //   162: aload 19
    //   164: invokestatic 165	rx/exceptions/e:a	(Ljava/lang/Throwable;)V
    //   167: iconst_1
    //   168: istore_2
    //   169: iload_2
    //   170: istore_1
    //   171: aload_0
    //   172: getfield 119	rx/z:c	Lrx/c/d/s;
    //   175: invokevirtual 132	rx/c/d/s:n_	()V
    //   178: iload_2
    //   179: istore_1
    //   180: aload 20
    //   182: aload 19
    //   184: invokevirtual 109	rx/z:a	(Ljava/lang/Throwable;)V
    //   187: return
    //   188: astore 18
    //   190: iload_1
    //   191: ifne +12 -> 203
    //   194: aload_0
    //   195: monitorenter
    //   196: aload_0
    //   197: iconst_0
    //   198: putfield 152	rx/c/a/o:k	Z
    //   201: aload_0
    //   202: monitorexit
    //   203: aload 18
    //   205: athrow
    //   206: iload 10
    //   208: istore_1
    //   209: aload_0
    //   210: invokevirtual 169	rx/c/a/o:d	()Ljava/util/Queue;
    //   213: aload 19
    //   215: invokeinterface 173 2 0
    //   220: pop
    //   221: goto -97 -> 124
    //   224: iload 10
    //   226: istore_1
    //   227: aload_0
    //   228: getfield 134	rx/c/a/o:j	Z
    //   231: istore 17
    //   233: iload 10
    //   235: istore_1
    //   236: aload_0
    //   237: getfield 177	rx/c/a/o:f	Ljava/util/Queue;
    //   240: astore 18
    //   242: iload 10
    //   244: istore_1
    //   245: aload_0
    //   246: getfield 70	rx/c/a/o:n	[Lrx/c/a/m;
    //   249: astore 21
    //   251: iload 10
    //   253: istore_1
    //   254: aload 21
    //   256: arraylength
    //   257: istore 12
    //   259: iload 17
    //   261: ifeq +88 -> 349
    //   264: aload 18
    //   266: ifnull +16 -> 282
    //   269: iload 10
    //   271: istore_1
    //   272: aload 18
    //   274: invokeinterface 127 1 0
    //   279: ifeq +70 -> 349
    //   282: iload 12
    //   284: ifne +65 -> 349
    //   287: iload 10
    //   289: istore_1
    //   290: aload_0
    //   291: getfield 91	rx/c/a/o:h	Ljava/util/concurrent/ConcurrentLinkedQueue;
    //   294: astore 18
    //   296: aload 18
    //   298: ifnull +16 -> 314
    //   301: iload 10
    //   303: istore_1
    //   304: aload 18
    //   306: invokeinterface 127 1 0
    //   311: ifeq +30 -> 341
    //   314: iload 10
    //   316: istore_1
    //   317: aload 20
    //   319: invokevirtual 238	rx/z:a	()V
    //   322: return
    //   323: iload 10
    //   325: istore_1
    //   326: aload_0
    //   327: getfield 145	rx/c/a/o:e	Lrx/c/a/n;
    //   330: iload_2
    //   331: ineg
    //   332: i2l
    //   333: invokevirtual 160	rx/c/a/n:addAndGet	(J)J
    //   336: lstore 13
    //   338: goto +769 -> 1107
    //   341: iload 10
    //   343: istore_1
    //   344: aload_0
    //   345: invokespecial 129	rx/c/a/o:h	()V
    //   348: return
    //   349: iload 12
    //   351: ifle +701 -> 1052
    //   354: iload 10
    //   356: istore_1
    //   357: aload_0
    //   358: getfield 240	rx/c/a/o:p	J
    //   361: lstore 13
    //   363: iload 10
    //   365: istore_1
    //   366: aload_0
    //   367: getfield 242	rx/c/a/o:q	I
    //   370: istore 4
    //   372: iload 12
    //   374: iload 4
    //   376: if_icmple +764 -> 1140
    //   379: iload 10
    //   381: istore_1
    //   382: iload 4
    //   384: istore_3
    //   385: aload 21
    //   387: iload 4
    //   389: aaload
    //   390: getfield 244	rx/c/a/m:b	J
    //   393: lload 13
    //   395: lcmp
    //   396: ifeq +771 -> 1167
    //   399: goto +741 -> 1140
    //   402: iload 4
    //   404: iload 12
    //   406: if_icmpge +36 -> 442
    //   409: iload 10
    //   411: istore_1
    //   412: aload 21
    //   414: iload_3
    //   415: aaload
    //   416: getfield 244	rx/c/a/m:b	J
    //   419: lload 13
    //   421: lcmp
    //   422: ifeq +20 -> 442
    //   425: iload_3
    //   426: iconst_1
    //   427: iadd
    //   428: istore_1
    //   429: iload_1
    //   430: istore_3
    //   431: iload_1
    //   432: iload 12
    //   434: if_icmpne +724 -> 1158
    //   437: iconst_0
    //   438: istore_3
    //   439: goto +719 -> 1158
    //   442: iload 10
    //   444: istore_1
    //   445: aload_0
    //   446: iload_3
    //   447: putfield 242	rx/c/a/o:q	I
    //   450: iload 10
    //   452: istore_1
    //   453: aload_0
    //   454: aload 21
    //   456: iload_3
    //   457: aaload
    //   458: getfield 244	rx/c/a/m:b	J
    //   461: putfield 240	rx/c/a/o:p	J
    //   464: goto +703 -> 1167
    //   467: iload_3
    //   468: istore 6
    //   470: iload_2
    //   471: istore 5
    //   473: iload 9
    //   475: iload 12
    //   477: if_icmpge +467 -> 944
    //   480: iload 10
    //   482: istore_1
    //   483: aload_0
    //   484: invokespecial 229	rx/c/a/o:i	()Z
    //   487: ifne +574 -> 1061
    //   490: aload 21
    //   492: iload 8
    //   494: aaload
    //   495: astore 22
    //   497: aconst_null
    //   498: astore 19
    //   500: lload 13
    //   502: lstore 15
    //   504: goto +678 -> 1182
    //   507: aload 19
    //   509: astore 18
    //   511: lload 13
    //   513: lconst_0
    //   514: lcmp
    //   515: ifle +130 -> 645
    //   518: iload 10
    //   520: istore_1
    //   521: aload_0
    //   522: invokespecial 229	rx/c/a/o:i	()Z
    //   525: ifne +536 -> 1061
    //   528: iload 10
    //   530: istore_1
    //   531: aload 22
    //   533: getfield 247	rx/c/a/m:e	Lrx/c/d/f;
    //   536: astore 23
    //   538: aload 19
    //   540: astore 18
    //   542: aload 23
    //   544: ifnull +101 -> 645
    //   547: iload 10
    //   549: istore_1
    //   550: aload 23
    //   552: invokevirtual 249	rx/c/d/f:e	()Ljava/lang/Object;
    //   555: astore 19
    //   557: aload 19
    //   559: astore 18
    //   561: aload 19
    //   563: ifnull +82 -> 645
    //   566: iload 10
    //   568: istore_1
    //   569: aload 19
    //   571: invokestatic 236	rx/c/a/b:b	(Ljava/lang/Object;)Ljava/lang/Object;
    //   574: astore 18
    //   576: iload 10
    //   578: istore_1
    //   579: aload 20
    //   581: aload 18
    //   583: invokevirtual 154	rx/z:a	(Ljava/lang/Object;)V
    //   586: iload 4
    //   588: iconst_1
    //   589: iadd
    //   590: istore 4
    //   592: lload 13
    //   594: lconst_1
    //   595: lsub
    //   596: lstore 13
    //   598: goto -91 -> 507
    //   601: astore 18
    //   603: iconst_1
    //   604: istore_2
    //   605: iload_2
    //   606: istore_1
    //   607: aload 18
    //   609: invokestatic 165	rx/exceptions/e:a	(Ljava/lang/Throwable;)V
    //   612: aload 20
    //   614: aload 18
    //   616: invokevirtual 109	rx/z:a	(Ljava/lang/Throwable;)V
    //   619: iload_2
    //   620: istore_1
    //   621: aload_0
    //   622: getfield 119	rx/z:c	Lrx/c/d/s;
    //   625: invokevirtual 132	rx/c/d/s:n_	()V
    //   628: return
    //   629: astore 18
    //   631: iload_2
    //   632: istore_1
    //   633: aload_0
    //   634: getfield 119	rx/z:c	Lrx/c/d/s;
    //   637: invokevirtual 132	rx/c/d/s:n_	()V
    //   640: iload_2
    //   641: istore_1
    //   642: aload 18
    //   644: athrow
    //   645: iload 4
    //   647: ifle +545 -> 1192
    //   650: iload 7
    //   652: ifne +622 -> 1274
    //   655: iload 10
    //   657: istore_1
    //   658: aload_0
    //   659: getfield 145	rx/c/a/o:e	Lrx/c/a/n;
    //   662: iload 4
    //   664: ineg
    //   665: i2l
    //   666: invokevirtual 160	rx/c/a/n:addAndGet	(J)J
    //   669: lstore 13
    //   671: iload 10
    //   673: istore_1
    //   674: aload 22
    //   676: iload 4
    //   678: i2l
    //   679: invokevirtual 251	rx/c/a/m:b	(J)V
    //   682: goto +510 -> 1192
    //   685: iload 10
    //   687: istore_1
    //   688: aload 22
    //   690: getfield 253	rx/c/a/m:d	Z
    //   693: istore 17
    //   695: iload 10
    //   697: istore_1
    //   698: aload 22
    //   700: getfield 247	rx/c/a/m:e	Lrx/c/d/f;
    //   703: astore 18
    //   705: iload_3
    //   706: istore_1
    //   707: iload_2
    //   708: istore 4
    //   710: iload 17
    //   712: ifeq +516 -> 1228
    //   715: aload 18
    //   717: ifnull +24 -> 741
    //   720: iload 10
    //   722: istore_1
    //   723: aload 18
    //   725: getfield 255	rx/c/d/f:a	Ljava/util/Queue;
    //   728: astore 18
    //   730: aload 18
    //   732: ifnonnull +115 -> 847
    //   735: iconst_1
    //   736: istore 17
    //   738: goto +477 -> 1215
    //   741: iload 10
    //   743: istore_1
    //   744: aload 22
    //   746: getfield 247	rx/c/a/m:e	Lrx/c/d/f;
    //   749: astore 18
    //   751: aload 18
    //   753: ifnull +11 -> 764
    //   756: iload 10
    //   758: istore_1
    //   759: aload 18
    //   761: invokevirtual 257	rx/c/d/f:d	()V
    //   764: iload 10
    //   766: istore_1
    //   767: aload_0
    //   768: getfield 81	rx/c/a/o:g	Lrx/f/c;
    //   771: aload 22
    //   773: invokevirtual 259	rx/f/c:b	(Lrx/aa;)V
    //   776: iload 10
    //   778: istore_1
    //   779: aload_0
    //   780: getfield 68	rx/c/a/o:m	Ljava/lang/Object;
    //   783: astore 18
    //   785: iload 10
    //   787: istore_1
    //   788: aload 18
    //   790: monitorenter
    //   791: aload_0
    //   792: getfield 70	rx/c/a/o:n	[Lrx/c/a/m;
    //   795: astore 19
    //   797: aload 19
    //   799: arraylength
    //   800: istore_3
    //   801: iconst_0
    //   802: istore_1
    //   803: iload_1
    //   804: iload_3
    //   805: if_icmpge +242 -> 1047
    //   808: aload 22
    //   810: aload 19
    //   812: iload_1
    //   813: aaload
    //   814: invokevirtual 262	java/lang/Object:equals	(Ljava/lang/Object;)Z
    //   817: ifeq +45 -> 862
    //   820: iload_1
    //   821: ifge +48 -> 869
    //   824: aload 18
    //   826: monitorexit
    //   827: iload 10
    //   829: istore_1
    //   830: aload_0
    //   831: invokespecial 229	rx/c/a/o:i	()Z
    //   834: ifne +227 -> 1061
    //   837: iload_2
    //   838: iconst_1
    //   839: iadd
    //   840: istore 4
    //   842: iconst_1
    //   843: istore_1
    //   844: goto +384 -> 1228
    //   847: iload 10
    //   849: istore_1
    //   850: aload 18
    //   852: invokeinterface 127 1 0
    //   857: istore 17
    //   859: goto +356 -> 1215
    //   862: iload_1
    //   863: iconst_1
    //   864: iadd
    //   865: istore_1
    //   866: goto -63 -> 803
    //   869: iload_3
    //   870: iconst_1
    //   871: if_icmpne +27 -> 898
    //   874: aload_0
    //   875: getstatic 45	rx/c/a/o:r	[Lrx/c/a/m;
    //   878: putfield 70	rx/c/a/o:n	[Lrx/c/a/m;
    //   881: aload 18
    //   883: monitorexit
    //   884: goto -57 -> 827
    //   887: astore 19
    //   889: aload 18
    //   891: monitorexit
    //   892: iload 10
    //   894: istore_1
    //   895: aload 19
    //   897: athrow
    //   898: iload_3
    //   899: iconst_1
    //   900: isub
    //   901: anewarray 43	rx/c/a/m
    //   904: astore 22
    //   906: aload 19
    //   908: iconst_0
    //   909: aload 22
    //   911: iconst_0
    //   912: iload_1
    //   913: invokestatic 220	java/lang/System:arraycopy	(Ljava/lang/Object;ILjava/lang/Object;II)V
    //   916: aload 19
    //   918: iload_1
    //   919: iconst_1
    //   920: iadd
    //   921: aload 22
    //   923: iload_1
    //   924: iload_3
    //   925: iload_1
    //   926: isub
    //   927: iconst_1
    //   928: isub
    //   929: invokestatic 220	java/lang/System:arraycopy	(Ljava/lang/Object;ILjava/lang/Object;II)V
    //   932: aload_0
    //   933: aload 22
    //   935: putfield 70	rx/c/a/o:n	[Lrx/c/a/m;
    //   938: aload 18
    //   940: monitorexit
    //   941: goto -114 -> 827
    //   944: iload 10
    //   946: istore_1
    //   947: aload_0
    //   948: iload 8
    //   950: putfield 242	rx/c/a/o:q	I
    //   953: iload 10
    //   955: istore_1
    //   956: aload_0
    //   957: aload 21
    //   959: iload 8
    //   961: aaload
    //   962: getfield 244	rx/c/a/m:b	J
    //   965: putfield 240	rx/c/a/o:p	J
    //   968: iload 5
    //   970: ifle +13 -> 983
    //   973: iload 10
    //   975: istore_1
    //   976: aload_0
    //   977: iload 5
    //   979: i2l
    //   980: invokevirtual 76	rx/c/a/o:a	(J)V
    //   983: iload 6
    //   985: ifne -970 -> 15
    //   988: iload 10
    //   990: istore_1
    //   991: aload_0
    //   992: monitorenter
    //   993: iload 11
    //   995: istore_1
    //   996: aload_0
    //   997: getfield 162	rx/c/a/o:l	Z
    //   1000: ifne +24 -> 1024
    //   1003: iconst_1
    //   1004: istore_2
    //   1005: iload_2
    //   1006: istore_1
    //   1007: aload_0
    //   1008: iconst_0
    //   1009: putfield 152	rx/c/a/o:k	Z
    //   1012: iload_2
    //   1013: istore_1
    //   1014: aload_0
    //   1015: monitorexit
    //   1016: return
    //   1017: astore 18
    //   1019: aload_0
    //   1020: monitorexit
    //   1021: aload 18
    //   1023: athrow
    //   1024: iload 11
    //   1026: istore_1
    //   1027: aload_0
    //   1028: iconst_0
    //   1029: putfield 162	rx/c/a/o:l	Z
    //   1032: iload 11
    //   1034: istore_1
    //   1035: aload_0
    //   1036: monitorexit
    //   1037: goto -1022 -> 15
    //   1040: astore 18
    //   1042: aload_0
    //   1043: monitorexit
    //   1044: aload 18
    //   1046: athrow
    //   1047: iconst_m1
    //   1048: istore_1
    //   1049: goto -229 -> 820
    //   1052: iconst_0
    //   1053: istore 6
    //   1055: iload_2
    //   1056: istore 5
    //   1058: goto -90 -> 968
    //   1061: return
    //   1062: iconst_0
    //   1063: istore_1
    //   1064: iconst_0
    //   1065: istore_2
    //   1066: lload 13
    //   1068: lstore 15
    //   1070: aload 21
    //   1072: ifnull -848 -> 224
    //   1075: lload 13
    //   1077: lstore 15
    //   1079: iconst_0
    //   1080: istore_2
    //   1081: aconst_null
    //   1082: astore 18
    //   1084: iload_1
    //   1085: istore_3
    //   1086: lload 15
    //   1088: lstore 13
    //   1090: goto -1028 -> 62
    //   1093: iload_2
    //   1094: ifle +13 -> 1107
    //   1097: iload 7
    //   1099: ifeq -776 -> 323
    //   1102: ldc2_w 72
    //   1105: lstore 13
    //   1107: iload_3
    //   1108: istore_2
    //   1109: lload 13
    //   1111: lstore 15
    //   1113: lload 13
    //   1115: lconst_0
    //   1116: lcmp
    //   1117: ifeq -893 -> 224
    //   1120: iload_3
    //   1121: istore_1
    //   1122: lload 13
    //   1124: lstore 15
    //   1126: aload 19
    //   1128: ifnonnull -49 -> 1079
    //   1131: iload_3
    //   1132: istore_2
    //   1133: lload 13
    //   1135: lstore 15
    //   1137: goto -913 -> 224
    //   1140: iload 4
    //   1142: istore_3
    //   1143: iload 12
    //   1145: iload 4
    //   1147: if_icmpgt +5 -> 1152
    //   1150: iconst_0
    //   1151: istore_3
    //   1152: iconst_0
    //   1153: istore 4
    //   1155: goto -753 -> 402
    //   1158: iload 4
    //   1160: iconst_1
    //   1161: iadd
    //   1162: istore 4
    //   1164: goto -762 -> 402
    //   1167: iconst_0
    //   1168: istore 9
    //   1170: iload_3
    //   1171: istore 8
    //   1173: iconst_0
    //   1174: istore_3
    //   1175: lload 15
    //   1177: lstore 13
    //   1179: goto -712 -> 467
    //   1182: iconst_0
    //   1183: istore 4
    //   1185: lload 15
    //   1187: lstore 13
    //   1189: goto -682 -> 507
    //   1192: lload 13
    //   1194: lconst_0
    //   1195: lcmp
    //   1196: ifeq -511 -> 685
    //   1199: aload 18
    //   1201: astore 19
    //   1203: lload 13
    //   1205: lstore 15
    //   1207: aload 18
    //   1209: ifnonnull -27 -> 1182
    //   1212: goto -527 -> 685
    //   1215: iload_3
    //   1216: istore_1
    //   1217: iload_2
    //   1218: istore 4
    //   1220: iload 17
    //   1222: ifeq +6 -> 1228
    //   1225: goto -484 -> 741
    //   1228: iload_1
    //   1229: istore 6
    //   1231: iload 4
    //   1233: istore 5
    //   1235: lload 13
    //   1237: lconst_0
    //   1238: lcmp
    //   1239: ifeq -295 -> 944
    //   1242: iload 8
    //   1244: iconst_1
    //   1245: iadd
    //   1246: istore_3
    //   1247: iload_3
    //   1248: istore_2
    //   1249: iload_3
    //   1250: iload 12
    //   1252: if_icmpne +5 -> 1257
    //   1255: iconst_0
    //   1256: istore_2
    //   1257: iload 9
    //   1259: iconst_1
    //   1260: iadd
    //   1261: istore 9
    //   1263: iload_2
    //   1264: istore 8
    //   1266: iload_1
    //   1267: istore_3
    //   1268: iload 4
    //   1270: istore_2
    //   1271: goto -804 -> 467
    //   1274: ldc2_w 72
    //   1277: lstore 13
    //   1279: goto -608 -> 671
    //
    // Exception table:
    //   from	to	target	type
    //   117	124	147	java/lang/Throwable
    //   9	15	188	finally
    //   18	25	188	finally
    //   29	35	188	finally
    //   38	47	188	finally
    //   76	85	188	finally
    //   88	95	188	finally
    //   107	114	188	finally
    //   117	124	188	finally
    //   152	159	188	finally
    //   162	167	188	finally
    //   171	178	188	finally
    //   180	187	188	finally
    //   209	221	188	finally
    //   227	233	188	finally
    //   236	242	188	finally
    //   245	251	188	finally
    //   254	259	188	finally
    //   272	282	188	finally
    //   290	296	188	finally
    //   304	314	188	finally
    //   317	322	188	finally
    //   326	338	188	finally
    //   344	348	188	finally
    //   357	363	188	finally
    //   366	372	188	finally
    //   385	399	188	finally
    //   412	425	188	finally
    //   445	450	188	finally
    //   453	464	188	finally
    //   483	490	188	finally
    //   521	528	188	finally
    //   531	538	188	finally
    //   550	557	188	finally
    //   569	576	188	finally
    //   579	586	188	finally
    //   607	612	188	finally
    //   621	628	188	finally
    //   633	640	188	finally
    //   642	645	188	finally
    //   658	671	188	finally
    //   674	682	188	finally
    //   688	695	188	finally
    //   698	705	188	finally
    //   723	730	188	finally
    //   744	751	188	finally
    //   759	764	188	finally
    //   767	776	188	finally
    //   779	785	188	finally
    //   788	791	188	finally
    //   830	837	188	finally
    //   850	859	188	finally
    //   895	898	188	finally
    //   947	953	188	finally
    //   956	968	188	finally
    //   976	983	188	finally
    //   991	993	188	finally
    //   1021	1024	188	finally
    //   579	586	601	java/lang/Throwable
    //   612	619	629	finally
    //   791	801	887	finally
    //   808	820	887	finally
    //   824	827	887	finally
    //   874	884	887	finally
    //   889	892	887	finally
    //   898	941	887	finally
    //   996	1003	1017	finally
    //   1007	1012	1017	finally
    //   1014	1016	1017	finally
    //   1019	1021	1017	finally
    //   1027	1032	1017	finally
    //   1035	1037	1017	finally
    //   196	203	1040	finally
    //   1042	1044	1040	finally
  }
}

/* Location:           C:\crazyd\work\ustone\odm2016031702\baidu\android\nut-dex2jar.jar
 * Qualified Name:     rx.c.a.o
 * JD-Core Version:    0.6.2
 */