package com.squareup.picasso;

import android.content.ContentResolver;
import android.content.ContentUris;
import android.content.Context;
import android.graphics.Bitmap;
import android.graphics.BitmapFactory.Options;
import android.net.Uri;
import android.provider.MediaStore.Images.Thumbnails;
import android.provider.MediaStore.Video.Thumbnails;
import java.io.IOException;

class MediaStoreRequestHandler extends ContentStreamRequestHandler
{
  private static final String[] CONTENT_ORIENTATION = { "orientation" };

  MediaStoreRequestHandler(Context paramContext)
  {
    super(paramContext);
  }

  // ERROR //
  static int getExifOrientation(ContentResolver paramContentResolver, Uri paramUri)
  {
    // Byte code:
    //   0: aload_0
    //   1: aload_1
    //   2: getstatic 14	com/squareup/picasso/MediaStoreRequestHandler:CONTENT_ORIENTATION	[Ljava/lang/String;
    //   5: aconst_null
    //   6: aconst_null
    //   7: aconst_null
    //   8: invokevirtual 29	android/content/ContentResolver:query	(Landroid/net/Uri;[Ljava/lang/String;Ljava/lang/String;[Ljava/lang/String;Ljava/lang/String;)Landroid/database/Cursor;
    //   11: astore_0
    //   12: aload_0
    //   13: ifnull +16 -> 29
    //   16: aload_0
    //   17: invokeinterface 35 1 0
    //   22: istore 4
    //   24: iload 4
    //   26: ifne +17 -> 43
    //   29: aload_0
    //   30: ifnull +9 -> 39
    //   33: aload_0
    //   34: invokeinterface 38 1 0
    //   39: iconst_0
    //   40: istore_2
    //   41: iload_2
    //   42: ireturn
    //   43: aload_0
    //   44: iconst_0
    //   45: invokeinterface 42 2 0
    //   50: istore_3
    //   51: iload_3
    //   52: istore_2
    //   53: aload_0
    //   54: ifnull -13 -> 41
    //   57: aload_0
    //   58: invokeinterface 38 1 0
    //   63: iload_3
    //   64: ireturn
    //   65: astore_0
    //   66: aconst_null
    //   67: astore_0
    //   68: aload_0
    //   69: ifnull +9 -> 78
    //   72: aload_0
    //   73: invokeinterface 38 1 0
    //   78: iconst_0
    //   79: ireturn
    //   80: astore_1
    //   81: aconst_null
    //   82: astore_0
    //   83: aload_0
    //   84: ifnull +9 -> 93
    //   87: aload_0
    //   88: invokeinterface 38 1 0
    //   93: aload_1
    //   94: athrow
    //   95: astore_1
    //   96: goto -13 -> 83
    //   99: astore_1
    //   100: goto -32 -> 68
    //
    // Exception table:
    //   from	to	target	type
    //   0	12	65	java/lang/RuntimeException
    //   0	12	80	finally
    //   16	24	95	finally
    //   43	51	95	finally
    //   16	24	99	java/lang/RuntimeException
    //   43	51	99	java/lang/RuntimeException
  }

  static MediaStoreRequestHandler.PicassoKind getPicassoKind(int paramInt1, int paramInt2)
  {
    if ((paramInt1 <= MediaStoreRequestHandler.PicassoKind.MICRO.width) && (paramInt2 <= MediaStoreRequestHandler.PicassoKind.MICRO.height))
      return MediaStoreRequestHandler.PicassoKind.MICRO;
    if ((paramInt1 <= MediaStoreRequestHandler.PicassoKind.MINI.width) && (paramInt2 <= MediaStoreRequestHandler.PicassoKind.MINI.height))
      return MediaStoreRequestHandler.PicassoKind.MINI;
    return MediaStoreRequestHandler.PicassoKind.FULL;
  }

  public boolean canHandleRequest(Request paramRequest)
  {
    paramRequest = paramRequest.uri;
    return ("content".equals(paramRequest.getScheme())) && ("media".equals(paramRequest.getAuthority()));
  }

  public RequestHandler.Result load(Request paramRequest, int paramInt)
    throws IOException
  {
    Object localObject1 = this.context.getContentResolver();
    int i = getExifOrientation((ContentResolver)localObject1, paramRequest.uri);
    Object localObject2 = ((ContentResolver)localObject1).getType(paramRequest.uri);
    if ((localObject2 != null) && (((String)localObject2).startsWith("video/")))
      paramInt = 1;
    while (paramRequest.hasSize())
    {
      localObject2 = getPicassoKind(paramRequest.targetWidth, paramRequest.targetHeight);
      if ((paramInt == 0) && (localObject2 == MediaStoreRequestHandler.PicassoKind.FULL))
      {
        return new RequestHandler.Result(null, getInputStream(paramRequest), Picasso.LoadedFrom.DISK, i);
        paramInt = 0;
      }
      else
      {
        long l = ContentUris.parseId(paramRequest.uri);
        BitmapFactory.Options localOptions = createBitmapOptions(paramRequest);
        localOptions.inJustDecodeBounds = true;
        calculateInSampleSize(paramRequest.targetWidth, paramRequest.targetHeight, ((MediaStoreRequestHandler.PicassoKind)localObject2).width, ((MediaStoreRequestHandler.PicassoKind)localObject2).height, localOptions, paramRequest);
        if (paramInt != 0)
          if (localObject2 == MediaStoreRequestHandler.PicassoKind.FULL)
            paramInt = 1;
        for (localObject1 = MediaStore.Video.Thumbnails.getThumbnail((ContentResolver)localObject1, l, paramInt, localOptions); ; localObject1 = MediaStore.Images.Thumbnails.getThumbnail((ContentResolver)localObject1, l, ((MediaStoreRequestHandler.PicassoKind)localObject2).androidKind, localOptions))
        {
          if (localObject1 == null)
            break label221;
          return new RequestHandler.Result((Bitmap)localObject1, null, Picasso.LoadedFrom.DISK, i);
          paramInt = ((MediaStoreRequestHandler.PicassoKind)localObject2).androidKind;
          break;
        }
      }
    }
    label221: return new RequestHandler.Result(null, getInputStream(paramRequest), Picasso.LoadedFrom.DISK, i);
  }
}

/* Location:           C:\crazyd\work\ustone\odm2016031702\baidu\android\nut-dex2jar.jar
 * Qualified Name:     com.squareup.picasso.MediaStoreRequestHandler
 * JD-Core Version:    0.6.2
 */