package okhttp3;

import java.io.IOException;
import okhttp3.internal.b.c;
import okhttp3.internal.http.ab;
import okhttp3.internal.http.p;
import okhttp3.internal.http.u;
import okhttp3.internal.o;

final class aq
  implements g
{
  final am a;
  volatile boolean b;
  at c;
  p d;
  private boolean e;

  protected aq(am paramam, at paramat)
  {
    this.a = paramam;
    this.c = paramat;
  }

  public final at a()
  {
    return this.c;
  }

  // ERROR //
  final az a(at paramat, boolean paramBoolean)
    throws IOException
  {
    // Byte code:
    //   0: aload_1
    //   1: getfield 38	okhttp3/at:d	Lokhttp3/av;
    //   4: astore 16
    //   6: aload 16
    //   8: ifnull +3194 -> 3202
    //   11: aload_1
    //   12: invokevirtual 41	okhttp3/at:a	()Lokhttp3/au;
    //   15: astore_1
    //   16: aload 16
    //   18: invokevirtual 47	okhttp3/av:contentType	()Lokhttp3/ai;
    //   21: astore 17
    //   23: aload 17
    //   25: ifnull +15 -> 40
    //   28: aload_1
    //   29: ldc 49
    //   31: aload 17
    //   33: invokevirtual 55	okhttp3/ai:toString	()Ljava/lang/String;
    //   36: invokevirtual 60	okhttp3/au:a	(Ljava/lang/String;Ljava/lang/String;)Lokhttp3/au;
    //   39: pop
    //   40: aload 16
    //   42: invokevirtual 64	okhttp3/av:contentLength	()J
    //   45: lstore 6
    //   47: lload 6
    //   49: ldc2_w 65
    //   52: lcmp
    //   53: ifeq +80 -> 133
    //   56: aload_1
    //   57: ldc 68
    //   59: lload 6
    //   61: invokestatic 73	java/lang/Long:toString	(J)Ljava/lang/String;
    //   64: invokevirtual 60	okhttp3/au:a	(Ljava/lang/String;Ljava/lang/String;)Lokhttp3/au;
    //   67: pop
    //   68: aload_1
    //   69: ldc 75
    //   71: invokevirtual 78	okhttp3/au:b	(Ljava/lang/String;)Lokhttp3/au;
    //   74: pop
    //   75: aload_1
    //   76: invokevirtual 80	okhttp3/au:a	()Lokhttp3/at;
    //   79: astore_1
    //   80: aload_0
    //   81: new 82	okhttp3/internal/http/p
    //   84: dup
    //   85: aload_0
    //   86: getfield 22	okhttp3/aq:a	Lokhttp3/am;
    //   89: aload_1
    //   90: iconst_0
    //   91: iconst_0
    //   92: iload_2
    //   93: aconst_null
    //   94: aconst_null
    //   95: invokespecial 85	okhttp3/internal/http/p:<init>	(Lokhttp3/am;Lokhttp3/at;ZZZLokhttp3/internal/http/ab;Lokhttp3/az;)V
    //   98: putfield 87	okhttp3/aq:d	Lokhttp3/internal/http/p;
    //   101: iconst_0
    //   102: istore_3
    //   103: aload_0
    //   104: getfield 89	okhttp3/aq:b	Z
    //   107: ifeq +45 -> 152
    //   110: aload_0
    //   111: getfield 87	okhttp3/aq:d	Lokhttp3/internal/http/p;
    //   114: getfield 92	okhttp3/internal/http/p:c	Lokhttp3/internal/http/ab;
    //   117: iconst_0
    //   118: iconst_1
    //   119: iconst_0
    //   120: invokevirtual 97	okhttp3/internal/http/ab:a	(ZZZ)V
    //   123: new 29	java/io/IOException
    //   126: dup
    //   127: ldc 99
    //   129: invokespecial 102	java/io/IOException:<init>	(Ljava/lang/String;)V
    //   132: athrow
    //   133: aload_1
    //   134: ldc 75
    //   136: ldc 104
    //   138: invokevirtual 60	okhttp3/au:a	(Ljava/lang/String;Ljava/lang/String;)Lokhttp3/au;
    //   141: pop
    //   142: aload_1
    //   143: ldc 68
    //   145: invokevirtual 78	okhttp3/au:b	(Ljava/lang/String;)Lokhttp3/au;
    //   148: pop
    //   149: goto -74 -> 75
    //   152: aload_0
    //   153: getfield 87	okhttp3/aq:d	Lokhttp3/internal/http/p;
    //   156: astore 18
    //   158: aload 18
    //   160: getfield 108	okhttp3/internal/http/p:r	Lokhttp3/internal/http/b;
    //   163: ifnonnull +431 -> 594
    //   166: aload 18
    //   168: getfield 111	okhttp3/internal/http/p:e	Lokhttp3/internal/http/u;
    //   171: ifnull +39 -> 210
    //   174: new 113	java/lang/IllegalStateException
    //   177: dup
    //   178: invokespecial 114	java/lang/IllegalStateException:<init>	()V
    //   181: athrow
    //   182: astore_1
    //   183: aload_1
    //   184: invokevirtual 117	okhttp3/internal/http/RequestException:a	()Ljava/io/IOException;
    //   187: athrow
    //   188: astore_1
    //   189: iconst_1
    //   190: istore_3
    //   191: iload_3
    //   192: ifeq +16 -> 208
    //   195: aload_0
    //   196: getfield 87	okhttp3/aq:d	Lokhttp3/internal/http/p;
    //   199: invokevirtual 120	okhttp3/internal/http/p:b	()Lokhttp3/internal/http/ab;
    //   202: iconst_0
    //   203: iconst_1
    //   204: iconst_0
    //   205: invokevirtual 97	okhttp3/internal/http/ab:a	(ZZZ)V
    //   208: aload_1
    //   209: athrow
    //   210: aload 18
    //   212: getfield 123	okhttp3/internal/http/p:i	Lokhttp3/at;
    //   215: astore_1
    //   216: aload_1
    //   217: invokevirtual 41	okhttp3/at:a	()Lokhttp3/au;
    //   220: astore 16
    //   222: aload_1
    //   223: ldc 125
    //   225: invokevirtual 128	okhttp3/at:a	(Ljava/lang/String;)Ljava/lang/String;
    //   228: ifnonnull +19 -> 247
    //   231: aload 16
    //   233: ldc 125
    //   235: aload_1
    //   236: getfield 131	okhttp3/at:a	Lokhttp3/ad;
    //   239: iconst_0
    //   240: invokestatic 136	okhttp3/internal/o:a	(Lokhttp3/ad;Z)Ljava/lang/String;
    //   243: invokevirtual 60	okhttp3/au:a	(Ljava/lang/String;Ljava/lang/String;)Lokhttp3/au;
    //   246: pop
    //   247: aload_1
    //   248: ldc 138
    //   250: invokevirtual 128	okhttp3/at:a	(Ljava/lang/String;)Ljava/lang/String;
    //   253: ifnonnull +13 -> 266
    //   256: aload 16
    //   258: ldc 138
    //   260: ldc 140
    //   262: invokevirtual 60	okhttp3/au:a	(Ljava/lang/String;Ljava/lang/String;)Lokhttp3/au;
    //   265: pop
    //   266: aload_1
    //   267: ldc 142
    //   269: invokevirtual 128	okhttp3/at:a	(Ljava/lang/String;)Ljava/lang/String;
    //   272: ifnonnull +19 -> 291
    //   275: aload 18
    //   277: iconst_1
    //   278: putfield 145	okhttp3/internal/http/p:g	Z
    //   281: aload 16
    //   283: ldc 142
    //   285: ldc 147
    //   287: invokevirtual 60	okhttp3/au:a	(Ljava/lang/String;Ljava/lang/String;)Lokhttp3/au;
    //   290: pop
    //   291: aload 18
    //   293: getfield 149	okhttp3/internal/http/p:b	Lokhttp3/am;
    //   296: getfield 155	okhttp3/am:h	Lokhttp3/t;
    //   299: invokeinterface 160 1 0
    //   304: astore 17
    //   306: aload 17
    //   308: invokeinterface 166 1 0
    //   313: ifne +16 -> 329
    //   316: aload 16
    //   318: ldc 168
    //   320: aload 17
    //   322: invokestatic 171	okhttp3/internal/http/p:a	(Ljava/util/List;)Ljava/lang/String;
    //   325: invokevirtual 60	okhttp3/au:a	(Ljava/lang/String;Ljava/lang/String;)Lokhttp3/au;
    //   328: pop
    //   329: aload_1
    //   330: ldc 173
    //   332: invokevirtual 128	okhttp3/at:a	(Ljava/lang/String;)Ljava/lang/String;
    //   335: ifnonnull +13 -> 348
    //   338: aload 16
    //   340: ldc 173
    //   342: ldc 175
    //   344: invokevirtual 60	okhttp3/au:a	(Ljava/lang/String;Ljava/lang/String;)Lokhttp3/au;
    //   347: pop
    //   348: aload 16
    //   350: invokevirtual 80	okhttp3/au:a	()Lokhttp3/at;
    //   353: astore 19
    //   355: getstatic 180	okhttp3/internal/f:b	Lokhttp3/internal/f;
    //   358: aload 18
    //   360: getfield 149	okhttp3/internal/http/p:b	Lokhttp3/am;
    //   363: invokevirtual 183	okhttp3/internal/f:a	(Lokhttp3/am;)Lokhttp3/internal/g;
    //   366: astore_1
    //   367: aload_1
    //   368: ifnull +301 -> 669
    //   371: aload_1
    //   372: invokeinterface 188 1 0
    //   377: astore 16
    //   379: new 190	okhttp3/internal/http/c
    //   382: dup
    //   383: invokestatic 195	java/lang/System:currentTimeMillis	()J
    //   386: aload 19
    //   388: aload 16
    //   390: invokespecial 198	okhttp3/internal/http/c:<init>	(JLokhttp3/at;Lokhttp3/az;)V
    //   393: astore 20
    //   395: aload 20
    //   397: getfield 201	okhttp3/internal/http/c:c	Lokhttp3/az;
    //   400: ifnonnull +275 -> 675
    //   403: new 203	okhttp3/internal/http/b
    //   406: dup
    //   407: aload 20
    //   409: getfield 205	okhttp3/internal/http/c:b	Lokhttp3/at;
    //   412: aconst_null
    //   413: iconst_0
    //   414: invokespecial 208	okhttp3/internal/http/b:<init>	(Lokhttp3/at;Lokhttp3/az;B)V
    //   417: astore_1
    //   418: aload_1
    //   419: astore 17
    //   421: aload_1
    //   422: getfield 210	okhttp3/internal/http/b:a	Lokhttp3/at;
    //   425: ifnull +32 -> 457
    //   428: aload_1
    //   429: astore 17
    //   431: aload 20
    //   433: getfield 205	okhttp3/internal/http/c:b	Lokhttp3/at;
    //   436: invokevirtual 213	okhttp3/at:b	()Lokhttp3/e;
    //   439: getfield 218	okhttp3/e:k	Z
    //   442: ifeq +15 -> 457
    //   445: new 203	okhttp3/internal/http/b
    //   448: dup
    //   449: aconst_null
    //   450: aconst_null
    //   451: iconst_0
    //   452: invokespecial 208	okhttp3/internal/http/b:<init>	(Lokhttp3/at;Lokhttp3/az;B)V
    //   455: astore 17
    //   457: aload 18
    //   459: aload 17
    //   461: putfield 108	okhttp3/internal/http/p:r	Lokhttp3/internal/http/b;
    //   464: aload 18
    //   466: aload 18
    //   468: getfield 108	okhttp3/internal/http/p:r	Lokhttp3/internal/http/b;
    //   471: getfield 210	okhttp3/internal/http/b:a	Lokhttp3/at;
    //   474: putfield 221	okhttp3/internal/http/p:j	Lokhttp3/at;
    //   477: aload 18
    //   479: aload 18
    //   481: getfield 108	okhttp3/internal/http/p:r	Lokhttp3/internal/http/b;
    //   484: getfield 223	okhttp3/internal/http/b:b	Lokhttp3/az;
    //   487: putfield 225	okhttp3/internal/http/p:k	Lokhttp3/az;
    //   490: aload 16
    //   492: ifnull +19 -> 511
    //   495: aload 18
    //   497: getfield 225	okhttp3/internal/http/p:k	Lokhttp3/az;
    //   500: ifnonnull +11 -> 511
    //   503: aload 16
    //   505: getfield 231	okhttp3/az:f	Lokhttp3/bb;
    //   508: invokestatic 234	okhttp3/internal/o:a	(Ljava/io/Closeable;)V
    //   511: aload 18
    //   513: getfield 221	okhttp3/internal/http/p:j	Lokhttp3/at;
    //   516: ifnonnull +951 -> 1467
    //   519: aload 18
    //   521: getfield 225	okhttp3/internal/http/p:k	Lokhttp3/az;
    //   524: ifnonnull +943 -> 1467
    //   527: new 236	okhttp3/ba
    //   530: dup
    //   531: invokespecial 237	okhttp3/ba:<init>	()V
    //   534: astore_1
    //   535: aload_1
    //   536: aload 18
    //   538: getfield 123	okhttp3/internal/http/p:i	Lokhttp3/at;
    //   541: putfield 238	okhttp3/ba:a	Lokhttp3/at;
    //   544: aload_1
    //   545: aload 18
    //   547: getfield 240	okhttp3/internal/http/p:d	Lokhttp3/az;
    //   550: invokestatic 243	okhttp3/internal/http/p:a	(Lokhttp3/az;)Lokhttp3/az;
    //   553: invokevirtual 246	okhttp3/ba:c	(Lokhttp3/az;)Lokhttp3/ba;
    //   556: astore_1
    //   557: aload_1
    //   558: getstatic 251	okhttp3/ap:b	Lokhttp3/ap;
    //   561: putfield 252	okhttp3/ba:b	Lokhttp3/ap;
    //   564: aload_1
    //   565: sipush 504
    //   568: putfield 255	okhttp3/ba:c	I
    //   571: aload_1
    //   572: ldc_w 257
    //   575: putfield 260	okhttp3/ba:d	Ljava/lang/String;
    //   578: aload_1
    //   579: getstatic 262	okhttp3/internal/http/p:a	Lokhttp3/bb;
    //   582: putfield 264	okhttp3/ba:g	Lokhttp3/bb;
    //   585: aload 18
    //   587: aload_1
    //   588: invokevirtual 265	okhttp3/ba:a	()Lokhttp3/az;
    //   591: putfield 268	okhttp3/internal/http/p:l	Lokhttp3/az;
    //   594: aload_0
    //   595: getfield 87	okhttp3/aq:d	Lokhttp3/internal/http/p;
    //   598: astore 17
    //   600: aload 17
    //   602: getfield 268	okhttp3/internal/http/p:l	Lokhttp3/az;
    //   605: ifnonnull +1405 -> 2010
    //   608: aload 17
    //   610: getfield 221	okhttp3/internal/http/p:j	Lokhttp3/at;
    //   613: ifnonnull +1203 -> 1816
    //   616: aload 17
    //   618: getfield 225	okhttp3/internal/http/p:k	Lokhttp3/az;
    //   621: ifnonnull +1195 -> 1816
    //   624: new 113	java/lang/IllegalStateException
    //   627: dup
    //   628: ldc_w 270
    //   631: invokespecial 271	java/lang/IllegalStateException:<init>	(Ljava/lang/String;)V
    //   634: athrow
    //   635: astore_1
    //   636: aload_0
    //   637: getfield 87	okhttp3/aq:d	Lokhttp3/internal/http/p;
    //   640: aload_1
    //   641: getfield 274	okhttp3/internal/http/RouteException:b	Ljava/io/IOException;
    //   644: invokevirtual 277	okhttp3/internal/http/p:a	(Ljava/io/IOException;)Lokhttp3/internal/http/p;
    //   647: astore 16
    //   649: aload 16
    //   651: ifnull +1921 -> 2572
    //   654: aload_0
    //   655: aload 16
    //   657: putfield 87	okhttp3/aq:d	Lokhttp3/internal/http/p;
    //   660: goto -557 -> 103
    //   663: iconst_0
    //   664: istore_3
    //   665: astore_1
    //   666: goto -475 -> 191
    //   669: aconst_null
    //   670: astore 16
    //   672: goto -293 -> 379
    //   675: aload 20
    //   677: getfield 205	okhttp3/internal/http/c:b	Lokhttp3/at;
    //   680: invokevirtual 279	okhttp3/at:c	()Z
    //   683: ifeq +57 -> 740
    //   686: aload 20
    //   688: getfield 201	okhttp3/internal/http/c:c	Lokhttp3/az;
    //   691: getfield 282	okhttp3/az:d	Lokhttp3/aa;
    //   694: ifnonnull +46 -> 740
    //   697: new 203	okhttp3/internal/http/b
    //   700: dup
    //   701: aload 20
    //   703: getfield 205	okhttp3/internal/http/c:b	Lokhttp3/at;
    //   706: aconst_null
    //   707: iconst_0
    //   708: invokespecial 208	okhttp3/internal/http/b:<init>	(Lokhttp3/at;Lokhttp3/az;B)V
    //   711: astore_1
    //   712: goto -294 -> 418
    //   715: astore_1
    //   716: aload_0
    //   717: getfield 87	okhttp3/aq:d	Lokhttp3/internal/http/p;
    //   720: aload_1
    //   721: invokevirtual 277	okhttp3/internal/http/p:a	(Ljava/io/IOException;)Lokhttp3/internal/http/p;
    //   724: astore 16
    //   726: aload 16
    //   728: ifnull +1849 -> 2577
    //   731: aload_0
    //   732: aload 16
    //   734: putfield 87	okhttp3/aq:d	Lokhttp3/internal/http/p;
    //   737: goto -634 -> 103
    //   740: aload 20
    //   742: getfield 201	okhttp3/internal/http/c:c	Lokhttp3/az;
    //   745: aload 20
    //   747: getfield 205	okhttp3/internal/http/c:b	Lokhttp3/at;
    //   750: invokestatic 285	okhttp3/internal/http/b:a	(Lokhttp3/az;Lokhttp3/at;)Z
    //   753: ifne +21 -> 774
    //   756: new 203	okhttp3/internal/http/b
    //   759: dup
    //   760: aload 20
    //   762: getfield 205	okhttp3/internal/http/c:b	Lokhttp3/at;
    //   765: aconst_null
    //   766: iconst_0
    //   767: invokespecial 208	okhttp3/internal/http/b:<init>	(Lokhttp3/at;Lokhttp3/az;B)V
    //   770: astore_1
    //   771: goto -353 -> 418
    //   774: aload 20
    //   776: getfield 205	okhttp3/internal/http/c:b	Lokhttp3/at;
    //   779: invokevirtual 213	okhttp3/at:b	()Lokhttp3/e;
    //   782: astore 17
    //   784: aload 17
    //   786: getfield 287	okhttp3/e:c	Z
    //   789: ifne +14 -> 803
    //   792: aload 20
    //   794: getfield 205	okhttp3/internal/http/c:b	Lokhttp3/at;
    //   797: invokestatic 290	okhttp3/internal/http/c:a	(Lokhttp3/at;)Z
    //   800: ifeq +21 -> 821
    //   803: new 203	okhttp3/internal/http/b
    //   806: dup
    //   807: aload 20
    //   809: getfield 205	okhttp3/internal/http/c:b	Lokhttp3/at;
    //   812: aconst_null
    //   813: iconst_0
    //   814: invokespecial 208	okhttp3/internal/http/b:<init>	(Lokhttp3/at;Lokhttp3/az;B)V
    //   817: astore_1
    //   818: goto -400 -> 418
    //   821: aload 20
    //   823: getfield 293	okhttp3/internal/http/c:d	Ljava/util/Date;
    //   826: ifnull +2379 -> 3205
    //   829: lconst_0
    //   830: aload 20
    //   832: getfield 296	okhttp3/internal/http/c:j	J
    //   835: aload 20
    //   837: getfield 293	okhttp3/internal/http/c:d	Ljava/util/Date;
    //   840: invokevirtual 301	java/util/Date:getTime	()J
    //   843: lsub
    //   844: invokestatic 307	java/lang/Math:max	(JJ)J
    //   847: lstore 6
    //   849: lload 6
    //   851: lstore 8
    //   853: aload 20
    //   855: getfield 309	okhttp3/internal/http/c:l	I
    //   858: iconst_m1
    //   859: if_icmpeq +22 -> 881
    //   862: lload 6
    //   864: getstatic 315	java/util/concurrent/TimeUnit:SECONDS	Ljava/util/concurrent/TimeUnit;
    //   867: aload 20
    //   869: getfield 309	okhttp3/internal/http/c:l	I
    //   872: i2l
    //   873: invokevirtual 319	java/util/concurrent/TimeUnit:toMillis	(J)J
    //   876: invokestatic 307	java/lang/Math:max	(JJ)J
    //   879: lstore 8
    //   881: lload 8
    //   883: aload 20
    //   885: getfield 296	okhttp3/internal/http/c:j	J
    //   888: aload 20
    //   890: getfield 321	okhttp3/internal/http/c:i	J
    //   893: lsub
    //   894: ladd
    //   895: aload 20
    //   897: getfield 323	okhttp3/internal/http/c:a	J
    //   900: aload 20
    //   902: getfield 296	okhttp3/internal/http/c:j	J
    //   905: lsub
    //   906: ladd
    //   907: lstore 14
    //   909: aload 20
    //   911: getfield 201	okhttp3/internal/http/c:c	Lokhttp3/az;
    //   914: invokevirtual 325	okhttp3/az:c	()Lokhttp3/e;
    //   917: astore_1
    //   918: aload_1
    //   919: getfield 327	okhttp3/e:e	I
    //   922: iconst_m1
    //   923: if_icmpeq +237 -> 1160
    //   926: getstatic 315	java/util/concurrent/TimeUnit:SECONDS	Ljava/util/concurrent/TimeUnit;
    //   929: aload_1
    //   930: getfield 327	okhttp3/e:e	I
    //   933: i2l
    //   934: invokevirtual 319	java/util/concurrent/TimeUnit:toMillis	(J)J
    //   937: lstore 6
    //   939: aload 17
    //   941: getfield 327	okhttp3/e:e	I
    //   944: iconst_m1
    //   945: if_icmpeq +2254 -> 3199
    //   948: lload 6
    //   950: getstatic 315	java/util/concurrent/TimeUnit:SECONDS	Ljava/util/concurrent/TimeUnit;
    //   953: aload 17
    //   955: getfield 327	okhttp3/e:e	I
    //   958: i2l
    //   959: invokevirtual 319	java/util/concurrent/TimeUnit:toMillis	(J)J
    //   962: invokestatic 330	java/lang/Math:min	(JJ)J
    //   965: lstore 6
    //   967: aload 17
    //   969: getfield 332	okhttp3/e:j	I
    //   972: iconst_m1
    //   973: if_icmpeq +2220 -> 3193
    //   976: getstatic 315	java/util/concurrent/TimeUnit:SECONDS	Ljava/util/concurrent/TimeUnit;
    //   979: aload 17
    //   981: getfield 332	okhttp3/e:j	I
    //   984: i2l
    //   985: invokevirtual 319	java/util/concurrent/TimeUnit:toMillis	(J)J
    //   988: lstore 8
    //   990: lconst_0
    //   991: lstore 12
    //   993: aload 20
    //   995: getfield 201	okhttp3/internal/http/c:c	Lokhttp3/az;
    //   998: invokevirtual 325	okhttp3/az:c	()Lokhttp3/e;
    //   1001: astore_1
    //   1002: lload 12
    //   1004: lstore 10
    //   1006: aload_1
    //   1007: getfield 334	okhttp3/e:h	Z
    //   1010: ifne +30 -> 1040
    //   1013: lload 12
    //   1015: lstore 10
    //   1017: aload 17
    //   1019: getfield 336	okhttp3/e:i	I
    //   1022: iconst_m1
    //   1023: if_icmpeq +17 -> 1040
    //   1026: getstatic 315	java/util/concurrent/TimeUnit:SECONDS	Ljava/util/concurrent/TimeUnit;
    //   1029: aload 17
    //   1031: getfield 336	okhttp3/e:i	I
    //   1034: i2l
    //   1035: invokevirtual 319	java/util/concurrent/TimeUnit:toMillis	(J)J
    //   1038: lstore 10
    //   1040: aload_1
    //   1041: getfield 287	okhttp3/e:c	Z
    //   1044: ifne +301 -> 1345
    //   1047: lload 14
    //   1049: lload 8
    //   1051: ladd
    //   1052: lload 10
    //   1054: lload 6
    //   1056: ladd
    //   1057: lcmp
    //   1058: ifge +287 -> 1345
    //   1061: aload 20
    //   1063: getfield 201	okhttp3/internal/http/c:c	Lokhttp3/az;
    //   1066: invokevirtual 339	okhttp3/az:b	()Lokhttp3/ba;
    //   1069: astore_1
    //   1070: lload 8
    //   1072: lload 14
    //   1074: ladd
    //   1075: lload 6
    //   1077: lcmp
    //   1078: iflt +14 -> 1092
    //   1081: aload_1
    //   1082: ldc_w 341
    //   1085: ldc_w 343
    //   1088: invokevirtual 346	okhttp3/ba:b	(Ljava/lang/String;Ljava/lang/String;)Lokhttp3/ba;
    //   1091: pop
    //   1092: lload 14
    //   1094: ldc2_w 347
    //   1097: lcmp
    //   1098: ifle +45 -> 1143
    //   1101: aload 20
    //   1103: getfield 201	okhttp3/internal/http/c:c	Lokhttp3/az;
    //   1106: invokevirtual 325	okhttp3/az:c	()Lokhttp3/e;
    //   1109: getfield 327	okhttp3/e:e	I
    //   1112: iconst_m1
    //   1113: if_icmpne +2110 -> 3223
    //   1116: aload 20
    //   1118: getfield 350	okhttp3/internal/http/c:h	Ljava/util/Date;
    //   1121: ifnonnull +2102 -> 3223
    //   1124: iconst_1
    //   1125: istore 4
    //   1127: iload 4
    //   1129: ifeq +14 -> 1143
    //   1132: aload_1
    //   1133: ldc_w 341
    //   1136: ldc_w 352
    //   1139: invokevirtual 346	okhttp3/ba:b	(Ljava/lang/String;Ljava/lang/String;)Lokhttp3/ba;
    //   1142: pop
    //   1143: new 203	okhttp3/internal/http/b
    //   1146: dup
    //   1147: aconst_null
    //   1148: aload_1
    //   1149: invokevirtual 265	okhttp3/ba:a	()Lokhttp3/az;
    //   1152: iconst_0
    //   1153: invokespecial 208	okhttp3/internal/http/b:<init>	(Lokhttp3/at;Lokhttp3/az;B)V
    //   1156: astore_1
    //   1157: goto -739 -> 418
    //   1160: aload 20
    //   1162: getfield 350	okhttp3/internal/http/c:h	Ljava/util/Date;
    //   1165: ifnull +61 -> 1226
    //   1168: aload 20
    //   1170: getfield 293	okhttp3/internal/http/c:d	Ljava/util/Date;
    //   1173: ifnull +43 -> 1216
    //   1176: aload 20
    //   1178: getfield 293	okhttp3/internal/http/c:d	Ljava/util/Date;
    //   1181: invokevirtual 301	java/util/Date:getTime	()J
    //   1184: lstore 6
    //   1186: aload 20
    //   1188: getfield 350	okhttp3/internal/http/c:h	Ljava/util/Date;
    //   1191: invokevirtual 301	java/util/Date:getTime	()J
    //   1194: lload 6
    //   1196: lsub
    //   1197: lstore 8
    //   1199: lload 8
    //   1201: lstore 6
    //   1203: lload 8
    //   1205: lconst_0
    //   1206: lcmp
    //   1207: ifgt -268 -> 939
    //   1210: lconst_0
    //   1211: lstore 6
    //   1213: goto -274 -> 939
    //   1216: aload 20
    //   1218: getfield 296	okhttp3/internal/http/c:j	J
    //   1221: lstore 6
    //   1223: goto -37 -> 1186
    //   1226: aload 20
    //   1228: getfield 354	okhttp3/internal/http/c:f	Ljava/util/Date;
    //   1231: ifnull +1986 -> 3217
    //   1234: aload 20
    //   1236: getfield 201	okhttp3/internal/http/c:c	Lokhttp3/az;
    //   1239: getfield 355	okhttp3/az:a	Lokhttp3/at;
    //   1242: getfield 131	okhttp3/at:a	Lokhttp3/ad;
    //   1245: astore_1
    //   1246: aload_1
    //   1247: getfield 360	okhttp3/ad:e	Ljava/util/List;
    //   1250: ifnonnull +58 -> 1308
    //   1253: aconst_null
    //   1254: astore_1
    //   1255: aload_1
    //   1256: ifnonnull +1961 -> 3217
    //   1259: aload 20
    //   1261: getfield 293	okhttp3/internal/http/c:d	Ljava/util/Date;
    //   1264: ifnull +71 -> 1335
    //   1267: aload 20
    //   1269: getfield 293	okhttp3/internal/http/c:d	Ljava/util/Date;
    //   1272: invokevirtual 301	java/util/Date:getTime	()J
    //   1275: lstore 6
    //   1277: lload 6
    //   1279: aload 20
    //   1281: getfield 354	okhttp3/internal/http/c:f	Ljava/util/Date;
    //   1284: invokevirtual 301	java/util/Date:getTime	()J
    //   1287: lsub
    //   1288: lstore 6
    //   1290: lload 6
    //   1292: lconst_0
    //   1293: lcmp
    //   1294: ifle +1917 -> 3211
    //   1297: lload 6
    //   1299: ldc2_w 361
    //   1302: ldiv
    //   1303: lstore 6
    //   1305: goto -366 -> 939
    //   1308: new 364	java/lang/StringBuilder
    //   1311: dup
    //   1312: invokespecial 365	java/lang/StringBuilder:<init>	()V
    //   1315: astore 21
    //   1317: aload 21
    //   1319: aload_1
    //   1320: getfield 360	okhttp3/ad:e	Ljava/util/List;
    //   1323: invokestatic 368	okhttp3/ad:b	(Ljava/lang/StringBuilder;Ljava/util/List;)V
    //   1326: aload 21
    //   1328: invokevirtual 369	java/lang/StringBuilder:toString	()Ljava/lang/String;
    //   1331: astore_1
    //   1332: goto -77 -> 1255
    //   1335: aload 20
    //   1337: getfield 321	okhttp3/internal/http/c:i	J
    //   1340: lstore 6
    //   1342: goto -65 -> 1277
    //   1345: aload 20
    //   1347: getfield 205	okhttp3/internal/http/c:b	Lokhttp3/at;
    //   1350: invokevirtual 41	okhttp3/at:a	()Lokhttp3/au;
    //   1353: astore_1
    //   1354: aload 20
    //   1356: getfield 371	okhttp3/internal/http/c:k	Ljava/lang/String;
    //   1359: ifnull +46 -> 1405
    //   1362: aload_1
    //   1363: ldc_w 373
    //   1366: aload 20
    //   1368: getfield 371	okhttp3/internal/http/c:k	Ljava/lang/String;
    //   1371: invokevirtual 60	okhttp3/au:a	(Ljava/lang/String;Ljava/lang/String;)Lokhttp3/au;
    //   1374: pop
    //   1375: aload_1
    //   1376: invokevirtual 80	okhttp3/au:a	()Lokhttp3/at;
    //   1379: astore_1
    //   1380: aload_1
    //   1381: invokestatic 290	okhttp3/internal/http/c:a	(Lokhttp3/at;)Z
    //   1384: ifeq +69 -> 1453
    //   1387: new 203	okhttp3/internal/http/b
    //   1390: dup
    //   1391: aload_1
    //   1392: aload 20
    //   1394: getfield 201	okhttp3/internal/http/c:c	Lokhttp3/az;
    //   1397: iconst_0
    //   1398: invokespecial 208	okhttp3/internal/http/b:<init>	(Lokhttp3/at;Lokhttp3/az;B)V
    //   1401: astore_1
    //   1402: goto -984 -> 418
    //   1405: aload 20
    //   1407: getfield 354	okhttp3/internal/http/c:f	Ljava/util/Date;
    //   1410: ifnull +19 -> 1429
    //   1413: aload_1
    //   1414: ldc_w 375
    //   1417: aload 20
    //   1419: getfield 377	okhttp3/internal/http/c:g	Ljava/lang/String;
    //   1422: invokevirtual 60	okhttp3/au:a	(Ljava/lang/String;Ljava/lang/String;)Lokhttp3/au;
    //   1425: pop
    //   1426: goto -51 -> 1375
    //   1429: aload 20
    //   1431: getfield 293	okhttp3/internal/http/c:d	Ljava/util/Date;
    //   1434: ifnull -59 -> 1375
    //   1437: aload_1
    //   1438: ldc_w 375
    //   1441: aload 20
    //   1443: getfield 379	okhttp3/internal/http/c:e	Ljava/lang/String;
    //   1446: invokevirtual 60	okhttp3/au:a	(Ljava/lang/String;Ljava/lang/String;)Lokhttp3/au;
    //   1449: pop
    //   1450: goto -75 -> 1375
    //   1453: new 203	okhttp3/internal/http/b
    //   1456: dup
    //   1457: aload_1
    //   1458: aconst_null
    //   1459: iconst_0
    //   1460: invokespecial 208	okhttp3/internal/http/b:<init>	(Lokhttp3/at;Lokhttp3/az;B)V
    //   1463: astore_1
    //   1464: goto -1046 -> 418
    //   1467: aload 18
    //   1469: getfield 221	okhttp3/internal/http/p:j	Lokhttp3/at;
    //   1472: ifnonnull +70 -> 1542
    //   1475: aload 18
    //   1477: getfield 225	okhttp3/internal/http/p:k	Lokhttp3/az;
    //   1480: invokevirtual 339	okhttp3/az:b	()Lokhttp3/ba;
    //   1483: astore_1
    //   1484: aload_1
    //   1485: aload 18
    //   1487: getfield 123	okhttp3/internal/http/p:i	Lokhttp3/at;
    //   1490: putfield 238	okhttp3/ba:a	Lokhttp3/at;
    //   1493: aload 18
    //   1495: aload_1
    //   1496: aload 18
    //   1498: getfield 240	okhttp3/internal/http/p:d	Lokhttp3/az;
    //   1501: invokestatic 243	okhttp3/internal/http/p:a	(Lokhttp3/az;)Lokhttp3/az;
    //   1504: invokevirtual 246	okhttp3/ba:c	(Lokhttp3/az;)Lokhttp3/ba;
    //   1507: aload 18
    //   1509: getfield 225	okhttp3/internal/http/p:k	Lokhttp3/az;
    //   1512: invokestatic 243	okhttp3/internal/http/p:a	(Lokhttp3/az;)Lokhttp3/az;
    //   1515: invokevirtual 381	okhttp3/ba:b	(Lokhttp3/az;)Lokhttp3/ba;
    //   1518: invokevirtual 265	okhttp3/ba:a	()Lokhttp3/az;
    //   1521: putfield 268	okhttp3/internal/http/p:l	Lokhttp3/az;
    //   1524: aload 18
    //   1526: aload 18
    //   1528: aload 18
    //   1530: getfield 268	okhttp3/internal/http/p:l	Lokhttp3/az;
    //   1533: invokevirtual 383	okhttp3/internal/http/p:b	(Lokhttp3/az;)Lokhttp3/az;
    //   1536: putfield 268	okhttp3/internal/http/p:l	Lokhttp3/az;
    //   1539: goto -945 -> 594
    //   1542: aload 18
    //   1544: getfield 221	okhttp3/internal/http/p:j	Lokhttp3/at;
    //   1547: getfield 385	okhttp3/at:b	Ljava/lang/String;
    //   1550: ldc_w 387
    //   1553: invokevirtual 393	java/lang/String:equals	(Ljava/lang/Object;)Z
    //   1556: ifne +151 -> 1707
    //   1559: iconst_1
    //   1560: istore 5
    //   1562: aload 18
    //   1564: aload 18
    //   1566: getfield 92	okhttp3/internal/http/p:c	Lokhttp3/internal/http/ab;
    //   1569: aload 18
    //   1571: getfield 149	okhttp3/internal/http/p:b	Lokhttp3/am;
    //   1574: getfield 396	okhttp3/am:w	I
    //   1577: aload 18
    //   1579: getfield 149	okhttp3/internal/http/p:b	Lokhttp3/am;
    //   1582: getfield 399	okhttp3/am:x	I
    //   1585: aload 18
    //   1587: getfield 149	okhttp3/internal/http/p:b	Lokhttp3/am;
    //   1590: getfield 402	okhttp3/am:y	I
    //   1593: aload 18
    //   1595: getfield 149	okhttp3/internal/http/p:b	Lokhttp3/am;
    //   1598: getfield 405	okhttp3/am:v	Z
    //   1601: iload 5
    //   1603: invokevirtual 408	okhttp3/internal/http/ab:a	(IIIZZ)Lokhttp3/internal/http/u;
    //   1606: putfield 111	okhttp3/internal/http/p:e	Lokhttp3/internal/http/u;
    //   1609: aload 18
    //   1611: getfield 111	okhttp3/internal/http/p:e	Lokhttp3/internal/http/u;
    //   1614: aload 18
    //   1616: invokeinterface 413 2 0
    //   1621: aload 18
    //   1623: getfield 416	okhttp3/internal/http/p:o	Z
    //   1626: ifeq +87 -> 1713
    //   1629: aload 18
    //   1631: getfield 221	okhttp3/internal/http/p:j	Lokhttp3/at;
    //   1634: invokestatic 417	okhttp3/internal/http/p:a	(Lokhttp3/at;)Z
    //   1637: ifeq +76 -> 1713
    //   1640: aload 18
    //   1642: getfield 421	okhttp3/internal/http/p:m	La/z;
    //   1645: ifnonnull +68 -> 1713
    //   1648: iconst_1
    //   1649: istore 4
    //   1651: iload 4
    //   1653: ifeq -1059 -> 594
    //   1656: aload 19
    //   1658: invokestatic 426	okhttp3/internal/http/v:a	(Lokhttp3/at;)J
    //   1661: lstore 6
    //   1663: aload 18
    //   1665: getfield 427	okhttp3/internal/http/p:h	Z
    //   1668: ifeq +108 -> 1776
    //   1671: lload 6
    //   1673: ldc2_w 428
    //   1676: lcmp
    //   1677: ifle +42 -> 1719
    //   1680: new 113	java/lang/IllegalStateException
    //   1683: dup
    //   1684: ldc_w 431
    //   1687: invokespecial 271	java/lang/IllegalStateException:<init>	(Ljava/lang/String;)V
    //   1690: athrow
    //   1691: astore_1
    //   1692: aload 16
    //   1694: ifnull +11 -> 1705
    //   1697: aload 16
    //   1699: getfield 231	okhttp3/az:f	Lokhttp3/bb;
    //   1702: invokestatic 234	okhttp3/internal/o:a	(Ljava/io/Closeable;)V
    //   1705: aload_1
    //   1706: athrow
    //   1707: iconst_0
    //   1708: istore 5
    //   1710: goto -148 -> 1562
    //   1713: iconst_0
    //   1714: istore 4
    //   1716: goto -65 -> 1651
    //   1719: lload 6
    //   1721: ldc2_w 65
    //   1724: lcmp
    //   1725: ifeq +36 -> 1761
    //   1728: aload 18
    //   1730: getfield 111	okhttp3/internal/http/p:e	Lokhttp3/internal/http/u;
    //   1733: aload 18
    //   1735: getfield 221	okhttp3/internal/http/p:j	Lokhttp3/at;
    //   1738: invokeinterface 434 2 0
    //   1743: aload 18
    //   1745: new 436	okhttp3/internal/http/y
    //   1748: dup
    //   1749: lload 6
    //   1751: l2i
    //   1752: invokespecial 439	okhttp3/internal/http/y:<init>	(I)V
    //   1755: putfield 421	okhttp3/internal/http/p:m	La/z;
    //   1758: goto -1164 -> 594
    //   1761: aload 18
    //   1763: new 436	okhttp3/internal/http/y
    //   1766: dup
    //   1767: invokespecial 440	okhttp3/internal/http/y:<init>	()V
    //   1770: putfield 421	okhttp3/internal/http/p:m	La/z;
    //   1773: goto -1179 -> 594
    //   1776: aload 18
    //   1778: getfield 111	okhttp3/internal/http/p:e	Lokhttp3/internal/http/u;
    //   1781: aload 18
    //   1783: getfield 221	okhttp3/internal/http/p:j	Lokhttp3/at;
    //   1786: invokeinterface 434 2 0
    //   1791: aload 18
    //   1793: aload 18
    //   1795: getfield 111	okhttp3/internal/http/p:e	Lokhttp3/internal/http/u;
    //   1798: aload 18
    //   1800: getfield 221	okhttp3/internal/http/p:j	Lokhttp3/at;
    //   1803: lload 6
    //   1805: invokeinterface 443 4 0
    //   1810: putfield 421	okhttp3/internal/http/p:m	La/z;
    //   1813: goto -1219 -> 594
    //   1816: aload 17
    //   1818: getfield 221	okhttp3/internal/http/p:j	Lokhttp3/at;
    //   1821: ifnull +189 -> 2010
    //   1824: aload 17
    //   1826: getfield 446	okhttp3/internal/http/p:p	Z
    //   1829: ifeq +201 -> 2030
    //   1832: aload 17
    //   1834: getfield 111	okhttp3/internal/http/p:e	Lokhttp3/internal/http/u;
    //   1837: aload 17
    //   1839: getfield 221	okhttp3/internal/http/p:j	Lokhttp3/at;
    //   1842: invokeinterface 434 2 0
    //   1847: aload 17
    //   1849: invokevirtual 448	okhttp3/internal/http/p:c	()Lokhttp3/az;
    //   1852: astore_1
    //   1853: aload 17
    //   1855: aload_1
    //   1856: getfield 451	okhttp3/az:e	Lokhttp3/ab;
    //   1859: invokevirtual 454	okhttp3/internal/http/p:a	(Lokhttp3/ab;)V
    //   1862: aload 17
    //   1864: getfield 225	okhttp3/internal/http/p:k	Lokhttp3/az;
    //   1867: ifnull +412 -> 2279
    //   1870: aload 17
    //   1872: getfield 225	okhttp3/internal/http/p:k	Lokhttp3/az;
    //   1875: aload_1
    //   1876: invokestatic 457	okhttp3/internal/http/p:a	(Lokhttp3/az;Lokhttp3/az;)Z
    //   1879: ifeq +389 -> 2268
    //   1882: aload 17
    //   1884: getfield 225	okhttp3/internal/http/p:k	Lokhttp3/az;
    //   1887: invokevirtual 339	okhttp3/az:b	()Lokhttp3/ba;
    //   1890: astore 16
    //   1892: aload 16
    //   1894: aload 17
    //   1896: getfield 123	okhttp3/internal/http/p:i	Lokhttp3/at;
    //   1899: putfield 238	okhttp3/ba:a	Lokhttp3/at;
    //   1902: aload 17
    //   1904: aload 16
    //   1906: aload 17
    //   1908: getfield 240	okhttp3/internal/http/p:d	Lokhttp3/az;
    //   1911: invokestatic 243	okhttp3/internal/http/p:a	(Lokhttp3/az;)Lokhttp3/az;
    //   1914: invokevirtual 246	okhttp3/ba:c	(Lokhttp3/az;)Lokhttp3/ba;
    //   1917: aload 17
    //   1919: getfield 225	okhttp3/internal/http/p:k	Lokhttp3/az;
    //   1922: getfield 451	okhttp3/az:e	Lokhttp3/ab;
    //   1925: aload_1
    //   1926: getfield 451	okhttp3/az:e	Lokhttp3/ab;
    //   1929: invokestatic 460	okhttp3/internal/http/p:a	(Lokhttp3/ab;Lokhttp3/ab;)Lokhttp3/ab;
    //   1932: invokevirtual 463	okhttp3/ba:a	(Lokhttp3/ab;)Lokhttp3/ba;
    //   1935: aload 17
    //   1937: getfield 225	okhttp3/internal/http/p:k	Lokhttp3/az;
    //   1940: invokestatic 243	okhttp3/internal/http/p:a	(Lokhttp3/az;)Lokhttp3/az;
    //   1943: invokevirtual 381	okhttp3/ba:b	(Lokhttp3/az;)Lokhttp3/ba;
    //   1946: aload_1
    //   1947: invokestatic 243	okhttp3/internal/http/p:a	(Lokhttp3/az;)Lokhttp3/az;
    //   1950: invokevirtual 465	okhttp3/ba:a	(Lokhttp3/az;)Lokhttp3/ba;
    //   1953: invokevirtual 265	okhttp3/ba:a	()Lokhttp3/az;
    //   1956: putfield 268	okhttp3/internal/http/p:l	Lokhttp3/az;
    //   1959: aload_1
    //   1960: getfield 231	okhttp3/az:f	Lokhttp3/bb;
    //   1963: invokevirtual 470	okhttp3/bb:close	()V
    //   1966: aload 17
    //   1968: getfield 92	okhttp3/internal/http/p:c	Lokhttp3/internal/http/ab;
    //   1971: invokevirtual 472	okhttp3/internal/http/ab:b	()V
    //   1974: getstatic 180	okhttp3/internal/f:b	Lokhttp3/internal/f;
    //   1977: aload 17
    //   1979: getfield 149	okhttp3/internal/http/p:b	Lokhttp3/am;
    //   1982: invokevirtual 183	okhttp3/internal/f:a	(Lokhttp3/am;)Lokhttp3/internal/g;
    //   1985: pop
    //   1986: aload 17
    //   1988: getfield 268	okhttp3/internal/http/p:l	Lokhttp3/az;
    //   1991: invokestatic 243	okhttp3/internal/http/p:a	(Lokhttp3/az;)Lokhttp3/az;
    //   1994: pop
    //   1995: aload 17
    //   1997: aload 17
    //   1999: aload 17
    //   2001: getfield 268	okhttp3/internal/http/p:l	Lokhttp3/az;
    //   2004: invokevirtual 383	okhttp3/internal/http/p:b	(Lokhttp3/az;)Lokhttp3/az;
    //   2007: putfield 268	okhttp3/internal/http/p:l	Lokhttp3/az;
    //   2010: aload_0
    //   2011: getfield 87	okhttp3/aq:d	Lokhttp3/internal/http/p;
    //   2014: astore_1
    //   2015: aload_1
    //   2016: getfield 268	okhttp3/internal/http/p:l	Lokhttp3/az;
    //   2019: ifnonnull +560 -> 2579
    //   2022: new 113	java/lang/IllegalStateException
    //   2025: dup
    //   2026: invokespecial 114	java/lang/IllegalStateException:<init>	()V
    //   2029: athrow
    //   2030: aload 17
    //   2032: getfield 416	okhttp3/internal/http/p:o	Z
    //   2035: ifne +30 -> 2065
    //   2038: new 474	okhttp3/internal/http/s
    //   2041: dup
    //   2042: aload 17
    //   2044: iconst_0
    //   2045: aload 17
    //   2047: getfield 221	okhttp3/internal/http/p:j	Lokhttp3/at;
    //   2050: invokespecial 477	okhttp3/internal/http/s:<init>	(Lokhttp3/internal/http/p;ILokhttp3/at;)V
    //   2053: aload 17
    //   2055: getfield 221	okhttp3/internal/http/p:j	Lokhttp3/at;
    //   2058: invokevirtual 480	okhttp3/internal/http/s:a	(Lokhttp3/at;)Lokhttp3/az;
    //   2061: astore_1
    //   2062: goto -209 -> 1853
    //   2065: aload 17
    //   2067: getfield 484	okhttp3/internal/http/p:n	La/i;
    //   2070: ifnull +32 -> 2102
    //   2073: aload 17
    //   2075: getfield 484	okhttp3/internal/http/p:n	La/i;
    //   2078: invokeinterface 489 1 0
    //   2083: getfield 493	a/f:b	J
    //   2086: lconst_0
    //   2087: lcmp
    //   2088: ifle +14 -> 2102
    //   2091: aload 17
    //   2093: getfield 484	okhttp3/internal/http/p:n	La/i;
    //   2096: invokeinterface 496 1 0
    //   2101: pop
    //   2102: aload 17
    //   2104: getfield 498	okhttp3/internal/http/p:f	J
    //   2107: ldc2_w 65
    //   2110: lcmp
    //   2111: ifne +86 -> 2197
    //   2114: aload 17
    //   2116: getfield 221	okhttp3/internal/http/p:j	Lokhttp3/at;
    //   2119: invokestatic 426	okhttp3/internal/http/v:a	(Lokhttp3/at;)J
    //   2122: ldc2_w 65
    //   2125: lcmp
    //   2126: ifne +56 -> 2182
    //   2129: aload 17
    //   2131: getfield 421	okhttp3/internal/http/p:m	La/z;
    //   2134: instanceof 436
    //   2137: ifeq +45 -> 2182
    //   2140: aload 17
    //   2142: getfield 421	okhttp3/internal/http/p:m	La/z;
    //   2145: checkcast 436	okhttp3/internal/http/y
    //   2148: getfield 501	okhttp3/internal/http/y:a	La/f;
    //   2151: getfield 493	a/f:b	J
    //   2154: lstore 6
    //   2156: aload 17
    //   2158: aload 17
    //   2160: getfield 221	okhttp3/internal/http/p:j	Lokhttp3/at;
    //   2163: invokevirtual 41	okhttp3/at:a	()Lokhttp3/au;
    //   2166: ldc 68
    //   2168: lload 6
    //   2170: invokestatic 73	java/lang/Long:toString	(J)Ljava/lang/String;
    //   2173: invokevirtual 60	okhttp3/au:a	(Ljava/lang/String;Ljava/lang/String;)Lokhttp3/au;
    //   2176: invokevirtual 80	okhttp3/au:a	()Lokhttp3/at;
    //   2179: putfield 221	okhttp3/internal/http/p:j	Lokhttp3/at;
    //   2182: aload 17
    //   2184: getfield 111	okhttp3/internal/http/p:e	Lokhttp3/internal/http/u;
    //   2187: aload 17
    //   2189: getfield 221	okhttp3/internal/http/p:j	Lokhttp3/at;
    //   2192: invokeinterface 434 2 0
    //   2197: aload 17
    //   2199: getfield 421	okhttp3/internal/http/p:m	La/z;
    //   2202: ifnull -355 -> 1847
    //   2205: aload 17
    //   2207: getfield 484	okhttp3/internal/http/p:n	La/i;
    //   2210: ifnull +45 -> 2255
    //   2213: aload 17
    //   2215: getfield 484	okhttp3/internal/http/p:n	La/i;
    //   2218: invokeinterface 502 1 0
    //   2223: aload 17
    //   2225: getfield 421	okhttp3/internal/http/p:m	La/z;
    //   2228: instanceof 436
    //   2231: ifeq -384 -> 1847
    //   2234: aload 17
    //   2236: getfield 111	okhttp3/internal/http/p:e	Lokhttp3/internal/http/u;
    //   2239: aload 17
    //   2241: getfield 421	okhttp3/internal/http/p:m	La/z;
    //   2244: checkcast 436	okhttp3/internal/http/y
    //   2247: invokeinterface 505 2 0
    //   2252: goto -405 -> 1847
    //   2255: aload 17
    //   2257: getfield 421	okhttp3/internal/http/p:m	La/z;
    //   2260: invokeinterface 508 1 0
    //   2265: goto -42 -> 2223
    //   2268: aload 17
    //   2270: getfield 225	okhttp3/internal/http/p:k	Lokhttp3/az;
    //   2273: getfield 231	okhttp3/az:f	Lokhttp3/bb;
    //   2276: invokestatic 234	okhttp3/internal/o:a	(Ljava/io/Closeable;)V
    //   2279: aload_1
    //   2280: invokevirtual 339	okhttp3/az:b	()Lokhttp3/ba;
    //   2283: astore 16
    //   2285: aload 16
    //   2287: aload 17
    //   2289: getfield 123	okhttp3/internal/http/p:i	Lokhttp3/at;
    //   2292: putfield 238	okhttp3/ba:a	Lokhttp3/at;
    //   2295: aload 17
    //   2297: aload 16
    //   2299: aload 17
    //   2301: getfield 240	okhttp3/internal/http/p:d	Lokhttp3/az;
    //   2304: invokestatic 243	okhttp3/internal/http/p:a	(Lokhttp3/az;)Lokhttp3/az;
    //   2307: invokevirtual 246	okhttp3/ba:c	(Lokhttp3/az;)Lokhttp3/ba;
    //   2310: aload 17
    //   2312: getfield 225	okhttp3/internal/http/p:k	Lokhttp3/az;
    //   2315: invokestatic 243	okhttp3/internal/http/p:a	(Lokhttp3/az;)Lokhttp3/az;
    //   2318: invokevirtual 381	okhttp3/ba:b	(Lokhttp3/az;)Lokhttp3/ba;
    //   2321: aload_1
    //   2322: invokestatic 243	okhttp3/internal/http/p:a	(Lokhttp3/az;)Lokhttp3/az;
    //   2325: invokevirtual 465	okhttp3/ba:a	(Lokhttp3/az;)Lokhttp3/ba;
    //   2328: invokevirtual 265	okhttp3/ba:a	()Lokhttp3/az;
    //   2331: putfield 268	okhttp3/internal/http/p:l	Lokhttp3/az;
    //   2334: aload 17
    //   2336: getfield 268	okhttp3/internal/http/p:l	Lokhttp3/az;
    //   2339: invokestatic 511	okhttp3/internal/http/p:c	(Lokhttp3/az;)Z
    //   2342: ifeq -332 -> 2010
    //   2345: getstatic 180	okhttp3/internal/f:b	Lokhttp3/internal/f;
    //   2348: aload 17
    //   2350: getfield 149	okhttp3/internal/http/p:b	Lokhttp3/am;
    //   2353: invokevirtual 183	okhttp3/internal/f:a	(Lokhttp3/am;)Lokhttp3/internal/g;
    //   2356: astore_1
    //   2357: aload_1
    //   2358: ifnull +76 -> 2434
    //   2361: aload 17
    //   2363: getfield 268	okhttp3/internal/http/p:l	Lokhttp3/az;
    //   2366: aload 17
    //   2368: getfield 221	okhttp3/internal/http/p:j	Lokhttp3/at;
    //   2371: invokestatic 285	okhttp3/internal/http/b:a	(Lokhttp3/az;Lokhttp3/at;)Z
    //   2374: ifne +96 -> 2470
    //   2377: aload 17
    //   2379: getfield 221	okhttp3/internal/http/p:j	Lokhttp3/at;
    //   2382: getfield 385	okhttp3/at:b	Ljava/lang/String;
    //   2385: astore_1
    //   2386: aload_1
    //   2387: ldc_w 513
    //   2390: invokevirtual 393	java/lang/String:equals	(Ljava/lang/Object;)Z
    //   2393: ifne +41 -> 2434
    //   2396: aload_1
    //   2397: ldc_w 515
    //   2400: invokevirtual 393	java/lang/String:equals	(Ljava/lang/Object;)Z
    //   2403: ifne +31 -> 2434
    //   2406: aload_1
    //   2407: ldc_w 517
    //   2410: invokevirtual 393	java/lang/String:equals	(Ljava/lang/Object;)Z
    //   2413: ifne +21 -> 2434
    //   2416: aload_1
    //   2417: ldc_w 519
    //   2420: invokevirtual 393	java/lang/String:equals	(Ljava/lang/Object;)Z
    //   2423: ifne +11 -> 2434
    //   2426: aload_1
    //   2427: ldc_w 521
    //   2430: invokevirtual 393	java/lang/String:equals	(Ljava/lang/Object;)Z
    //   2433: pop
    //   2434: aload 17
    //   2436: getfield 525	okhttp3/internal/http/p:q	Lokhttp3/internal/http/a;
    //   2439: astore 18
    //   2441: aload 17
    //   2443: getfield 268	okhttp3/internal/http/p:l	Lokhttp3/az;
    //   2446: astore 16
    //   2448: aload 18
    //   2450: ifnonnull +43 -> 2493
    //   2453: aload 16
    //   2455: astore_1
    //   2456: aload 17
    //   2458: aload 17
    //   2460: aload_1
    //   2461: invokevirtual 383	okhttp3/internal/http/p:b	(Lokhttp3/az;)Lokhttp3/az;
    //   2464: putfield 268	okhttp3/internal/http/p:l	Lokhttp3/az;
    //   2467: goto -457 -> 2010
    //   2470: aload 17
    //   2472: getfield 268	okhttp3/internal/http/p:l	Lokhttp3/az;
    //   2475: invokestatic 243	okhttp3/internal/http/p:a	(Lokhttp3/az;)Lokhttp3/az;
    //   2478: pop
    //   2479: aload 17
    //   2481: aload_1
    //   2482: invokeinterface 528 1 0
    //   2487: putfield 525	okhttp3/internal/http/p:q	Lokhttp3/internal/http/a;
    //   2490: goto -56 -> 2434
    //   2493: aload 18
    //   2495: invokeinterface 533 1 0
    //   2500: astore 19
    //   2502: aload 16
    //   2504: astore_1
    //   2505: aload 19
    //   2507: ifnull -51 -> 2456
    //   2510: new 535	okhttp3/internal/http/r
    //   2513: dup
    //   2514: aload 17
    //   2516: aload 16
    //   2518: getfield 231	okhttp3/az:f	Lokhttp3/bb;
    //   2521: invokevirtual 539	okhttp3/bb:source	()La/j;
    //   2524: aload 18
    //   2526: aload 19
    //   2528: invokestatic 544	a/q:a	(La/z;)La/i;
    //   2531: invokespecial 547	okhttp3/internal/http/r:<init>	(Lokhttp3/internal/http/p;La/j;Lokhttp3/internal/http/a;La/i;)V
    //   2534: astore_1
    //   2535: aload 16
    //   2537: invokevirtual 339	okhttp3/az:b	()Lokhttp3/ba;
    //   2540: astore 18
    //   2542: aload 18
    //   2544: new 549	okhttp3/internal/http/w
    //   2547: dup
    //   2548: aload 16
    //   2550: getfield 451	okhttp3/az:e	Lokhttp3/ab;
    //   2553: aload_1
    //   2554: invokestatic 552	a/q:a	(La/aa;)La/j;
    //   2557: invokespecial 555	okhttp3/internal/http/w:<init>	(Lokhttp3/ab;La/j;)V
    //   2560: putfield 264	okhttp3/ba:g	Lokhttp3/bb;
    //   2563: aload 18
    //   2565: invokevirtual 265	okhttp3/ba:a	()Lokhttp3/az;
    //   2568: astore_1
    //   2569: goto -113 -> 2456
    //   2572: aload_1
    //   2573: getfield 274	okhttp3/internal/http/RouteException:b	Ljava/io/IOException;
    //   2576: athrow
    //   2577: aload_1
    //   2578: athrow
    //   2579: aload_1
    //   2580: getfield 268	okhttp3/internal/http/p:l	Lokhttp3/az;
    //   2583: astore 17
    //   2585: aload_0
    //   2586: getfield 87	okhttp3/aq:d	Lokhttp3/internal/http/p;
    //   2589: astore 16
    //   2591: aload 16
    //   2593: getfield 268	okhttp3/internal/http/p:l	Lokhttp3/az;
    //   2596: ifnonnull +11 -> 2607
    //   2599: new 113	java/lang/IllegalStateException
    //   2602: dup
    //   2603: invokespecial 114	java/lang/IllegalStateException:<init>	()V
    //   2606: athrow
    //   2607: aload 16
    //   2609: getfield 92	okhttp3/internal/http/p:c	Lokhttp3/internal/http/ab;
    //   2612: invokevirtual 558	okhttp3/internal/http/ab:a	()Lokhttp3/internal/b/c;
    //   2615: astore_1
    //   2616: aload_1
    //   2617: ifnull +138 -> 2755
    //   2620: aload_1
    //   2621: invokeinterface 563 1 0
    //   2626: astore_1
    //   2627: aload 16
    //   2629: getfield 268	okhttp3/internal/http/p:l	Lokhttp3/az;
    //   2632: getfield 565	okhttp3/az:b	I
    //   2635: istore 4
    //   2637: aload 16
    //   2639: getfield 123	okhttp3/internal/http/p:i	Lokhttp3/at;
    //   2642: getfield 385	okhttp3/at:b	Ljava/lang/String;
    //   2645: astore 18
    //   2647: iload 4
    //   2649: lookupswitch	default:+83->2732, 300:+192->2841, 301:+192->2841, 302:+192->2841, 303:+192->2841, 307:+170->2819, 308:+170->2819, 401:+153->2802, 407:+111->2760, 408:+388->3037
    //   2733: astore_1
    //   2734: aload_1
    //   2735: ifnonnull +352 -> 3087
    //   2738: iload_2
    //   2739: ifne +13 -> 2752
    //   2742: aload_0
    //   2743: getfield 87	okhttp3/aq:d	Lokhttp3/internal/http/p;
    //   2746: getfield 92	okhttp3/internal/http/p:c	Lokhttp3/internal/http/ab;
    //   2749: invokevirtual 472	okhttp3/internal/http/ab:b	()V
    //   2752: aload 17
    //   2754: areturn
    //   2755: aconst_null
    //   2756: astore_1
    //   2757: goto -130 -> 2627
    //   2760: aload_1
    //   2761: ifnull +29 -> 2790
    //   2764: aload_1
    //   2765: getfield 570	okhttp3/bd:b	Ljava/net/Proxy;
    //   2768: astore_1
    //   2769: aload_1
    //   2770: invokevirtual 576	java/net/Proxy:type	()Ljava/net/Proxy$Type;
    //   2773: getstatic 582	java/net/Proxy$Type:HTTP	Ljava/net/Proxy$Type;
    //   2776: if_acmpeq +26 -> 2802
    //   2779: new 584	java/net/ProtocolException
    //   2782: dup
    //   2783: ldc_w 586
    //   2786: invokespecial 587	java/net/ProtocolException:<init>	(Ljava/lang/String;)V
    //   2789: athrow
    //   2790: aload 16
    //   2792: getfield 149	okhttp3/internal/http/p:b	Lokhttp3/am;
    //   2795: getfield 588	okhttp3/am:b	Ljava/net/Proxy;
    //   2798: astore_1
    //   2799: goto -30 -> 2769
    //   2802: aload 16
    //   2804: getfield 149	okhttp3/internal/http/p:b	Lokhttp3/am;
    //   2807: getfield 591	okhttp3/am:q	Lokhttp3/b;
    //   2810: invokeinterface 594 1 0
    //   2815: astore_1
    //   2816: goto -82 -> 2734
    //   2819: aload 18
    //   2821: ldc_w 387
    //   2824: invokevirtual 393	java/lang/String:equals	(Ljava/lang/Object;)Z
    //   2827: ifne +14 -> 2841
    //   2830: aload 18
    //   2832: ldc_w 596
    //   2835: invokevirtual 393	java/lang/String:equals	(Ljava/lang/Object;)Z
    //   2838: ifeq -106 -> 2732
    //   2841: aload 16
    //   2843: getfield 149	okhttp3/internal/http/p:b	Lokhttp3/am;
    //   2846: getfield 599	okhttp3/am:u	Z
    //   2849: ifeq -117 -> 2732
    //   2852: aload 16
    //   2854: getfield 268	okhttp3/internal/http/p:l	Lokhttp3/az;
    //   2857: ldc_w 601
    //   2860: invokevirtual 602	okhttp3/az:a	(Ljava/lang/String;)Ljava/lang/String;
    //   2863: astore_1
    //   2864: aload_1
    //   2865: ifnull -133 -> 2732
    //   2868: aload 16
    //   2870: getfield 123	okhttp3/internal/http/p:i	Lokhttp3/at;
    //   2873: getfield 131	okhttp3/at:a	Lokhttp3/ad;
    //   2876: aload_1
    //   2877: invokevirtual 605	okhttp3/ad:c	(Ljava/lang/String;)Lokhttp3/ad;
    //   2880: astore_1
    //   2881: aload_1
    //   2882: ifnull -150 -> 2732
    //   2885: aload_1
    //   2886: getfield 607	okhttp3/ad:a	Ljava/lang/String;
    //   2889: aload 16
    //   2891: getfield 123	okhttp3/internal/http/p:i	Lokhttp3/at;
    //   2894: getfield 131	okhttp3/at:a	Lokhttp3/ad;
    //   2897: getfield 607	okhttp3/ad:a	Ljava/lang/String;
    //   2900: invokevirtual 393	java/lang/String:equals	(Ljava/lang/Object;)Z
    //   2903: ifne +14 -> 2917
    //   2906: aload 16
    //   2908: getfield 149	okhttp3/internal/http/p:b	Lokhttp3/am;
    //   2911: getfield 610	okhttp3/am:t	Z
    //   2914: ifeq -182 -> 2732
    //   2917: aload 16
    //   2919: getfield 123	okhttp3/internal/http/p:i	Lokhttp3/at;
    //   2922: invokevirtual 41	okhttp3/at:a	()Lokhttp3/au;
    //   2925: astore 19
    //   2927: aload 18
    //   2929: invokestatic 615	okhttp3/internal/http/t:b	(Ljava/lang/String;)Z
    //   2932: ifeq +56 -> 2988
    //   2935: aload 18
    //   2937: ldc_w 617
    //   2940: invokevirtual 393	java/lang/String:equals	(Ljava/lang/Object;)Z
    //   2943: ifne +76 -> 3019
    //   2946: iconst_1
    //   2947: istore 4
    //   2949: iload 4
    //   2951: ifeq +74 -> 3025
    //   2954: aload 19
    //   2956: ldc_w 387
    //   2959: aconst_null
    //   2960: invokevirtual 620	okhttp3/au:a	(Ljava/lang/String;Lokhttp3/av;)Lokhttp3/au;
    //   2963: pop
    //   2964: aload 19
    //   2966: ldc 75
    //   2968: invokevirtual 78	okhttp3/au:b	(Ljava/lang/String;)Lokhttp3/au;
    //   2971: pop
    //   2972: aload 19
    //   2974: ldc 68
    //   2976: invokevirtual 78	okhttp3/au:b	(Ljava/lang/String;)Lokhttp3/au;
    //   2979: pop
    //   2980: aload 19
    //   2982: ldc 49
    //   2984: invokevirtual 78	okhttp3/au:b	(Ljava/lang/String;)Lokhttp3/au;
    //   2987: pop
    //   2988: aload 16
    //   2990: aload_1
    //   2991: invokevirtual 623	okhttp3/internal/http/p:a	(Lokhttp3/ad;)Z
    //   2994: ifne +12 -> 3006
    //   2997: aload 19
    //   2999: ldc_w 625
    //   3002: invokevirtual 78	okhttp3/au:b	(Ljava/lang/String;)Lokhttp3/au;
    //   3005: pop
    //   3006: aload 19
    //   3008: aload_1
    //   3009: invokevirtual 628	okhttp3/au:a	(Lokhttp3/ad;)Lokhttp3/au;
    //   3012: invokevirtual 80	okhttp3/au:a	()Lokhttp3/at;
    //   3015: astore_1
    //   3016: goto -282 -> 2734
    //   3019: iconst_0
    //   3020: istore 4
    //   3022: goto -73 -> 2949
    //   3025: aload 19
    //   3027: aload 18
    //   3029: aconst_null
    //   3030: invokevirtual 620	okhttp3/au:a	(Ljava/lang/String;Lokhttp3/av;)Lokhttp3/au;
    //   3033: pop
    //   3034: goto -70 -> 2964
    //   3037: aload 16
    //   3039: getfield 421	okhttp3/internal/http/p:m	La/z;
    //   3042: ifnull +14 -> 3056
    //   3045: aload 16
    //   3047: getfield 421	okhttp3/internal/http/p:m	La/z;
    //   3050: instanceof 436
    //   3053: ifeq +28 -> 3081
    //   3056: iconst_1
    //   3057: istore 4
    //   3059: aload 16
    //   3061: getfield 416	okhttp3/internal/http/p:o	Z
    //   3064: ifeq +8 -> 3072
    //   3067: iload 4
    //   3069: ifeq -337 -> 2732
    //   3072: aload 16
    //   3074: getfield 123	okhttp3/internal/http/p:i	Lokhttp3/at;
    //   3077: astore_1
    //   3078: goto -344 -> 2734
    //   3081: iconst_0
    //   3082: istore 4
    //   3084: goto -25 -> 3059
    //   3087: aload_0
    //   3088: getfield 87	okhttp3/aq:d	Lokhttp3/internal/http/p;
    //   3091: invokevirtual 120	okhttp3/internal/http/p:b	()Lokhttp3/internal/http/ab;
    //   3094: astore 16
    //   3096: iload_3
    //   3097: iconst_1
    //   3098: iadd
    //   3099: istore_3
    //   3100: iload_3
    //   3101: bipush 20
    //   3103: if_icmple +36 -> 3139
    //   3106: aload 16
    //   3108: iconst_0
    //   3109: iconst_1
    //   3110: iconst_0
    //   3111: invokevirtual 97	okhttp3/internal/http/ab:a	(ZZZ)V
    //   3114: new 584	java/net/ProtocolException
    //   3117: dup
    //   3118: new 364	java/lang/StringBuilder
    //   3121: dup
    //   3122: ldc_w 630
    //   3125: invokespecial 631	java/lang/StringBuilder:<init>	(Ljava/lang/String;)V
    //   3128: iload_3
    //   3129: invokevirtual 635	java/lang/StringBuilder:append	(I)Ljava/lang/StringBuilder;
    //   3132: invokevirtual 369	java/lang/StringBuilder:toString	()Ljava/lang/String;
    //   3135: invokespecial 587	java/net/ProtocolException:<init>	(Ljava/lang/String;)V
    //   3138: athrow
    //   3139: aload_0
    //   3140: getfield 87	okhttp3/aq:d	Lokhttp3/internal/http/p;
    //   3143: aload_1
    //   3144: getfield 131	okhttp3/at:a	Lokhttp3/ad;
    //   3147: invokevirtual 623	okhttp3/internal/http/p:a	(Lokhttp3/ad;)Z
    //   3150: ifne +40 -> 3190
    //   3153: aload 16
    //   3155: iconst_0
    //   3156: iconst_1
    //   3157: iconst_0
    //   3158: invokevirtual 97	okhttp3/internal/http/ab:a	(ZZZ)V
    //   3161: aconst_null
    //   3162: astore 16
    //   3164: aload_0
    //   3165: new 82	okhttp3/internal/http/p
    //   3168: dup
    //   3169: aload_0
    //   3170: getfield 22	okhttp3/aq:a	Lokhttp3/am;
    //   3173: aload_1
    //   3174: iconst_0
    //   3175: iconst_0
    //   3176: iload_2
    //   3177: aload 16
    //   3179: aload 17
    //   3181: invokespecial 85	okhttp3/internal/http/p:<init>	(Lokhttp3/am;Lokhttp3/at;ZZZLokhttp3/internal/http/ab;Lokhttp3/az;)V
    //   3184: putfield 87	okhttp3/aq:d	Lokhttp3/internal/http/p;
    //   3187: goto -3084 -> 103
    //   3190: goto -26 -> 3164
    //   3193: lconst_0
    //   3194: lstore 8
    //   3196: goto -2206 -> 990
    //   3199: goto -2232 -> 967
    //   3202: goto -3122 -> 80
    //   3205: lconst_0
    //   3206: lstore 6
    //   3208: goto -2359 -> 849
    //   3211: lconst_0
    //   3212: lstore 6
    //   3214: goto -2275 -> 939
    //   3217: lconst_0
    //   3218: lstore 6
    //   3220: goto -2281 -> 939
    //   3223: iconst_0
    //   3224: istore 4
    //   3226: goto -2099 -> 1127
    //
    // Exception table:
    //   from	to	target	type
    //   152	182	182	okhttp3/internal/http/RequestException
    //   210	247	182	okhttp3/internal/http/RequestException
    //   247	266	182	okhttp3/internal/http/RequestException
    //   266	291	182	okhttp3/internal/http/RequestException
    //   291	329	182	okhttp3/internal/http/RequestException
    //   329	348	182	okhttp3/internal/http/RequestException
    //   348	367	182	okhttp3/internal/http/RequestException
    //   371	379	182	okhttp3/internal/http/RequestException
    //   379	418	182	okhttp3/internal/http/RequestException
    //   421	428	182	okhttp3/internal/http/RequestException
    //   431	457	182	okhttp3/internal/http/RequestException
    //   457	490	182	okhttp3/internal/http/RequestException
    //   495	511	182	okhttp3/internal/http/RequestException
    //   511	594	182	okhttp3/internal/http/RequestException
    //   594	635	182	okhttp3/internal/http/RequestException
    //   675	712	182	okhttp3/internal/http/RequestException
    //   740	771	182	okhttp3/internal/http/RequestException
    //   774	803	182	okhttp3/internal/http/RequestException
    //   803	818	182	okhttp3/internal/http/RequestException
    //   821	849	182	okhttp3/internal/http/RequestException
    //   853	881	182	okhttp3/internal/http/RequestException
    //   881	939	182	okhttp3/internal/http/RequestException
    //   939	967	182	okhttp3/internal/http/RequestException
    //   967	990	182	okhttp3/internal/http/RequestException
    //   993	1002	182	okhttp3/internal/http/RequestException
    //   1006	1013	182	okhttp3/internal/http/RequestException
    //   1017	1040	182	okhttp3/internal/http/RequestException
    //   1040	1047	182	okhttp3/internal/http/RequestException
    //   1061	1070	182	okhttp3/internal/http/RequestException
    //   1081	1092	182	okhttp3/internal/http/RequestException
    //   1101	1124	182	okhttp3/internal/http/RequestException
    //   1132	1143	182	okhttp3/internal/http/RequestException
    //   1143	1157	182	okhttp3/internal/http/RequestException
    //   1160	1186	182	okhttp3/internal/http/RequestException
    //   1186	1199	182	okhttp3/internal/http/RequestException
    //   1216	1223	182	okhttp3/internal/http/RequestException
    //   1226	1253	182	okhttp3/internal/http/RequestException
    //   1259	1277	182	okhttp3/internal/http/RequestException
    //   1277	1290	182	okhttp3/internal/http/RequestException
    //   1297	1305	182	okhttp3/internal/http/RequestException
    //   1308	1332	182	okhttp3/internal/http/RequestException
    //   1335	1342	182	okhttp3/internal/http/RequestException
    //   1345	1375	182	okhttp3/internal/http/RequestException
    //   1375	1402	182	okhttp3/internal/http/RequestException
    //   1405	1426	182	okhttp3/internal/http/RequestException
    //   1429	1450	182	okhttp3/internal/http/RequestException
    //   1453	1464	182	okhttp3/internal/http/RequestException
    //   1467	1539	182	okhttp3/internal/http/RequestException
    //   1697	1705	182	okhttp3/internal/http/RequestException
    //   1705	1707	182	okhttp3/internal/http/RequestException
    //   1816	1847	182	okhttp3/internal/http/RequestException
    //   1847	1853	182	okhttp3/internal/http/RequestException
    //   1853	2010	182	okhttp3/internal/http/RequestException
    //   2030	2062	182	okhttp3/internal/http/RequestException
    //   2065	2102	182	okhttp3/internal/http/RequestException
    //   2102	2182	182	okhttp3/internal/http/RequestException
    //   2182	2197	182	okhttp3/internal/http/RequestException
    //   2197	2223	182	okhttp3/internal/http/RequestException
    //   2223	2252	182	okhttp3/internal/http/RequestException
    //   2255	2265	182	okhttp3/internal/http/RequestException
    //   2268	2279	182	okhttp3/internal/http/RequestException
    //   2279	2357	182	okhttp3/internal/http/RequestException
    //   2361	2434	182	okhttp3/internal/http/RequestException
    //   2434	2448	182	okhttp3/internal/http/RequestException
    //   2456	2467	182	okhttp3/internal/http/RequestException
    //   2470	2490	182	okhttp3/internal/http/RequestException
    //   2493	2502	182	okhttp3/internal/http/RequestException
    //   2510	2569	182	okhttp3/internal/http/RequestException
    //   152	182	188	finally
    //   183	188	188	finally
    //   210	247	188	finally
    //   247	266	188	finally
    //   266	291	188	finally
    //   291	329	188	finally
    //   329	348	188	finally
    //   348	367	188	finally
    //   371	379	188	finally
    //   379	418	188	finally
    //   421	428	188	finally
    //   431	457	188	finally
    //   457	490	188	finally
    //   495	511	188	finally
    //   511	594	188	finally
    //   594	635	188	finally
    //   636	649	188	finally
    //   675	712	188	finally
    //   716	726	188	finally
    //   740	771	188	finally
    //   774	803	188	finally
    //   803	818	188	finally
    //   821	849	188	finally
    //   853	881	188	finally
    //   881	939	188	finally
    //   939	967	188	finally
    //   967	990	188	finally
    //   993	1002	188	finally
    //   1006	1013	188	finally
    //   1017	1040	188	finally
    //   1040	1047	188	finally
    //   1061	1070	188	finally
    //   1081	1092	188	finally
    //   1101	1124	188	finally
    //   1132	1143	188	finally
    //   1143	1157	188	finally
    //   1160	1186	188	finally
    //   1186	1199	188	finally
    //   1216	1223	188	finally
    //   1226	1253	188	finally
    //   1259	1277	188	finally
    //   1277	1290	188	finally
    //   1297	1305	188	finally
    //   1308	1332	188	finally
    //   1335	1342	188	finally
    //   1345	1375	188	finally
    //   1375	1402	188	finally
    //   1405	1426	188	finally
    //   1429	1450	188	finally
    //   1453	1464	188	finally
    //   1467	1539	188	finally
    //   1697	1705	188	finally
    //   1705	1707	188	finally
    //   1816	1847	188	finally
    //   1847	1853	188	finally
    //   1853	2010	188	finally
    //   2030	2062	188	finally
    //   2065	2102	188	finally
    //   2102	2182	188	finally
    //   2182	2197	188	finally
    //   2197	2223	188	finally
    //   2223	2252	188	finally
    //   2255	2265	188	finally
    //   2268	2279	188	finally
    //   2279	2357	188	finally
    //   2361	2434	188	finally
    //   2434	2448	188	finally
    //   2456	2467	188	finally
    //   2470	2490	188	finally
    //   2493	2502	188	finally
    //   2510	2569	188	finally
    //   2572	2577	188	finally
    //   2577	2579	188	finally
    //   152	182	635	okhttp3/internal/http/RouteException
    //   210	247	635	okhttp3/internal/http/RouteException
    //   247	266	635	okhttp3/internal/http/RouteException
    //   266	291	635	okhttp3/internal/http/RouteException
    //   291	329	635	okhttp3/internal/http/RouteException
    //   329	348	635	okhttp3/internal/http/RouteException
    //   348	367	635	okhttp3/internal/http/RouteException
    //   371	379	635	okhttp3/internal/http/RouteException
    //   379	418	635	okhttp3/internal/http/RouteException
    //   421	428	635	okhttp3/internal/http/RouteException
    //   431	457	635	okhttp3/internal/http/RouteException
    //   457	490	635	okhttp3/internal/http/RouteException
    //   495	511	635	okhttp3/internal/http/RouteException
    //   511	594	635	okhttp3/internal/http/RouteException
    //   594	635	635	okhttp3/internal/http/RouteException
    //   675	712	635	okhttp3/internal/http/RouteException
    //   740	771	635	okhttp3/internal/http/RouteException
    //   774	803	635	okhttp3/internal/http/RouteException
    //   803	818	635	okhttp3/internal/http/RouteException
    //   821	849	635	okhttp3/internal/http/RouteException
    //   853	881	635	okhttp3/internal/http/RouteException
    //   881	939	635	okhttp3/internal/http/RouteException
    //   939	967	635	okhttp3/internal/http/RouteException
    //   967	990	635	okhttp3/internal/http/RouteException
    //   993	1002	635	okhttp3/internal/http/RouteException
    //   1006	1013	635	okhttp3/internal/http/RouteException
    //   1017	1040	635	okhttp3/internal/http/RouteException
    //   1040	1047	635	okhttp3/internal/http/RouteException
    //   1061	1070	635	okhttp3/internal/http/RouteException
    //   1081	1092	635	okhttp3/internal/http/RouteException
    //   1101	1124	635	okhttp3/internal/http/RouteException
    //   1132	1143	635	okhttp3/internal/http/RouteException
    //   1143	1157	635	okhttp3/internal/http/RouteException
    //   1160	1186	635	okhttp3/internal/http/RouteException
    //   1186	1199	635	okhttp3/internal/http/RouteException
    //   1216	1223	635	okhttp3/internal/http/RouteException
    //   1226	1253	635	okhttp3/internal/http/RouteException
    //   1259	1277	635	okhttp3/internal/http/RouteException
    //   1277	1290	635	okhttp3/internal/http/RouteException
    //   1297	1305	635	okhttp3/internal/http/RouteException
    //   1308	1332	635	okhttp3/internal/http/RouteException
    //   1335	1342	635	okhttp3/internal/http/RouteException
    //   1345	1375	635	okhttp3/internal/http/RouteException
    //   1375	1402	635	okhttp3/internal/http/RouteException
    //   1405	1426	635	okhttp3/internal/http/RouteException
    //   1429	1450	635	okhttp3/internal/http/RouteException
    //   1453	1464	635	okhttp3/internal/http/RouteException
    //   1467	1539	635	okhttp3/internal/http/RouteException
    //   1697	1705	635	okhttp3/internal/http/RouteException
    //   1705	1707	635	okhttp3/internal/http/RouteException
    //   1816	1847	635	okhttp3/internal/http/RouteException
    //   1847	1853	635	okhttp3/internal/http/RouteException
    //   1853	2010	635	okhttp3/internal/http/RouteException
    //   2030	2062	635	okhttp3/internal/http/RouteException
    //   2065	2102	635	okhttp3/internal/http/RouteException
    //   2102	2182	635	okhttp3/internal/http/RouteException
    //   2182	2197	635	okhttp3/internal/http/RouteException
    //   2197	2223	635	okhttp3/internal/http/RouteException
    //   2223	2252	635	okhttp3/internal/http/RouteException
    //   2255	2265	635	okhttp3/internal/http/RouteException
    //   2268	2279	635	okhttp3/internal/http/RouteException
    //   2279	2357	635	okhttp3/internal/http/RouteException
    //   2361	2434	635	okhttp3/internal/http/RouteException
    //   2434	2448	635	okhttp3/internal/http/RouteException
    //   2456	2467	635	okhttp3/internal/http/RouteException
    //   2470	2490	635	okhttp3/internal/http/RouteException
    //   2493	2502	635	okhttp3/internal/http/RouteException
    //   2510	2569	635	okhttp3/internal/http/RouteException
    //   654	660	663	finally
    //   731	737	663	finally
    //   152	182	715	java/io/IOException
    //   210	247	715	java/io/IOException
    //   247	266	715	java/io/IOException
    //   266	291	715	java/io/IOException
    //   291	329	715	java/io/IOException
    //   329	348	715	java/io/IOException
    //   348	367	715	java/io/IOException
    //   371	379	715	java/io/IOException
    //   379	418	715	java/io/IOException
    //   421	428	715	java/io/IOException
    //   431	457	715	java/io/IOException
    //   457	490	715	java/io/IOException
    //   495	511	715	java/io/IOException
    //   511	594	715	java/io/IOException
    //   594	635	715	java/io/IOException
    //   675	712	715	java/io/IOException
    //   740	771	715	java/io/IOException
    //   774	803	715	java/io/IOException
    //   803	818	715	java/io/IOException
    //   821	849	715	java/io/IOException
    //   853	881	715	java/io/IOException
    //   881	939	715	java/io/IOException
    //   939	967	715	java/io/IOException
    //   967	990	715	java/io/IOException
    //   993	1002	715	java/io/IOException
    //   1006	1013	715	java/io/IOException
    //   1017	1040	715	java/io/IOException
    //   1040	1047	715	java/io/IOException
    //   1061	1070	715	java/io/IOException
    //   1081	1092	715	java/io/IOException
    //   1101	1124	715	java/io/IOException
    //   1132	1143	715	java/io/IOException
    //   1143	1157	715	java/io/IOException
    //   1160	1186	715	java/io/IOException
    //   1186	1199	715	java/io/IOException
    //   1216	1223	715	java/io/IOException
    //   1226	1253	715	java/io/IOException
    //   1259	1277	715	java/io/IOException
    //   1277	1290	715	java/io/IOException
    //   1297	1305	715	java/io/IOException
    //   1308	1332	715	java/io/IOException
    //   1335	1342	715	java/io/IOException
    //   1345	1375	715	java/io/IOException
    //   1375	1402	715	java/io/IOException
    //   1405	1426	715	java/io/IOException
    //   1429	1450	715	java/io/IOException
    //   1453	1464	715	java/io/IOException
    //   1467	1539	715	java/io/IOException
    //   1697	1705	715	java/io/IOException
    //   1705	1707	715	java/io/IOException
    //   1816	1847	715	java/io/IOException
    //   1847	1853	715	java/io/IOException
    //   1853	2010	715	java/io/IOException
    //   2030	2062	715	java/io/IOException
    //   2065	2102	715	java/io/IOException
    //   2102	2182	715	java/io/IOException
    //   2182	2197	715	java/io/IOException
    //   2197	2223	715	java/io/IOException
    //   2223	2252	715	java/io/IOException
    //   2255	2265	715	java/io/IOException
    //   2268	2279	715	java/io/IOException
    //   2279	2357	715	java/io/IOException
    //   2361	2434	715	java/io/IOException
    //   2434	2448	715	java/io/IOException
    //   2456	2467	715	java/io/IOException
    //   2470	2490	715	java/io/IOException
    //   2493	2502	715	java/io/IOException
    //   2510	2569	715	java/io/IOException
    //   1542	1559	1691	finally
    //   1562	1648	1691	finally
    //   1656	1671	1691	finally
    //   1680	1691	1691	finally
    //   1728	1758	1691	finally
    //   1761	1773	1691	finally
    //   1776	1813	1691	finally
  }

  final az a(boolean paramBoolean)
    throws IOException
  {
    return new ar(this, 0, this.c, paramBoolean).a(this.c);
  }

  public final void a(i parami)
  {
    try
    {
      if (this.e)
        throw new IllegalStateException("Already Executed");
    }
    finally
    {
    }
    this.e = true;
    this.a.a.a(new as(this, parami, (byte)0));
  }

  public final az b()
    throws IOException
  {
    try
    {
      if (this.e)
        throw new IllegalStateException("Already Executed");
    }
    finally
    {
    }
    this.e = true;
    try
    {
      this.a.a.a(this);
      az localaz1 = a(false);
      if (localaz1 == null)
        throw new IOException("Canceled");
    }
    finally
    {
      this.a.a.a(this);
    }
    this.a.a.a(this);
    return localaz2;
  }

  public final void c()
  {
    this.b = true;
    Object localObject2;
    if (this.d != null)
      localObject2 = this.d.c;
    do
      synchronized (((ab)localObject2).b)
      {
        ((ab)localObject2).e = true;
        u localu = ((ab)localObject2).f;
        localObject2 = ((ab)localObject2).d;
        if (localu != null)
        {
          localu.a();
          return;
        }
      }
    while (localObject2 == null);
    o.a(((c)localObject2).c);
  }
}

/* Location:           C:\crazyd\work\ustone\odm2016031702\baidu\android\nut-dex2jar.jar
 * Qualified Name:     okhttp3.aq
 * JD-Core Version:    0.6.2
 */