package com.sina.weibo.sdk.c;

final class c
{
  // ERROR //
  public static void a(java.lang.String paramString1, java.lang.String paramString2, boolean paramBoolean)
  {
    // Byte code:
    //   0: ldc 2
    //   2: monitorenter
    //   3: aload_0
    //   4: invokestatic 14	android/text/TextUtils:isEmpty	(Ljava/lang/CharSequence;)Z
    //   7: istore_3
    //   8: iload_3
    //   9: ifeq +7 -> 16
    //   12: ldc 2
    //   14: monitorexit
    //   15: return
    //   16: ldc 16
    //   18: new 18	java/lang/StringBuilder
    //   21: dup
    //   22: ldc 20
    //   24: invokespecial 24	java/lang/StringBuilder:<init>	(Ljava/lang/String;)V
    //   27: aload_0
    //   28: invokevirtual 28	java/lang/StringBuilder:append	(Ljava/lang/String;)Ljava/lang/StringBuilder;
    //   31: invokevirtual 32	java/lang/StringBuilder:toString	()Ljava/lang/String;
    //   34: invokestatic 38	com/sina/weibo/sdk/d/i:b	(Ljava/lang/String;Ljava/lang/String;)V
    //   37: aload_1
    //   38: ifnull -26 -> 12
    //   41: aload_1
    //   42: invokevirtual 44	java/lang/String:length	()I
    //   45: ifeq -33 -> 12
    //   48: new 18	java/lang/StringBuilder
    //   51: dup
    //   52: aload_1
    //   53: invokespecial 24	java/lang/StringBuilder:<init>	(Ljava/lang/String;)V
    //   56: astore 8
    //   58: aload 8
    //   60: iconst_0
    //   61: invokevirtual 48	java/lang/StringBuilder:charAt	(I)C
    //   64: bipush 91
    //   66: if_icmpne +13 -> 79
    //   69: aload 8
    //   71: iconst_0
    //   72: iconst_1
    //   73: ldc 50
    //   75: invokevirtual 54	java/lang/StringBuilder:replace	(IILjava/lang/String;)Ljava/lang/StringBuilder;
    //   78: pop
    //   79: aload 8
    //   81: aload 8
    //   83: invokevirtual 55	java/lang/StringBuilder:length	()I
    //   86: iconst_1
    //   87: isub
    //   88: invokevirtual 48	java/lang/StringBuilder:charAt	(I)C
    //   91: bipush 44
    //   93: if_icmpeq +23 -> 116
    //   96: aload 8
    //   98: aload 8
    //   100: invokevirtual 55	java/lang/StringBuilder:length	()I
    //   103: iconst_1
    //   104: isub
    //   105: aload 8
    //   107: invokevirtual 55	java/lang/StringBuilder:length	()I
    //   110: ldc 57
    //   112: invokevirtual 54	java/lang/StringBuilder:replace	(IILjava/lang/String;)Ljava/lang/StringBuilder;
    //   115: pop
    //   116: new 59	java/io/File
    //   119: dup
    //   120: aload_0
    //   121: invokespecial 60	java/io/File:<init>	(Ljava/lang/String;)V
    //   124: astore_0
    //   125: aconst_null
    //   126: astore_1
    //   127: aload_0
    //   128: invokevirtual 64	java/io/File:getParentFile	()Ljava/io/File;
    //   131: astore 9
    //   133: aload 9
    //   135: invokevirtual 68	java/io/File:exists	()Z
    //   138: ifne +9 -> 147
    //   141: aload 9
    //   143: invokevirtual 71	java/io/File:mkdirs	()Z
    //   146: pop
    //   147: aload_0
    //   148: invokevirtual 68	java/io/File:exists	()Z
    //   151: ifne +54 -> 205
    //   154: aload_0
    //   155: invokevirtual 74	java/io/File:createNewFile	()Z
    //   158: pop
    //   159: iload_2
    //   160: istore_3
    //   161: new 76	java/io/FileWriter
    //   164: dup
    //   165: aload_0
    //   166: iload_3
    //   167: invokespecial 79	java/io/FileWriter:<init>	(Ljava/io/File;Z)V
    //   170: astore_0
    //   171: aload_0
    //   172: aload 8
    //   174: invokevirtual 32	java/lang/StringBuilder:toString	()Ljava/lang/String;
    //   177: invokevirtual 82	java/io/FileWriter:write	(Ljava/lang/String;)V
    //   180: aload_0
    //   181: invokevirtual 86	java/io/FileWriter:flush	()V
    //   184: aload_0
    //   185: invokevirtual 89	java/io/FileWriter:close	()V
    //   188: goto -176 -> 12
    //   191: astore_0
    //   192: aload_0
    //   193: invokevirtual 92	java/io/IOException:printStackTrace	()V
    //   196: goto -184 -> 12
    //   199: astore_0
    //   200: ldc 2
    //   202: monitorexit
    //   203: aload_0
    //   204: athrow
    //   205: iload_2
    //   206: istore_3
    //   207: aload_0
    //   208: invokevirtual 96	java/io/File:lastModified	()J
    //   211: lconst_0
    //   212: lcmp
    //   213: ifle -52 -> 161
    //   216: invokestatic 101	java/lang/System:currentTimeMillis	()J
    //   219: lstore 4
    //   221: aload_0
    //   222: invokevirtual 96	java/io/File:lastModified	()J
    //   225: lstore 6
    //   227: iload_2
    //   228: istore_3
    //   229: lload 4
    //   231: lload 6
    //   233: lsub
    //   234: ldc2_w 102
    //   237: lcmp
    //   238: ifle -77 -> 161
    //   241: iconst_0
    //   242: istore_3
    //   243: goto -82 -> 161
    //   246: astore_0
    //   247: aload_1
    //   248: astore_0
    //   249: aload_0
    //   250: ifnull -238 -> 12
    //   253: aload_0
    //   254: invokevirtual 89	java/io/FileWriter:close	()V
    //   257: goto -245 -> 12
    //   260: astore_0
    //   261: aload_0
    //   262: invokevirtual 92	java/io/IOException:printStackTrace	()V
    //   265: goto -253 -> 12
    //   268: astore_1
    //   269: aconst_null
    //   270: astore_0
    //   271: aload_0
    //   272: ifnull +7 -> 279
    //   275: aload_0
    //   276: invokevirtual 89	java/io/FileWriter:close	()V
    //   279: aload_1
    //   280: athrow
    //   281: astore_0
    //   282: aload_0
    //   283: invokevirtual 92	java/io/IOException:printStackTrace	()V
    //   286: goto -7 -> 279
    //   289: astore_1
    //   290: goto -19 -> 271
    //   293: astore_1
    //   294: goto -45 -> 249
    //
    // Exception table:
    //   from	to	target	type
    //   184	188	191	java/io/IOException
    //   3	8	199	finally
    //   16	37	199	finally
    //   41	79	199	finally
    //   79	116	199	finally
    //   116	125	199	finally
    //   184	188	199	finally
    //   192	196	199	finally
    //   253	257	199	finally
    //   261	265	199	finally
    //   275	279	199	finally
    //   279	281	199	finally
    //   282	286	199	finally
    //   127	147	246	java/io/IOException
    //   147	159	246	java/io/IOException
    //   161	171	246	java/io/IOException
    //   207	227	246	java/io/IOException
    //   253	257	260	java/io/IOException
    //   127	147	268	finally
    //   147	159	268	finally
    //   161	171	268	finally
    //   207	227	268	finally
    //   275	279	281	java/io/IOException
    //   171	184	289	finally
    //   171	184	293	java/io/IOException
  }
}

/* Location:           C:\crazyd\work\ustone\odm2016031702\baidu\android\nut-dex2jar.jar
 * Qualified Name:     com.sina.weibo.sdk.c.c
 * JD-Core Version:    0.6.2
 */